Workbook

Sheet Cover Page
A1: Income Forecast
A32: Your Personal Finance Organizer

Sheet Main
A1: Money In Terms Of (tens, hundred, thousands, millions) | B1: tens
A2: A Month (TRUE or FALSE) | B2: TRUE
A3: Date Range Start From (dd/mm/yyyy) | B3: 45402
A4: Date Range End To (A month dd/mm/yyyy) | B4: =IF(B2,TEXT(EDATE(B3,1)-1,"dd-mmm-yyyy"),TEXT(EDATE(B3,1)-1,"dd-mmm-yyyy")) -> 19-May-2024
A5: Specify Date Range End To (dd/mm/yyyy) (If a month is not checked) | B5: 45777
A8: Work Sheet Name
A9: =TEXT(B3,"dd mmmm yyyy")&" - "&IF(B2,TEXT(EDATE(B3,1)-1,"dd mmmm yyyy"),TEXT(B3+B5-B3,"dd mmmm yyyy")) -> 20 April 2024 - 19 May 2024 | B9: April 2024 - June 2024
A10: =IF(B2,TEXT(EDATE(B3,1),"dd mmmm yyyy"),TEXT(B3+(B5-B3)+1,"dd mmmm yyyy"))&" - "&IF(B2,TEXT(EDATE(B3,2)-1,"dd mmmm yyyy"),TEXT(B3+(B5-B3)*2+1,"dd mmmm yyyy")) -> 20 May 2024 - 19 June 2024
A11: =IF(B2,TEXT(EDATE(B3,2),"dd mmmm yyyy"),TEXT(B3+((B5-B3)*2)+2,"dd mmmm yyyy"))&" - "&IF(B2,TEXT(EDATE(B3,3)-1,"dd mmmm yyyy"),TEXT(B3+((B5-B3)*3+2),"dd mmmm yyyy")) -> 20 June 2024 - 19 July 2024
A12: =IF(B2,TEXT(EDATE(B3,3),"dd mmmm yyyy"),TEXT(B3+((B5-B3)*3)+3,"dd mmmm yyyy"))&" - "&IF(B2,TEXT(EDATE(B3,4)-1,"dd mmmm yyyy"),TEXT(B3+(((B5-B3)*4)+3),"dd mmmm yyyy")) -> 20 July 2024 - 19 August 2024 | B12: July 2024 - September 2024
A13: =IF(B2,TEXT(EDATE(B3,4),"dd mmmm yyyy"),TEXT(B3+((B5-B3)*4)+4,"dd mmmm yyyy"))&" - "&IF(B2,TEXT(EDATE(B3,5)-1,"dd mmmm yyyy"),TEXT(B3+(((B5-B3)*5)+4),"dd mmmm yyyy")) -> 20 August 2024 - 19 September 2024
A14: =IF(B2,TEXT(EDATE(B3,5),"dd mmmm yyyy"),TEXT(B3+((B5-B3)*5)+5,"dd mmmm yyyy"))&" - "&IF(B2,TEXT(EDATE(B3,6)-1,"dd mmmm yyyy"),TEXT(B3+(((B5-B3)*6)+5),"dd mmmm yyyy")) -> 20 September 2024 - 19 October 2024
A15: =IF(B2,TEXT(EDATE(B3,6),"dd mmmm yyyy"),TEXT(B3+((B5-B3)*6)+6,"dd mmmm yyyy"))&" - "&IF(B2,TEXT(EDATE(B3,7)-1,"dd mmmm yyyy"),TEXT(B3+(((B5-B3)*7)+6),"dd mmmm yyyy")) -> 20 October 2024 - 19 November 2024 | B15: October 2024 - December 2024
A16: =IF(B2,TEXT(EDATE(B3,7),"dd mmmm yyyy"),TEXT(B3+((B5-B3)*7)+7,"dd mmmm yyyy"))&" - "&IF(B2,TEXT(EDATE(B3,8)-1,"dd mmmm yyyy"),TEXT(B3+(((B5-B3)*8)+7),"dd mmmm yyyy")) -> 20 November 2024 - 19 December 2024
A17: =IF(B2,TEXT(EDATE(B3,8),"dd mmmm yyyy"),TEXT(B3+((B5-B3)*8)+8,"dd mmmm yyyy"))&" - "&IF(B2,TEXT(EDATE(B3,9)-1,"dd mmmm yyyy"),TEXT(B3+(((B5-B3)*9)+8),"dd mmmm yyyy")) -> 20 December 2024 - 19 January 2025
A18: =IF(B2,TEXT(EDATE(B3,9),"dd mmmm yyyy"),TEXT(B3+((B5-B3)*9)+9,"dd mmmm yyyy"))&" - "&IF(B2,TEXT(EDATE(B3,10)-1,"dd mmmm yyyy"),TEXT(B3+(((B5-B3)*10)+9),"dd mmmm yyyy")) -> 20 January 2025 - 19 February 2025 | B18: January 2025 - March 2025
A19: =IF(B2,TEXT(EDATE(B3,10),"dd mmmm yyyy"),TEXT(B3+((B5-B3)*10)+10,"dd mmmm yyyy"))&" - "&IF(B2,TEXT(EDATE(B3,11)-1,"dd mmmm yyyy"),TEXT(B3+(((B5-B3)*11)+10),"dd mmmm yyyy")) -> 20 February 2025 - 19 March 2025
A20: =IF(B2,TEXT(EDATE(B3,11),"dd mmmm yyyy"),TEXT(B3+((B5-B3)*11)+11,"dd mmmm yyyy"))&" - "&IF(B2,TEXT(EDATE(B3,12)-1,"dd mmmm yyyy"),TEXT(B3+(((B5-B3)*12)+11),"dd mmmm yyyy")) -> 20 March 2025 - 19 April 2025
A21: =IF(B2,TEXT(EDATE(B3,12),"dd mmmm yyyy"),TEXT(B3+((B5-B3)*12)+12,"dd mmmm yyyy"))&" - "&IF(B2,TEXT(EDATE(B3,13)-1,"dd mmmm yyyy"),TEXT(B3+(((B5-B3)*13)+12),"dd mmmm yyyy")) -> 20 April 2025 - 19 May 2025 | B21: April 2025 - June 2025
A22: =IF(B2,TEXT(EDATE(B3,13),"dd mmmm yyyy"),TEXT(B3+((B5-B3)*13)+13,"dd mmmm yyyy"))&" - "&IF(B2,TEXT(EDATE(B3,14)-1,"dd mmmm yyyy"),TEXT(B3+(((B5-B3)*14)+13),"dd mmmm yyyy")) -> 20 May 2025 - 19 June 2025
A23: =IF(B2,TEXT(EDATE(B3,14),"dd mmmm yyyy"),TEXT(B3+((B5-B3)*14)+14,"dd mmmm yyyy"))&" - "&IF(B2,TEXT(EDATE(B3,15)-1,"dd mmmm yyyy"),TEXT(B3+(((B5-B3)*15)+14),"dd mmmm yyyy")) -> 20 June 2025 - 19 July 2025
A24: =IF(B2,TEXT(EDATE(B3,15),"dd mmmm yyyy"),TEXT(B3+((B5-B3)*15)+15,"dd mmmm yyyy"))&" - "&IF(B2,TEXT(EDATE(B3,16)-1,"dd mmmm yyyy"),TEXT(B3+(((B5-B3)*16)+15),"dd mmmm yyyy")) -> 20 July 2025 - 19 August 2025 | B24: July 2025 - September 2025
A25: =IF(B2,TEXT(EDATE(B3,16),"dd mmmm yyyy"),TEXT(B3+((B5-B3)*16)+16,"dd mmmm yyyy"))&" - "&IF(B2,TEXT(EDATE(B3,17)-1,"dd mmmm yyyy"),TEXT(B3+(((B5-B3)*17)+16),"dd mmmm yyyy")) -> 20 August 2025 - 19 September 2025
A26: =IF(B2,TEXT(EDATE(B3,17),"dd mmmm yyyy"),TEXT(B3+((B5-B3)*17)+17,"dd mmmm yyyy"))&" - "&IF(B2,TEXT(EDATE(B3,18)-1,"dd mmmm yyyy"),TEXT(B3+(((B5-B3)*18)+17),"dd mmmm yyyy")) -> 20 September 2025 - 19 October 2025
A27: =IF(B2,TEXT(EDATE(B3,18),"dd mmmm yyyy"),TEXT(B3+((B5-B3)*18)+18,"dd mmmm yyyy"))&" - "&IF(B2,TEXT(EDATE(B3,19)-1,"dd mmmm yyyy"),TEXT(B3+(((B5-B3)*19)+18),"dd mmmm yyyy")) -> 20 October 2025 - 19 November 2025 | B27: October 2025 - December 2025
A28: =IF(B2,TEXT(EDATE(B3,19),"dd mmmm yyyy"),TEXT(B3+((B5-B3)*19)+19,"dd mmmm yyyy"))&" - "&IF(B2,TEXT(EDATE(B3,20)-1,"dd mmmm yyyy"),TEXT(B3+(((B5-B3)*20)+19),"dd mmmm yyyy")) -> 20 November 2025 - 19 December 2025
A29: =IF(B2,TEXT(EDATE(B3,20),"dd mmmm yyyy"),TEXT(B3+((B5-B3)*20)+20,"dd mmmm yyyy"))&" - "&IF(B2,TEXT(EDATE(B3,21)-1,"dd mmmm yyyy"),TEXT(B3+(((B5-B3)*21)+20),"dd mmmm yyyy")) -> 20 December 2025 - 19 January 2026
A30: =IF(B2,TEXT(EDATE(B3,21),"dd mmmm yyyy"),TEXT(B3+((B5-B3)*21)+21,"dd mmmm yyyy"))&" - "&IF(B2,TEXT(EDATE(B3,22)-1,"dd mmmm yyyy"),TEXT(B3+(((B5-B3)*22)+21),"dd mmmm yyyy")) -> 20 January 2026 - 19 February 2026 | B30: January 2026 - March 2026
A31: =IF(B2,TEXT(EDATE(B3,22),"dd mmmm yyyy"),TEXT(B3+((B5-B3)*22)+22,"dd mmmm yyyy"))&" - "&IF(B2,TEXT(EDATE(B3,23)-1,"dd mmmm yyyy"),TEXT(B3+(((B5-B3)*23)+22),"dd mmmm yyyy")) -> 20 February 2026 - 19 March 2026
A32: =IF(B2,TEXT(EDATE(B3,23),"dd mmmm yyyy"),TEXT(B3+((B5-B3)*23)+23,"dd mmmm yyyy"))&" - "&IF(B2,TEXT(EDATE(B3,24)-1,"dd mmmm yyyy"),TEXT(B3+(((B5-B3)*24)+23),"dd mmmm yyyy")) -> 20 March 2026 - 19 April 2026
A33: =IF(B2,TEXT(EDATE(B3,24),"dd mmmm yyyy"),TEXT(B3+((B5-B3)*24)+24,"dd mmmm yyyy"))&" - "&IF(B2,TEXT(EDATE(B3,25)-1,"dd mmmm yyyy"),TEXT(B3+(((B5-B3)*25)+24),"dd mmmm yyyy")) -> 20 April 2026 - 19 May 2026 | B33: April 2026 - June 2026
A34: =IF(B2,TEXT(EDATE(B3,25),"dd mmmm yyyy"),TEXT(B3+((B5-B3)*25)+25,"dd mmmm yyyy"))&" - "&IF(B2,TEXT(EDATE(B3,26)-1,"dd mmmm yyyy"),TEXT(B3+(((B5-B3)*26)+25),"dd mmmm yyyy")) -> 20 May 2026 - 19 June 2026
A35: =IF(B2,TEXT(EDATE(B3,26),"dd mmmm yyyy"),TEXT(B3+((B5-B3)*26)+26,"dd mmmm yyyy"))&" - "&IF(B2,TEXT(EDATE(B3,27)-1,"dd mmmm yyyy"),TEXT(B3+(((B5-B3)*27)+26),"dd mmmm yyyy")) -> 20 June 2026 - 19 July 2026
A36: =IF(B2,TEXT(EDATE(B3,27),"dd mmmm yyyy"),TEXT(B3+((B5-B3)*27)+27,"dd mmmm yyyy"))&" - "&IF(B2,TEXT(EDATE(B3,28)-1,"dd mmmm yyyy"),TEXT(B3+(((B5-B3)*28)+27),"dd mmmm yyyy")) -> 20 July 2026 - 19 August 2026 | B36: July 2026 - September 2026
A37: =IF(B2,TEXT(EDATE(B3,28),"dd mmmm yyyy"),TEXT(B3+((B5-B3)*28)+28,"dd mmmm yyyy"))&" - "&IF(B2,TEXT(EDATE(B3,29)-1,"dd mmmm yyyy"),TEXT(B3+(((B5-B3)*29)+28),"dd mmmm yyyy")) -> 20 August 2026 - 19 September 2026
A38: =IF(B2,TEXT(EDATE(B3,29),"dd mmmm yyyy"),TEXT(B3+((B5-B3)*29)+29,"dd mmmm yyyy"))&" - "&IF(B2,TEXT(EDATE(B3,30)-1,"dd mmmm yyyy"),TEXT(B3+(((B5-B3)*30)+29),"dd mmmm yyyy")) -> 20 September 2026 - 19 October 2026
A39: =IF(B2,TEXT(EDATE(B3,30),"dd mmmm yyyy"),TEXT(B3+((B5-B3)*30)+30,"dd mmmm yyyy"))&" - "&IF(B2,TEXT(EDATE(B3,31)-1,"dd mmmm yyyy"),TEXT(B3+(((B5-B3)*31)+30),"dd mmmm yyyy")) -> 20 October 2026 - 19 November 2026 | B39: October 2026 - December 2026
A40: =IF(B2,TEXT(EDATE(B3,31),"dd mmmm yyyy"),TEXT(B3+((B5-B3)*31)+31,"dd mmmm yyyy"))&" - "&IF(B2,TEXT(EDATE(B3,32)-1,"dd mmmm yyyy"),TEXT(B3+(((B5-B3)*32)+31),"dd mmmm yyyy")) -> 20 November 2026 - 19 December 2026
A41: =IF(B2,TEXT(EDATE(B3,32),"dd mmmm yyyy"),TEXT(B3+((B5-B3)*32)+32,"dd mmmm yyyy"))&" - "&IF(B2,TEXT(EDATE(B3,33)-1,"dd mmmm yyyy"),TEXT(B3+(((B5-B3)*33)+32),"dd mmmm yyyy")) -> 20 December 2026 - 19 January 2027
A42: =IF(B2,TEXT(EDATE(B3,33),"dd mmmm yyyy"),TEXT(B3+((B5-B3)*33)+33,"dd mmmm yyyy"))&" - "&IF(B2,TEXT(EDATE(B3,34)-1,"dd mmmm yyyy"),TEXT(B3+(((B5-B3)*34)+33),"dd mmmm yyyy")) -> 20 January 2027 - 19 February 2027 | B42: January 2027 - March 2027
A43: =IF(B2,TEXT(EDATE(B3,34),"dd mmmm yyyy"),TEXT(B3+((B5-B3)*34)+34,"dd mmmm yyyy"))&" - "&IF(B2,TEXT(EDATE(B3,35)-1,"dd mmmm yyyy"),TEXT(B3+(((B5-B3)*35)+34),"dd mmmm yyyy")) -> 20 February 2027 - 19 March 2027
A44: =IF(B2,TEXT(EDATE(B3,35),"dd mmmm yyyy"),TEXT(B3+((B5-B3)*35)+35,"dd mmmm yyyy"))&" - "&IF(B2,TEXT(EDATE(B3,36)-1,"dd mmmm yyyy"),TEXT(B3+(((B5-B3)*36)+35),"dd mmmm yyyy")) -> 20 March 2027 - 19 April 2027
A45: =IF(B2,TEXT(EDATE(B3,36),"dd mmmm yyyy"),TEXT(B3+((B5-B3)*36)+36,"dd mmmm yyyy"))&" - "&IF(B2,TEXT(EDATE(B3,37)-1,"dd mmmm yyyy"),TEXT(B3+(((B5-B3)*37)+36),"dd mmmm yyyy")) -> 20 April 2027 - 19 May 2027 | B45: April 2027 - June 2027
A46: =IF(B2,TEXT(EDATE(B3,37),"dd mmmm yyyy"),TEXT(B3+((B5-B3)*37)+37,"dd mmmm yyyy"))&" - "&IF(B2,TEXT(EDATE(B3,38)-1,"dd mmmm yyyy"),TEXT(B3+(((B5-B3)*38)+37),"dd mmmm yyyy")) -> 20 May 2027 - 19 June 2027
A47: =IF(B2,TEXT(EDATE(B3,38),"dd mmmm yyyy"),TEXT(B3+((B5-B3)*38)+38,"dd mmmm yyyy"))&" - "&IF(B2,TEXT(EDATE(B3,39)-1,"dd mmmm yyyy"),TEXT(B3+(((B5-B3)*39)+38),"dd mmmm yyyy")) -> 20 June 2027 - 19 July 2027
A48: =IF(B2,TEXT(EDATE(B3,39),"dd mmmm yyyy"),TEXT(B3+((B5-B3)*39)+39,"dd mmmm yyyy"))&" - "&IF(B2,TEXT(EDATE(B3,40)-1,"dd mmmm yyyy"),TEXT(B3+(((B5-B3)*40)+39),"dd mmmm yyyy")) -> 20 July 2027 - 19 August 2027 | B48: Forecast_14
A49: =IF(B2,TEXT(EDATE(B3,40),"dd mmmm yyyy"),TEXT(B3+((B5-B3)*40)+40,"dd mmmm yyyy"))&" - "&IF(B2,TEXT(EDATE(B3,41)-1,"dd mmmm yyyy"),TEXT(B3+(((B5-B3)*41)+40),"dd mmmm yyyy")) -> 20 August 2027 - 19 September 2027
A50: =IF(B2,TEXT(EDATE(B3,41),"dd mmmm yyyy"),TEXT(B3+((B5-B3)*41)+41,"dd mmmm yyyy"))&" - "&IF(B2,TEXT(EDATE(B3,42)-1,"dd mmmm yyyy"),TEXT(B3+(((B5-B3)*42)+41),"dd mmmm yyyy")) -> 20 September 2027 - 19 October 2027
A51: =IF(B2,TEXT(EDATE(B3,42),"dd mmmm yyyy"),TEXT(B3+((B5-B3)*42)+42,"dd mmmm yyyy"))&" - "&IF(B2,TEXT(EDATE(B3,43)-1,"dd mmmm yyyy"),TEXT(B3+(((B5-B3)*43)+42),"dd mmmm yyyy")) -> 20 October 2027 - 19 November 2027 | B51: Forecast_15
A52: =IF(B2,TEXT(EDATE(B3,43),"dd mmmm yyyy"),TEXT(B3+((B5-B3)*43)+43,"dd mmmm yyyy"))&" - "&IF(B2,TEXT(EDATE(B3,44)-1,"dd mmmm yyyy"),TEXT(B3+(((B5-B3)*44)+43),"dd mmmm yyyy")) -> 20 November 2027 - 19 December 2027
A53: =IF(B2,TEXT(EDATE(B3,44),"dd mmmm yyyy"),TEXT(B3+((B5-B3)*44)+44,"dd mmmm yyyy"))&" - "&IF(B2,TEXT(EDATE(B3,45)-1,"dd mmmm yyyy"),TEXT(B3+(((B5-B3)*45)+44),"dd mmmm yyyy")) -> 20 December 2027 - 19 January 2028
A54: =IF(B2,TEXT(EDATE(B3,45),"dd mmmm yyyy"),TEXT(B3+((B5-B3)*45)+45,"dd mmmm yyyy"))&" - "&IF(B2,TEXT(EDATE(B3,46)-1,"dd mmmm yyyy"),TEXT(B3+(((B5-B3)*46)+45),"dd mmmm yyyy")) -> 20 January 2028 - 19 February 2028 | B54: Forecast_16
A55: =IF(B2,TEXT(EDATE(B3,46),"dd mmmm yyyy"),TEXT(B3+((B5-B3)*46)+46,"dd mmmm yyyy"))&" - "&IF(B2,TEXT(EDATE(B3,47)-1,"dd mmmm yyyy"),TEXT(B3+(((B5-B3)*47)+46),"dd mmmm yyyy")) -> 20 February 2028 - 19 March 2028
A56: =IF(B2,TEXT(EDATE(B3,47),"dd mmmm yyyy"),TEXT(B3+((B5-B3)*47)+47,"dd mmmm yyyy"))&" - "&IF(B2,TEXT(EDATE(B3,48)-1,"dd mmmm yyyy"),TEXT(B3+(((B5-B3)*48)+47),"dd mmmm yyyy")) -> 20 March 2028 - 19 April 2028

Sheet April 2024 - June 2024
A1: ="Forecasts For the Year "&TEXT(Main!B3,"mmmm yyyy")&" to "&IF(Main!B2,TEXT(EDATE(Main!B3,3)-1,"mmmm yyyy"),TEXT(Main!B3+((Main!B5-Main!B3)*3+2),"mmmm yyyy")) -> Forecasts For the Year April 2024 to July 2024 | I1: Monthly Balance | M1: Quarterly Debts
A2: Current | D2: Previous | I2: Date | J2: Last Balance | M2: Quarter | N2: Debts Amount
A3: Assets | B3: HSBC Bank Account | C3: 875.3 | D3: Assets | E3: HSBC Bank Account | F3: 875.3 | I3: =TEXT(Main!B3,"dd mmmm yyyy")&" - "&IF(Main!B2,TEXT(EDATE(Main!B3,1)-1,"dd mmmm yyyy"),TEXT(Main!B3+(Main!B5-Main!B3)*1,"dd mmmm yyyy")) -> 20 April 2024 - 19 May 2024 | J3: =E149 -> 0 | M3: =TEXT(Main!B3,"dd mmmm yyyy")&" - "&IF(Main!B2,TEXT(EDATE(Main!B3,3)-1,"dd mmmm yyyy"),TEXT(Main!B3+((Main!B5-Main!B3)*3+2),"dd mmmm yyyy")) -> 20 April 2024 - 19 July 2024 | N3: =-C122 -> -24333
B4: cash | C4: 120 | E4: cash | F4: 120 | I4: =IF(Main!B2,TEXT(EDATE(Main!B3,1),"dd mmmm yyyy"),TEXT(Main!B3+(Main!B5-Main!B3)+1,"dd mmmm yyyy"))&" - "&IF(Main!B2,TEXT(EDATE(Main!B3,2)-1,"dd mmmm yyyy"),TEXT(Main!B3+(Main!B5-Main!B3)*2+1,"dd mmmm yyyy")) -> 20 May 2024 - 19 June 2024 | J4: =E176 -> -416.68 | M4: =IF(Main!B2,TEXT(EDATE(Main!B3,3),"dd mmmm yyyy"),TEXT(Main!B3+((Main!B5-Main!B3)*3+3),"dd mmmm yyyy"))&" - "&IF(Main!B2,TEXT(EDATE(Main!B3,6)-1,"dd mmmm yyyy"),TEXT(Main!B3+((Main!B5-Main!B3)*6+5),"dd mmmm yyyy")) -> 20 July 2024 - 19 October 2024 | N4: ='July 2024 - September 2024'!C5 -> -11683
B5: Unit Trusts / Charity Trusts | C5: 0 | E5: Unit Trusts / Charity Trusts | F5: 0 | I5: =IF(Main!B2,TEXT(EDATE(Main!B3,2),"dd mmmm yyyy"),TEXT(Main!B3+((Main!B5-Main!B3)*2)+2,"dd mmmm yyyy"))&" - "&IF(Main!B2,TEXT(EDATE(Main!B3,3)-1,"dd mmmm yyyy"),TEXT(Main!B3+((Main!B5-Main!B3)*3+2),"dd mmmm yyyy")) -> 20 June 2024 - 19 July 2024 | J5: =E203 -> 3260.12 | M5: =IF(Main!B2,TEXT(EDATE(Main!B3,6),"dd mmmm yyyy"),TEXT(Main!B3+((Main!B5-Main!B3)*6+6),"dd mmmm yyyy"))&" - "&IF(Main!B2,TEXT(EDATE(Main!B3,9)-1,"dd mmmm yyyy"),TEXT(Main!B3+((Main!B5-Main!B3)*9+8),"dd mmmm yyyy")) -> 20 October 2024 - 19 January 2025 | N5: ='October 2024 - December 2024'!C5 -> -10683
B6: Bank Cheque From Tax | C6: 0 | E6: Bank Cheque From Tax | F6: 0 | I6: =IF(Main!B2,TEXT(EDATE(Main!B3,3),"dd mmmm yyyy"),TEXT(Main!B3+((Main!B5-Main!B3)*3)+3,"dd mmmm yyyy"))&" - "&IF(Main!B2,TEXT(EDATE(Main!B3,4)-1,"dd mmmm yyyy"),TEXT(Main!B3+((Main!B5-Main!B3)*4+3),"dd mmmm yyyy")) -> 20 July 2024 - 19 August 2024 | J6: ='July 2024 - September 2024'!E136 -> 699.84 | M6: =IF(Main!B2,TEXT(EDATE(Main!B3,9),"dd mmmm yyyy"),TEXT(Main!B3+((Main!B5-Main!B3)*9+9),"dd mmmm yyyy"))&" - "&IF(Main!B2,TEXT(EDATE(Main!B3,12)-1,"dd mmmm yyyy"),TEXT(Main!B3+((Main!B5-Main!B3)*12+11),"dd mmmm yyyy")) -> 20 January 2025 - 19 April 2025 | N6: ='January 2025 - March 2025'!C5 -> -6983
B7: Payment System (Alipay) | C7: 0 | E7: Payment System (Alipay) | F7: 0 | I7: =IF(Main!B2,TEXT(EDATE(Main!B3,4),"dd mmmm yyyy"),TEXT(Main!B3+((Main!B5-Main!B3)*4)+4,"dd mmmm yyyy"))&" - "&IF(Main!B2,TEXT(EDATE(Main!B3,5)-1,"dd mmmm yyyy"),TEXT(Main!B3+((Main!B5-Main!B3)*5+4),"dd mmmm yyyy")) -> 20 August 2024 - 19 September 2024 | J7: ='July 2024 - September 2024'!E163 -> 625.07 | M7: =IF(Main!B2,TEXT(EDATE(Main!B3,12),"dd mmmm yyyy"),TEXT(Main!B3+((Main!B5-Main!B3)*12+12),"dd mmmm yyyy"))&" - "&IF(Main!B2,TEXT(EDATE(Main!B3,15)-1,"dd mmmm yyyy"),TEXT(Main!B3+((Main!B5-Main!B3)*15+14),"dd mmmm yyyy")) -> 20 April 2025 - 19 July 2025 | N7: ='April 2025 - June 2025'!C5 -> -3083
B8: Payment System (internet) | C8: 0 | E8: Payment System (internet) | F8: 0 | I8: =IF(Main!B2,TEXT(EDATE(Main!B3,5),"dd mmmm yyyy"),TEXT(Main!B3+((Main!B5-Main!B3)*5)+5,"dd mmmm yyyy"))&" - "&IF(Main!B2,TEXT(EDATE(Main!B3,6)-1,"dd mmmm yyyy"),TEXT(Main!B3+((Main!B5-Main!B3)*6+5),"dd mmmm yyyy")) -> 20 September 2024 - 19 October 2024 | J8: ='July 2024 - September 2024'!E190 -> 502.71 | M8: =IF(Main!B2,TEXT(EDATE(Main!B3,15),"dd mmmm yyyy"),TEXT(Main!B3+((Main!B5-Main!B3)*15+15),"dd mmmm yyyy"))&" - "&IF(Main!B2,TEXT(EDATE(Main!B3,18)-1,"dd mmmm yyyy"),TEXT(Main!B3+((Main!B5-Main!B3)*18+17),"dd mmmm yyyy")) -> 20 July 2025 - 19 October 2025 | N8: ='July 2025 - September 2025'!C5 -> 0
B9: Fixed Assest Properties / Data Centers | C9: 0 | E9: Fixed Assest Properties / Data Centers | F9: 0 | I9: =IF(Main!B2,TEXT(EDATE(Main!B3,6),"dd mmmm yyyy"),TEXT(Main!B3+((Main!B5-Main!B3)*6)+6,"dd mmmm yyyy"))&" - "&IF(Main!B2,TEXT(EDATE(Main!B3,7)-1,"dd mmmm yyyy"),TEXT(Main!B3+((Main!B5-Main!B3)*7+6),"dd mmmm yyyy")) -> 20 October 2024 - 19 November 2024 | J9: ='October 2024 - December 2024'!E136 -> 125.16 | M9: =IF(Main!B2,TEXT(EDATE(Main!B3,18),"dd mmmm yyyy"),TEXT(Main!B3+((Main!B5-Main!B3)*18+18),"dd mmmm yyyy"))&" - "&IF(Main!B2,TEXT(EDATE(Main!B3,21)-1,"dd mmmm yyyy"),TEXT(Main!B3+((Main!B5-Main!B3)*21+20),"dd mmmm yyyy")) -> 20 October 2025 - 19 January 2026 | N9: ='October 2025 - December 2025'!C5 -> 0
B10: Removable Assets | C10: 0 | E10: Removable Assets | F10: 0 | I10: =IF(Main!B2,TEXT(EDATE(Main!B3,7),"dd mmmm yyyy"),TEXT(Main!B3+((Main!B5-Main!B3)*7)+7,"dd mmmm yyyy"))&" - "&IF(Main!B2,TEXT(EDATE(Main!B3,8)-1,"dd mmmm yyyy"),TEXT(Main!B3+((Main!B5-Main!B3)*8+7),"dd mmmm yyyy")) -> 20 November 2024 - 19 December 2024 | J10: ='October 2024 - December 2024'!E163 -> 229.4 | M10: =IF(Main!B2,TEXT(EDATE(Main!B3,21),"dd mmmm yyyy"),TEXT(Main!B3+((Main!B5-Main!B3)*21+21),"dd mmmm yyyy"))&" - "&IF(Main!B2,TEXT(EDATE(Main!B3,24)-1,"dd mmmm yyyy"),TEXT(Main!B3+((Main!B5-Main!B3)*24+23),"dd mmmm yyyy")) -> 20 January 2026 - 19 April 2026 | N10: ='January 2026 - March 2026'!C5 -> 0
B11: Coins | C11: 7.8 | E11: Coins | F11: 7.8 | I11: =IF(Main!B2,TEXT(EDATE(Main!B3,8),"dd mmmm yyyy"),TEXT(Main!B3+((Main!B5-Main!B3)*8)+8,"dd mmmm yyyy"))&" - "&IF(Main!B2,TEXT(EDATE(Main!B3,9)-1,"dd mmmm yyyy"),TEXT(Main!B3+((Main!B5-Main!B3)*9+8),"dd mmmm yyyy")) -> 20 December 2024 - 19 January 2025 | J11: ='October 2024 - December 2024'!E190 -> 173.34 | M11: =IF(Main!B2,TEXT(EDATE(Main!B3,24),"dd mmmm yyyy"),TEXT(Main!B3+((Main!B5-Main!B3)*24+24),"dd mmmm yyyy"))&" - "&IF(Main!B2,TEXT(EDATE(Main!B3,27)-1,"dd mmmm yyyy"),TEXT(Main!B3+((Main!B5-Main!B3)*27+26),"dd mmmm yyyy")) -> 20 April 2026 - 19 July 2026 | N11: ='April 2026 - June 2026'!C5 -> 0
B12: Google Play (play.google.com/redeem) | C12: 138 | E12: Google Play (play.google.com/redeem) | F12: 2 | I12: =IF(Main!B2,TEXT(EDATE(Main!B3,9),"dd mmmm yyyy"),TEXT(Main!B3+((Main!B5-Main!B3)*9)+9,"dd mmmm yyyy"))&" - "&IF(Main!B2,TEXT(EDATE(Main!B3,10)-1,"dd mmmm yyyy"),TEXT(Main!B3+((Main!B5-Main!B3)*10+9),"dd mmmm yyyy")) -> 20 January 2025 - 19 February 2025 | J12: ='January 2025 - March 2025'!E136 -> 112 | M12: =IF(Main!B2,TEXT(EDATE(Main!B3,27),"dd mmmm yyyy"),TEXT(Main!B3+((Main!B5-Main!B3)*27+27),"dd mmmm yyyy"))&" - "&IF(Main!B2,TEXT(EDATE(Main!B3,30)-1,"dd mmmm yyyy"),TEXT(Main!B3+((Main!B5-Main!B3)*30+29),"dd mmmm yyyy")) -> 20 July 2026 - 19 October 2026 | N12: ='July 2026 - September 2026'!C5 -> 0
B13: yuu / MoneyBack / Bestmart 360 | C13: 0 | E13: yuu / MoneyBack / Bestmart 360 | F13: 0 | I13: =IF(Main!B2,TEXT(EDATE(Main!B3,10),"dd mmmm yyyy"),TEXT(Main!B3+((Main!B5-Main!B3)*10)+10,"dd mmmm yyyy"))&" - "&IF(Main!B2,TEXT(EDATE(Main!B3,11)-1,"dd mmmm yyyy"),TEXT(Main!B3+((Main!B5-Main!B3)*11+10),"dd mmmm yyyy")) -> 20 February 2025 - 19 March 2025 | J13: ='January 2025 - March 2025'!E163 -> 355.2 | M13: =IF(Main!B2,TEXT(EDATE(Main!B3,30),"dd mmmm yyyy"),TEXT(Main!B3+((Main!B5-Main!B3)*30+30),"dd mmmm yyyy"))&" - "&IF(Main!B2,TEXT(EDATE(Main!B3,33)-1,"dd mmmm yyyy"),TEXT(Main!B3+((Main!B5-Main!B3)*33+32),"dd mmmm yyyy")) -> 20 October 2026 - 19 January 2027 | N13: ='October 2026 - December 2026'!C5 -> 0
B14: Octopus Remain Value | C14: 30.4 | E14: Octopus Remain Value | F14: 30.4 | I14: =IF(Main!B2,TEXT(EDATE(Main!B3,11),"dd mmmm yyyy"),TEXT(Main!B3+((Main!B5-Main!B3)*11)+11,"dd mmmm yyyy"))&" - "&IF(Main!B2,TEXT(EDATE(Main!B3,12)-1,"dd mmmm yyyy"),TEXT(Main!B3+((Main!B5-Main!B3)*12+11),"dd mmmm yyyy")) -> 20 March 2025 - 19 April 2025 | J14: ='January 2025 - March 2025'!E190 -> 166.5 | M14: =IF(Main!B2,TEXT(EDATE(Main!B3,33),"dd mmmm yyyy"),TEXT(Main!B3+((Main!B5-Main!B3)*33+33),"dd mmmm yyyy"))&" - "&IF(Main!B2,TEXT(EDATE(Main!B3,36)-1,"dd mmmm yyyy"),TEXT(Main!B3+((Main!B5-Main!B3)*36+35),"dd mmmm yyyy")) -> 20 January 2027 - 19 April 2027 | N14: ='January 2027 - March 2027'!C5 -> 0
B15: Starbucks Gold Card | C15: 10 | E15: Starbucks Gold Card | F15: 10 | I15: =IF(Main!B2,TEXT(EDATE(Main!B3,12),"dd mmmm yyyy"),TEXT(Main!B3+((Main!B5-Main!B3)*12)+12,"dd mmmm yyyy"))&" - "&IF(Main!B2,TEXT(EDATE(Main!B3,13)-1,"dd mmmm yyyy"),TEXT(Main!B3+((Main!B5-Main!B3)*13+12),"dd mmmm yyyy")) -> 20 April 2025 - 19 May 2025 | J15: ='April 2025 - June 2025'!E136 -> 1056.5 | M15: =IF(Main!B2,TEXT(EDATE(Main!B3,36),"dd mmmm yyyy"),TEXT(Main!B3+((Main!B5-Main!B3)*36+36),"dd mmmm yyyy"))&" - "&IF(Main!B2,TEXT(EDATE(Main!B3,39)-1,"dd mmmm yyyy"),TEXT(Main!B3+((Main!B5-Main!B3)*39+38),"dd mmmm yyyy")) -> 20 April 2027 - 19 July 2027 | N15: ='April 2027 - June 2027'!C5 -> 0
B16: Total | C16: =SUM(C3:C15) -> 1181.5 | E16: Total | F16: =SUM(F3:F15) -> 1045.5 | I16: =IF(Main!B2,TEXT(EDATE(Main!B3,13),"dd mmmm yyyy"),TEXT(Main!B3+((Main!B5-Main!B3)*13)+13,"dd mmmm yyyy"))&" - "&IF(Main!B2,TEXT(EDATE(Main!B3,14)-1,"dd mmmm yyyy"),TEXT(Main!B3+((Main!B5-Main!B3)*14+13),"dd mmmm yyyy")) -> 20 May 2025 - 19 June 2025 | J16: ='April 2025 - June 2025'!E163 -> 1207.5 | M16: =IF(Main!B2,TEXT(EDATE(Main!B3,39),"dd mmmm yyyy"),TEXT(Main!B3+((Main!B5-Main!B3)*39+39),"dd mmmm yyyy"))&" - "&IF(Main!B2,TEXT(EDATE(Main!B3,42)-1,"dd mmmm yyyy"),TEXT(Main!B3+((Main!B5-Main!B3)*42+41),"dd mmmm yyyy")) -> 20 July 2027 - 19 October 2027 | N16: =Forecast_14!C5 -> 0
I17: =IF(Main!B2,TEXT(EDATE(Main!B3,14),"dd mmmm yyyy"),TEXT(Main!B3+((Main!B5-Main!B3)*14)+14,"dd mmmm yyyy"))&" - "&IF(Main!B2,TEXT(EDATE(Main!B3,15)-1,"dd mmmm yyyy"),TEXT(Main!B3+((Main!B5-Main!B3)*15+14),"dd mmmm yyyy")) -> 20 June 2025 - 19 July 2025 | J17: ='April 2025 - June 2025'!E190 -> 967.5 | M17: =IF(Main!B2,TEXT(EDATE(Main!B3,42),"dd mmmm yyyy"),TEXT(Main!B3+((Main!B5-Main!B3)*42+42),"dd mmmm yyyy"))&" - "&IF(Main!B2,TEXT(EDATE(Main!B3,45)-1,"dd mmmm yyyy"),TEXT(Main!B3+((Main!B5-Main!B3)*45+44),"dd mmmm yyyy")) -> 20 October 2027 - 19 January 2028 | N17: =Forecast_15!C5 -> 0
I18: =IF(Main!B2,TEXT(EDATE(Main!B3,15),"dd mmmm yyyy"),TEXT(Main!B3+((Main!B5-Main!B3)*15)+15,"dd mmmm yyyy"))&" - "&IF(Main!B2,TEXT(EDATE(Main!B3,16)-1,"dd mmmm yyyy"),TEXT(Main!B3+((Main!B5-Main!B3)*16+15),"dd mmmm yyyy")) -> 20 July 2025 - 19 August 2025 | J18: ='July 2025 - September 2025'!E136 -> 833.5 | M18: =IF(Main!B2,TEXT(EDATE(Main!B3,45),"dd mmmm yyyy"),TEXT(Main!B3+((Main!B5-Main!B3)*45+45),"dd mmmm yyyy"))&" - "&IF(Main!B2,TEXT(EDATE(Main!B3,48)-1,"dd mmmm yyyy"),TEXT(Main!B3+((Main!B5-Main!B3)*48+47),"dd mmmm yyyy")) -> 20 January 2028 - 19 April 2028 | N18: =Forecast_16!C5 -> 0
I19: =IF(Main!B2,TEXT(EDATE(Main!B3,16),"dd mmmm yyyy"),TEXT(Main!B3+((Main!B5-Main!B3)*16)+16,"dd mmmm yyyy"))&" - "&IF(Main!B2,TEXT(EDATE(Main!B3,17)-1,"dd mmmm yyyy"),TEXT(Main!B3+((Main!B5-Main!B3)*17+16),"dd mmmm yyyy")) -> 20 August 2025 - 19 September 2025 | J19: ='July 2025 - September 2025'!E163 -> 843.5
I20: =IF(Main!B2,TEXT(EDATE(Main!B3,17),"dd mmmm yyyy"),TEXT(Main!B3+((Main!B5-Main!B3)*17)+17,"dd mmmm yyyy"))&" - "&IF(Main!B2,TEXT(EDATE(Main!B3,18)-1,"dd mmmm yyyy"),TEXT(Main!B3+((Main!B5-Main!B3)*18+17),"dd mmmm yyyy")) -> 20 September 2025 - 19 October 2025 | J20: ='July 2025 - September 2025'!E190 -> 775.5
I21: =IF(Main!B2,TEXT(EDATE(Main!B3,18),"dd mmmm yyyy"),TEXT(Main!B3+((Main!B5-Main!B3)*18)+18,"dd mmmm yyyy"))&" - "&IF(Main!B2,TEXT(EDATE(Main!B3,19)-1,"dd mmmm yyyy"),TEXT(Main!B3+((Main!B5-Main!B3)*19+18),"dd mmmm yyyy")) -> 20 October 2025 - 19 November 2025 | J21: ='October 2025 - December 2025'!E136 -> 1363.2
A22: =TEXT(Main!B3,"dd mmmm yyyy")&" - "&IF(Main!B2,TEXT(EDATE(Main!B3,1)-1,"dd mmmm yyyy"),TEXT(Main!B3+Main!B5-Main!B3,"dd mmmm yyyy"))&" / "&" (Revenue / Deferred Debts Or Expenses)" -> 20 April 2024 - 19 May 2024 / (Revenue / Deferred Debts Or Expenses) | I22: =IF(Main!B2,TEXT(EDATE(Main!B3,19),"dd mmmm yyyy"),TEXT(Main!B3+((Main!B5-Main!B3)*19)+19,"dd mmmm yyyy"))&" - "&IF(Main!B2,TEXT(EDATE(Main!B3,20)-1,"dd mmmm yyyy"),TEXT(Main!B3+((Main!B5-Main!B3)*20+19),"dd mmmm yyyy")) -> 20 November 2025 - 19 December 2025 | J22: ='October 2025 - December 2025'!E163 -> 2155.9
A23: Date | B23: Name | D23: Description | F23: Amount | I23: =IF(Main!B2,TEXT(EDATE(Main!B3,20),"dd mmmm yyyy"),TEXT(Main!B3+((Main!B5-Main!B3)*20)+20,"dd mmmm yyyy"))&" - "&IF(Main!B2,TEXT(EDATE(Main!B3,21)-1,"dd mmmm yyyy"),TEXT(Main!B3+((Main!B5-Main!B3)*21+20),"dd mmmm yyyy")) -> 20 December 2025 - 19 January 2026 | J23: ='October 2025 - December 2025'!E190 -> 2707.6
A24: 17th January 2025 | B24: Social Welfare | D24: N/A | F24: 2405 | I24: =IF(Main!B2,TEXT(EDATE(Main!B3,21),"dd mmmm yyyy"),TEXT(Main!B3+((Main!B5-Main!B3)*21)+21,"dd mmmm yyyy"))&" - "&IF(Main!B2,TEXT(EDATE(Main!B3,22)-1,"dd mmmm yyyy"),TEXT(Main!B3+((Main!B5-Main!B3)*22+21),"dd mmmm yyyy")) -> 20 January 2026 - 19 February 2026 | J24: ='January 2026 - March 2026'!E136 -> 3550.3
F25: 0 | I25: =IF(Main!B2,TEXT(EDATE(Main!B3,22),"dd mmmm yyyy"),TEXT(Main!B3+((Main!B5-Main!B3)*22)+22,"dd mmmm yyyy"))&" - "&IF(Main!B2,TEXT(EDATE(Main!B3,23)-1,"dd mmmm yyyy"),TEXT(Main!B3+((Main!B5-Main!B3)*23+22),"dd mmmm yyyy")) -> 20 February 2026 - 19 March 2026 | J25: ='January 2026 - March 2026'!E163 -> 3942
F26: 0 | I26: =IF(Main!B2,TEXT(EDATE(Main!B3,23),"dd mmmm yyyy"),TEXT(Main!B3+((Main!B5-Main!B3)*23)+23,"dd mmmm yyyy"))&" - "&IF(Main!B2,TEXT(EDATE(Main!B3,24)-1,"dd mmmm yyyy"),TEXT(Main!B3+((Main!B5-Main!B3)*24+23),"dd mmmm yyyy")) -> 20 March 2026 - 19 April 2026 | J26: ='January 2026 - March 2026'!E190 -> 4784.7
F27: 0 | I27: =IF(Main!B2,TEXT(EDATE(Main!B3,24),"dd mmmm yyyy"),TEXT(Main!B3+((Main!B5-Main!B3)*24)+24,"dd mmmm yyyy"))&" - "&IF(Main!B2,TEXT(EDATE(Main!B3,25)-1,"dd mmmm yyyy"),TEXT(Main!B3+((Main!B5-Main!B3)*25+24),"dd mmmm yyyy")) -> 20 April 2026 - 19 May 2026 | J27: ='April 2026 - June 2026'!E136 -> 5336.4
F28: 0 | I28: =IF(Main!B2,TEXT(EDATE(Main!B3,25),"dd mmmm yyyy"),TEXT(Main!B3+((Main!B5-Main!B3)*25)+25,"dd mmmm yyyy"))&" - "&IF(Main!B2,TEXT(EDATE(Main!B3,26)-1,"dd mmmm yyyy"),TEXT(Main!B3+((Main!B5-Main!B3)*26+25),"dd mmmm yyyy")) -> 20 May 2026 - 19 June 2026 | J28: ='April 2026 - June 2026'!E163 -> 6019.1
F29: 0 | I29: =IF(Main!B2,TEXT(EDATE(Main!B3,26),"dd mmmm yyyy"),TEXT(Main!B3+((Main!B5-Main!B3)*26)+26,"dd mmmm yyyy"))&" - "&IF(Main!B2,TEXT(EDATE(Main!B3,27)-1,"dd mmmm yyyy"),TEXT(Main!B3+((Main!B5-Main!B3)*27+26),"dd mmmm yyyy")) -> 20 June 2026 - 19 July 2026 | J29: ='April 2026 - June 2026'!E190 -> 6570.8
D30: Total Revenue | F30: =SUM(F24:G29) -> 2405 | I30: =IF(Main!B2,TEXT(EDATE(Main!B3,27),"dd mmmm yyyy"),TEXT(Main!B3+((Main!B5-Main!B3)*27)+27,"dd mmmm yyyy"))&" - "&IF(Main!B2,TEXT(EDATE(Main!B3,28)-1,"dd mmmm yyyy"),TEXT(Main!B3+((Main!B5-Main!B3)*28+27),"dd mmmm yyyy")) -> 20 July 2026 - 19 August 2026 | J30: ='July 2026 - September 2026'!E136 -> 7413.5
I31: =IF(Main!B2,TEXT(EDATE(Main!B3,28),"dd mmmm yyyy"),TEXT(Main!B3+((Main!B5-Main!B3)*28)+28,"dd mmmm yyyy"))&" - "&IF(Main!B2,TEXT(EDATE(Main!B3,29)-1,"dd mmmm yyyy"),TEXT(Main!B3+((Main!B5-Main!B3)*29+28),"dd mmmm yyyy")) -> 20 August 2026 - 19 September 2026 | J31: ='July 2026 - September 2026'!E163 -> 7805.2
I32: =IF(Main!B2,TEXT(EDATE(Main!B3,29),"dd mmmm yyyy"),TEXT(Main!B3+((Main!B5-Main!B3)*29)+29,"dd mmmm yyyy"))&" - "&IF(Main!B2,TEXT(EDATE(Main!B3,30)-1,"dd mmmm yyyy"),TEXT(Main!B3+((Main!B5-Main!B3)*30+29),"dd mmmm yyyy")) -> 20 September 2026 - 19 October 2026 | J32: ='July 2026 - September 2026'!E190 -> 8585
I33: =IF(Main!B2,TEXT(EDATE(Main!B3,30),"dd mmmm yyyy"),TEXT(Main!B3+((Main!B5-Main!B3)*30)+30,"dd mmmm yyyy"))&" - "&IF(Main!B2,TEXT(EDATE(Main!B3,31)-1,"dd mmmm yyyy"),TEXT(Main!B3+((Main!B5-Main!B3)*31+30),"dd mmmm yyyy")) -> 20 October 2026 - 19 November 2026 | J33: ='October 2026 - December 2026'!E136 -> 9136.7
A34: =IF(Main!B2,TEXT(EDATE(Main!B3,1),"dd mmmm yyyy"),TEXT(Main!B3+(Main!B5-Main!B3)+1,"dd mmmm yyyy"))&" - "&IF(Main!B2,TEXT(EDATE(Main!B3,2)-1,"dd mmmm yyyy"),TEXT(Main!B3+(Main!B5-Main!B3)*2+1,"dd mmmm yyyy"))&" (Revenue / Deferred Debts Or Expenses)" -> 20 May 2024 - 19 June 2024 (Revenue / Deferred Debts Or Expenses) | I34: =IF(Main!B2,TEXT(EDATE(Main!B3,31),"dd mmmm yyyy"),TEXT(Main!B3+((Main!B5-Main!B3)*31)+31,"dd mmmm yyyy"))&" - "&IF(Main!B2,TEXT(EDATE(Main!B3,32)-1,"dd mmmm yyyy"),TEXT(Main!B3+((Main!B5-Main!B3)*32+31),"dd mmmm yyyy")) -> 20 November 2026 - 19 December 2026 | J34: ='October 2026 - December 2026'!E163 -> 9819.4
A35: Date | B35: Name | D35: Description | F35: Amount | I35: =IF(Main!B2,TEXT(EDATE(Main!B3,32),"dd mmmm yyyy"),TEXT(Main!B3+((Main!B5-Main!B3)*32)+32,"dd mmmm yyyy"))&" - "&IF(Main!B2,TEXT(EDATE(Main!B3,33)-1,"dd mmmm yyyy"),TEXT(Main!B3+((Main!B5-Main!B3)*33+32),"dd mmmm yyyy")) -> 20 December 2026 - 19 January 2027 | J35: ='October 2026 - December 2026'!E190 -> 10371.1
A36: 20th May 2024 | B36: Social Welfare | D36: N/A | F36: 2405 | I36: =IF(Main!B2,TEXT(EDATE(Main!B3,33),"dd mmmm yyyy"),TEXT(Main!B3+((Main!B5-Main!B3)*33)+33,"dd mmmm yyyy"))&" - "&IF(Main!B2,TEXT(EDATE(Main!B3,34)-1,"dd mmmm yyyy"),TEXT(Main!B3+((Main!B5-Main!B3)*34+33),"dd mmmm yyyy")) -> 20 January 2027 - 19 February 2027 | J36: ='January 2027 - March 2027'!E136 -> 11213.8
A37: 04th June 2024 | B37: Social Welfare | D37: Additional half month | F37: 1035 | I37: =IF(Main!B2,TEXT(EDATE(Main!B3,34),"dd mmmm yyyy"),TEXT(Main!B3+((Main!B5-Main!B3)*34)+34,"dd mmmm yyyy"))&" - "&IF(Main!B2,TEXT(EDATE(Main!B3,35)-1,"dd mmmm yyyy"),TEXT(Main!B3+((Main!B5-Main!B3)*35+34),"dd mmmm yyyy")) -> 20 February 2027 - 19 March 2027 | J37: ='January 2027 - March 2027'!E163 -> 11605.5
A38: 7th June 2024 | B38: Sosim | D38: Sosim Prepaid | F38: 50 | I38: =IF(Main!B2,TEXT(EDATE(Main!B3,35),"dd mmmm yyyy"),TEXT(Main!B3+((Main!B5-Main!B3)*35)+35,"dd mmmm yyyy"))&" - "&IF(Main!B2,TEXT(EDATE(Main!B3,36)-1,"dd mmmm yyyy"),TEXT(Main!B3+((Main!B5-Main!B3)*36+35),"dd mmmm yyyy")) -> 20 March 2027 - 19 April 2027 | J38: ='January 2027 - March 2027'!E190 -> 12448.2
F39: 0 | I39: =IF(Main!B2,TEXT(EDATE(Main!B3,36),"dd mmmm yyyy"),TEXT(Main!B3+((Main!B5-Main!B3)*36)+36,"dd mmmm yyyy"))&" - "&IF(Main!B2,TEXT(EDATE(Main!B3,37)-1,"dd mmmm yyyy"),TEXT(Main!B3+((Main!B5-Main!B3)*37+36),"dd mmmm yyyy")) -> 20 April 2027 - 19 May 2027 | J39: ='April 2027 - June 2027'!E136 -> 12999.9
F40: 0 | I40: =IF(Main!B2,TEXT(EDATE(Main!B3,37),"dd mmmm yyyy"),TEXT(Main!B3+((Main!B5-Main!B3)*37)+37,"dd mmmm yyyy"))&" - "&IF(Main!B2,TEXT(EDATE(Main!B3,38)-1,"dd mmmm yyyy"),TEXT(Main!B3+((Main!B5-Main!B3)*38+37),"dd mmmm yyyy")) -> 20 May 2027 - 19 June 2027 | J40: ='April 2027 - June 2027'!E163 -> 13682.6
F41: 0 | I41: =IF(Main!B2,TEXT(EDATE(Main!B3,38),"dd mmmm yyyy"),TEXT(Main!B3+((Main!B5-Main!B3)*38)+38,"dd mmmm yyyy"))&" - "&IF(Main!B2,TEXT(EDATE(Main!B3,39)-1,"dd mmmm yyyy"),TEXT(Main!B3+((Main!B5-Main!B3)*39+38),"dd mmmm yyyy")) -> 20 June 2027 - 19 July 2027 | J41: ='April 2027 - June 2027'!E190 -> 14234.3
D42: Total Revenue | F42: =SUM(F36:G41) -> 3490 | I42: =IF(Main!B2,TEXT(EDATE(Main!B3,39),"dd mmmm yyyy"),TEXT(Main!B3+((Main!B5-Main!B3)*39)+39,"dd mmmm yyyy"))&" - "&IF(Main!B2,TEXT(EDATE(Main!B3,40)-1,"dd mmmm yyyy"),TEXT(Main!B3+((Main!B5-Main!B3)*40+39),"dd mmmm yyyy")) -> 20 July 2027 - 19 August 2027 | J42: =Forecast_14!E136 -> 14234.3
I43: =IF(Main!B2,TEXT(EDATE(Main!B3,40),"dd mmmm yyyy"),TEXT(Main!B3+((Main!B5-Main!B3)*40)+40,"dd mmmm yyyy"))&" - "&IF(Main!B2,TEXT(EDATE(Main!B3,41)-1,"dd mmmm yyyy"),TEXT(Main!B3+((Main!B5-Main!B3)*41+40),"dd mmmm yyyy")) -> 20 August 2027 - 19 September 2027 | J43: =Forecast_14!E163 -> 14234.3
I44: =IF(Main!B2,TEXT(EDATE(Main!B3,41),"dd mmmm yyyy"),TEXT(Main!B3+((Main!B5-Main!B3)*41)+41,"dd mmmm yyyy"))&" - "&IF(Main!B2,TEXT(EDATE(Main!B3,42)-1,"dd mmmm yyyy"),TEXT(Main!B3+((Main!B5-Main!B3)*42+41),"dd mmmm yyyy")) -> 20 September 2027 - 19 October 2027 | J44: =Forecast_14!E190 -> 14234.3
I45: =IF(Main!B2,TEXT(EDATE(Main!B3,42),"dd mmmm yyyy"),TEXT(Main!B3+((Main!B5-Main!B3)*42)+42,"dd mmmm yyyy"))&" - "&IF(Main!B2,TEXT(EDATE(Main!B3,43)-1,"dd mmmm yyyy"),TEXT(Main!B3+((Main!B5-Main!B3)*43+42),"dd mmmm yyyy")) -> 20 October 2027 - 19 November 2027 | J45: =Forecast_15!E136 -> 14234.3
A46: =IF(Main!B2,TEXT(EDATE(Main!B3,2),"dd mmmm yyyy"),TEXT(Main!B3+((Main!B5-Main!B3)*2)+2,"dd mmmm yyyy"))&" - "&IF(Main!B2,TEXT(EDATE(Main!B3,3)-1,"dd mmmm yyyy"),TEXT(Main!B3+((Main!B5-Main!B3)*3+2),"dd mmmm yyyy"))&" (Revenue / Deferred Debts Or Expenses)" -> 20 June 2024 - 19 July 2024 (Revenue / Deferred Debts Or Expenses) | I46: =IF(Main!B2,TEXT(EDATE(Main!B3,43),"dd mmmm yyyy"),TEXT(Main!B3+((Main!B5-Main!B3)*43)+43,"dd mmmm yyyy"))&" - "&IF(Main!B2,TEXT(EDATE(Main!B3,44)-1,"dd mmmm yyyy"),TEXT(Main!B3+((Main!B5-Main!B3)*44+43),"dd mmmm yyyy")) -> 20 November 2027 - 19 December 2027 | J46: =Forecast_15!E163 -> 14234.3
A47: Date | B47: Name | D47: Description | F47: Amount | I47: =IF(Main!B2,TEXT(EDATE(Main!B3,44),"dd mmmm yyyy"),TEXT(Main!B3+((Main!B5-Main!B3)*44)+44,"dd mmmm yyyy"))&" - "&IF(Main!B2,TEXT(EDATE(Main!B3,45)-1,"dd mmmm yyyy"),TEXT(Main!B3+((Main!B5-Main!B3)*45+44),"dd mmmm yyyy")) -> 20 December 2027 - 19 January 2028 | J47: =Forecast_15!E190 -> 14234.3
A48: 18th June 2024 | B48: Google Play Store Add in Value | D48: Add in Value Used For Sportify Monthly Fee | F48: 150 | I48: =IF(Main!B2,TEXT(EDATE(Main!B3,45),"dd mmmm yyyy"),TEXT(Main!B3+((Main!B5-Main!B3)*45)+45,"dd mmmm yyyy"))&" - "&IF(Main!B2,TEXT(EDATE(Main!B3,46)-1,"dd mmmm yyyy"),TEXT(Main!B3+((Main!B5-Main!B3)*46+45),"dd mmmm yyyy")) -> 20 January 2028 - 19 February 2028 | J48: =Forecast_16!E136 -> 14234.3
A49: 20th June 2024 | B49: Social Welfare | D49: N/A | F49: 2405 | I49: =IF(Main!B2,TEXT(EDATE(Main!B3,46),"dd mmmm yyyy"),TEXT(Main!B3+((Main!B5-Main!B3)*46)+46,"dd mmmm yyyy"))&" - "&IF(Main!B2,TEXT(EDATE(Main!B3,47)-1,"dd mmmm yyyy"),TEXT(Main!B3+((Main!B5-Main!B3)*47+46),"dd mmmm yyyy")) -> 20 February 2028 - 19 March 2028 | J49: =Forecast_16!E163 -> 14234.3
A50: 24th June 2024 | B50: Salary | D50: Salary From 24th June to End Of June - No MPF Deduction (not over 3 months) | F50: 7700 | I50: =IF(Main!B2,TEXT(EDATE(Main!B3,47),"dd mmmm yyyy"),TEXT(Main!B3+((Main!B5-Main!B3)*47)+47,"dd mmmm yyyy"))&" - "&IF(Main!B2,TEXT(EDATE(Main!B3,48)-1,"dd mmmm yyyy"),TEXT(Main!B3+((Main!B5-Main!B3)*48+47),"dd mmmm yyyy")) -> 20 March 2028 - 19 April 2028 | J50: =Forecast_16!E190 -> 14234.3
A51: 15th July 2024 15th July 2024 | B51: Prepaid HGC BroadBand - $204 Prepaid China Mobile - $207.5 | F51: 411.5
A52: 15th July 2024 | B52: Last Salary | D52: End Of Service - Last Salary Paid On 15th July 2024 | F52: 9350
F53: 0
D54: Total Revenue | F54: =SUM(F48:G53) -> 20016.5
A58: ="Fixed Expense For the Year "&TEXT(Main!B3,"mmmm yyyy")&" - "&IF(Main!B2,TEXT(EDATE(Main!B3,3)-1,"mmmm yyyy"),TEXT(Main!B3+((Main!B5-Main!B3)*3+2),"mmmm yyyy")) -> Fixed Expense For the Year April 2024 - July 2024
A59: Name | B59: Description | C59: Amount
A60: Mobile And Communications/ Housing Expenses
A61: Broadband | C61: 204
A62: China Mobile | C62: 197
A63: Telephone (Fixed Line) | C63: 0
A64: Sosim | C64: 42
A65: Birdie Sim Card Pay date (7th Of Each Month) | C65: 0
C66: 0
C67: 0
C68: 0
B69: Total Expenses | C69: =SUM(C61:C68) -> 443
A70: Credit Card Installments/Government Installments
A71: Citi Bank | C71: 0
A72: SC Bank | C72: 0
A73: Bank Of China | C73: 0
A74: HSBC | C74: 0
C75: 0
C76: 0
C77: 0
C78: 0
C79: 0
B80: Total Expenses | C80: =SUM(C71:C79) -> 0
A81: Donation
A82: Traversy | B82: Traversy Media | C82: 0
A83: Orbis | B83: Orbis Eye Flight | C83: 0
C84: 0
C85: 0
C86: 0
C87: 0
C88: 0
B89: Total Expenses | C89: =SUM(C82:C88) -> 0
A90: Insurance (Personal / Properties / Medical)
A91: AIA | C91: 0
C92: 0
C93: 0
C94: 0
C95: 0
C96: 0
C97: 0
C98: 0
B99: Total Expenses | C99: =SUM(C91:C98) -> 0
A100: Other Expenses
A101: Other Stuff | B101: Food, Transport…. | C101: 300
A102: Entertainment | B102: Sportify Music / Changed to Apple Music on 13th May 2025 | C102: 0
A103: Hair Cutting | B103: Hair Cut not Include Color treatment | C103: 0
...

Sheet July 2024 - September 2024
A1: ="Forecasts For the Year "&IF(Main!B2,TEXT(EDATE(Main!B3,3),"mmmm yyyy"),TEXT(Main!B3+((Main!B5-Main!B3)*3+3),"mmmm yyyy"))&" to "&IF(Main!B2,TEXT(EDATE(Main!B3,6)-1,"mmmm yyyy"),TEXT(Main!B3+((Main!B5-Main!B3)*6+5),"mmmm yyyy")) -> Forecasts For the Year July 2024 to October 2024
A2: Assets | B2: Overall | C2: {=INDIRECT("'"&Main!B9&"'!$C$16")} -> 1181.5
B3: Forecasts | C3: =E190 -> 502.71
A4: Total | C4: =SUM(C2:G3) -> 1684.21
A5: Net Debts: | C5: =C108 -> -11683
A8: =IF(Main!B2,TEXT(EDATE(Main!B3,3),"dd mmmm yyyy"),TEXT(Main!B3+((Main!B5-Main!B3)*3+3),"dd mmmm yyyy"))&" - "&IF(Main!B2,TEXT(EDATE(Main!B3,4)-1,"dd mmmm yyyy"),TEXT(Main!B3+((Main!B5-Main!B3)*4+3),"dd mmmm yyyy"))&" / "&" (Revenue / Deferred Debts Or Expenses)" -> 20 July 2024 - 19 August 2024 / (Revenue / Deferred Debts Or Expenses)
A9: Date | B9: Name | D9: Description | F9: Amount
A10: 20th July 2024 | B10: Social Welfare | D10: N/A | F10: 2405
B11: Balance the expense for Hair Cutting And Bleaching | F11: 27
B12: Original Expense Hair Cutting And Bleaching Expense is $62 | F12: 17
A13: 12th August 2024 | B13: Borrowed $1500 From Lawrence | F13: 1500
F14: 0
F15: 0
D16: Total Revenue | F16: =SUM(F10:G15) -> 3949
A20: =IF(Main!B2,TEXT(EDATE(Main!B3,4),"dd mmmm yyyy"),TEXT(Main!B3+((Main!B5-Main!B3)*4+4),"dd mmmm yyyy"))&" - "&IF(Main!B2,TEXT(EDATE(Main!B3,5)-1,"dd mmmm yyyy"),TEXT(Main!B3+((Main!B5-Main!B3)*5+4),"dd mmmm yyyy"))&" / "&" (Revenue / Deferred Debts Or Expenses)" -> 20 August 2024 - 19 September 2024 / (Revenue / Deferred Debts Or Expenses)
A21: Date | B21: Name | D21: Description | F21: Amount
A22: 16th August 2024 16th August 2024 1st September 2024 | B22: 1. HGC BroadBand Fee 2. China Mobile Fee 3. Broadband | D22: 1. Last Payment Prepaid HGC Broadband Fee ~ $204 2. Prepaid China Mobile Fee ~ $ $207.5 3. Switch to China Mobile Broadband | F22: 411.5
A23: 17th August 2024 | B23: 30 Packet of Cigarette | D23: Prepaid Cigarette Fee | F23: 900
A24: 20th August 2024 | B24: Social Welfare | D24: N/A | F24: 2405
B25: Original Expense Hair Cutting And Bleaching Expense is $62 | F25: 17
B26: Balance the expense for Hair Cutting And Bleaching | F26: 27
A27: 31st August 2024 | B27: Salary | D27: Deduct 5% MPF | F27: 0
D28: Total Revenue | F28: =SUM(F22:G27) -> 3760.5
A32: =IF(Main!B2,TEXT(EDATE(Main!B3,5),"dd mmmm yyyy"),TEXT(Main!B3+((Main!B5-Main!B3)*5+5),"dd mmmm yyyy"))&" - "&IF(Main!B2,TEXT(EDATE(Main!B3,6)-1,"dd mmmm yyyy"),TEXT(Main!B3+((Main!B5-Main!B3)*6+5),"dd mmmm yyyy"))&" / "&" (Revenue / Deferred Debts Or Expenses)" -> 20 September 2024 - 19 October 2024 / (Revenue / Deferred Debts Or Expenses)
A33: Date | B33: Name | D33: Description | F33: Amount
A34: 20th September 2024 | B34: Salary | D34: Deduct 5% MPF | F34: 0
B35: Food And Transport Expense Switched to $600 to $330 | F35: 270
A36: 20th September 2024 | B36: Social Welfare | D36: N/A | F36: 2405
B37: HGC BroadBand End Of Service | F37: 204
A38: 20th September 2024 | B38: Cancel Color Treatment | F38: 27
A39: 21th September 2024 21th September 2024 6th October 2024 | B39: 1. Birthday Present From Lawrence - $1000 2. $100 From Lawrence 3. $500 From Lawrence 4. Sell Safe to Mom | D39: 2. Receive $100 HKD from Lawrence, no need to return back 3. Help Lawrence to print, scan the documents and export to PDF. 4. Sell Safe to Mom of the price $800 | F39: 2400
D40: Total Revenue | F40: =SUM(F34:G39) -> 5306
A44: ="Fixed Expense For the Year "&IF(Main!B2,TEXT(EDATE(Main!B3,3),"mmmm yyyy"),TEXT(Main!B3+((Main!B5-Main!B3)*3+3),"mmmm yyyy"))&" to "&IF(Main!B2,TEXT(EDATE(Main!B3,6)-1,"mmmm yyyy"),TEXT(Main!B3+((Main!B5-Main!B3)*6+5),"mmmm yyyy")) -> Fixed Expense For the Year July 2024 to October 2024
A45: Name | B45: Description | C45: Amount
A46: {=IF((INDIRECT("'"&INDIRECT("Main!B9")&"'!A60"))=0,"",(INDIRECT("'"&INDIRECT("Main!B9")&"'!A60")))} -> Mobile And Communications/ Housing Expenses
A47: {=IF((INDIRECT("'"&INDIRECT("Main!B9")&"'!A61"))=0,"",(INDIRECT("'"&INDIRECT("Main!B9")&"'!A61")))} -> Broadband | B47: {=IF((INDIRECT("'"&INDIRECT("Main!B9")&"'!B61"))=0,"",(INDIRECT("'"&INDIRECT("Main!B9")&"'!B61")))} | C47: 204
A48: {=IF((INDIRECT("'"&INDIRECT("Main!B9")&"'!A62"))=0,"",(INDIRECT("'"&INDIRECT("Main!B9")&"'!A62")))} -> China Mobile | B48: {=IF((INDIRECT("'"&INDIRECT("Main!B9")&"'!B62"))=0,"",(INDIRECT("'"&INDIRECT("Main!B9")&"'!B62")))} | C48: 207.5
A49: {=IF((INDIRECT("'"&INDIRECT("Main!B9")&"'!A63"))=0,"",(INDIRECT("'"&INDIRECT("Main!B9")&"'!A63")))} -> Telephone (Fixed Line) | B49: {=IF((INDIRECT("'"&INDIRECT("Main!B9")&"'!B63"))=0,"",(INDIRECT("'"&INDIRECT("Main!B9")&"'!B63")))} | C49: 0
A50: {=IF((INDIRECT("'"&INDIRECT("Main!B9")&"'!A64"))=0,"",(INDIRECT("'"&INDIRECT("Main!B9")&"'!A64")))} -> Sosim | B50: {=IF((INDIRECT("'"&INDIRECT("Main!B9")&"'!B64"))=0,"",(INDIRECT("'"&INDIRECT("Main!B9")&"'!B64")))} | C50: 0
A51: {=IF((INDIRECT("'"&INDIRECT("Main!B9")&"'!A65"))=0,"",(INDIRECT("'"&INDIRECT("Main!B9")&"'!A65")))} -> Birdie Sim Card Pay date (7th Of Each Month) | B51: {=IF((INDIRECT("'"&INDIRECT("Main!B9")&"'!B65"))=0,"",(INDIRECT("'"&INDIRECT("Main!B9")&"'!B65")))} | C51: 0
A52: {=IF((INDIRECT("'"&INDIRECT("Main!B9")&"'!A66"))=0,"",(INDIRECT("'"&INDIRECT("Main!B9")&"'!A66")))} | B52: {=IF((INDIRECT("'"&INDIRECT("Main!B9")&"'!B66"))=0,"",(INDIRECT("'"&INDIRECT("Main!B9")&"'!B66")))} | C52: 0
A53: {=IF((INDIRECT("'"&INDIRECT("Main!B9")&"'!A67"))=0,"",(INDIRECT("'"&INDIRECT("Main!B9")&"'!A67")))} | B53: {=IF((INDIRECT("'"&INDIRECT("Main!B9")&"'!B67"))=0,"",(INDIRECT("'"&INDIRECT("Main!B9")&"'!B67")))} | C53: 0
A54: {=IF((INDIRECT("'"&INDIRECT("Main!B9")&"'!A68"))=0,"",(INDIRECT("'"&INDIRECT("Main!B9")&"'!A68")))} | B54: {=IF((INDIRECT("'"&INDIRECT("Main!B9")&"'!B68"))=0,"",(INDIRECT("'"&INDIRECT("Main!B9")&"'!B68")))} | C54: 0
B55: Total Expenses | C55: =SUM(C47:C54) -> 411.5
A56: {=IF((INDIRECT("'"&INDIRECT("Main!B9")&"'!A70"))=0,"",(INDIRECT("'"&INDIRECT("Main!B9")&"'!A70")))} -> Credit Card Installments/Government Installments
A57: {=IF((INDIRECT("'"&INDIRECT("Main!B9")&"'!A71"))=0,"",(INDIRECT("'"&INDIRECT("Main!B9")&"'!A71")))} -> Citi Bank | B57: {=IF((INDIRECT("'"&INDIRECT("Main!B9")&"'!B71"))=0,"",(INDIRECT("'"&INDIRECT("Main!B9")&"'!B71")))} | C57: 0
A58: {=IF((INDIRECT("'"&INDIRECT("Main!B9")&"'!A72"))=0,"",(INDIRECT("'"&INDIRECT("Main!B9")&"'!A72")))} -> SC Bank | B58: {=IF((INDIRECT("'"&INDIRECT("Main!B9")&"'!B72"))=0,"",(INDIRECT("'"&INDIRECT("Main!B9")&"'!B72")))} | C58: 0
A59: {=IF((INDIRECT("'"&INDIRECT("Main!B9")&"'!A73"))=0,"",(INDIRECT("'"&INDIRECT("Main!B9")&"'!A73")))} -> Bank Of China | B59: {=IF((INDIRECT("'"&INDIRECT("Main!B9")&"'!B73"))=0,"",(INDIRECT("'"&INDIRECT("Main!B9")&"'!B73")))} | C59: 0
A60: {=IF((INDIRECT("'"&INDIRECT("Main!B9")&"'!A74"))=0,"",(INDIRECT("'"&INDIRECT("Main!B9")&"'!A74")))} -> HSBC | B60: {=IF((INDIRECT("'"&INDIRECT("Main!B9")&"'!B74"))=0,"",(INDIRECT("'"&INDIRECT("Main!B9")&"'!B74")))} | C60: 0
A61: {=IF((INDIRECT("'"&INDIRECT("Main!B9")&"'!A75"))=0,"",(INDIRECT("'"&INDIRECT("Main!B9")&"'!A75")))} | B61: {=IF((INDIRECT("'"&INDIRECT("Main!B9")&"'!B75"))=0,"",(INDIRECT("'"&INDIRECT("Main!B9")&"'!B75")))} | C61: 0
A62: {=IF((INDIRECT("'"&INDIRECT("Main!B9")&"'!A76"))=0,"",(INDIRECT("'"&INDIRECT("Main!B9")&"'!A76")))} | B62: {=IF((INDIRECT("'"&INDIRECT("Main!B9")&"'!B76"))=0,"",(INDIRECT("'"&INDIRECT("Main!B9")&"'!B76")))} | C62: 0
A63: {=IF((INDIRECT("'"&INDIRECT("Main!B9")&"'!A77"))=0,"",(INDIRECT("'"&INDIRECT("Main!B9")&"'!A77")))} | B63: {=IF((INDIRECT("'"&INDIRECT("Main!B9")&"'!B77"))=0,"",(INDIRECT("'"&INDIRECT("Main!B9")&"'!B77")))} | C63: 0
A64: {=IF((INDIRECT("'"&INDIRECT("Main!B9")&"'!A78"))=0,"",(INDIRECT("'"&INDIRECT("Main!B9")&"'!A78")))} | B64: {=IF((INDIRECT("'"&INDIRECT("Main!B9")&"'!B78"))=0,"",(INDIRECT("'"&INDIRECT("Main!B9")&"'!B78")))} | C64: 0
A65: {=IF((INDIRECT("'"&INDIRECT("Main!B9")&"'!A79"))=0,"",(INDIRECT("'"&INDIRECT("Main!B9")&"'!A79")))} | B65: {=IF((INDIRECT("'"&INDIRECT("Main!B9")&"'!B79"))=0,"",(INDIRECT("'"&INDIRECT("Main!B9")&"'!B79")))} | C65: 0
B66: Total Expenses | C66: =SUM(C57:C65) -> 0
A67: {=IF((INDIRECT("'"&INDIRECT("Main!B9")&"'!A81"))=0,"",(INDIRECT("'"&INDIRECT("Main!B9")&"'!A81")))} -> Donation
A68: {=IF((INDIRECT("'"&INDIRECT("Main!B9")&"'!A82"))=0,"",(INDIRECT("'"&INDIRECT("Main!B9")&"'!A82")))} -> Traversy | B68: {=IF((INDIRECT("'"&INDIRECT("Main!B9")&"'!B82"))=0,"",(INDIRECT("'"&INDIRECT("Main!B9")&"'!B82")))} -> Traversy Media | C68: 0
A69: {=IF((INDIRECT("'"&INDIRECT("Main!B9")&"'!A83"))=0,"",(INDIRECT("'"&INDIRECT("Main!B9")&"'!A83")))} -> Orbis | B69: {=IF((INDIRECT("'"&INDIRECT("Main!B9")&"'!B83"))=0,"",(INDIRECT("'"&INDIRECT("Main!B9")&"'!B83")))} -> Orbis Eye Flight | C69: 0
A70: {=IF((INDIRECT("'"&INDIRECT("Main!B9")&"'!A84"))=0,"",(INDIRECT("'"&INDIRECT("Main!B9")&"'!A84")))} | B70: {=IF((INDIRECT("'"&INDIRECT("Main!B9")&"'!B84"))=0,"",(INDIRECT("'"&INDIRECT("Main!B9")&"'!B84")))} | C70: 0
A71: {=IF((INDIRECT("'"&INDIRECT("Main!B9")&"'!A85"))=0,"",(INDIRECT("'"&INDIRECT("Main!B9")&"'!A85")))} | B71: {=IF((INDIRECT("'"&INDIRECT("Main!B9")&"'!B85"))=0,"",(INDIRECT("'"&INDIRECT("Main!B9")&"'!B85")))} | C71: 0
A72: {=IF((INDIRECT("'"&INDIRECT("Main!B9")&"'!A86"))=0,"",(INDIRECT("'"&INDIRECT("Main!B9")&"'!A86")))} | B72: {=IF((INDIRECT("'"&INDIRECT("Main!B9")&"'!B86"))=0,"",(INDIRECT("'"&INDIRECT("Main!B9")&"'!B86")))} | C72: 0
A73: {=IF((INDIRECT("'"&INDIRECT("Main!B9")&"'!A87"))=0,"",(INDIRECT("'"&INDIRECT("Main!B9")&"'!A87")))} | B73: {=IF((INDIRECT("'"&INDIRECT("Main!B9")&"'!B87"))=0,"",(INDIRECT("'"&INDIRECT("Main!B9")&"'!B87")))} | C73: 0
A74: {=IF((INDIRECT("'"&INDIRECT("Main!B9")&"'!A88"))=0,"",(INDIRECT("'"&INDIRECT("Main!B9")&"'!A88")))} | B74: {=IF((INDIRECT("'"&INDIRECT("Main!B9")&"'!B88"))=0,"",(INDIRECT("'"&INDIRECT("Main!B9")&"'!B88")))} | C74: 0
B75: Total Expenses | C75: =SUM(C68:C74) -> 0
A76: {=IF((INDIRECT("'"&INDIRECT("Main!B9")&"'!A90"))=0,"",(INDIRECT("'"&INDIRECT("Main!B9")&"'!A90")))} -> Insurance (Personal / Properties / Medical)
A77: {=IF((INDIRECT("'"&INDIRECT("Main!B9")&"'!A91"))=0,"",(INDIRECT("'"&INDIRECT("Main!B9")&"'!A91")))} -> AIA | B77: {=IF((INDIRECT("'"&INDIRECT("Main!B9")&"'!B91"))=0,"",(INDIRECT("'"&INDIRECT("Main!B9")&"'!B91")))} | C77: 0
A78: {=IF((INDIRECT("'"&INDIRECT("Main!B9")&"'!A92"))=0,"",(INDIRECT("'"&INDIRECT("Main!B9")&"'!A92")))} | B78: {=IF((INDIRECT("'"&INDIRECT("Main!B9")&"'!B92"))=0,"",(INDIRECT("'"&INDIRECT("Main!B9")&"'!B92")))} | C78: 0
A79: {=IF((INDIRECT("'"&INDIRECT("Main!B9")&"'!A93"))=0,"",(INDIRECT("'"&INDIRECT("Main!B9")&"'!A93")))} | B79: {=IF((INDIRECT("'"&INDIRECT("Main!B9")&"'!B93"))=0,"",(INDIRECT("'"&INDIRECT("Main!B9")&"'!B93")))} | C79: 0
A80: {=IF((INDIRECT("'"&INDIRECT("Main!B9")&"'!A94"))=0,"",(INDIRECT("'"&INDIRECT("Main!B9")&"'!A94")))} | B80: {=IF((INDIRECT("'"&INDIRECT("Main!B9")&"'!B94"))=0,"",(INDIRECT("'"&INDIRECT("Main!B9")&"'!B94")))} | C80: 0
A81: {=IF((INDIRECT("'"&INDIRECT("Main!B9")&"'!A95"))=0,"",(INDIRECT("'"&INDIRECT("Main!B9")&"'!A95")))} | B81: {=IF((INDIRECT("'"&INDIRECT("Main!B9")&"'!B95"))=0,"",(INDIRECT("'"&INDIRECT("Main!B9")&"'!B95")))} | C81: 0
A82: {=IF((INDIRECT("'"&INDIRECT("Main!B9")&"'!A96"))=0,"",(INDIRECT("'"&INDIRECT("Main!B9")&"'!A96")))} | B82: {=IF((INDIRECT("'"&INDIRECT("Main!B9")&"'!B96"))=0,"",(INDIRECT("'"&INDIRECT("Main!B9")&"'!B96")))} | C82: 0
A83: {=IF((INDIRECT("'"&INDIRECT("Main!B9")&"'!A97"))=0,"",(INDIRECT("'"&INDIRECT("Main!B9")&"'!A97")))} | B83: {=IF((INDIRECT("'"&INDIRECT("Main!B9")&"'!B97"))=0,"",(INDIRECT("'"&INDIRECT("Main!B9")&"'!B97")))} | C83: 0
A84: {=IF((INDIRECT("'"&INDIRECT("Main!B9")&"'!A98"))=0,"",(INDIRECT("'"&INDIRECT("Main!B9")&"'!A98")))} | B84: {=IF((INDIRECT("'"&INDIRECT("Main!B9")&"'!B98"))=0,"",(INDIRECT("'"&INDIRECT("Main!B9")&"'!B98")))} | C84: 0
B85: Total Expenses | C85: =SUM(C77:C84) -> 0
A86: {=IF((INDIRECT("'"&INDIRECT("Main!B9")&"'!A100"))=0,"",(INDIRECT("'"&INDIRECT("Main!B9")&"'!A100")))} -> Other Expenses
A87: {=IF((INDIRECT("'"&INDIRECT("Main!B9")&"'!A101"))=0,"",(INDIRECT("'"&INDIRECT("Main!B9")&"'!A101")))} -> Other Stuff | B87: {=IF((INDIRECT("'"&INDIRECT("Main!B9")&"'!B101"))=0,"",(INDIRECT("'"&INDIRECT("Main!B9")&"'!B101")))} -> Food, Transport…. | C87: 600
A88: {=IF((INDIRECT("'"&INDIRECT("Main!B9")&"'!A102"))=0,"",(INDIRECT("'"&INDIRECT("Main!B9")&"'!A102")))} -> Entertainment | B88: {=IF((INDIRECT("'"&INDIRECT("Main!B9")&"'!B102"))=0,"",(INDIRECT("'"&INDIRECT("Main!B9")&"'!B102")))} -> Sportify Music / Changed to Apple Music on 13th May 2025 | C88: 68
A89: {=IF((INDIRECT("'"&INDIRECT("Main!B9")&"'!A103"))=0,"",(INDIRECT("'"&INDIRECT("Main!B9")&"'!A103")))} -> Hair Cutting | B89: {=IF((INDIRECT("'"&INDIRECT("Main!B9")&"'!B103"))=0,"",(INDIRECT("'"&INDIRECT("Main!B9")&"'!B103")))} -> Hair Cut not Include Color treatment | C89: 79
A90: {=IF((INDIRECT("'"&INDIRECT("Main!B9")&"'!A104"))=0,"",(INDIRECT("'"&INDIRECT("Main!B9")&"'!A104")))} -> Cigarettes | B90: {=IF((INDIRECT("'"&INDIRECT("Main!B9")&"'!B104"))=0,"",(INDIRECT("'"&INDIRECT("Main!B9")&"'!B104")))} -> 30 packets | C90: 870
A91: {=IF((INDIRECT("'"&INDIRECT("Main!B9")&"'!A105"))=0,"",(INDIRECT("'"&INDIRECT("Main!B9")&"'!A105")))} | B91: {=IF((INDIRECT("'"&INDIRECT("Main!B9")&"'!B105"))=0,"",(INDIRECT("'"&INDIRECT("Main!B9")&"'!B105")))} | C91: 0
A92: {=IF((INDIRECT("'"&INDIRECT("Main!B9")&"'!A106"))=0,"",(INDIRECT("'"&INDIRECT("Main!B9")&"'!A106")))} | B92: {=IF((INDIRECT("'"&INDIRECT("Main!B9")&"'!B106"))=0,"",(INDIRECT("'"&INDIRECT("Main!B9")&"'!B106")))} | C92: 0
A93: {=IF((INDIRECT("'"&INDIRECT("Main!B9")&"'!A107"))=0,"",(INDIRECT("'"&INDIRECT("Main!B9")&"'!A107")))} | B93: {=IF((INDIRECT("'"&INDIRECT("Main!B9")&"'!B107"))=0,"",(INDIRECT("'"&INDIRECT("Main!B9")&"'!B107")))} | C93: 0
A94: {=IF((INDIRECT("'"&INDIRECT("Main!B9")&"'!A108"))=0,"",(INDIRECT("'"&INDIRECT("Main!B9")&"'!A108")))} | B94: {=IF((INDIRECT("'"&INDIRECT("Main!B9")&"'!B108"))=0,"",(INDIRECT("'"&INDIRECT("Main!B9")&"'!B108")))} | C94: 0
B95: Total Expenses | C95: =SUM(C87:C94) -> 1617
B96: Grand Expenses Total | C96: =C55+C66+C75+C85+C95 -> 2028.5
A97: {=IF((INDIRECT("'"&INDIRECT("Main!B9")&"'!A111"))=0,"",(INDIRECT("'"&INDIRECT("Main!B9")&"'!A111")))} -> Debts
A98: {=IF((INDIRECT("'"&INDIRECT("Main!B9")&"'!A112"))=0,"",(INDIRECT("'"&INDIRECT("Main!B9")&"'!A112")))} -> Mother | B98: {=IF((INDIRECT("'"&INDIRECT("Main!B9")&"'!B112"))=0,"",(INDIRECT("'"&INDIRECT("Main!B9")&"'!B112")))} | C98: {=(((INDIRECT("'"&INDIRECT("Main!B9")&"'!E131")+INDIRECT("'"&INDIRECT("Main!B9")&"'!E158")+INDIRECT("'"&INDIRECT("Main!B9")&"'!E185")))+SUM(E118+E145+E172))-INDIRECT("'"&INDIRECT("Main!B9")&"'!C112")} -> -8300
A99: {=IF((INDIRECT("'"&INDIRECT("Main!B9")&"'!A113"))=0,"",(INDIRECT("'"&INDIRECT("Main!B9")&"'!A113")))} -> Ng Wing Lam | B99: {=IF((INDIRECT("'"&INDIRECT("Main!B9")&"'!B113"))=0,"",(INDIRECT("'"&INDIRECT("Main!B9")&"'!B113")))} | C99: {=(((INDIRECT("'"&INDIRECT("Main!B9")&"'!E132")+INDIRECT("'"&INDIRECT("Main!B9")&"'!E159")+INDIRECT("'"&INDIRECT("Main!B9")&"'!E186")))+SUM(E119+E146+E173))-INDIRECT("'"&INDIRECT("Main!B9")&"'!C113")} -> 0
A100: {=IF((INDIRECT("'"&INDIRECT("Main!B9")&"'!A114"))=0,"",(INDIRECT("'"&INDIRECT("Main!B9")&"'!A114")))} -> Lawrence | B100: {=IF((INDIRECT("'"&INDIRECT("Main!B9")&"'!B114"))=0,"",(INDIRECT("'"&INDIRECT("Main!B9")&"'!B114")))} | C100: {=(((INDIRECT("'"&INDIRECT("Main!B9")&"'!E133")+INDIRECT("'"&INDIRECT("Main!B9")&"'!E160")+INDIRECT("'"&INDIRECT("Main!B9")&"'!E187")))+SUM(E120+E147+E174))-INDIRECT("'"&INDIRECT("Main!B9")&"'!C114")} -> -2300
A101: {=IF((INDIRECT("'"&INDIRECT("Main!B9")&"'!A115"))=0,"",(INDIRECT("'"&INDIRECT("Main!B9")&"'!A115")))} -> Hong Kong Government Hospital Authority | B101: {=IF((INDIRECT("'"&INDIRECT("Main!B9")&"'!B115"))=0,"",(INDIRECT("'"&INDIRECT("Main!B9")&"'!B115")))} | C101: {=(((INDIRECT("'"&INDIRECT("Main!B9")&"'!E134")+INDIRECT("'"&INDIRECT("Main!B9")&"'!E161")+INDIRECT("'"&INDIRECT("Main!B9")&"'!E188")))+SUM(E121+E148+E175))-INDIRECT("'"&INDIRECT("Main!B9")&"'!C115")} -> 0
A102: {=IF((INDIRECT("'"&INDIRECT("Main!B9")&"'!A116"))=0,"",(INDIRECT("'"&INDIRECT("Main!B9")&"'!A116")))} -> Bankruptcy Department / Bank | B102: {=IF((INDIRECT("'"&INDIRECT("Main!B9")&"'!B116"))=0,"",(INDIRECT("'"&INDIRECT("Main!B9")&"'!B116")))} | C102: {=(((INDIRECT("'"&INDIRECT("Main!B9")&"'!E135")+INDIRECT("'"&INDIRECT("Main!B9")&"'!E162")+INDIRECT("'"&INDIRECT("Main!B9")&"'!E189")))+SUM(E122+E149+E176))-INDIRECT("'"&INDIRECT("Main!B9")&"'!C116")} -> 0
A103: {=IF((INDIRECT("'"&INDIRECT("Main!B9")&"'!A117"))=0,"",(INDIRECT("'"&INDIRECT("Main!B9")&"'!A117")))} -> Mother Air Ticket | B103: {=IF((INDIRECT("'"&INDIRECT("Main!B9")&"'!B117"))=0,"",(INDIRECT("'"&INDIRECT("Main!B9")&"'!B117")))} | C103: {=(((INDIRECT("'"&INDIRECT("Main!B9")&"'!E136")+INDIRECT("'"&INDIRECT("Main!B9")&"'!E163")+INDIRECT("'"&INDIRECT("Main!B9")&"'!E190")))+SUM(E123+E150+E177))-INDIRECT("'"&INDIRECT("Main!B9")&"'!C117")} -> -1083
A104: {=IF((INDIRECT("'"&INDIRECT("Main!B9")&"'!A118"))=0,"",(INDIRECT("'"&INDIRECT("Main!B9")&"'!A118")))} | B104: {=IF((INDIRECT("'"&INDIRECT("Main!B9")&"'!B118"))=0,"",(INDIRECT("'"&INDIRECT("Main!B9")&"'!B118")))} | C104: {=(((INDIRECT("'"&INDIRECT("Main!B9")&"'!E137")+INDIRECT("'"&INDIRECT("Main!B9")&"'!E164")+INDIRECT("'"&INDIRECT("Main!B9")&"'!E191")))+SUM(E124+E151+E178))-INDIRECT("'"&INDIRECT("Main!B9")&"'!C118")} -> 0
A105: {=IF((INDIRECT("'"&INDIRECT("Main!B9")&"'!A119"))=0,"",(INDIRECT("'"&INDIRECT("Main!B9")&"'!A119")))} | B105: {=IF((INDIRECT("'"&INDIRECT("Main!B9")&"'!B119"))=0,"",(INDIRECT("'"&INDIRECT("Main!B9")&"'!B119")))} | C105: {=(((INDIRECT("'"&INDIRECT("Main!B9")&"'!E138")+INDIRECT("'"&INDIRECT("Main!B9")&"'!E165")+INDIRECT("'"&INDIRECT("Main!B9")&"'!E192")))+SUM(E125+E152+E179))-INDIRECT("'"&INDIRECT("Main!B9")&"'!C119")} -> 0
A106: {=IF((INDIRECT("'"&INDIRECT("Main!B9")&"'!A120"))=0,"",(INDIRECT("'"&INDIRECT("Main!B9")&"'!A120")))} | B106: {=IF((INDIRECT("'"&INDIRECT("Main!B9")&"'!B120"))=0,"",(INDIRECT("'"&INDIRECT("Main!B9")&"'!B120")))} | C106: {=(((INDIRECT("'"&INDIRECT("Main!B9")&"'!E139")+INDIRECT("'"&INDIRECT("Main!B9")&"'!E166")+INDIRECT("'"&INDIRECT("Main!B9")&"'!E193")))+SUM(E126+E153+E180))-INDIRECT("'"&INDIRECT("Main!B9")&"'!C120")} -> 0
A107: {=IF((INDIRECT("'"&INDIRECT("Main!B9")&"'!A121"))=0,"",(INDIRECT("'"&INDIRECT("Main!B9")&"'!A121")))} | B107: {=IF((INDIRECT("'"&INDIRECT("Main!B9")&"'!B121"))=0,"",(INDIRECT("'"&INDIRECT("Main!B9")&"'!B121")))} | C107: {=(((INDIRECT("'"&INDIRECT("Main!B9")&"'!E140")+INDIRECT("'"&INDIRECT("Main!B9")&"'!E167")+INDIRECT("'"&INDIRECT("Main!B9")&"'!E194")))+SUM(E127+E154+E181))-INDIRECT("'"&INDIRECT("Main!B9")&"'!C121")} -> 0
B108: Total Debts | C108: =SUM(C98:C107) -> -11683
B109: Grand Total | C109: =C108-C96 -> -13711.5
A114: ="Debts Or Credits For the Comming "&IF(Main!B2,TEXT(EDATE(Main!B3,3),"mmmm dd yyyy"),TEXT(Main!B3+((Main!B5-Main!B3)*3+3),"mmmm dd yyyy"))&" to "&IF(Main!B2,TEXT(EDATE(Main!B3,4)-1,"mmmm dd yyyy"),TEXT(Main!B3+((Main!B5-Main!B3)*4+3),"mmmm dd yyyy")) -> Debts Or Credits For the Comming July 20 2024 to August 19 2024
A115: Principal | C115: Description | E115: Amount
...

Sheet October 2024 - December 2024
A1: ="Forecasts For the Year "&IF(Main!B2,TEXT(EDATE(Main!B3,6),"mmmm yyyy"),TEXT(Main!B3+((Main!B5-Main!B3)*6+6),"mmmm yyyy"))&" to "&IF(Main!B2,TEXT(EDATE(Main!B3,9)-1,"mmmm yyyy"),TEXT(Main!B3+((Main!B5-Main!B3)*9+8),"mmmm yyyy")) -> Forecasts For the Year October 2024 to January 2025
A2: Assets | B2: Overall | C2: {=INDIRECT("'"&Main!B9&"'!$C$16")} -> 1181.5
B3: Forecasts | C3: =E190 -> 173.34
A4: Total | C4: =SUM(C2:G3) -> 1354.84
A5: Net Debts: | C5: =C108 -> -10683
A8: =IF(Main!B2,TEXT(EDATE(Main!B3,6),"dd mmmm yyyy"),TEXT(Main!B3+((Main!B5-Main!B3)*6+6),"dd mmmm yyyy"))&" - "&IF(Main!B2,TEXT(EDATE(Main!B3,7)-1,"dd mmmm yyyy"),TEXT(Main!B3+((Main!B5-Main!B3)*7+6),"dd mmmm yyyy"))&" / "&" (Revenue / Deferred Debts Or Expenses)" -> 20 October 2024 - 19 November 2024 / (Revenue / Deferred Debts Or Expenses)
A9: Date | B9: Name | D9: Description | F9: Amount
A10: 31st October 2024 | B10: Salary | D10: Deduct 5% MPF | F10: 0
A11: 26th September 2024 | B11: China Mobile Broadband | D11: Prepaid October Broadband Fees | F11: 78
A12: 18th October 2024 | B12: China Mobile | D12: Joox Refund - Total 3 Months | F12: 174
A13: 18th October 2024 | B13: Sportify Monthly Payment | D13: N/A | F13: 68
A14: 18th November 2024 | B14: Sportify Monthly Payment | D14: N/A | F14: 68
A15: 20th October 2024 | B15: Social Welfare | D15: N/A | F15: 2405
D16: Total Revenue | F16: =SUM(F10:G15) -> 2793
A20: =IF(Main!B2,TEXT(EDATE(Main!B3,7),"dd mmmm yyyy"),TEXT(Main!B3+((Main!B5-Main!B3)*7+7),"dd mmmm yyyy"))&" - "&IF(Main!B2,TEXT(EDATE(Main!B3,8)-1,"dd mmmm yyyy"),TEXT(Main!B3+((Main!B5-Main!B3)*8+7),"dd mmmm yyyy"))&" / "&" (Revenue / Deferred Debts Or Expenses)" -> 20 November 2024 - 19 December 2024 / (Revenue / Deferred Debts Or Expenses)
A21: Date | B21: Name | D21: Description | F21: Amount
A22: 30th November 2024 | B22: Salary | D22: Deduct 5% MPF | F22: 0
A23: 20th November 2024 | B23: Social Welfare | D23: N/A | F23: 2405
A24: 29rd November 2024 3rd December 2024 11th December 2024 17th December 2024 23rd November 2024 2nd December 2024 | B24: 1. Mother 2. Lawrence 3. Lawrence 4. Lawrence 5. WingOn Travel 6. Return Taxi Remaining | D24: 1. Give $500 without return 2. Lawrence give $500 For Mother Hospital Expenses 3. Borrow $1000 From Lawrence 4. Lawrence give $600 For Mother Hospital Expenses 5. Bangkok Air ticket refund – Money is refund to Mother’s HSBC credit card account. 6. Receive $100 From Mom For return Taxi. Still remain $12. | F24: 2612
A25: 2nd December 2024 | B25: Remaining Add In Value For Octopus. | D25: Octopus Add In value $50 1. $9.5 For Water 2. -$8.6 Negative Deposit. 3. $4 round trip to hospital. 4. U-mart expenses $20.8 5. add in value $50 6. $4 round trip to Kowloon Hospital. 7. $4 round trip to East Kowloon Hospital. | F25: 49.1
A26: 21st November 2024 | B26: Cigarette | D26: Deduct 10 packet of Cigarette | F26: 300
A27: 3rd December 2024 | B27: Alipay | D27: Alipay $3 discount plus $2.04 Alipay Points Used | F27: 5.04
D28: Total Revenue | F28: =SUM(F22:G27) -> 5371.14
A32: =IF(Main!B2,TEXT(EDATE(Main!B3,8),"dd mmmm yyyy"),TEXT(Main!B3+((Main!B5-Main!B3)*8+8),"dd mmmm yyyy"))&" - "&IF(Main!B2,TEXT(EDATE(Main!B3,9)-1,"dd mmmm yyyy"),TEXT(Main!B3+((Main!B5-Main!B3)*9+8),"dd mmmm yyyy"))&" / "&" (Revenue / Deferred Debts Or Expenses)" -> 20 December 2024 - 19 January 2025 / (Revenue / Deferred Debts Or Expenses)
A33: Date | B33: Name | D33: Description | F33: Amount
A34: 31st December 2024 | B34: Salary | D34: Deduct 5% MPF | F34: 0
A35: 20th December 2024 | B35: Social Welfare | D35: N/A | F35: 2405
B36: Deduct Cigarette | D36: Deduct 30 packet of Cigarette | F36: 900
A37: 1. 25th December 2024 2. 27th December 2024 3. 28th December 2024 4. 28th December 2024 5. 31st December 2024 6. 1st December 2024 | B37: 1. Lawrence 2. Mother 3. Mother 4. Mother 5. Lawrence 6. Lawrence 7. Mother | D37: 1. Lawrence give $100 For Christmas 2. Mother give $900 For Car License Renewal. 3. Mother borrow $50 4. Mother give $16.14 coins 5. Lawrence give $50 For Octopus Add In Value 6. Lawrence give $100 For the help of Carrying luggages to the bus station. 7. Mother Owe Me $78.4 for Taxi to QE Hospital, Plus Give me $100 for Return Taxi to home from QE Hospital. Return Taxi Fee is $78.4, $12 remaining. Therefore total Mom still owes me $78.4 - $12 which is equal to $66.4. | F37: 1282.54
A38: 20th December 2024 | B38: Food And Transport Expenses | D38: Deduct $200 From Food And Transport Expenses. | F38: 200
B39: Balance Assets | D39: Balance The Total Assets | F39: 229.6
D40: Total Revenue | F40: =SUM(F34:G39) -> 5017.14
A44: ="Fixed Expense For the Year "&IF(Main!B2,TEXT(EDATE(Main!B3,6),"mmmm yyyy"),TEXT(Main!B3+((Main!B5-Main!B3)*6+6),"mmmm yyyy"))&" to "&IF(Main!B2,TEXT(EDATE(Main!B3,9)-1,"mmmm yyyy"),TEXT(Main!B3+((Main!B5-Main!B3)*9+8),"mmmm yyyy")) -> Fixed Expense For the Year October 2024 to January 2025
A45: Name | B45: Description | C45: Amount
A46: Mobile And Communications/ Housing Expenses
A47: {=IF((INDIRECT("'"&INDIRECT("Main!B9")&"'!A61"))=0,"",(INDIRECT("'"&INDIRECT("Main!B9")&"'!A61")))} -> Broadband | B47: {=IF((INDIRECT("'"&INDIRECT("Main!B9")&"'!B61"))=0,"",(INDIRECT("'"&INDIRECT("Main!B9")&"'!B61")))} | C47: 0
A48: {=IF((INDIRECT("'"&INDIRECT("Main!B9")&"'!A62"))=0,"",(INDIRECT("'"&INDIRECT("Main!B9")&"'!A62")))} -> China Mobile | B48: {=IF((INDIRECT("'"&INDIRECT("Main!B9")&"'!B62"))=0,"",(INDIRECT("'"&INDIRECT("Main!B9")&"'!B62")))} | C48: 149
A49: {=IF((INDIRECT("'"&INDIRECT("Main!B9")&"'!A63"))=0,"",(INDIRECT("'"&INDIRECT("Main!B9")&"'!A63")))} -> Telephone (Fixed Line) | B49: {=IF((INDIRECT("'"&INDIRECT("Main!B9")&"'!B63"))=0,"",(INDIRECT("'"&INDIRECT("Main!B9")&"'!B63")))} | C49: 0
A50: {=IF((INDIRECT("'"&INDIRECT("Main!B9")&"'!A64"))=0,"",(INDIRECT("'"&INDIRECT("Main!B9")&"'!A64")))} -> Sosim | B50: {=IF((INDIRECT("'"&INDIRECT("Main!B9")&"'!B64"))=0,"",(INDIRECT("'"&INDIRECT("Main!B9")&"'!B64")))} | C50: 0
A51: {=IF((INDIRECT("'"&INDIRECT("Main!B9")&"'!A65"))=0,"",(INDIRECT("'"&INDIRECT("Main!B9")&"'!A65")))} -> Birdie Sim Card Pay date (7th Of Each Month) | B51: {=IF((INDIRECT("'"&INDIRECT("Main!B9")&"'!B65"))=0,"",(INDIRECT("'"&INDIRECT("Main!B9")&"'!B65")))} | C51: 0
A52: {=IF((INDIRECT("'"&INDIRECT("Main!B9")&"'!A66"))=0,"",(INDIRECT("'"&INDIRECT("Main!B9")&"'!A66")))} | B52: {=IF((INDIRECT("'"&INDIRECT("Main!B9")&"'!B66"))=0,"",(INDIRECT("'"&INDIRECT("Main!B9")&"'!B66")))} | C52: 0
A53: {=IF((INDIRECT("'"&INDIRECT("Main!B9")&"'!A67"))=0,"",(INDIRECT("'"&INDIRECT("Main!B9")&"'!A67")))} | B53: {=IF((INDIRECT("'"&INDIRECT("Main!B9")&"'!B67"))=0,"",(INDIRECT("'"&INDIRECT("Main!B9")&"'!B67")))} | C53: 0
A54: {=IF((INDIRECT("'"&INDIRECT("Main!B9")&"'!A68"))=0,"",(INDIRECT("'"&INDIRECT("Main!B9")&"'!A68")))} | B54: {=IF((INDIRECT("'"&INDIRECT("Main!B9")&"'!B68"))=0,"",(INDIRECT("'"&INDIRECT("Main!B9")&"'!B68")))} | C54: 0
B55: Total Expenses | C55: =SUM(C47:C54) -> 149
A56: Credit Card Installments/Government Installments
A57: {=IF((INDIRECT("'"&INDIRECT("Main!B9")&"'!A71"))=0,"",(INDIRECT("'"&INDIRECT("Main!B9")&"'!A71")))} -> Citi Bank | B57: {=IF((INDIRECT("'"&INDIRECT("Main!B9")&"'!B71"))=0,"",(INDIRECT("'"&INDIRECT("Main!B9")&"'!B71")))} | C57: 0
A58: {=IF((INDIRECT("'"&INDIRECT("Main!B9")&"'!A72"))=0,"",(INDIRECT("'"&INDIRECT("Main!B9")&"'!A72")))} -> SC Bank | B58: {=IF((INDIRECT("'"&INDIRECT("Main!B9")&"'!B72"))=0,"",(INDIRECT("'"&INDIRECT("Main!B9")&"'!B72")))} | C58: 0
A59: {=IF((INDIRECT("'"&INDIRECT("Main!B9")&"'!A73"))=0,"",(INDIRECT("'"&INDIRECT("Main!B9")&"'!A73")))} -> Bank Of China | B59: {=IF((INDIRECT("'"&INDIRECT("Main!B9")&"'!B73"))=0,"",(INDIRECT("'"&INDIRECT("Main!B9")&"'!B73")))} | C59: 0
A60: {=IF((INDIRECT("'"&INDIRECT("Main!B9")&"'!A74"))=0,"",(INDIRECT("'"&INDIRECT("Main!B9")&"'!A74")))} -> HSBC | B60: {=IF((INDIRECT("'"&INDIRECT("Main!B9")&"'!B74"))=0,"",(INDIRECT("'"&INDIRECT("Main!B9")&"'!B74")))} | C60: 0
A61: {=IF((INDIRECT("'"&INDIRECT("Main!B9")&"'!A75"))=0,"",(INDIRECT("'"&INDIRECT("Main!B9")&"'!A75")))} | B61: {=IF((INDIRECT("'"&INDIRECT("Main!B9")&"'!B75"))=0,"",(INDIRECT("'"&INDIRECT("Main!B9")&"'!B75")))} | C61: 0
A62: {=IF((INDIRECT("'"&INDIRECT("Main!B9")&"'!A76"))=0,"",(INDIRECT("'"&INDIRECT("Main!B9")&"'!A76")))} | B62: {=IF((INDIRECT("'"&INDIRECT("Main!B9")&"'!B76"))=0,"",(INDIRECT("'"&INDIRECT("Main!B9")&"'!B76")))} | C62: 0
A63: {=IF((INDIRECT("'"&INDIRECT("Main!B9")&"'!A77"))=0,"",(INDIRECT("'"&INDIRECT("Main!B9")&"'!A77")))} | B63: {=IF((INDIRECT("'"&INDIRECT("Main!B9")&"'!B77"))=0,"",(INDIRECT("'"&INDIRECT("Main!B9")&"'!B77")))} | C63: 0
A64: {=IF((INDIRECT("'"&INDIRECT("Main!B9")&"'!A78"))=0,"",(INDIRECT("'"&INDIRECT("Main!B9")&"'!A78")))} | B64: {=IF((INDIRECT("'"&INDIRECT("Main!B9")&"'!B78"))=0,"",(INDIRECT("'"&INDIRECT("Main!B9")&"'!B78")))} | C64: 0
A65: {=IF((INDIRECT("'"&INDIRECT("Main!B9")&"'!A79"))=0,"",(INDIRECT("'"&INDIRECT("Main!B9")&"'!A79")))} | B65: {=IF((INDIRECT("'"&INDIRECT("Main!B9")&"'!B79"))=0,"",(INDIRECT("'"&INDIRECT("Main!B9")&"'!B79")))} | C65: 0
B66: Total Expenses | C66: =SUM(C57:C65) -> 0
A67: Donation
A68: {=IF((INDIRECT("'"&INDIRECT("Main!B9")&"'!A82"))=0,"",(INDIRECT("'"&INDIRECT("Main!B9")&"'!A82")))} -> Traversy | B68: {=IF((INDIRECT("'"&INDIRECT("Main!B9")&"'!B82"))=0,"",(INDIRECT("'"&INDIRECT("Main!B9")&"'!B82")))} -> Traversy Media | C68: 0
A69: {=IF((INDIRECT("'"&INDIRECT("Main!B9")&"'!A83"))=0,"",(INDIRECT("'"&INDIRECT("Main!B9")&"'!A83")))} -> Orbis | B69: {=IF((INDIRECT("'"&INDIRECT("Main!B9")&"'!B83"))=0,"",(INDIRECT("'"&INDIRECT("Main!B9")&"'!B83")))} -> Orbis Eye Flight | C69: 0
A70: {=IF((INDIRECT("'"&INDIRECT("Main!B9")&"'!A84"))=0,"",(INDIRECT("'"&INDIRECT("Main!B9")&"'!A84")))} | B70: {=IF((INDIRECT("'"&INDIRECT("Main!B9")&"'!B84"))=0,"",(INDIRECT("'"&INDIRECT("Main!B9")&"'!B84")))} | C70: 0
A71: {=IF((INDIRECT("'"&INDIRECT("Main!B9")&"'!A85"))=0,"",(INDIRECT("'"&INDIRECT("Main!B9")&"'!A85")))} | B71: {=IF((INDIRECT("'"&INDIRECT("Main!B9")&"'!B85"))=0,"",(INDIRECT("'"&INDIRECT("Main!B9")&"'!B85")))} | C71: 0
A72: {=IF((INDIRECT("'"&INDIRECT("Main!B9")&"'!A86"))=0,"",(INDIRECT("'"&INDIRECT("Main!B9")&"'!A86")))} | B72: {=IF((INDIRECT("'"&INDIRECT("Main!B9")&"'!B86"))=0,"",(INDIRECT("'"&INDIRECT("Main!B9")&"'!B86")))} | C72: 0
A73: {=IF((INDIRECT("'"&INDIRECT("Main!B9")&"'!A87"))=0,"",(INDIRECT("'"&INDIRECT("Main!B9")&"'!A87")))} | B73: {=IF((INDIRECT("'"&INDIRECT("Main!B9")&"'!B87"))=0,"",(INDIRECT("'"&INDIRECT("Main!B9")&"'!B87")))} | C73: 0
A74: {=IF((INDIRECT("'"&INDIRECT("Main!B9")&"'!A88"))=0,"",(INDIRECT("'"&INDIRECT("Main!B9")&"'!A88")))} | B74: {=IF((INDIRECT("'"&INDIRECT("Main!B9")&"'!B88"))=0,"",(INDIRECT("'"&INDIRECT("Main!B9")&"'!B88")))} | C74: 0
B75: Total Expenses | C75: =SUM(C68:C74) -> 0
A76: Insurance (Personal / Properties / Medical)
A77: {=IF((INDIRECT("'"&INDIRECT("Main!B9")&"'!A91"))=0,"",(INDIRECT("'"&INDIRECT("Main!B9")&"'!A91")))} -> AIA | B77: {=IF((INDIRECT("'"&INDIRECT("Main!B9")&"'!B91"))=0,"",(INDIRECT("'"&INDIRECT("Main!B9")&"'!B91")))} | C77: 0
A78: {=IF((INDIRECT("'"&INDIRECT("Main!B9")&"'!A92"))=0,"",(INDIRECT("'"&INDIRECT("Main!B9")&"'!A92")))} | B78: {=IF((INDIRECT("'"&INDIRECT("Main!B9")&"'!B92"))=0,"",(INDIRECT("'"&INDIRECT("Main!B9")&"'!B92")))} | C78: 0
A79: {=IF((INDIRECT("'"&INDIRECT("Main!B9")&"'!A93"))=0,"",(INDIRECT("'"&INDIRECT("Main!B9")&"'!A93")))} | B79: {=IF((INDIRECT("'"&INDIRECT("Main!B9")&"'!B93"))=0,"",(INDIRECT("'"&INDIRECT("Main!B9")&"'!B93")))} | C79: 0
A80: {=IF((INDIRECT("'"&INDIRECT("Main!B9")&"'!A94"))=0,"",(INDIRECT("'"&INDIRECT("Main!B9")&"'!A94")))} | B80: {=IF((INDIRECT("'"&INDIRECT("Main!B9")&"'!B94"))=0,"",(INDIRECT("'"&INDIRECT("Main!B9")&"'!B94")))} | C80: 0
A81: {=IF((INDIRECT("'"&INDIRECT("Main!B9")&"'!A95"))=0,"",(INDIRECT("'"&INDIRECT("Main!B9")&"'!A95")))} | B81: {=IF((INDIRECT("'"&INDIRECT("Main!B9")&"'!B95"))=0,"",(INDIRECT("'"&INDIRECT("Main!B9")&"'!B95")))} | C81: 0
A82: {=IF((INDIRECT("'"&INDIRECT("Main!B9")&"'!A96"))=0,"",(INDIRECT("'"&INDIRECT("Main!B9")&"'!A96")))} | B82: {=IF((INDIRECT("'"&INDIRECT("Main!B9")&"'!B96"))=0,"",(INDIRECT("'"&INDIRECT("Main!B9")&"'!B96")))} | C82: 0
A83: {=IF((INDIRECT("'"&INDIRECT("Main!B9")&"'!A97"))=0,"",(INDIRECT("'"&INDIRECT("Main!B9")&"'!A97")))} | B83: {=IF((INDIRECT("'"&INDIRECT("Main!B9")&"'!B97"))=0,"",(INDIRECT("'"&INDIRECT("Main!B9")&"'!B97")))} | C83: 0
A84: {=IF((INDIRECT("'"&INDIRECT("Main!B9")&"'!A98"))=0,"",(INDIRECT("'"&INDIRECT("Main!B9")&"'!A98")))} | B84: {=IF((INDIRECT("'"&INDIRECT("Main!B9")&"'!B98"))=0,"",(INDIRECT("'"&INDIRECT("Main!B9")&"'!B98")))} | C84: 0
B85: Total Expenses | C85: =SUM(C77:C84) -> 0
A86: Other Expenses
A87: {=IF((INDIRECT("'"&INDIRECT("Main!B9")&"'!A101"))=0,"",(INDIRECT("'"&INDIRECT("Main!B9")&"'!A101")))} -> Other Stuff | B87: {=IF((INDIRECT("'"&INDIRECT("Main!B9")&"'!B101"))=0,"",(INDIRECT("'"&INDIRECT("Main!B9")&"'!B101")))} -> Food, Transport…. | C87: 200
A88: {=IF((INDIRECT("'"&INDIRECT("Main!B9")&"'!A102"))=0,"",(INDIRECT("'"&INDIRECT("Main!B9")&"'!A102")))} -> Entertainment | B88: {=IF((INDIRECT("'"&INDIRECT("Main!B9")&"'!B102"))=0,"",(INDIRECT("'"&INDIRECT("Main!B9")&"'!B102")))} -> Sportify Music / Changed to Apple Music on 13th May 2025 | C88: 68
A89: {=IF((INDIRECT("'"&INDIRECT("Main!B9")&"'!A103"))=0,"",(INDIRECT("'"&INDIRECT("Main!B9")&"'!A103")))} -> Hair Cutting | B89: {=IF((INDIRECT("'"&INDIRECT("Main!B9")&"'!B103"))=0,"",(INDIRECT("'"&INDIRECT("Main!B9")&"'!B103")))} -> Hair Cut not Include Color treatment | C89: 52
A90: {=IF((INDIRECT("'"&INDIRECT("Main!B9")&"'!A104"))=0,"",(INDIRECT("'"&INDIRECT("Main!B9")&"'!A104")))} -> Cigarettes | B90: {=IF((INDIRECT("'"&INDIRECT("Main!B9")&"'!B104"))=0,"",(INDIRECT("'"&INDIRECT("Main!B9")&"'!B104")))} -> 30 packets | C90: 900
A91: {=IF((INDIRECT("'"&INDIRECT("Main!B9")&"'!A105"))=0,"",(INDIRECT("'"&INDIRECT("Main!B9")&"'!A105")))} | B91: {=IF((INDIRECT("'"&INDIRECT("Main!B9")&"'!B105"))=0,"",(INDIRECT("'"&INDIRECT("Main!B9")&"'!B105")))} | C91: 0
A92: {=IF((INDIRECT("'"&INDIRECT("Main!B9")&"'!A106"))=0,"",(INDIRECT("'"&INDIRECT("Main!B9")&"'!A106")))} | B92: {=IF((INDIRECT("'"&INDIRECT("Main!B9")&"'!B106"))=0,"",(INDIRECT("'"&INDIRECT("Main!B9")&"'!B106")))} | C92: 0
A93: {=IF((INDIRECT("'"&INDIRECT("Main!B9")&"'!A107"))=0,"",(INDIRECT("'"&INDIRECT("Main!B9")&"'!A107")))} | B93: {=IF((INDIRECT("'"&INDIRECT("Main!B9")&"'!B107"))=0,"",(INDIRECT("'"&INDIRECT("Main!B9")&"'!B107")))} | C93: 0
A94: {=IF((INDIRECT("'"&INDIRECT("Main!B9")&"'!A108"))=0,"",(INDIRECT("'"&INDIRECT("Main!B9")&"'!A108")))} | B94: {=IF((INDIRECT("'"&INDIRECT("Main!B9")&"'!B108"))=0,"",(INDIRECT("'"&INDIRECT("Main!B9")&"'!B108")))} | C94: 0
B95: Total Expenses | C95: =SUM(C87:C94) -> 1220
B96: Grand Expenses Total | C96: =C55+C66+C75+C85+C95 -> 1369
A97: Debts
A98: {=IF((INDIRECT("'"&INDIRECT("Main!B9")&"'!A112"))=0,"",(INDIRECT("'"&INDIRECT("Main!B9")&"'!A112")))} -> Mother | B98: {=IF((INDIRECT("'"&INDIRECT("Main!B9")&"'!B112"))=0,"",(INDIRECT("'"&INDIRECT("Main!B9")&"'!B112")))} | C98: {=INDIRECT("'"&INDIRECT("Main!B12")&"'!C98")+SUM(E118+E145+E172)} -> -8300
A99: {=IF((INDIRECT("'"&INDIRECT("Main!B9")&"'!A113"))=0,"",(INDIRECT("'"&INDIRECT("Main!B9")&"'!A113")))} -> Ng Wing Lam | B99: {=IF((INDIRECT("'"&INDIRECT("Main!B9")&"'!B113"))=0,"",(INDIRECT("'"&INDIRECT("Main!B9")&"'!B113")))} | C99: {=INDIRECT("'"&INDIRECT("Main!B12")&"'!C99")+SUM(E119+E146+E173)} -> 0
A100: {=IF((INDIRECT("'"&INDIRECT("Main!B9")&"'!A114"))=0,"",(INDIRECT("'"&INDIRECT("Main!B9")&"'!A114")))} -> Lawrence | B100: {=IF((INDIRECT("'"&INDIRECT("Main!B9")&"'!B114"))=0,"",(INDIRECT("'"&INDIRECT("Main!B9")&"'!B114")))} | C100: {=INDIRECT("'"&INDIRECT("Main!B12")&"'!C100")+SUM(E120+E147+E174)} -> -1300
A101: {=IF((INDIRECT("'"&INDIRECT("Main!B9")&"'!A115"))=0,"",(INDIRECT("'"&INDIRECT("Main!B9")&"'!A115")))} -> Hong Kong Government Hospital Authority | B101: {=IF((INDIRECT("'"&INDIRECT("Main!B9")&"'!B115"))=0,"",(INDIRECT("'"&INDIRECT("Main!B9")&"'!B115")))} | C101: {=INDIRECT("'"&INDIRECT("Main!B12")&"'!C101")+SUM(E121+E148+E175)} -> 0
A102: {=IF((INDIRECT("'"&INDIRECT("Main!B9")&"'!A116"))=0,"",(INDIRECT("'"&INDIRECT("Main!B9")&"'!A116")))} -> Bankruptcy Department / Bank | B102: {=IF((INDIRECT("'"&INDIRECT("Main!B9")&"'!B116"))=0,"",(INDIRECT("'"&INDIRECT("Main!B9")&"'!B116")))} | C102: {=INDIRECT("'"&INDIRECT("Main!B12")&"'!C102")+SUM(E122+E149+E176)} -> 0
A103: {=IF((INDIRECT("'"&INDIRECT("Main!B9")&"'!A117"))=0,"",(INDIRECT("'"&INDIRECT("Main!B9")&"'!A117")))} -> Mother Air Ticket | B103: {=IF((INDIRECT("'"&INDIRECT("Main!B9")&"'!B117"))=0,"",(INDIRECT("'"&INDIRECT("Main!B9")&"'!B117")))} | C103: {=INDIRECT("'"&INDIRECT("Main!B12")&"'!C103")+SUM(E123+E150+E177)} -> -1083
A104: {=IF((INDIRECT("'"&INDIRECT("Main!B9")&"'!A118"))=0,"",(INDIRECT("'"&INDIRECT("Main!B9")&"'!A118")))} | B104: {=IF((INDIRECT("'"&INDIRECT("Main!B9")&"'!B118"))=0,"",(INDIRECT("'"&INDIRECT("Main!B9")&"'!B118")))} | C104: {=INDIRECT("'"&INDIRECT("Main!B12")&"'!C104")+SUM(E124+E151+E178)} -> 0
A105: {=IF((INDIRECT("'"&INDIRECT("Main!B9")&"'!A119"))=0,"",(INDIRECT("'"&INDIRECT("Main!B9")&"'!A119")))} | B105: {=IF((INDIRECT("'"&INDIRECT("Main!B9")&"'!B119"))=0,"",(INDIRECT("'"&INDIRECT("Main!B9")&"'!B119")))} | C105: {=INDIRECT("'"&INDIRECT("Main!B12")&"'!C105")+SUM(E125+E152+E179)} -> 0
A106: {=IF((INDIRECT("'"&INDIRECT("Main!B9")&"'!A120"))=0,"",(INDIRECT("'"&INDIRECT("Main!B9")&"'!A120")))} | B106: {=IF((INDIRECT("'"&INDIRECT("Main!B9")&"'!B120"))=0,"",(INDIRECT("'"&INDIRECT("Main!B9")&"'!B120")))} | C106: {=INDIRECT("'"&INDIRECT("Main!B12")&"'!C106")+SUM(E126+E153+E180)} -> 0
A107: {=IF((INDIRECT("'"&INDIRECT("Main!B9")&"'!A121"))=0,"",(INDIRECT("'"&INDIRECT("Main!B9")&"'!A121")))} | B107: {=IF((INDIRECT("'"&INDIRECT("Main!B9")&"'!B121"))=0,"",(INDIRECT("'"&INDIRECT("Main!B9")&"'!B121")))} | C107: {=INDIRECT("'"&INDIRECT("Main!B12")&"'!C107")+SUM(E127+E154+E181)} -> 0
B108: Total Debts | C108: =SUM(C98:C107) -> -10683
B109: Grand Total | C109: =C108-C96 -> -12052
A114: ="Debts Or Credits For the Comming "&IF(Main!B2,TEXT(EDATE(Main!B3,6),"mmmm dd yyyy"),TEXT(Main!B3+((Main!B5-Main!B3)*6+6),"mmmm dd yyyy"))&" to "&IF(Main!B2,TEXT(EDATE(Main!B3,7)-1,"mmmm dd yyyy"),TEXT(Main!B3+((Main!B5-Main!B3)*7+6),"mmmm dd yyyy")) -> Debts Or Credits For the Comming October 20 2024 to November 19 2024
A115: Principal | C115: Description | E115: Amount
...

Sheet January 2025 - March 2025
A1: ="Forecasts For the Year "&IF(Main!B2,TEXT(EDATE(Main!B3,9),"mmmm yyyy"),TEXT(Main!B3+((Main!B5-Main!B3)*9+9),"mmmm yyyy"))&" to "&IF(Main!B2,TEXT(EDATE(Main!B3,12)-1,"mmmm yyyy"),TEXT(Main!B3+((Main!B5-Main!B3)*12+11),"mmmm yyyy")) -> Forecasts For the Year January 2025 to April 2025
A2: Assets | B2: Overall | C2: {=INDIRECT("'"&Main!B9&"'!$C$16")} -> 1181.5
B3: Forecasts | C3: =E190 -> 166.5
A4: Total | C4: =SUM(C2:G3) -> 1348
A5: Net Debts: | C5: =C108 -> -6983
A8: =IF(Main!B2,TEXT(EDATE(Main!B3,9),"dd mmmm yyyy"),TEXT(Main!B3+((Main!B5-Main!B3)*9+9),"dd mmmm yyyy"))&" - "&IF(Main!B2,TEXT(EDATE(Main!B3,10)-1,"dd mmmm yyyy"),TEXT(Main!B3+((Main!B5-Main!B3)*10+9),"dd mmmm yyyy"))&" / "&" (Revenue / Deferred Debts Or Expenses)" -> 20 January 2025 - 19 February 2025 / (Revenue / Deferred Debts Or Expenses)
A9: Date | B9: Name | D9: Description | F9: Amount
A10: 20th January 2025 | B10: Social Welfare | D10: N/A | F10: 2405
A11: 31th January 2025 | B11: Salary | D11: Deduct 5% MPF | F11: 0
A12: 1. 29th January 2025 2. 28th January 2025 3. 2nd Feburary 2025 4. 8th Feburary 2025 | B12: 1. Chineses New Year (Mother and Father) 2. Chineses New Year (Lawrence) 3. Mother 4. Mother 5. Mother | D12: 1. Chinese New Year Pocket Lai See ~ $1000 2. Chinese New Year Pocket Lai See ~ $1000 3. Borrow $500 From Mother for buying whey protein 4. Remaining of $4.5 HK Dollar of $50 give by Mother 5. Mother give me $2 | F12: 2506.5
A13: 1. 7th Feburary 2025 2. 7th Feburary 2025 3. 18th Feburary 2025 | B13: 1. yuu 2. Wellcome Supermarket 3. yuu 4. OK Store | D13: 1. Newly added / remain yuu points ~ $6 2. Redeem Yuu Points ~ $10 3. Newly added / remain yuu points ~ $1 4. Received Additional $1 when billed ~ $1 | F13: 18
F14: 0
F15: 0
D16: Total Revenue | F16: =SUM(F10:G15) -> 4929.5
A20: =IF(Main!B2,TEXT(EDATE(Main!B3,10),"dd mmmm yyyy"),TEXT(Main!B3+((Main!B5-Main!B3)*10+10),"dd mmmm yyyy"))&" - "&IF(Main!B2,TEXT(EDATE(Main!B3,11)-1,"dd mmmm yyyy"),TEXT(Main!B3+((Main!B5-Main!B3)*11+10),"dd mmmm yyyy"))&" / "&" (Revenue / Deferred Debts Or Expenses)" -> 20 February 2025 - 19 March 2025 / (Revenue / Deferred Debts Or Expenses)
A21: Date | B21: Name | D21: Description | F21: Amount
A22: 20th February 2025 | B22: Social Welfare | D22: N/A | F22: 2435
A23: 29th February 2025 | B23: Salary | D23: Deduct 5% MPF | F23: 0
B24: Cigarette Egg | D24: Brought in Advance | F24: 0
B25: Birdie Sim Card | D25: Pay in advance For Birdie Sim Card | F25: 50
A26: 25th Feburary 2025 | B26: Mother | D26: Remaining of $16 HK Dollar of $100 give by Mother for visiting Dad. | F26: 16
A27: 1st March 2025 | B27: Lawrence | D27: Borrowed $800 For Electronic Cigarettes | F27: 800
D28: Total Revenue | F28: =SUM(F22:G27) -> 3301
A32: =IF(Main!B2,TEXT(EDATE(Main!B3,11),"dd mmmm yyyy"),TEXT(Main!B3+((Main!B5-Main!B3)*11+11),"dd mmmm yyyy"))&" - "&IF(Main!B2,TEXT(EDATE(Main!B3,12)-1,"dd mmmm yyyy"),TEXT(Main!B3+((Main!B5-Main!B3)*12+11),"dd mmmm yyyy"))&" / "&" (Revenue / Deferred Debts Or Expenses)" -> 20 March 2025 - 19 April 2025 / (Revenue / Deferred Debts Or Expenses)
A33: Date | B33: Name | D33: Description | F33: Amount
B34: Social Welfare | D34: N/A | F34: 2435
A35: 31st March 2025 | B35: Salary | D35: Deduct 5% MPF | F35: 0
B36: Birdie Sim Card | D36: Pay in advance For Birdie Sim Card | F36: 50
A37: 22th March 2025 | B37: Lawrence | D37: Lawrence give me $1000 as a gift for selling his house | F37: 1000
A38: 1st April 2025 | B38: 1. Yuu 2. Starbucks | D38: 1. Newly added / remain yuu points ~ $2 2. Newly added Starbucks Card ~ $60 | F38: 62
A39: 7th April 2025 | B39: Mother | D39: 1. Borrowed $500 From Mother. 2. Receive $25 From Mother | F39: 525
D40: Total Revenue | F40: =SUM(F34:G39) -> 4072
A44: ="Fixed Expense For the Year "&IF(Main!B2,TEXT(EDATE(Main!B3,9),"mmmm yyyy"),TEXT(Main!B3+((Main!B5-Main!B3)*9+9),"mmmm yyyy"))&" to "&IF(Main!B2,TEXT(EDATE(Main!B3,12)-1,"mmmm yyyy"),TEXT(Main!B3+((Main!B5-Main!B3)*12+11),"mmmm yyyy")) -> Fixed Expense For the Year January 2025 to April 2025
A45: Name | B45: Description | C45: Amount
A46: Mobile And Communications/ Housing Expenses
A47: {=IF((INDIRECT("'"&INDIRECT("Main!B9")&"'!A61"))=0,"",(INDIRECT("'"&INDIRECT("Main!B9")&"'!A61")))} -> Broadband | B47: {=IF((INDIRECT("'"&INDIRECT("Main!B9")&"'!B61"))=0,"",(INDIRECT("'"&INDIRECT("Main!B9")&"'!B61")))} | C47: 78
A48: {=IF((INDIRECT("'"&INDIRECT("Main!B9")&"'!A62"))=0,"",(INDIRECT("'"&INDIRECT("Main!B9")&"'!A62")))} -> China Mobile | B48: {=IF((INDIRECT("'"&INDIRECT("Main!B9")&"'!B62"))=0,"",(INDIRECT("'"&INDIRECT("Main!B9")&"'!B62")))} | C48: 149
A49: {=IF((INDIRECT("'"&INDIRECT("Main!B9")&"'!A63"))=0,"",(INDIRECT("'"&INDIRECT("Main!B9")&"'!A63")))} -> Telephone (Fixed Line) | B49: {=IF((INDIRECT("'"&INDIRECT("Main!B9")&"'!B63"))=0,"",(INDIRECT("'"&INDIRECT("Main!B9")&"'!B63")))} | C49: 0
A50: {=IF((INDIRECT("'"&INDIRECT("Main!B9")&"'!A64"))=0,"",(INDIRECT("'"&INDIRECT("Main!B9")&"'!A64")))} -> Sosim | B50: {=IF((INDIRECT("'"&INDIRECT("Main!B9")&"'!B64"))=0,"",(INDIRECT("'"&INDIRECT("Main!B9")&"'!B64")))} | C50: 0
A51: {=IF((INDIRECT("'"&INDIRECT("Main!B9")&"'!A65"))=0,"",(INDIRECT("'"&INDIRECT("Main!B9")&"'!A65")))} -> Birdie Sim Card Pay date (7th Of Each Month) | B51: {=IF((INDIRECT("'"&INDIRECT("Main!B9")&"'!B65"))=0,"",(INDIRECT("'"&INDIRECT("Main!B9")&"'!B65")))} | C51: 50
A52: {=IF((INDIRECT("'"&INDIRECT("Main!B9")&"'!A66"))=0,"",(INDIRECT("'"&INDIRECT("Main!B9")&"'!A66")))} | B52: {=IF((INDIRECT("'"&INDIRECT("Main!B9")&"'!B66"))=0,"",(INDIRECT("'"&INDIRECT("Main!B9")&"'!B66")))} | C52: 0
A53: {=IF((INDIRECT("'"&INDIRECT("Main!B9")&"'!A67"))=0,"",(INDIRECT("'"&INDIRECT("Main!B9")&"'!A67")))} | B53: {=IF((INDIRECT("'"&INDIRECT("Main!B9")&"'!B67"))=0,"",(INDIRECT("'"&INDIRECT("Main!B9")&"'!B67")))} | C53: 0
A54: {=IF((INDIRECT("'"&INDIRECT("Main!B9")&"'!A68"))=0,"",(INDIRECT("'"&INDIRECT("Main!B9")&"'!A68")))} | B54: {=IF((INDIRECT("'"&INDIRECT("Main!B9")&"'!B68"))=0,"",(INDIRECT("'"&INDIRECT("Main!B9")&"'!B68")))} | C54: 0
B55: Total Expenses | C55: =SUM(C47:C54) -> 277
A56: Credit Card Installments/Government Installments
A57: {=IF((INDIRECT("'"&INDIRECT("Main!B9")&"'!A71"))=0,"",(INDIRECT("'"&INDIRECT("Main!B9")&"'!A71")))} -> Citi Bank | B57: {=IF((INDIRECT("'"&INDIRECT("Main!B9")&"'!B71"))=0,"",(INDIRECT("'"&INDIRECT("Main!B9")&"'!B71")))} | C57: 0
A58: {=IF((INDIRECT("'"&INDIRECT("Main!B9")&"'!A72"))=0,"",(INDIRECT("'"&INDIRECT("Main!B9")&"'!A72")))} -> SC Bank | B58: {=IF((INDIRECT("'"&INDIRECT("Main!B9")&"'!B72"))=0,"",(INDIRECT("'"&INDIRECT("Main!B9")&"'!B72")))} | C58: 0
A59: {=IF((INDIRECT("'"&INDIRECT("Main!B9")&"'!A73"))=0,"",(INDIRECT("'"&INDIRECT("Main!B9")&"'!A73")))} -> Bank Of China | B59: {=IF((INDIRECT("'"&INDIRECT("Main!B9")&"'!B73"))=0,"",(INDIRECT("'"&INDIRECT("Main!B9")&"'!B73")))} | C59: 0
A60: {=IF((INDIRECT("'"&INDIRECT("Main!B9")&"'!A74"))=0,"",(INDIRECT("'"&INDIRECT("Main!B9")&"'!A74")))} -> HSBC | B60: {=IF((INDIRECT("'"&INDIRECT("Main!B9")&"'!B74"))=0,"",(INDIRECT("'"&INDIRECT("Main!B9")&"'!B74")))} | C60: 0
A61: {=IF((INDIRECT("'"&INDIRECT("Main!B9")&"'!A75"))=0,"",(INDIRECT("'"&INDIRECT("Main!B9")&"'!A75")))} | B61: {=IF((INDIRECT("'"&INDIRECT("Main!B9")&"'!B75"))=0,"",(INDIRECT("'"&INDIRECT("Main!B9")&"'!B75")))} | C61: 0
A62: {=IF((INDIRECT("'"&INDIRECT("Main!B9")&"'!A76"))=0,"",(INDIRECT("'"&INDIRECT("Main!B9")&"'!A76")))} | B62: {=IF((INDIRECT("'"&INDIRECT("Main!B9")&"'!B76"))=0,"",(INDIRECT("'"&INDIRECT("Main!B9")&"'!B76")))} | C62: 0
A63: {=IF((INDIRECT("'"&INDIRECT("Main!B9")&"'!A77"))=0,"",(INDIRECT("'"&INDIRECT("Main!B9")&"'!A77")))} | B63: {=IF((INDIRECT("'"&INDIRECT("Main!B9")&"'!B77"))=0,"",(INDIRECT("'"&INDIRECT("Main!B9")&"'!B77")))} | C63: 0
A64: {=IF((INDIRECT("'"&INDIRECT("Main!B9")&"'!A78"))=0,"",(INDIRECT("'"&INDIRECT("Main!B9")&"'!A78")))} | B64: {=IF((INDIRECT("'"&INDIRECT("Main!B9")&"'!B78"))=0,"",(INDIRECT("'"&INDIRECT("Main!B9")&"'!B78")))} | C64: 0
A65: {=IF((INDIRECT("'"&INDIRECT("Main!B9")&"'!A79"))=0,"",(INDIRECT("'"&INDIRECT("Main!B9")&"'!A79")))} | B65: {=IF((INDIRECT("'"&INDIRECT("Main!B9")&"'!B79"))=0,"",(INDIRECT("'"&INDIRECT("Main!B9")&"'!B79")))} | C65: 0
B66: Total Expenses | C66: =SUM(C57:C65) -> 0
A67: Donation
A68: {=IF((INDIRECT("'"&INDIRECT("Main!B9")&"'!A82"))=0,"",(INDIRECT("'"&INDIRECT("Main!B9")&"'!A82")))} -> Traversy | B68: {=IF((INDIRECT("'"&INDIRECT("Main!B9")&"'!B82"))=0,"",(INDIRECT("'"&INDIRECT("Main!B9")&"'!B82")))} -> Traversy Media | C68: 0
A69: {=IF((INDIRECT("'"&INDIRECT("Main!B9")&"'!A83"))=0,"",(INDIRECT("'"&INDIRECT("Main!B9")&"'!A83")))} -> Orbis | B69: {=IF((INDIRECT("'"&INDIRECT("Main!B9")&"'!B83"))=0,"",(INDIRECT("'"&INDIRECT("Main!B9")&"'!B83")))} -> Orbis Eye Flight | C69: 0
A70: {=IF((INDIRECT("'"&INDIRECT("Main!B9")&"'!A84"))=0,"",(INDIRECT("'"&INDIRECT("Main!B9")&"'!A84")))} | B70: {=IF((INDIRECT("'"&INDIRECT("Main!B9")&"'!B84"))=0,"",(INDIRECT("'"&INDIRECT("Main!B9")&"'!B84")))} | C70: 0
A71: {=IF((INDIRECT("'"&INDIRECT("Main!B9")&"'!A85"))=0,"",(INDIRECT("'"&INDIRECT("Main!B9")&"'!A85")))} | B71: {=IF((INDIRECT("'"&INDIRECT("Main!B9")&"'!B85"))=0,"",(INDIRECT("'"&INDIRECT("Main!B9")&"'!B85")))} | C71: 0
A72: {=IF((INDIRECT("'"&INDIRECT("Main!B9")&"'!A86"))=0,"",(INDIRECT("'"&INDIRECT("Main!B9")&"'!A86")))} | B72: {=IF((INDIRECT("'"&INDIRECT("Main!B9")&"'!B86"))=0,"",(INDIRECT("'"&INDIRECT("Main!B9")&"'!B86")))} | C72: 0
A73: {=IF((INDIRECT("'"&INDIRECT("Main!B9")&"'!A87"))=0,"",(INDIRECT("'"&INDIRECT("Main!B9")&"'!A87")))} | B73: {=IF((INDIRECT("'"&INDIRECT("Main!B9")&"'!B87"))=0,"",(INDIRECT("'"&INDIRECT("Main!B9")&"'!B87")))} | C73: 0
A74: {=IF((INDIRECT("'"&INDIRECT("Main!B9")&"'!A88"))=0,"",(INDIRECT("'"&INDIRECT("Main!B9")&"'!A88")))} | B74: {=IF((INDIRECT("'"&INDIRECT("Main!B9")&"'!B88"))=0,"",(INDIRECT("'"&INDIRECT("Main!B9")&"'!B88")))} | C74: 0
B75: Total Expenses | C75: =SUM(C68:C74) -> 0
A76: Insurance (Personal / Properties / Medical)
A77: {=IF((INDIRECT("'"&INDIRECT("Main!B9")&"'!A91"))=0,"",(INDIRECT("'"&INDIRECT("Main!B9")&"'!A91")))} -> AIA | B77: {=IF((INDIRECT("'"&INDIRECT("Main!B9")&"'!B91"))=0,"",(INDIRECT("'"&INDIRECT("Main!B9")&"'!B91")))} | C77: 0
A78: {=IF((INDIRECT("'"&INDIRECT("Main!B9")&"'!A92"))=0,"",(INDIRECT("'"&INDIRECT("Main!B9")&"'!A92")))} | B78: {=IF((INDIRECT("'"&INDIRECT("Main!B9")&"'!B92"))=0,"",(INDIRECT("'"&INDIRECT("Main!B9")&"'!B92")))} | C78: 0
A79: {=IF((INDIRECT("'"&INDIRECT("Main!B9")&"'!A93"))=0,"",(INDIRECT("'"&INDIRECT("Main!B9")&"'!A93")))} | B79: {=IF((INDIRECT("'"&INDIRECT("Main!B9")&"'!B93"))=0,"",(INDIRECT("'"&INDIRECT("Main!B9")&"'!B93")))} | C79: 0
A80: {=IF((INDIRECT("'"&INDIRECT("Main!B9")&"'!A94"))=0,"",(INDIRECT("'"&INDIRECT("Main!B9")&"'!A94")))} | B80: {=IF((INDIRECT("'"&INDIRECT("Main!B9")&"'!B94"))=0,"",(INDIRECT("'"&INDIRECT("Main!B9")&"'!B94")))} | C80: 0
A81: {=IF((INDIRECT("'"&INDIRECT("Main!B9")&"'!A95"))=0,"",(INDIRECT("'"&INDIRECT("Main!B9")&"'!A95")))} | B81: {=IF((INDIRECT("'"&INDIRECT("Main!B9")&"'!B95"))=0,"",(INDIRECT("'"&INDIRECT("Main!B9")&"'!B95")))} | C81: 0
A82: {=IF((INDIRECT("'"&INDIRECT("Main!B9")&"'!A96"))=0,"",(INDIRECT("'"&INDIRECT("Main!B9")&"'!A96")))} | B82: {=IF((INDIRECT("'"&INDIRECT("Main!B9")&"'!B96"))=0,"",(INDIRECT("'"&INDIRECT("Main!B9")&"'!B96")))} | C82: 0
A83: {=IF((INDIRECT("'"&INDIRECT("Main!B9")&"'!A97"))=0,"",(INDIRECT("'"&INDIRECT("Main!B9")&"'!A97")))} | B83: {=IF((INDIRECT("'"&INDIRECT("Main!B9")&"'!B97"))=0,"",(INDIRECT("'"&INDIRECT("Main!B9")&"'!B97")))} | C83: 0
A84: {=IF((INDIRECT("'"&INDIRECT("Main!B9")&"'!A98"))=0,"",(INDIRECT("'"&INDIRECT("Main!B9")&"'!A98")))} | B84: {=IF((INDIRECT("'"&INDIRECT("Main!B9")&"'!B98"))=0,"",(INDIRECT("'"&INDIRECT("Main!B9")&"'!B98")))} | C84: 0
B85: Total Expenses | C85: =SUM(C77:C84) -> 0
A86: Other Expenses
A87: {=IF((INDIRECT("'"&INDIRECT("Main!B9")&"'!A101"))=0,"",(INDIRECT("'"&INDIRECT("Main!B9")&"'!A101")))} -> Other Stuff | B87: {=IF((INDIRECT("'"&INDIRECT("Main!B9")&"'!B101"))=0,"",(INDIRECT("'"&INDIRECT("Main!B9")&"'!B101")))} -> Food, Transport…. | C87: 0
A88: {=IF((INDIRECT("'"&INDIRECT("Main!B9")&"'!A102"))=0,"",(INDIRECT("'"&INDIRECT("Main!B9")&"'!A102")))} -> Entertainment | B88: {=IF((INDIRECT("'"&INDIRECT("Main!B9")&"'!B102"))=0,"",(INDIRECT("'"&INDIRECT("Main!B9")&"'!B102")))} -> Sportify Music / Changed to Apple Music on 13th May 2025 | C88: 68
A89: {=IF((INDIRECT("'"&INDIRECT("Main!B9")&"'!A103"))=0,"",(INDIRECT("'"&INDIRECT("Main!B9")&"'!A103")))} -> Hair Cutting | B89: {=IF((INDIRECT("'"&INDIRECT("Main!B9")&"'!B103"))=0,"",(INDIRECT("'"&INDIRECT("Main!B9")&"'!B103")))} -> Hair Cut not Include Color treatment | C89: 52
A90: {=IF((INDIRECT("'"&INDIRECT("Main!B9")&"'!A104"))=0,"",(INDIRECT("'"&INDIRECT("Main!B9")&"'!A104")))} -> Cigarettes | B90: {=IF((INDIRECT("'"&INDIRECT("Main!B9")&"'!B104"))=0,"",(INDIRECT("'"&INDIRECT("Main!B9")&"'!B104")))} -> 30 packets | C90: 0
A91: {=IF((INDIRECT("'"&INDIRECT("Main!B9")&"'!A105"))=0,"",(INDIRECT("'"&INDIRECT("Main!B9")&"'!A105")))} | B91: {=IF((INDIRECT("'"&INDIRECT("Main!B9")&"'!B105"))=0,"",(INDIRECT("'"&INDIRECT("Main!B9")&"'!B105")))} | C91: 0
A92: {=IF((INDIRECT("'"&INDIRECT("Main!B9")&"'!A106"))=0,"",(INDIRECT("'"&INDIRECT("Main!B9")&"'!A106")))} | B92: {=IF((INDIRECT("'"&INDIRECT("Main!B9")&"'!B106"))=0,"",(INDIRECT("'"&INDIRECT("Main!B9")&"'!B106")))} | C92: 0
A93: {=IF((INDIRECT("'"&INDIRECT("Main!B9")&"'!A107"))=0,"",(INDIRECT("'"&INDIRECT("Main!B9")&"'!A107")))} | B93: {=IF((INDIRECT("'"&INDIRECT("Main!B9")&"'!B107"))=0,"",(INDIRECT("'"&INDIRECT("Main!B9")&"'!B107")))} | C93: 0
A94: {=IF((INDIRECT("'"&INDIRECT("Main!B9")&"'!A108"))=0,"",(INDIRECT("'"&INDIRECT("Main!B9")&"'!A108")))} | B94: {=IF((INDIRECT("'"&INDIRECT("Main!B9")&"'!B108"))=0,"",(INDIRECT("'"&INDIRECT("Main!B9")&"'!B108")))} | C94: 0
B95: Total Expenses | C95: =SUM(C87:C94) -> 120
B96: Grand Expenses Total | C96: =C55+C66+C75+C85+C95 -> 397
A97: Debts
A98: {=IF((INDIRECT("'"&INDIRECT("Main!B9")&"'!A112"))=0,"",(INDIRECT("'"&INDIRECT("Main!B9")&"'!A112")))} -> Mother | B98: {=IF((INDIRECT("'"&INDIRECT("Main!B9")&"'!B112"))=0,"",(INDIRECT("'"&INDIRECT("Main!B9")&"'!B112")))} | C98: {=INDIRECT("'"&INDIRECT("Main!B15")&"'!C98")+SUM(E118+E145+E172)} -> -5900
A99: {=IF((INDIRECT("'"&INDIRECT("Main!B9")&"'!A113"))=0,"",(INDIRECT("'"&INDIRECT("Main!B9")&"'!A113")))} -> Ng Wing Lam | B99: {=IF((INDIRECT("'"&INDIRECT("Main!B9")&"'!B113"))=0,"",(INDIRECT("'"&INDIRECT("Main!B9")&"'!B113")))} | C99: {=INDIRECT("'"&INDIRECT("Main!B15")&"'!C99")+SUM(E119+E146+E173)} -> 0
A100: {=IF((INDIRECT("'"&INDIRECT("Main!B9")&"'!A114"))=0,"",(INDIRECT("'"&INDIRECT("Main!B9")&"'!A114")))} -> Lawrence | B100: {=IF((INDIRECT("'"&INDIRECT("Main!B9")&"'!B114"))=0,"",(INDIRECT("'"&INDIRECT("Main!B9")&"'!B114")))} | C100: {=INDIRECT("'"&INDIRECT("Main!B15")&"'!C100")+SUM(E120+E147+E174)} -> 0
A101: {=IF((INDIRECT("'"&INDIRECT("Main!B9")&"'!A115"))=0,"",(INDIRECT("'"&INDIRECT("Main!B9")&"'!A115")))} -> Hong Kong Government Hospital Authority | B101: {=IF((INDIRECT("'"&INDIRECT("Main!B9")&"'!B115"))=0,"",(INDIRECT("'"&INDIRECT("Main!B9")&"'!B115")))} | C101: {=INDIRECT("'"&INDIRECT("Main!B15")&"'!C101")+SUM(E121+E148+E175)} -> 0
A102: {=IF((INDIRECT("'"&INDIRECT("Main!B9")&"'!A116"))=0,"",(INDIRECT("'"&INDIRECT("Main!B9")&"'!A116")))} -> Bankruptcy Department / Bank | B102: {=IF((INDIRECT("'"&INDIRECT("Main!B9")&"'!B116"))=0,"",(INDIRECT("'"&INDIRECT("Main!B9")&"'!B116")))} | C102: {=INDIRECT("'"&INDIRECT("Main!B15")&"'!C102")+SUM(E122+E149+E176)} -> 0
A103: {=IF((INDIRECT("'"&INDIRECT("Main!B9")&"'!A117"))=0,"",(INDIRECT("'"&INDIRECT("Main!B9")&"'!A117")))} -> Mother Air Ticket | B103: {=IF((INDIRECT("'"&INDIRECT("Main!B9")&"'!B117"))=0,"",(INDIRECT("'"&INDIRECT("Main!B9")&"'!B117")))} | C103: {=INDIRECT("'"&INDIRECT("Main!B15")&"'!C103")+SUM(E123+E150+E177)} -> -1083
A104: {=IF((INDIRECT("'"&INDIRECT("Main!B9")&"'!A118"))=0,"",(INDIRECT("'"&INDIRECT("Main!B9")&"'!A118")))} | B104: {=IF((INDIRECT("'"&INDIRECT("Main!B9")&"'!B118"))=0,"",(INDIRECT("'"&INDIRECT("Main!B9")&"'!B118")))} | C104: {=INDIRECT("'"&INDIRECT("Main!B15")&"'!C104")+SUM(E124+E151+E178)} -> 0
A105: {=IF((INDIRECT("'"&INDIRECT("Main!B9")&"'!A119"))=0,"",(INDIRECT("'"&INDIRECT("Main!B9")&"'!A119")))} | B105: {=IF((INDIRECT("'"&INDIRECT("Main!B9")&"'!B119"))=0,"",(INDIRECT("'"&INDIRECT("Main!B9")&"'!B119")))} | C105: {=INDIRECT("'"&INDIRECT("Main!B15")&"'!C105")+SUM(E125+E152+E179)} -> 0
A106: {=IF((INDIRECT("'"&INDIRECT("Main!B9")&"'!A120"))=0,"",(INDIRECT("'"&INDIRECT("Main!B9")&"'!A120")))} | B106: {=IF((INDIRECT("'"&INDIRECT("Main!B9")&"'!B120"))=0,"",(INDIRECT("'"&INDIRECT("Main!B9")&"'!B120")))} | C106: {=INDIRECT("'"&INDIRECT("Main!B15")&"'!C106")+SUM(E126+E153+E180)} -> 0
A107: {=IF((INDIRECT("'"&INDIRECT("Main!B9")&"'!A121"))=0,"",(INDIRECT("'"&INDIRECT("Main!B9")&"'!A121")))} | B107: {=IF((INDIRECT("'"&INDIRECT("Main!B9")&"'!B121"))=0,"",(INDIRECT("'"&INDIRECT("Main!B9")&"'!B121")))} | C107: {=INDIRECT("'"&INDIRECT("Main!B15")&"'!C107")+SUM(E127+E154+E181)} -> 0
B108: Total Debts | C108: =SUM(C98:C107) -> -6983
B109: Grand Total | C109: =C108-C96 -> -7380
A114: ="Debts Or Credits For the Comming "&IF(Main!B2,TEXT(EDATE(Main!B3,9),"mmmm dd yyyy"),TEXT(Main!B3+((Main!B5-Main!B3)*9+9),"mmmm dd yyyy"))&" to "&IF(Main!B2,TEXT(EDATE(Main!B3,10)-1,"mmmm dd yyyy"),TEXT(Main!B3+((Main!B5-Main!B3)*10+9),"mmmm dd yyyy")) -> Debts Or Credits For the Comming January 20 2025 to February 19 2025
A115: Principal | C115: Description | E115: Amount
...

Sheet April 2025 - June 2025
A1: ="Forecasts For the Year "&IF(Main!B2,TEXT(EDATE(Main!B3,12),"mmmm yyyy"),TEXT(Main!B3+((Main!B5-Main!B3)*12+12),"mmmm yyyy"))&" to "&IF(Main!B2,TEXT(EDATE(Main!B3,15)-1,"mmmm yyyy"),TEXT(Main!B3+((Main!B5-Main!B3)*15+14),"mmmm yyyy")) -> Forecasts For the Year April 2025 to July 2025
A2: Assets | B2: Overall | C2: {=INDIRECT("'"&Main!B9&"'!$C$16")} -> 1181.5
B3: Forecasts | C3: =E190 -> 967.5
A4: Total | C4: =SUM(C2:G3) -> 2149
A5: Net Debts: | C5: =C108 -> -3083
A8: =IF(Main!B2,TEXT(EDATE(Main!B3,12),"dd mmmm yyyy"),TEXT(Main!B3+((Main!B5-Main!B3)*12+12),"dd mmmm yyyy"))&" - "&IF(Main!B2,TEXT(EDATE(Main!B3,13)-1,"dd mmmm yyyy"),TEXT(Main!B3+((Main!B5-Main!B3)*13+12),"dd mmmm yyyy"))&" / "&" (Revenue / Deferred Debts Or Expenses)" -> 20 April 2025 - 19 May 2025 / (Revenue / Deferred Debts Or Expenses)
A9: Date | B9: Name | D9: Description | F9: Amount
B10: Social Welfare | D10: N/A | F10: 2435
B11: Cigarette Egg | D11: Brought in Advance | F11: 0
A12: 30th April 2025 | B12: Salary | D12: Deduct 5% MPF | F12: 0
B13: Birdie | D13: Birdie Paid in advance | F13: 50
B14: 1. yuu 2. Google Play | D14: 1. Newly added / remain yuu points ~ $1 2. Google Play Newly top up $136 | F14: 137
F15: 0
D16: Total Revenue | F16: =SUM(F10:G15) -> 2622
A20: =IF(Main!B2,TEXT(EDATE(Main!B3,13),"dd mmmm yyyy"),TEXT(Main!B3+((Main!B5-Main!B3)*13+13),"dd mmmm yyyy"))&" - "&IF(Main!B2,TEXT(EDATE(Main!B3,14)-1,"dd mmmm yyyy"),TEXT(Main!B3+((Main!B5-Main!B3)*14+13),"dd mmmm yyyy"))&" / "&" (Revenue / Deferred Debts Or Expenses)" -> 20 May 2025 - 19 June 2025 / (Revenue / Deferred Debts Or Expenses)
A21: Date | B21: Name | D21: Description | F21: Amount
B22: Social Welfare | D22: N/A | F22: 2435
A23: 31th May 2025 | B23: Salary | D23: Deduct 5% MPF | F23: 0
B24: Social Welfare | D24: Additional Half Month Of Allowance | F24: 1035
F25: 0
F26: 0
F27: 0
D28: Total Revenue | F28: =SUM(F22:G27) -> 3470
A32: =IF(Main!B2,TEXT(EDATE(Main!B3,14),"dd mmmm yyyy"),TEXT(Main!B3+((Main!B5-Main!B3)*14+14),"dd mmmm yyyy"))&" - "&IF(Main!B2,TEXT(EDATE(Main!B3,15)-1,"dd mmmm yyyy"),TEXT(Main!B3+((Main!B5-Main!B3)*15+14),"dd mmmm yyyy"))&" / "&" (Revenue / Deferred Debts Or Expenses)" -> 20 June 2025 - 19 July 2025 / (Revenue / Deferred Debts Or Expenses)
A33: Date | B33: Name | D33: Description | F33: Amount
B34: Social Welfare | D34: N/A | F34: 2435
A35: 30th June 2025 | B35: Salary | D35: Deduct 5% MPF | F35: 0
B36: Cigarette Egg | D36: Brought in Advance | F36: 0
F37: 0
F38: 0
F39: 0
D40: Total Revenue | F40: =SUM(F34:G39) -> 2435
A44: ="Fixed Expense For the Year "&IF(Main!B2,TEXT(EDATE(Main!B3,12),"mmmm yyyy"),TEXT(Main!B3+((Main!B5-Main!B3)*12+12),"mmmm yyyy"))&" to "&IF(Main!B2,TEXT(EDATE(Main!B3,15)-1,"mmmm yyyy"),TEXT(Main!B3+((Main!B5-Main!B3)*15+14),"mmmm yyyy")) -> Fixed Expense For the Year April 2025 to July 2025
A45: Name | B45: Description | C45: Amount
A46: Mobile And Communications/ Housing Expenses
A47: {=IF((INDIRECT("'"&INDIRECT("Main!B9")&"'!A61"))=0,"",(INDIRECT("'"&INDIRECT("Main!B9")&"'!A61")))} -> Broadband | B47: {=IF((INDIRECT("'"&INDIRECT("Main!B9")&"'!B61"))=0,"",(INDIRECT("'"&INDIRECT("Main!B9")&"'!B61")))} | C47: 78
A48: {=IF((INDIRECT("'"&INDIRECT("Main!B9")&"'!A62"))=0,"",(INDIRECT("'"&INDIRECT("Main!B9")&"'!A62")))} -> China Mobile | B48: {=IF((INDIRECT("'"&INDIRECT("Main!B9")&"'!B62"))=0,"",(INDIRECT("'"&INDIRECT("Main!B9")&"'!B62")))} | C48: 149
A49: {=IF((INDIRECT("'"&INDIRECT("Main!B9")&"'!A63"))=0,"",(INDIRECT("'"&INDIRECT("Main!B9")&"'!A63")))} -> Telephone (Fixed Line) | B49: {=IF((INDIRECT("'"&INDIRECT("Main!B9")&"'!B63"))=0,"",(INDIRECT("'"&INDIRECT("Main!B9")&"'!B63")))} | C49: 0
A50: {=IF((INDIRECT("'"&INDIRECT("Main!B9")&"'!A64"))=0,"",(INDIRECT("'"&INDIRECT("Main!B9")&"'!A64")))} -> Sosim | B50: {=IF((INDIRECT("'"&INDIRECT("Main!B9")&"'!B64"))=0,"",(INDIRECT("'"&INDIRECT("Main!B9")&"'!B64")))} | C50: 0
A51: {=IF((INDIRECT("'"&INDIRECT("Main!B9")&"'!A65"))=0,"",(INDIRECT("'"&INDIRECT("Main!B9")&"'!A65")))} -> Birdie Sim Card Pay date (7th Of Each Month) | B51: {=IF((INDIRECT("'"&INDIRECT("Main!B9")&"'!B65"))=0,"",(INDIRECT("'"&INDIRECT("Main!B9")&"'!B65")))} | C51: 50
A52: {=IF((INDIRECT("'"&INDIRECT("Main!B9")&"'!A66"))=0,"",(INDIRECT("'"&INDIRECT("Main!B9")&"'!A66")))} | B52: {=IF((INDIRECT("'"&INDIRECT("Main!B9")&"'!B66"))=0,"",(INDIRECT("'"&INDIRECT("Main!B9")&"'!B66")))} | C52: 0
A53: {=IF((INDIRECT("'"&INDIRECT("Main!B9")&"'!A67"))=0,"",(INDIRECT("'"&INDIRECT("Main!B9")&"'!A67")))} | B53: {=IF((INDIRECT("'"&INDIRECT("Main!B9")&"'!B67"))=0,"",(INDIRECT("'"&INDIRECT("Main!B9")&"'!B67")))} | C53: 0
A54: {=IF((INDIRECT("'"&INDIRECT("Main!B9")&"'!A68"))=0,"",(INDIRECT("'"&INDIRECT("Main!B9")&"'!A68")))} | B54: {=IF((INDIRECT("'"&INDIRECT("Main!B9")&"'!B68"))=0,"",(INDIRECT("'"&INDIRECT("Main!B9")&"'!B68")))} | C54: 0
B55: Total Expenses | C55: =SUM(C47:C54) -> 277
A56: Credit Card Installments/Government Installments
A57: {=IF((INDIRECT("'"&INDIRECT("Main!B9")&"'!A71"))=0,"",(INDIRECT("'"&INDIRECT("Main!B9")&"'!A71")))} -> Citi Bank | B57: {=IF((INDIRECT("'"&INDIRECT("Main!B9")&"'!B71"))=0,"",(INDIRECT("'"&INDIRECT("Main!B9")&"'!B71")))} | C57: 0
A58: {=IF((INDIRECT("'"&INDIRECT("Main!B9")&"'!A72"))=0,"",(INDIRECT("'"&INDIRECT("Main!B9")&"'!A72")))} -> SC Bank | B58: {=IF((INDIRECT("'"&INDIRECT("Main!B9")&"'!B72"))=0,"",(INDIRECT("'"&INDIRECT("Main!B9")&"'!B72")))} | C58: 0
A59: {=IF((INDIRECT("'"&INDIRECT("Main!B9")&"'!A73"))=0,"",(INDIRECT("'"&INDIRECT("Main!B9")&"'!A73")))} -> Bank Of China | B59: {=IF((INDIRECT("'"&INDIRECT("Main!B9")&"'!B73"))=0,"",(INDIRECT("'"&INDIRECT("Main!B9")&"'!B73")))} | C59: 0
A60: {=IF((INDIRECT("'"&INDIRECT("Main!B9")&"'!A74"))=0,"",(INDIRECT("'"&INDIRECT("Main!B9")&"'!A74")))} -> HSBC | B60: {=IF((INDIRECT("'"&INDIRECT("Main!B9")&"'!B74"))=0,"",(INDIRECT("'"&INDIRECT("Main!B9")&"'!B74")))} | C60: 0
A61: {=IF((INDIRECT("'"&INDIRECT("Main!B9")&"'!A75"))=0,"",(INDIRECT("'"&INDIRECT("Main!B9")&"'!A75")))} | B61: {=IF((INDIRECT("'"&INDIRECT("Main!B9")&"'!B75"))=0,"",(INDIRECT("'"&INDIRECT("Main!B9")&"'!B75")))} | C61: 0
A62: {=IF((INDIRECT("'"&INDIRECT("Main!B9")&"'!A76"))=0,"",(INDIRECT("'"&INDIRECT("Main!B9")&"'!A76")))} | B62: {=IF((INDIRECT("'"&INDIRECT("Main!B9")&"'!B76"))=0,"",(INDIRECT("'"&INDIRECT("Main!B9")&"'!B76")))} | C62: 0
A63: {=IF((INDIRECT("'"&INDIRECT("Main!B9")&"'!A77"))=0,"",(INDIRECT("'"&INDIRECT("Main!B9")&"'!A77")))} | B63: {=IF((INDIRECT("'"&INDIRECT("Main!B9")&"'!B77"))=0,"",(INDIRECT("'"&INDIRECT("Main!B9")&"'!B77")))} | C63: 0
A64: {=IF((INDIRECT("'"&INDIRECT("Main!B9")&"'!A78"))=0,"",(INDIRECT("'"&INDIRECT("Main!B9")&"'!A78")))} | B64: {=IF((INDIRECT("'"&INDIRECT("Main!B9")&"'!B78"))=0,"",(INDIRECT("'"&INDIRECT("Main!B9")&"'!B78")))} | C64: 0
A65: {=IF((INDIRECT("'"&INDIRECT("Main!B9")&"'!A79"))=0,"",(INDIRECT("'"&INDIRECT("Main!B9")&"'!A79")))} | B65: {=IF((INDIRECT("'"&INDIRECT("Main!B9")&"'!B79"))=0,"",(INDIRECT("'"&INDIRECT("Main!B9")&"'!B79")))} | C65: 0
B66: Total Expenses | C66: =SUM(C57:C65) -> 0
A67: Donation
A68: {=IF((INDIRECT("'"&INDIRECT("Main!B9")&"'!A82"))=0,"",(INDIRECT("'"&INDIRECT("Main!B9")&"'!A82")))} -> Traversy | B68: {=IF((INDIRECT("'"&INDIRECT("Main!B9")&"'!B82"))=0,"",(INDIRECT("'"&INDIRECT("Main!B9")&"'!B82")))} -> Traversy Media | C68: 0
A69: {=IF((INDIRECT("'"&INDIRECT("Main!B9")&"'!A83"))=0,"",(INDIRECT("'"&INDIRECT("Main!B9")&"'!A83")))} -> Orbis | B69: {=IF((INDIRECT("'"&INDIRECT("Main!B9")&"'!B83"))=0,"",(INDIRECT("'"&INDIRECT("Main!B9")&"'!B83")))} -> Orbis Eye Flight | C69: 0
A70: {=IF((INDIRECT("'"&INDIRECT("Main!B9")&"'!A84"))=0,"",(INDIRECT("'"&INDIRECT("Main!B9")&"'!A84")))} | B70: {=IF((INDIRECT("'"&INDIRECT("Main!B9")&"'!B84"))=0,"",(INDIRECT("'"&INDIRECT("Main!B9")&"'!B84")))} | C70: 0
A71: {=IF((INDIRECT("'"&INDIRECT("Main!B9")&"'!A85"))=0,"",(INDIRECT("'"&INDIRECT("Main!B9")&"'!A85")))} | B71: {=IF((INDIRECT("'"&INDIRECT("Main!B9")&"'!B85"))=0,"",(INDIRECT("'"&INDIRECT("Main!B9")&"'!B85")))} | C71: 0
A72: {=IF((INDIRECT("'"&INDIRECT("Main!B9")&"'!A86"))=0,"",(INDIRECT("'"&INDIRECT("Main!B9")&"'!A86")))} | B72: {=IF((INDIRECT("'"&INDIRECT("Main!B9")&"'!B86"))=0,"",(INDIRECT("'"&INDIRECT("Main!B9")&"'!B86")))} | C72: 0
A73: {=IF((INDIRECT("'"&INDIRECT("Main!B9")&"'!A87"))=0,"",(INDIRECT("'"&INDIRECT("Main!B9")&"'!A87")))} | B73: {=IF((INDIRECT("'"&INDIRECT("Main!B9")&"'!B87"))=0,"",(INDIRECT("'"&INDIRECT("Main!B9")&"'!B87")))} | C73: 0
A74: {=IF((INDIRECT("'"&INDIRECT("Main!B9")&"'!A88"))=0,"",(INDIRECT("'"&INDIRECT("Main!B9")&"'!A88")))} | B74: {=IF((INDIRECT("'"&INDIRECT("Main!B9")&"'!B88"))=0,"",(INDIRECT("'"&INDIRECT("Main!B9")&"'!B88")))} | C74: 0
B75: Total Expenses | C75: =SUM(C68:C74) -> 0
A76: Insurance (Personal / Properties / Medical)
A77: {=IF((INDIRECT("'"&INDIRECT("Main!B9")&"'!A91"))=0,"",(INDIRECT("'"&INDIRECT("Main!B9")&"'!A91")))} -> AIA | B77: {=IF((INDIRECT("'"&INDIRECT("Main!B9")&"'!B91"))=0,"",(INDIRECT("'"&INDIRECT("Main!B9")&"'!B91")))} | C77: 0
A78: {=IF((INDIRECT("'"&INDIRECT("Main!B9")&"'!A92"))=0,"",(INDIRECT("'"&INDIRECT("Main!B9")&"'!A92")))} | B78: {=IF((INDIRECT("'"&INDIRECT("Main!B9")&"'!B92"))=0,"",(INDIRECT("'"&INDIRECT("Main!B9")&"'!B92")))} | C78: 0
A79: {=IF((INDIRECT("'"&INDIRECT("Main!B9")&"'!A93"))=0,"",(INDIRECT("'"&INDIRECT("Main!B9")&"'!A93")))} | B79: {=IF((INDIRECT("'"&INDIRECT("Main!B9")&"'!B93"))=0,"",(INDIRECT("'"&INDIRECT("Main!B9")&"'!B93")))} | C79: 0
A80: {=IF((INDIRECT("'"&INDIRECT("Main!B9")&"'!A94"))=0,"",(INDIRECT("'"&INDIRECT("Main!B9")&"'!A94")))} | B80: {=IF((INDIRECT("'"&INDIRECT("Main!B9")&"'!B94"))=0,"",(INDIRECT("'"&INDIRECT("Main!B9")&"'!B94")))} | C80: 0
A81: {=IF((INDIRECT("'"&INDIRECT("Main!B9")&"'!A95"))=0,"",(INDIRECT("'"&INDIRECT("Main!B9")&"'!A95")))} | B81: {=IF((INDIRECT("'"&INDIRECT("Main!B9")&"'!B95"))=0,"",(INDIRECT("'"&INDIRECT("Main!B9")&"'!B95")))} | C81: 0
A82: {=IF((INDIRECT("'"&INDIRECT("Main!B9")&"'!A96"))=0,"",(INDIRECT("'"&INDIRECT("Main!B9")&"'!A96")))} | B82: {=IF((INDIRECT("'"&INDIRECT("Main!B9")&"'!B96"))=0,"",(INDIRECT("'"&INDIRECT("Main!B9")&"'!B96")))} | C82: 0
A83: {=IF((INDIRECT("'"&INDIRECT("Main!B9")&"'!A97"))=0,"",(INDIRECT("'"&INDIRECT("Main!B9")&"'!A97")))} | B83: {=IF((INDIRECT("'"&INDIRECT("Main!B9")&"'!B97"))=0,"",(INDIRECT("'"&INDIRECT("Main!B9")&"'!B97")))} | C83: 0
A84: {=IF((INDIRECT("'"&INDIRECT("Main!B9")&"'!A98"))=0,"",(INDIRECT("'"&INDIRECT("Main!B9")&"'!A98")))} | B84: {=IF((INDIRECT("'"&INDIRECT("Main!B9")&"'!B98"))=0,"",(INDIRECT("'"&INDIRECT("Main!B9")&"'!B98")))} | C84: 0
B85: Total Expenses | C85: =SUM(C77:C84) -> 0
A86: Other Expenses
A87: {=IF((INDIRECT("'"&INDIRECT("Main!B9")&"'!A101"))=0,"",(INDIRECT("'"&INDIRECT("Main!B9")&"'!A101")))} -> Other Stuff | B87: {=IF((INDIRECT("'"&INDIRECT("Main!B9")&"'!B101"))=0,"",(INDIRECT("'"&INDIRECT("Main!B9")&"'!B101")))} -> Food, Transport…. | C87: 0
A88: {=IF((INDIRECT("'"&INDIRECT("Main!B9")&"'!A102"))=0,"",(INDIRECT("'"&INDIRECT("Main!B9")&"'!A102")))} -> Entertainment | B88: {=IF((INDIRECT("'"&INDIRECT("Main!B9")&"'!B102"))=0,"",(INDIRECT("'"&INDIRECT("Main!B9")&"'!B102")))} -> Sportify Music / Changed to Apple Music on 13th May 2025 | C88: 68
A89: {=IF((INDIRECT("'"&INDIRECT("Main!B9")&"'!A103"))=0,"",(INDIRECT("'"&INDIRECT("Main!B9")&"'!A103")))} -> Hair Cutting | B89: {=IF((INDIRECT("'"&INDIRECT("Main!B9")&"'!B103"))=0,"",(INDIRECT("'"&INDIRECT("Main!B9")&"'!B103")))} -> Hair Cut not Include Color treatment | C89: 55
A90: {=IF((INDIRECT("'"&INDIRECT("Main!B9")&"'!A104"))=0,"",(INDIRECT("'"&INDIRECT("Main!B9")&"'!A104")))} -> Cigarettes | B90: {=IF((INDIRECT("'"&INDIRECT("Main!B9")&"'!B104"))=0,"",(INDIRECT("'"&INDIRECT("Main!B9")&"'!B104")))} -> 30 packets | C90: 0
A91: {=IF((INDIRECT("'"&INDIRECT("Main!B9")&"'!A105"))=0,"",(INDIRECT("'"&INDIRECT("Main!B9")&"'!A105")))} | B91: {=IF((INDIRECT("'"&INDIRECT("Main!B9")&"'!B105"))=0,"",(INDIRECT("'"&INDIRECT("Main!B9")&"'!B105")))} | C91: 0
A92: {=IF((INDIRECT("'"&INDIRECT("Main!B9")&"'!A106"))=0,"",(INDIRECT("'"&INDIRECT("Main!B9")&"'!A106")))} | B92: {=IF((INDIRECT("'"&INDIRECT("Main!B9")&"'!B106"))=0,"",(INDIRECT("'"&INDIRECT("Main!B9")&"'!B106")))} | C92: 0
A93: {=IF((INDIRECT("'"&INDIRECT("Main!B9")&"'!A107"))=0,"",(INDIRECT("'"&INDIRECT("Main!B9")&"'!A107")))} | B93: {=IF((INDIRECT("'"&INDIRECT("Main!B9")&"'!B107"))=0,"",(INDIRECT("'"&INDIRECT("Main!B9")&"'!B107")))} | C93: 0
A94: {=IF((INDIRECT("'"&INDIRECT("Main!B9")&"'!A108"))=0,"",(INDIRECT("'"&INDIRECT("Main!B9")&"'!A108")))} | B94: {=IF((INDIRECT("'"&INDIRECT("Main!B9")&"'!B108"))=0,"",(INDIRECT("'"&INDIRECT("Main!B9")&"'!B108")))} | C94: 0
B95: Total Expenses | C95: =SUM(C87:C94) -> 123
B96: Grand Expenses Total | C96: =C55+C66+C75+C85+C95 -> 400
A97: Debts
A98: {=IF((INDIRECT("'"&INDIRECT("Main!B9")&"'!A112"))=0,"",(INDIRECT("'"&INDIRECT("Main!B9")&"'!A112")))} -> Mother | B98: {=IF((INDIRECT("'"&INDIRECT("Main!B9")&"'!B112"))=0,"",(INDIRECT("'"&INDIRECT("Main!B9")&"'!B112")))} | C98: {=INDIRECT("'"&INDIRECT("Main!B18")&"'!C98")+SUM(E118+E145+E172)} -> -2000
A99: {=IF((INDIRECT("'"&INDIRECT("Main!B9")&"'!A113"))=0,"",(INDIRECT("'"&INDIRECT("Main!B9")&"'!A113")))} -> Ng Wing Lam | B99: {=IF((INDIRECT("'"&INDIRECT("Main!B9")&"'!B113"))=0,"",(INDIRECT("'"&INDIRECT("Main!B9")&"'!B113")))} | C99: {=INDIRECT("'"&INDIRECT("Main!B18")&"'!C99")+SUM(E119+E146+E173)} -> 0
A100: {=IF((INDIRECT("'"&INDIRECT("Main!B9")&"'!A114"))=0,"",(INDIRECT("'"&INDIRECT("Main!B9")&"'!A114")))} -> Lawrence | B100: {=IF((INDIRECT("'"&INDIRECT("Main!B9")&"'!B114"))=0,"",(INDIRECT("'"&INDIRECT("Main!B9")&"'!B114")))} | C100: {=INDIRECT("'"&INDIRECT("Main!B18")&"'!C100")+SUM(E120+E147+E174)} -> 0
A101: {=IF((INDIRECT("'"&INDIRECT("Main!B9")&"'!A115"))=0,"",(INDIRECT("'"&INDIRECT("Main!B9")&"'!A115")))} -> Hong Kong Government Hospital Authority | B101: {=IF((INDIRECT("'"&INDIRECT("Main!B9")&"'!B115"))=0,"",(INDIRECT("'"&INDIRECT("Main!B9")&"'!B115")))} | C101: {=INDIRECT("'"&INDIRECT("Main!B18")&"'!C101")+SUM(E121+E148+E175)} -> 0
A102: {=IF((INDIRECT("'"&INDIRECT("Main!B9")&"'!A116"))=0,"",(INDIRECT("'"&INDIRECT("Main!B9")&"'!A116")))} -> Bankruptcy Department / Bank | B102: {=IF((INDIRECT("'"&INDIRECT("Main!B9")&"'!B116"))=0,"",(INDIRECT("'"&INDIRECT("Main!B9")&"'!B116")))} | C102: {=INDIRECT("'"&INDIRECT("Main!B18")&"'!C102")+SUM(E122+E149+E176)} -> 0
A103: {=IF((INDIRECT("'"&INDIRECT("Main!B9")&"'!A117"))=0,"",(INDIRECT("'"&INDIRECT("Main!B9")&"'!A117")))} -> Mother Air Ticket | B103: {=IF((INDIRECT("'"&INDIRECT("Main!B9")&"'!B117"))=0,"",(INDIRECT("'"&INDIRECT("Main!B9")&"'!B117")))} | C103: {=INDIRECT("'"&INDIRECT("Main!B18")&"'!C103")+SUM(E123+E150+E177)} -> -1083
A104: {=IF((INDIRECT("'"&INDIRECT("Main!B9")&"'!A118"))=0,"",(INDIRECT("'"&INDIRECT("Main!B9")&"'!A118")))} | B104: {=IF((INDIRECT("'"&INDIRECT("Main!B9")&"'!B118"))=0,"",(INDIRECT("'"&INDIRECT("Main!B9")&"'!B118")))} | C104: {=INDIRECT("'"&INDIRECT("Main!B18")&"'!C104")+SUM(E124+E151+E178)} -> 0
A105: {=IF((INDIRECT("'"&INDIRECT("Main!B9")&"'!A119"))=0,"",(INDIRECT("'"&INDIRECT("Main!B9")&"'!A119")))} | B105: {=IF((INDIRECT("'"&INDIRECT("Main!B9")&"'!B119"))=0,"",(INDIRECT("'"&INDIRECT("Main!B9")&"'!B119")))} | C105: {=INDIRECT("'"&INDIRECT("Main!B18")&"'!C105")+SUM(E125+E152+E179)} -> 0
A106: {=IF((INDIRECT("'"&INDIRECT("Main!B9")&"'!A120"))=0,"",(INDIRECT("'"&INDIRECT("Main!B9")&"'!A120")))} | B106: {=IF((INDIRECT("'"&INDIRECT("Main!B9")&"'!B120"))=0,"",(INDIRECT("'"&INDIRECT("Main!B9")&"'!B120")))} | C106: {=INDIRECT("'"&INDIRECT("Main!B18")&"'!C106")+SUM(E126+E153+E180)} -> 0
A107: {=IF((INDIRECT("'"&INDIRECT("Main!B9")&"'!A121"))=0,"",(INDIRECT("'"&INDIRECT("Main!B9")&"'!A121")))} | B107: {=IF((INDIRECT("'"&INDIRECT("Main!B9")&"'!B121"))=0,"",(INDIRECT("'"&INDIRECT("Main!B9")&"'!B121")))} | C107: {=INDIRECT("'"&INDIRECT("Main!B18")&"'!C107")+SUM(E127+E154+E181)} -> 0
B108: Total Debts | C108: =SUM(C98:C107) -> -3083
B109: Grand Total | C109: =C108-C96 -> -3483
A114: ="Debts Or Credits For the Comming "&IF(Main!B2,TEXT(EDATE(Main!B3,12),"mmmm dd yyyy"),TEXT(Main!B3+((Main!B5-Main!B3)*12+12),"mmmm dd yyyy"))&" to "&IF(Main!B2,TEXT(EDATE(Main!B3,13)-1,"mmmm dd yyyy"),TEXT(Main!B3+((Main!B5-Main!B3)*13+12),"mmmm dd yyyy")) -> Debts Or Credits For the Comming April 20 2025 to May 19 2025
A115: Principal | C115: Description | E115: Amount
...

Sheet July 2025 - September 2025
A1: ="Forecasts For the Year "&IF(Main!B2,TEXT(EDATE(Main!B3,15),"mmmm yyyy"),TEXT(Main!B3+((Main!B5-Main!B3)*15+15),"mmmm yyyy"))&" to "&IF(Main!B2,TEXT(EDATE(Main!B3,18)-1,"mmmm yyyy"),TEXT(Main!B3+((Main!B5-Main!B3)*18+17),"mmmm yyyy")) -> Forecasts For the Year July 2025 to October 2025
A2: Assets | B2: Overall | C2: {=INDIRECT("'"&Main!B9&"'!$C$16")} -> 1181.5
B3: Forecasts | C3: =E190 -> 775.5
A4: Total | C4: =SUM(C2:G3) -> 1957
A5: Net Debts: | C5: =C108 -> 0
A8: =IF(Main!B2,TEXT(EDATE(Main!B3,15),"dd mmmm yyyy"),TEXT(Main!B3+((Main!B5-Main!B3)*15+15),"dd mmmm yyyy"))&" - "&IF(Main!B2,TEXT(EDATE(Main!B3,16)-1,"dd mmmm yyyy"),TEXT(Main!B3+((Main!B5-Main!B3)*16+15),"dd mmmm yyyy"))&" / "&" (Revenue / Deferred Debts Or Expenses)" -> 20 July 2025 - 19 August 2025 / (Revenue / Deferred Debts Or Expenses)
A9: Date | B9: Name | D9: Description | F9: Amount
B10: Social Welfare | D10: N/A | F10: 2435
A11: 31st July 2025 | B11: Salary | D11: Deduct 5% MPF | F11: 0
B12: Mother Salary | D12: Deferred Salary to next Month | F12: 0
F13: 0
F14: 0
F15: 0
D16: Total Revenue | F16: =SUM(F10:G15) -> 2435
A20: =IF(Main!B2,TEXT(EDATE(Main!B3,16),"dd mmmm yyyy"),TEXT(Main!B3+((Main!B5-Main!B3)*16+16),"dd mmmm yyyy"))&" - "&IF(Main!B2,TEXT(EDATE(Main!B3,17)-1,"dd mmmm yyyy"),TEXT(Main!B3+((Main!B5-Main!B3)*17+16),"dd mmmm yyyy"))&" / "&" (Revenue / Deferred Debts Or Expenses)" -> 20 August 2025 - 19 September 2025 / (Revenue / Deferred Debts Or Expenses)
A21: Date | B21: Name | D21: Description | F21: Amount
B22: Social Welfare | D22: N/A | F22: 2435
A23: 31st August 2025 | B23: Salary | D23: Deduct 5% MPF | F23: 0
B24: Cigarette Egg | D24: Brought in Advance | F24: 0
F25: 0
F26: 0
F27: 0
D28: Total Revenue | F28: =SUM(F22:G27) -> 2435
A32: =IF(Main!B2,TEXT(EDATE(Main!B3,17),"dd mmmm yyyy"),TEXT(Main!B3+((Main!B5-Main!B3)*17+17),"dd mmmm yyyy"))&" - "&IF(Main!B2,TEXT(EDATE(Main!B3,18)-1,"dd mmmm yyyy"),TEXT(Main!B3+((Main!B5-Main!B3)*18+17),"dd mmmm yyyy"))&" / "&" (Revenue / Deferred Debts Or Expenses)" -> 20 September 2025 - 19 October 2025 / (Revenue / Deferred Debts Or Expenses)
A33: Date | B33: Name | D33: Description | F33: Amount
B34: Social Welfare | D34: N/A | F34: 2435
A35: 30th September 2025 | B35: Salary | D35: Deduct 5% MPF | F35: 0
B36: Sing Lun Birthday | D36: Receive cash | F36: 0
B37: Deffered Mobile to next month | F37: 149
F38: 0
F39: 0
D40: Total Revenue | F40: =SUM(F34:G39) -> 2584
A44: ="Fixed Expense For the Year "&IF(Main!B2,TEXT(EDATE(Main!B3,15),"mmmm yyyy"),TEXT(Main!B3+((Main!B5-Main!B3)*15+15),"mmmm yyyy"))&" to "&IF(Main!B2,TEXT(EDATE(Main!B3,18)-1,"mmmm yyyy"),TEXT(Main!B3+((Main!B5-Main!B3)*18+17),"mmmm yyyy")) -> Fixed Expense For the Year July 2025 to October 2025
A45: Name | B45: Description | C45: Amount
A46: Mobile And Communications/ Housing Expenses
A47: {=IF((INDIRECT("'"&INDIRECT("Main!B9")&"'!A61"))=0,"",(INDIRECT("'"&INDIRECT("Main!B9")&"'!A61")))} -> Broadband | B47: {=IF((INDIRECT("'"&INDIRECT("Main!B9")&"'!B61"))=0,"",(INDIRECT("'"&INDIRECT("Main!B9")&"'!B61")))} | C47: 78
A48: {=IF((INDIRECT("'"&INDIRECT("Main!B9")&"'!A62"))=0,"",(INDIRECT("'"&INDIRECT("Main!B9")&"'!A62")))} -> China Mobile | B48: {=IF((INDIRECT("'"&INDIRECT("Main!B9")&"'!B62"))=0,"",(INDIRECT("'"&INDIRECT("Main!B9")&"'!B62")))} | C48: 149
A49: {=IF((INDIRECT("'"&INDIRECT("Main!B9")&"'!A63"))=0,"",(INDIRECT("'"&INDIRECT("Main!B9")&"'!A63")))} -> Telephone (Fixed Line) | B49: {=IF((INDIRECT("'"&INDIRECT("Main!B9")&"'!B63"))=0,"",(INDIRECT("'"&INDIRECT("Main!B9")&"'!B63")))} | C49: 0
A50: {=IF((INDIRECT("'"&INDIRECT("Main!B9")&"'!A64"))=0,"",(INDIRECT("'"&INDIRECT("Main!B9")&"'!A64")))} -> Sosim | B50: {=IF((INDIRECT("'"&INDIRECT("Main!B9")&"'!B64"))=0,"",(INDIRECT("'"&INDIRECT("Main!B9")&"'!B64")))} | C50: 0
A51: {=IF((INDIRECT("'"&INDIRECT("Main!B9")&"'!A65"))=0,"",(INDIRECT("'"&INDIRECT("Main!B9")&"'!A65")))} -> Birdie Sim Card Pay date (7th Of Each Month) | B51: {=IF((INDIRECT("'"&INDIRECT("Main!B9")&"'!B65"))=0,"",(INDIRECT("'"&INDIRECT("Main!B9")&"'!B65")))} | C51: 50
A52: {=IF((INDIRECT("'"&INDIRECT("Main!B9")&"'!A66"))=0,"",(INDIRECT("'"&INDIRECT("Main!B9")&"'!A66")))} | B52: {=IF((INDIRECT("'"&INDIRECT("Main!B9")&"'!B66"))=0,"",(INDIRECT("'"&INDIRECT("Main!B9")&"'!B66")))} | C52: 0
A53: {=IF((INDIRECT("'"&INDIRECT("Main!B9")&"'!A67"))=0,"",(INDIRECT("'"&INDIRECT("Main!B9")&"'!A67")))} | B53: {=IF((INDIRECT("'"&INDIRECT("Main!B9")&"'!B67"))=0,"",(INDIRECT("'"&INDIRECT("Main!B9")&"'!B67")))} | C53: 0
A54: {=IF((INDIRECT("'"&INDIRECT("Main!B9")&"'!A68"))=0,"",(INDIRECT("'"&INDIRECT("Main!B9")&"'!A68")))} | B54: {=IF((INDIRECT("'"&INDIRECT("Main!B9")&"'!B68"))=0,"",(INDIRECT("'"&INDIRECT("Main!B9")&"'!B68")))} | C54: 0
B55: Total Expenses | C55: =SUM(C47:C54) -> 277
A56: Credit Card Installments/Government Installments
A57: {=IF((INDIRECT("'"&INDIRECT("Main!B9")&"'!A71"))=0,"",(INDIRECT("'"&INDIRECT("Main!B9")&"'!A71")))} -> Citi Bank | B57: {=IF((INDIRECT("'"&INDIRECT("Main!B9")&"'!B71"))=0,"",(INDIRECT("'"&INDIRECT("Main!B9")&"'!B71")))} | C57: 0
A58: {=IF((INDIRECT("'"&INDIRECT("Main!B9")&"'!A72"))=0,"",(INDIRECT("'"&INDIRECT("Main!B9")&"'!A72")))} -> SC Bank | B58: {=IF((INDIRECT("'"&INDIRECT("Main!B9")&"'!B72"))=0,"",(INDIRECT("'"&INDIRECT("Main!B9")&"'!B72")))} | C58: 0
A59: {=IF((INDIRECT("'"&INDIRECT("Main!B9")&"'!A73"))=0,"",(INDIRECT("'"&INDIRECT("Main!B9")&"'!A73")))} -> Bank Of China | B59: {=IF((INDIRECT("'"&INDIRECT("Main!B9")&"'!B73"))=0,"",(INDIRECT("'"&INDIRECT("Main!B9")&"'!B73")))} | C59: 0
A60: {=IF((INDIRECT("'"&INDIRECT("Main!B9")&"'!A74"))=0,"",(INDIRECT("'"&INDIRECT("Main!B9")&"'!A74")))} -> HSBC | B60: {=IF((INDIRECT("'"&INDIRECT("Main!B9")&"'!B74"))=0,"",(INDIRECT("'"&INDIRECT("Main!B9")&"'!B74")))} | C60: 0
A61: {=IF((INDIRECT("'"&INDIRECT("Main!B9")&"'!A75"))=0,"",(INDIRECT("'"&INDIRECT("Main!B9")&"'!A75")))} | B61: {=IF((INDIRECT("'"&INDIRECT("Main!B9")&"'!B75"))=0,"",(INDIRECT("'"&INDIRECT("Main!B9")&"'!B75")))} | C61: 0
A62: {=IF((INDIRECT("'"&INDIRECT("Main!B9")&"'!A76"))=0,"",(INDIRECT("'"&INDIRECT("Main!B9")&"'!A76")))} | B62: {=IF((INDIRECT("'"&INDIRECT("Main!B9")&"'!B76"))=0,"",(INDIRECT("'"&INDIRECT("Main!B9")&"'!B76")))} | C62: 0
A63: {=IF((INDIRECT("'"&INDIRECT("Main!B9")&"'!A77"))=0,"",(INDIRECT("'"&INDIRECT("Main!B9")&"'!A77")))} | B63: {=IF((INDIRECT("'"&INDIRECT("Main!B9")&"'!B77"))=0,"",(INDIRECT("'"&INDIRECT("Main!B9")&"'!B77")))} | C63: 0
A64: {=IF((INDIRECT("'"&INDIRECT("Main!B9")&"'!A78"))=0,"",(INDIRECT("'"&INDIRECT("Main!B9")&"'!A78")))} | B64: {=IF((INDIRECT("'"&INDIRECT("Main!B9")&"'!B78"))=0,"",(INDIRECT("'"&INDIRECT("Main!B9")&"'!B78")))} | C64: 0
A65: {=IF((INDIRECT("'"&INDIRECT("Main!B9")&"'!A79"))=0,"",(INDIRECT("'"&INDIRECT("Main!B9")&"'!A79")))} | B65: {=IF((INDIRECT("'"&INDIRECT("Main!B9")&"'!B79"))=0,"",(INDIRECT("'"&INDIRECT("Main!B9")&"'!B79")))} | C65: 0
B66: Total Expenses | C66: =SUM(C57:C65) -> 0
A67: Donation
A68: {=IF((INDIRECT("'"&INDIRECT("Main!B9")&"'!A82"))=0,"",(INDIRECT("'"&INDIRECT("Main!B9")&"'!A82")))} -> Traversy | B68: {=IF((INDIRECT("'"&INDIRECT("Main!B9")&"'!B82"))=0,"",(INDIRECT("'"&INDIRECT("Main!B9")&"'!B82")))} -> Traversy Media | C68: 0
A69: {=IF((INDIRECT("'"&INDIRECT("Main!B9")&"'!A83"))=0,"",(INDIRECT("'"&INDIRECT("Main!B9")&"'!A83")))} -> Orbis | B69: {=IF((INDIRECT("'"&INDIRECT("Main!B9")&"'!B83"))=0,"",(INDIRECT("'"&INDIRECT("Main!B9")&"'!B83")))} -> Orbis Eye Flight | C69: 0
A70: {=IF((INDIRECT("'"&INDIRECT("Main!B9")&"'!A84"))=0,"",(INDIRECT("'"&INDIRECT("Main!B9")&"'!A84")))} | B70: {=IF((INDIRECT("'"&INDIRECT("Main!B9")&"'!B84"))=0,"",(INDIRECT("'"&INDIRECT("Main!B9")&"'!B84")))} | C70: 0
A71: {=IF((INDIRECT("'"&INDIRECT("Main!B9")&"'!A85"))=0,"",(INDIRECT("'"&INDIRECT("Main!B9")&"'!A85")))} | B71: {=IF((INDIRECT("'"&INDIRECT("Main!B9")&"'!B85"))=0,"",(INDIRECT("'"&INDIRECT("Main!B9")&"'!B85")))} | C71: 0
A72: {=IF((INDIRECT("'"&INDIRECT("Main!B9")&"'!A86"))=0,"",(INDIRECT("'"&INDIRECT("Main!B9")&"'!A86")))} | B72: {=IF((INDIRECT("'"&INDIRECT("Main!B9")&"'!B86"))=0,"",(INDIRECT("'"&INDIRECT("Main!B9")&"'!B86")))} | C72: 0
A73: {=IF((INDIRECT("'"&INDIRECT("Main!B9")&"'!A87"))=0,"",(INDIRECT("'"&INDIRECT("Main!B9")&"'!A87")))} | B73: {=IF((INDIRECT("'"&INDIRECT("Main!B9")&"'!B87"))=0,"",(INDIRECT("'"&INDIRECT("Main!B9")&"'!B87")))} | C73: 0
A74: {=IF((INDIRECT("'"&INDIRECT("Main!B9")&"'!A88"))=0,"",(INDIRECT("'"&INDIRECT("Main!B9")&"'!A88")))} | B74: {=IF((INDIRECT("'"&INDIRECT("Main!B9")&"'!B88"))=0,"",(INDIRECT("'"&INDIRECT("Main!B9")&"'!B88")))} | C74: 0
B75: Total Expenses | C75: =SUM(C68:C74) -> 0
A76: Insurance (Personal / Properties / Medical)
A77: {=IF((INDIRECT("'"&INDIRECT("Main!B9")&"'!A91"))=0,"",(INDIRECT("'"&INDIRECT("Main!B9")&"'!A91")))} -> AIA | B77: {=IF((INDIRECT("'"&INDIRECT("Main!B9")&"'!B91"))=0,"",(INDIRECT("'"&INDIRECT("Main!B9")&"'!B91")))} | C77: 0
A78: {=IF((INDIRECT("'"&INDIRECT("Main!B9")&"'!A92"))=0,"",(INDIRECT("'"&INDIRECT("Main!B9")&"'!A92")))} | B78: {=IF((INDIRECT("'"&INDIRECT("Main!B9")&"'!B92"))=0,"",(INDIRECT("'"&INDIRECT("Main!B9")&"'!B92")))} | C78: 0
A79: {=IF((INDIRECT("'"&INDIRECT("Main!B9")&"'!A93"))=0,"",(INDIRECT("'"&INDIRECT("Main!B9")&"'!A93")))} | B79: {=IF((INDIRECT("'"&INDIRECT("Main!B9")&"'!B93"))=0,"",(INDIRECT("'"&INDIRECT("Main!B9")&"'!B93")))} | C79: 0
A80: {=IF((INDIRECT("'"&INDIRECT("Main!B9")&"'!A94"))=0,"",(INDIRECT("'"&INDIRECT("Main!B9")&"'!A94")))} | B80: {=IF((INDIRECT("'"&INDIRECT("Main!B9")&"'!B94"))=0,"",(INDIRECT("'"&INDIRECT("Main!B9")&"'!B94")))} | C80: 0
A81: {=IF((INDIRECT("'"&INDIRECT("Main!B9")&"'!A95"))=0,"",(INDIRECT("'"&INDIRECT("Main!B9")&"'!A95")))} | B81: {=IF((INDIRECT("'"&INDIRECT("Main!B9")&"'!B95"))=0,"",(INDIRECT("'"&INDIRECT("Main!B9")&"'!B95")))} | C81: 0
A82: {=IF((INDIRECT("'"&INDIRECT("Main!B9")&"'!A96"))=0,"",(INDIRECT("'"&INDIRECT("Main!B9")&"'!A96")))} | B82: {=IF((INDIRECT("'"&INDIRECT("Main!B9")&"'!B96"))=0,"",(INDIRECT("'"&INDIRECT("Main!B9")&"'!B96")))} | C82: 0
A83: {=IF((INDIRECT("'"&INDIRECT("Main!B9")&"'!A97"))=0,"",(INDIRECT("'"&INDIRECT("Main!B9")&"'!A97")))} | B83: {=IF((INDIRECT("'"&INDIRECT("Main!B9")&"'!B97"))=0,"",(INDIRECT("'"&INDIRECT("Main!B9")&"'!B97")))} | C83: 0
A84: {=IF((INDIRECT("'"&INDIRECT("Main!B9")&"'!A98"))=0,"",(INDIRECT("'"&INDIRECT("Main!B9")&"'!A98")))} | B84: {=IF((INDIRECT("'"&INDIRECT("Main!B9")&"'!B98"))=0,"",(INDIRECT("'"&INDIRECT("Main!B9")&"'!B98")))} | C84: 0
B85: Total Expenses | C85: =SUM(C77:C84) -> 0
A86: Other Expenses
A87: {=IF((INDIRECT("'"&INDIRECT("Main!B9")&"'!A101"))=0,"",(INDIRECT("'"&INDIRECT("Main!B9")&"'!A101")))} -> Other Stuff | B87: {=IF((INDIRECT("'"&INDIRECT("Main!B9")&"'!B101"))=0,"",(INDIRECT("'"&INDIRECT("Main!B9")&"'!B101")))} -> Food, Transport…. | C87: 0
A88: {=IF((INDIRECT("'"&INDIRECT("Main!B9")&"'!A102"))=0,"",(INDIRECT("'"&INDIRECT("Main!B9")&"'!A102")))} -> Entertainment | B88: {=IF((INDIRECT("'"&INDIRECT("Main!B9")&"'!B102"))=0,"",(INDIRECT("'"&INDIRECT("Main!B9")&"'!B102")))} -> Sportify Music / Changed to Apple Music on 13th May 2025 | C88: 68
A89: {=IF((INDIRECT("'"&INDIRECT("Main!B9")&"'!A103"))=0,"",(INDIRECT("'"&INDIRECT("Main!B9")&"'!A103")))} -> Hair Cutting | B89: {=IF((INDIRECT("'"&INDIRECT("Main!B9")&"'!B103"))=0,"",(INDIRECT("'"&INDIRECT("Main!B9")&"'!B103")))} -> Hair Cut not Include Color treatment | C89: 55
A90: {=IF((INDIRECT("'"&INDIRECT("Main!B9")&"'!A104"))=0,"",(INDIRECT("'"&INDIRECT("Main!B9")&"'!A104")))} -> Cigarettes | B90: {=IF((INDIRECT("'"&INDIRECT("Main!B9")&"'!B104"))=0,"",(INDIRECT("'"&INDIRECT("Main!B9")&"'!B104")))} -> 30 packets | C90: 0
A91: {=IF((INDIRECT("'"&INDIRECT("Main!B9")&"'!A105"))=0,"",(INDIRECT("'"&INDIRECT("Main!B9")&"'!A105")))} | B91: {=IF((INDIRECT("'"&INDIRECT("Main!B9")&"'!B105"))=0,"",(INDIRECT("'"&INDIRECT("Main!B9")&"'!B105")))} | C91: 0
A92: {=IF((INDIRECT("'"&INDIRECT("Main!B9")&"'!A106"))=0,"",(INDIRECT("'"&INDIRECT("Main!B9")&"'!A106")))} | B92: {=IF((INDIRECT("'"&INDIRECT("Main!B9")&"'!B106"))=0,"",(INDIRECT("'"&INDIRECT("Main!B9")&"'!B106")))} | C92: 0
A93: {=IF((INDIRECT("'"&INDIRECT("Main!B9")&"'!A107"))=0,"",(INDIRECT("'"&INDIRECT("Main!B9")&"'!A107")))} | B93: {=IF((INDIRECT("'"&INDIRECT("Main!B9")&"'!B107"))=0,"",(INDIRECT("'"&INDIRECT("Main!B9")&"'!B107")))} | C93: 0
A94: {=IF((INDIRECT("'"&INDIRECT("Main!B9")&"'!A108"))=0,"",(INDIRECT("'"&INDIRECT("Main!B9")&"'!A108")))} | B94: {=IF((INDIRECT("'"&INDIRECT("Main!B9")&"'!B108"))=0,"",(INDIRECT("'"&INDIRECT("Main!B9")&"'!B108")))} | C94: 0
B95: Total Expenses | C95: =SUM(C87:C94) -> 123
B96: Grand Expenses Total | C96: =C55+C66+C75+C85+C95 -> 400
A97: Debts
A98: {=IF((INDIRECT("'"&INDIRECT("Main!B9")&"'!A112"))=0,"",(INDIRECT("'"&INDIRECT("Main!B9")&"'!A112")))} -> Mother | B98: {=IF((INDIRECT("'"&INDIRECT("Main!B9")&"'!B112"))=0,"",(INDIRECT("'"&INDIRECT("Main!B9")&"'!B112")))} | C98: {=INDIRECT("'"&INDIRECT("Main!B21")&"'!C98")+SUM(E118+E145+E172)} -> 0
A99: {=IF((INDIRECT("'"&INDIRECT("Main!B9")&"'!A113"))=0,"",(INDIRECT("'"&INDIRECT("Main!B9")&"'!A113")))} -> Ng Wing Lam | B99: {=IF((INDIRECT("'"&INDIRECT("Main!B9")&"'!B113"))=0,"",(INDIRECT("'"&INDIRECT("Main!B9")&"'!B113")))} | C99: {=INDIRECT("'"&INDIRECT("Main!B21")&"'!C99")+SUM(E119+E146+E173)} -> 0
A100: {=IF((INDIRECT("'"&INDIRECT("Main!B9")&"'!A114"))=0,"",(INDIRECT("'"&INDIRECT("Main!B9")&"'!A114")))} -> Lawrence | B100: {=IF((INDIRECT("'"&INDIRECT("Main!B9")&"'!B114"))=0,"",(INDIRECT("'"&INDIRECT("Main!B9")&"'!B114")))} | C100: {=INDIRECT("'"&INDIRECT("Main!B21")&"'!C100")+SUM(E120+E147+E174)} -> 0
A101: {=IF((INDIRECT("'"&INDIRECT("Main!B9")&"'!A115"))=0,"",(INDIRECT("'"&INDIRECT("Main!B9")&"'!A115")))} -> Hong Kong Government Hospital Authority | B101: {=IF((INDIRECT("'"&INDIRECT("Main!B9")&"'!B115"))=0,"",(INDIRECT("'"&INDIRECT("Main!B9")&"'!B115")))} | C101: {=INDIRECT("'"&INDIRECT("Main!B21")&"'!C101")+SUM(E121+E148+E175)} -> 0
A102: {=IF((INDIRECT("'"&INDIRECT("Main!B9")&"'!A116"))=0,"",(INDIRECT("'"&INDIRECT("Main!B9")&"'!A116")))} -> Bankruptcy Department / Bank | B102: {=IF((INDIRECT("'"&INDIRECT("Main!B9")&"'!B116"))=0,"",(INDIRECT("'"&INDIRECT("Main!B9")&"'!B116")))} | C102: {=INDIRECT("'"&INDIRECT("Main!B21")&"'!C102")+SUM(E122+E149+E176)} -> 0
A103: {=IF((INDIRECT("'"&INDIRECT("Main!B9")&"'!A117"))=0,"",(INDIRECT("'"&INDIRECT("Main!B9")&"'!A117")))} -> Mother Air Ticket | B103: {=IF((INDIRECT("'"&INDIRECT("Main!B9")&"'!B117"))=0,"",(INDIRECT("'"&INDIRECT("Main!B9")&"'!B117")))} | C103: {=INDIRECT("'"&INDIRECT("Main!B21")&"'!C103")+SUM(E123+E150+E177)} -> 0
A104: {=IF((INDIRECT("'"&INDIRECT("Main!B9")&"'!A118"))=0,"",(INDIRECT("'"&INDIRECT("Main!B9")&"'!A118")))} | B104: {=IF((INDIRECT("'"&INDIRECT("Main!B9")&"'!B118"))=0,"",(INDIRECT("'"&INDIRECT("Main!B9")&"'!B118")))} | C104: {=INDIRECT("'"&INDIRECT("Main!B21")&"'!C104")+SUM(E124+E151+E178)} -> 0
A105: {=IF((INDIRECT("'"&INDIRECT("Main!B9")&"'!A119"))=0,"",(INDIRECT("'"&INDIRECT("Main!B9")&"'!A119")))} | B105: {=IF((INDIRECT("'"&INDIRECT("Main!B9")&"'!B119"))=0,"",(INDIRECT("'"&INDIRECT("Main!B9")&"'!B119")))} | C105: {=INDIRECT("'"&INDIRECT("Main!B21")&"'!C105")+SUM(E125+E152+E179)} -> 0
A106: {=IF((INDIRECT("'"&INDIRECT("Main!B9")&"'!A120"))=0,"",(INDIRECT("'"&INDIRECT("Main!B9")&"'!A120")))} | B106: {=IF((INDIRECT("'"&INDIRECT("Main!B9")&"'!B120"))=0,"",(INDIRECT("'"&INDIRECT("Main!B9")&"'!B120")))} | C106: {=INDIRECT("'"&INDIRECT("Main!B21")&"'!C106")+SUM(E126+E153+E180)} -> 0
A107: {=IF((INDIRECT("'"&INDIRECT("Main!B9")&"'!A121"))=0,"",(INDIRECT("'"&INDIRECT("Main!B9")&"'!A121")))} | B107: {=IF((INDIRECT("'"&INDIRECT("Main!B9")&"'!B121"))=0,"",(INDIRECT("'"&INDIRECT("Main!B9")&"'!B121")))} | C107: {=INDIRECT("'"&INDIRECT("Main!B21")&"'!C107")+SUM(E127+E154+E181)} -> 0
B108: Total Debts | C108: =SUM(C98:C107) -> 0
B109: Grand Total | C109: =C108-C96 -> -400
A114: ="Debts Or Credits For the Comming "&IF(Main!B2,TEXT(EDATE(Main!B3,15),"mmmm dd yyyy"),TEXT(Main!B3+((Main!B5-Main!B3)*15+15),"mmmm dd yyyy"))&" to "&IF(Main!B2,TEXT(EDATE(Main!B3,16)-1,"mmmm dd yyyy"),TEXT(Main!B3+((Main!B5-Main!B3)*16+15),"mmmm dd yyyy")) -> Debts Or Credits For the Comming July 20 2025 to August 19 2025
A115: Principal | C115: Description | E115: Amount
...

Sheet October 2025 - December 2025
A1: ="Forecasts For the Year "&IF(Main!B2,TEXT(EDATE(Main!B3,18),"mmmm yyyy"),TEXT(Main!B3+((Main!B5-Main!B3)*18+18),"mmmm yyyy"))&" to "&IF(Main!B2,TEXT(EDATE(Main!B3,21)-1,"mmmm yyyy"),TEXT(Main!B3+((Main!B5-Main!B3)*21+20),"mmmm yyyy")) -> Forecasts For the Year October 2025 to January 2026
A2: Assets | B2: Overall | C2: {=INDIRECT("'"&Main!B9&"'!$C$16")} -> 1181.5
B3: Forecasts | C3: =E190 -> 2707.6
A4: Total | C4: =SUM(C2:G3) -> 3889.1
A5: Net Debts: | C5: =C108 -> 0
A8: =IF(Main!B2,TEXT(EDATE(Main!B3,18),"dd mmmm yyyy"),TEXT(Main!B3+((Main!B5-Main!B3)*18+18),"dd mmmm yyyy"))&" - "&IF(Main!B2,TEXT(EDATE(Main!B3,19)-1,"dd mmmm yyyy"),TEXT(Main!B3+((Main!B5-Main!B3)*19+18),"dd mmmm yyyy"))&" / "&" (Revenue / Deferred Debts Or Expenses)" -> 20 October 2025 - 19 November 2025 / (Revenue / Deferred Debts Or Expenses)
A9: Date | B9: Name | D9: Description | F9: Amount
B10: Social Welfare | D10: N/A | F10: 2435
A11: 31st October 2025 | B11: Salary | D11: Deduct 5% MPF | F11: 0
B12: Cigarette Egg | D12: Brought in Advance | F12: 0
F13: 0
F14: 0
F15: 0
D16: Total Revenue | F16: =SUM(F10:G15) -> 2435
A20: =IF(Main!B2,TEXT(EDATE(Main!B3,19),"dd mmmm yyyy"),TEXT(Main!B3+((Main!B5-Main!B3)*19+19),"dd mmmm yyyy"))&" - "&IF(Main!B2,TEXT(EDATE(Main!B3,20)-1,"dd mmmm yyyy"),TEXT(Main!B3+((Main!B5-Main!B3)*20+19),"dd mmmm yyyy"))&" / "&" (Revenue / Deferred Debts Or Expenses)" -> 20 November 2025 - 19 December 2025 / (Revenue / Deferred Debts Or Expenses)
A21: Date | B21: Name | D21: Description | F21: Amount
B22: Social Welfare | D22: N/A | F22: 2435
A23: 31st November 2025 | B23: Salary | D23: Deduct 5% MPF | F23: 0
F24: 0
F25: 0
F26: 0
F27: 0
D28: Total Revenue | F28: =SUM(F22:G27) -> 2435
A32: =IF(Main!B2,TEXT(EDATE(Main!B3,20),"dd mmmm yyyy"),TEXT(Main!B3+((Main!B5-Main!B3)*20+20),"dd mmmm yyyy"))&" - "&IF(Main!B2,TEXT(EDATE(Main!B3,21)-1,"dd mmmm yyyy"),TEXT(Main!B3+((Main!B5-Main!B3)*21+20),"dd mmmm yyyy"))&" / "&" (Revenue / Deferred Debts Or Expenses)" -> 20 December 2025 - 19 January 2026 / (Revenue / Deferred Debts Or Expenses)
A33: Date | B33: Name | D33: Description | F33: Amount
B34: Social Welfare | D34: N/A | F34: 2435
A35: 30th December 2025 | B35: Salary | D35: Deduct 5% MPF | F35: 0
B36: Cigarette Egg | D36: Brought in Advance | F36: 0
F37: 0
F38: 0
F39: 0
D40: Total Revenue | F40: =SUM(F34:G39) -> 2435
A44: ="Fixed Expense For the Year "&IF(Main!B2,TEXT(EDATE(Main!B3,18),"mmmm yyyy"),TEXT(Main!B3+((Main!B5-Main!B3)*18+18),"mmmm yyyy"))&" to "&IF(Main!B2,TEXT(EDATE(Main!B3,21)-1,"mmmm yyyy"),TEXT(Main!B3+((Main!B5-Main!B3)*21+20),"mmmm yyyy")) -> Fixed Expense For the Year October 2025 to January 2026
A45: Name | B45: Description | C45: Amount
A46: Mobile And Communications/ Housing Expenses
A47: {=IF((INDIRECT("'"&INDIRECT("Main!B9")&"'!A61"))=0,"",(INDIRECT("'"&INDIRECT("Main!B9")&"'!A61")))} -> Broadband | B47: {=IF((INDIRECT("'"&INDIRECT("Main!B9")&"'!B61"))=0,"",(INDIRECT("'"&INDIRECT("Main!B9")&"'!B61")))} | C47: 78
A48: {=IF((INDIRECT("'"&INDIRECT("Main!B9")&"'!A62"))=0,"",(INDIRECT("'"&INDIRECT("Main!B9")&"'!A62")))} -> China Mobile | B48: {=IF((INDIRECT("'"&INDIRECT("Main!B9")&"'!B62"))=0,"",(INDIRECT("'"&INDIRECT("Main!B9")&"'!B62")))} | C48: 149
A49: {=IF((INDIRECT("'"&INDIRECT("Main!B9")&"'!A63"))=0,"",(INDIRECT("'"&INDIRECT("Main!B9")&"'!A63")))} -> Telephone (Fixed Line) | B49: {=IF((INDIRECT("'"&INDIRECT("Main!B9")&"'!B63"))=0,"",(INDIRECT("'"&INDIRECT("Main!B9")&"'!B63")))} | C49: 0
A50: {=IF((INDIRECT("'"&INDIRECT("Main!B9")&"'!A64"))=0,"",(INDIRECT("'"&INDIRECT("Main!B9")&"'!A64")))} -> Sosim | B50: {=IF((INDIRECT("'"&INDIRECT("Main!B9")&"'!B64"))=0,"",(INDIRECT("'"&INDIRECT("Main!B9")&"'!B64")))} | C50: 0
A51: {=IF((INDIRECT("'"&INDIRECT("Main!B9")&"'!A65"))=0,"",(INDIRECT("'"&INDIRECT("Main!B9")&"'!A65")))} -> Birdie Sim Card Pay date (7th Of Each Month) | B51: {=IF((INDIRECT("'"&INDIRECT("Main!B9")&"'!B65"))=0,"",(INDIRECT("'"&INDIRECT("Main!B9")&"'!B65")))} | C51: 50
A52: {=IF((INDIRECT("'"&INDIRECT("Main!B9")&"'!A66"))=0,"",(INDIRECT("'"&INDIRECT("Main!B9")&"'!A66")))} | B52: {=IF((INDIRECT("'"&INDIRECT("Main!B9")&"'!B66"))=0,"",(INDIRECT("'"&INDIRECT("Main!B9")&"'!B66")))} | C52: 0
A53: {=IF((INDIRECT("'"&INDIRECT("Main!B9")&"'!A67"))=0,"",(INDIRECT("'"&INDIRECT("Main!B9")&"'!A67")))} | B53: {=IF((INDIRECT("'"&INDIRECT("Main!B9")&"'!B67"))=0,"",(INDIRECT("'"&INDIRECT("Main!B9")&"'!B67")))} | C53: 0
A54: {=IF((INDIRECT("'"&INDIRECT("Main!B9")&"'!A68"))=0,"",(INDIRECT("'"&INDIRECT("Main!B9")&"'!A68")))} | B54: {=IF((INDIRECT("'"&INDIRECT("Main!B9")&"'!B68"))=0,"",(INDIRECT("'"&INDIRECT("Main!B9")&"'!B68")))} | C54: 0
B55: Total Expenses | C55: =SUM(C47:C54) -> 277
A56: Credit Card Installments/Government Installments
A57: {=IF((INDIRECT("'"&INDIRECT("Main!B9")&"'!A71"))=0,"",(INDIRECT("'"&INDIRECT("Main!B9")&"'!A71")))} -> Citi Bank | B57: {=IF((INDIRECT("'"&INDIRECT("Main!B9")&"'!B71"))=0,"",(INDIRECT("'"&INDIRECT("Main!B9")&"'!B71")))} | C57: 0
A58: {=IF((INDIRECT("'"&INDIRECT("Main!B9")&"'!A72"))=0,"",(INDIRECT("'"&INDIRECT("Main!B9")&"'!A72")))} -> SC Bank | B58: {=IF((INDIRECT("'"&INDIRECT("Main!B9")&"'!B72"))=0,"",(INDIRECT("'"&INDIRECT("Main!B9")&"'!B72")))} | C58: 0
A59: {=IF((INDIRECT("'"&INDIRECT("Main!B9")&"'!A73"))=0,"",(INDIRECT("'"&INDIRECT("Main!B9")&"'!A73")))} -> Bank Of China | B59: {=IF((INDIRECT("'"&INDIRECT("Main!B9")&"'!B73"))=0,"",(INDIRECT("'"&INDIRECT("Main!B9")&"'!B73")))} | C59: 0
A60: {=IF((INDIRECT("'"&INDIRECT("Main!B9")&"'!A74"))=0,"",(INDIRECT("'"&INDIRECT("Main!B9")&"'!A74")))} -> HSBC | B60: {=IF((INDIRECT("'"&INDIRECT("Main!B9")&"'!B74"))=0,"",(INDIRECT("'"&INDIRECT("Main!B9")&"'!B74")))} | C60: 0
A61: {=IF((INDIRECT("'"&INDIRECT("Main!B9")&"'!A75"))=0,"",(INDIRECT("'"&INDIRECT("Main!B9")&"'!A75")))} | B61: {=IF((INDIRECT("'"&INDIRECT("Main!B9")&"'!B75"))=0,"",(INDIRECT("'"&INDIRECT("Main!B9")&"'!B75")))} | C61: 0
A62: {=IF((INDIRECT("'"&INDIRECT("Main!B9")&"'!A76"))=0,"",(INDIRECT("'"&INDIRECT("Main!B9")&"'!A76")))} | B62: {=IF((INDIRECT("'"&INDIRECT("Main!B9")&"'!B76"))=0,"",(INDIRECT("'"&INDIRECT("Main!B9")&"'!B76")))} | C62: 0
A63: {=IF((INDIRECT("'"&INDIRECT("Main!B9")&"'!A77"))=0,"",(INDIRECT("'"&INDIRECT("Main!B9")&"'!A77")))} | B63: {=IF((INDIRECT("'"&INDIRECT("Main!B9")&"'!B77"))=0,"",(INDIRECT("'"&INDIRECT("Main!B9")&"'!B77")))} | C63: 0
A64: {=IF((INDIRECT("'"&INDIRECT("Main!B9")&"'!A78"))=0,"",(INDIRECT("'"&INDIRECT("Main!B9")&"'!A78")))} | B64: {=IF((INDIRECT("'"&INDIRECT("Main!B9")&"'!B78"))=0,"",(INDIRECT("'"&INDIRECT("Main!B9")&"'!B78")))} | C64: 0
A65: {=IF((INDIRECT("'"&INDIRECT("Main!B9")&"'!A79"))=0,"",(INDIRECT("'"&INDIRECT("Main!B9")&"'!A79")))} | B65: {=IF((INDIRECT("'"&INDIRECT("Main!B9")&"'!B79"))=0,"",(INDIRECT("'"&INDIRECT("Main!B9")&"'!B79")))} | C65: 0
B66: Total Expenses | C66: =SUM(C57:C65) -> 0
A67: Donation
A68: {=IF((INDIRECT("'"&INDIRECT("Main!B9")&"'!A82"))=0,"",(INDIRECT("'"&INDIRECT("Main!B9")&"'!A82")))} -> Traversy | B68: {=IF((INDIRECT("'"&INDIRECT("Main!B9")&"'!B82"))=0,"",(INDIRECT("'"&INDIRECT("Main!B9")&"'!B82")))} -> Traversy Media | C68: 0
A69: {=IF((INDIRECT("'"&INDIRECT("Main!B9")&"'!A83"))=0,"",(INDIRECT("'"&INDIRECT("Main!B9")&"'!A83")))} -> Orbis | B69: {=IF((INDIRECT("'"&INDIRECT("Main!B9")&"'!B83"))=0,"",(INDIRECT("'"&INDIRECT("Main!B9")&"'!B83")))} -> Orbis Eye Flight | C69: 0
A70: {=IF((INDIRECT("'"&INDIRECT("Main!B9")&"'!A84"))=0,"",(INDIRECT("'"&INDIRECT("Main!B9")&"'!A84")))} | B70: {=IF((INDIRECT("'"&INDIRECT("Main!B9")&"'!B84"))=0,"",(INDIRECT("'"&INDIRECT("Main!B9")&"'!B84")))} | C70: 0
A71: {=IF((INDIRECT("'"&INDIRECT("Main!B9")&"'!A85"))=0,"",(INDIRECT("'"&INDIRECT("Main!B9")&"'!A85")))} | B71: {=IF((INDIRECT("'"&INDIRECT("Main!B9")&"'!B85"))=0,"",(INDIRECT("'"&INDIRECT("Main!B9")&"'!B85")))} | C71: 0
A72: {=IF((INDIRECT("'"&INDIRECT("Main!B9")&"'!A86"))=0,"",(INDIRECT("'"&INDIRECT("Main!B9")&"'!A86")))} | B72: {=IF((INDIRECT("'"&INDIRECT("Main!B9")&"'!B86"))=0,"",(INDIRECT("'"&INDIRECT("Main!B9")&"'!B86")))} | C72: 0
A73: {=IF((INDIRECT("'"&INDIRECT("Main!B9")&"'!A87"))=0,"",(INDIRECT("'"&INDIRECT("Main!B9")&"'!A87")))} | B73: {=IF((INDIRECT("'"&INDIRECT("Main!B9")&"'!B87"))=0,"",(INDIRECT("'"&INDIRECT("Main!B9")&"'!B87")))} | C73: 0
A74: {=IF((INDIRECT("'"&INDIRECT("Main!B9")&"'!A88"))=0,"",(INDIRECT("'"&INDIRECT("Main!B9")&"'!A88")))} | B74: {=IF((INDIRECT("'"&INDIRECT("Main!B9")&"'!B88"))=0,"",(INDIRECT("'"&INDIRECT("Main!B9")&"'!B88")))} | C74: 0
B75: Total Expenses | C75: =SUM(C68:C74) -> 0
A76: Insurance (Personal / Properties / Medical)
A77: {=IF((INDIRECT("'"&INDIRECT("Main!B9")&"'!A91"))=0,"",(INDIRECT("'"&INDIRECT("Main!B9")&"'!A91")))} -> AIA | B77: {=IF((INDIRECT("'"&INDIRECT("Main!B9")&"'!B91"))=0,"",(INDIRECT("'"&INDIRECT("Main!B9")&"'!B91")))} | C77: 0
A78: {=IF((INDIRECT("'"&INDIRECT("Main!B9")&"'!A92"))=0,"",(INDIRECT("'"&INDIRECT("Main!B9")&"'!A92")))} | B78: {=IF((INDIRECT("'"&INDIRECT("Main!B9")&"'!B92"))=0,"",(INDIRECT("'"&INDIRECT("Main!B9")&"'!B92")))} | C78: 0
A79: {=IF((INDIRECT("'"&INDIRECT("Main!B9")&"'!A93"))=0,"",(INDIRECT("'"&INDIRECT("Main!B9")&"'!A93")))} | B79: {=IF((INDIRECT("'"&INDIRECT("Main!B9")&"'!B93"))=0,"",(INDIRECT("'"&INDIRECT("Main!B9")&"'!B93")))} | C79: 0
A80: {=IF((INDIRECT("'"&INDIRECT("Main!B9")&"'!A94"))=0,"",(INDIRECT("'"&INDIRECT("Main!B9")&"'!A94")))} | B80: {=IF((INDIRECT("'"&INDIRECT("Main!B9")&"'!B94"))=0,"",(INDIRECT("'"&INDIRECT("Main!B9")&"'!B94")))} | C80: 0
A81: {=IF((INDIRECT("'"&INDIRECT("Main!B9")&"'!A95"))=0,"",(INDIRECT("'"&INDIRECT("Main!B9")&"'!A95")))} | B81: {=IF((INDIRECT("'"&INDIRECT("Main!B9")&"'!B95"))=0,"",(INDIRECT("'"&INDIRECT("Main!B9")&"'!B95")))} | C81: 0
A82: {=IF((INDIRECT("'"&INDIRECT("Main!B9")&"'!A96"))=0,"",(INDIRECT("'"&INDIRECT("Main!B9")&"'!A96")))} | B82: {=IF((INDIRECT("'"&INDIRECT("Main!B9")&"'!B96"))=0,"",(INDIRECT("'"&INDIRECT("Main!B9")&"'!B96")))} | C82: 0
A83: {=IF((INDIRECT("'"&INDIRECT("Main!B9")&"'!A97"))=0,"",(INDIRECT("'"&INDIRECT("Main!B9")&"'!A97")))} | B83: {=IF((INDIRECT("'"&INDIRECT("Main!B9")&"'!B97"))=0,"",(INDIRECT("'"&INDIRECT("Main!B9")&"'!B97")))} | C83: 0
A84: {=IF((INDIRECT("'"&INDIRECT("Main!B9")&"'!A98"))=0,"",(INDIRECT("'"&INDIRECT("Main!B9")&"'!A98")))} | B84: {=IF((INDIRECT("'"&INDIRECT("Main!B9")&"'!B98"))=0,"",(INDIRECT("'"&INDIRECT("Main!B9")&"'!B98")))} | C84: 0
B85: Total Expenses | C85: =SUM(C77:C84) -> 0
A86: Other Expenses
A87: {=IF((INDIRECT("'"&INDIRECT("Main!B9")&"'!A101"))=0,"",(INDIRECT("'"&INDIRECT("Main!B9")&"'!A101")))} -> Other Stuff | B87: {=IF((INDIRECT("'"&INDIRECT("Main!B9")&"'!B101"))=0,"",(INDIRECT("'"&INDIRECT("Main!B9")&"'!B101")))} -> Food, Transport…. | C87: 0
A88: {=IF((INDIRECT("'"&INDIRECT("Main!B9")&"'!A102"))=0,"",(INDIRECT("'"&INDIRECT("Main!B9")&"'!A102")))} -> Entertainment | B88: {=IF((INDIRECT("'"&INDIRECT("Main!B9")&"'!B102"))=0,"",(INDIRECT("'"&INDIRECT("Main!B9")&"'!B102")))} -> Sportify Music / Changed to Apple Music on 13th May 2025 | C88: 68
A89: {=IF((INDIRECT("'"&INDIRECT("Main!B9")&"'!A103"))=0,"",(INDIRECT("'"&INDIRECT("Main!B9")&"'!A103")))} -> Hair Cutting | B89: {=IF((INDIRECT("'"&INDIRECT("Main!B9")&"'!B103"))=0,"",(INDIRECT("'"&INDIRECT("Main!B9")&"'!B103")))} -> Hair Cut not Include Color treatment | C89: 55
A90: {=IF((INDIRECT("'"&INDIRECT("Main!B9")&"'!A104"))=0,"",(INDIRECT("'"&INDIRECT("Main!B9")&"'!A104")))} -> Cigarettes | B90: {=IF((INDIRECT("'"&INDIRECT("Main!B9")&"'!B104"))=0,"",(INDIRECT("'"&INDIRECT("Main!B9")&"'!B104")))} -> 30 packets | C90: 0
A91: {=IF((INDIRECT("'"&INDIRECT("Main!B9")&"'!A105"))=0,"",(INDIRECT("'"&INDIRECT("Main!B9")&"'!A105")))} | B91: {=IF((INDIRECT("'"&INDIRECT("Main!B9")&"'!B105"))=0,"",(INDIRECT("'"&INDIRECT("Main!B9")&"'!B105")))} | C91: 0
A92: {=IF((INDIRECT("'"&INDIRECT("Main!B9")&"'!A106"))=0,"",(INDIRECT("'"&INDIRECT("Main!B9")&"'!A106")))} | B92: {=IF((INDIRECT("'"&INDIRECT("Main!B9")&"'!B106"))=0,"",(INDIRECT("'"&INDIRECT("Main!B9")&"'!B106")))} | C92: 0
A93: {=IF((INDIRECT("'"&INDIRECT("Main!B9")&"'!A107"))=0,"",(INDIRECT("'"&INDIRECT("Main!B9")&"'!A107")))} | B93: {=IF((INDIRECT("'"&INDIRECT("Main!B9")&"'!B107"))=0,"",(INDIRECT("'"&INDIRECT("Main!B9")&"'!B107")))} | C93: 0
A94: {=IF((INDIRECT("'"&INDIRECT("Main!B9")&"'!A108"))=0,"",(INDIRECT("'"&INDIRECT("Main!B9")&"'!A108")))} | B94: {=IF((INDIRECT("'"&INDIRECT("Main!B9")&"'!B108"))=0,"",(INDIRECT("'"&INDIRECT("Main!B9")&"'!B108")))} | C94: 0
B95: Total Expenses | C95: =SUM(C87:C94) -> 123
B96: Grand Expenses Total | C96: =C55+C66+C75+C85+C95 -> 400
A97: Debts
A98: {=IF((INDIRECT("'"&INDIRECT("Main!B9")&"'!A112"))=0,"",(INDIRECT("'"&INDIRECT("Main!B9")&"'!A112")))} -> Mother | B98: {=IF((INDIRECT("'"&INDIRECT("Main!B9")&"'!B112"))=0,"",(INDIRECT("'"&INDIRECT("Main!B9")&"'!B112")))} | C98: {=INDIRECT("'"&INDIRECT("Main!B24")&"'!C98")+SUM(E118+E145+E172)} -> 0
A99: {=IF((INDIRECT("'"&INDIRECT("Main!B9")&"'!A113"))=0,"",(INDIRECT("'"&INDIRECT("Main!B9")&"'!A113")))} -> Ng Wing Lam | B99: {=IF((INDIRECT("'"&INDIRECT("Main!B9")&"'!B113"))=0,"",(INDIRECT("'"&INDIRECT("Main!B9")&"'!B113")))} | C99: {=INDIRECT("'"&INDIRECT("Main!B24")&"'!C99")+SUM(E119+E146+E173)} -> 0
A100: {=IF((INDIRECT("'"&INDIRECT("Main!B9")&"'!A114"))=0,"",(INDIRECT("'"&INDIRECT("Main!B9")&"'!A114")))} -> Lawrence | B100: {=IF((INDIRECT("'"&INDIRECT("Main!B9")&"'!B114"))=0,"",(INDIRECT("'"&INDIRECT("Main!B9")&"'!B114")))} | C100: {=INDIRECT("'"&INDIRECT("Main!B24")&"'!C100")+SUM(E120+E147+E174)} -> 0
A101: {=IF((INDIRECT("'"&INDIRECT("Main!B9")&"'!A115"))=0,"",(INDIRECT("'"&INDIRECT("Main!B9")&"'!A115")))} -> Hong Kong Government Hospital Authority | B101: {=IF((INDIRECT("'"&INDIRECT("Main!B9")&"'!B115"))=0,"",(INDIRECT("'"&INDIRECT("Main!B9")&"'!B115")))} | C101: {=INDIRECT("'"&INDIRECT("Main!B24")&"'!C101")+SUM(E121+E148+E175)} -> 0
A102: {=IF((INDIRECT("'"&INDIRECT("Main!B9")&"'!A116"))=0,"",(INDIRECT("'"&INDIRECT("Main!B9")&"'!A116")))} -> Bankruptcy Department / Bank | B102: {=IF((INDIRECT("'"&INDIRECT("Main!B9")&"'!B116"))=0,"",(INDIRECT("'"&INDIRECT("Main!B9")&"'!B116")))} | C102: {=INDIRECT("'"&INDIRECT("Main!B24")&"'!C102")+SUM(E122+E149+E176)} -> 0
A103: {=IF((INDIRECT("'"&INDIRECT("Main!B9")&"'!A117"))=0,"",(INDIRECT("'"&INDIRECT("Main!B9")&"'!A117")))} -> Mother Air Ticket | B103: {=IF((INDIRECT("'"&INDIRECT("Main!B9")&"'!B117"))=0,"",(INDIRECT("'"&INDIRECT("Main!B9")&"'!B117")))} | C103: {=INDIRECT("'"&INDIRECT("Main!B24")&"'!C103")+SUM(E123+E150+E177)} -> 0
A104: {=IF((INDIRECT("'"&INDIRECT("Main!B9")&"'!A118"))=0,"",(INDIRECT("'"&INDIRECT("Main!B9")&"'!A118")))} | B104: {=IF((INDIRECT("'"&INDIRECT("Main!B9")&"'!B118"))=0,"",(INDIRECT("'"&INDIRECT("Main!B9")&"'!B118")))} | C104: {=INDIRECT("'"&INDIRECT("Main!B24")&"'!C104")+SUM(E124+E151+E178)} -> 0
A105: {=IF((INDIRECT("'"&INDIRECT("Main!B9")&"'!A119"))=0,"",(INDIRECT("'"&INDIRECT("Main!B9")&"'!A119")))} | B105: {=IF((INDIRECT("'"&INDIRECT("Main!B9")&"'!B119"))=0,"",(INDIRECT("'"&INDIRECT("Main!B9")&"'!B119")))} | C105: {=INDIRECT("'"&INDIRECT("Main!B24")&"'!C105")+SUM(E125+E152+E179)} -> 0
A106: {=IF((INDIRECT("'"&INDIRECT("Main!B9")&"'!A120"))=0,"",(INDIRECT("'"&INDIRECT("Main!B9")&"'!A120")))} | B106: {=IF((INDIRECT("'"&INDIRECT("Main!B9")&"'!B120"))=0,"",(INDIRECT("'"&INDIRECT("Main!B9")&"'!B120")))} | C106: {=INDIRECT("'"&INDIRECT("Main!B24")&"'!C106")+SUM(E126+E153+E180)} -> 0
A107: {=IF((INDIRECT("'"&INDIRECT("Main!B9")&"'!A121"))=0,"",(INDIRECT("'"&INDIRECT("Main!B9")&"'!A121")))} | B107: {=IF((INDIRECT("'"&INDIRECT("Main!B9")&"'!B121"))=0,"",(INDIRECT("'"&INDIRECT("Main!B9")&"'!B121")))} | C107: {=INDIRECT("'"&INDIRECT("Main!B24")&"'!C107")+SUM(E127+E154+E181)} -> 0
B108: Total Debts | C108: =SUM(C98:C107) -> 0
B109: Grand Total | C109: =C108-C96 -> -400
A114: ="Debts Or Credits For the Comming "&IF(Main!B2,TEXT(EDATE(Main!B3,18),"mmmm dd yyyy"),TEXT(Main!B3+((Main!B5-Main!B3)*18+18),"mmmm dd yyyy"))&" to "&IF(Main!B2,TEXT(EDATE(Main!B3,19)-1,"mmmm dd yyyy"),TEXT(Main!B3+((Main!B5-Main!B3)*19+18),"mmmm dd yyyy")) -> Debts Or Credits For the Comming October 20 2025 to November 19 2025
A115: Principal | C115: Description | E115: Amount
...

Sheet January 2026 - March 2026
A1: ="Forecasts For the Year "&IF(Main!B2,TEXT(EDATE(Main!B3,21),"mmmm yyyy"),TEXT(Main!B3+((Main!B5-Main!B3)*21+21),"mmmm yyyy"))&" to "&IF(Main!B2,TEXT(EDATE(Main!B3,24)-1,"mmmm yyyy"),TEXT(Main!B3+((Main!B5-Main!B3)*24+23),"mmmm yyyy")) -> Forecasts For the Year January 2026 to April 2026
A2: Assets | B2: Overall | C2: {=INDIRECT("'"&Main!B9&"'!$C$16")} -> 1181.5
B3: Forecasts | C3: =E190 -> 4784.7
A4: Total | C4: =SUM(C2:G3) -> 5966.2
A5: Net Debts: | C5: =C108 -> 0
A8: =IF(Main!B2,TEXT(EDATE(Main!B3,21),"dd mmmm yyyy"),TEXT(Main!B3+((Main!B5-Main!B3)*21+21),"dd mmmm yyyy"))&" - "&IF(Main!B2,TEXT(EDATE(Main!B3,22)-1,"dd mmmm yyyy"),TEXT(Main!B3+((Main!B5-Main!B3)*22+21),"dd mmmm yyyy"))&" / "&" (Revenue / Deferred Debts Or Expenses)" -> 20 January 2026 - 19 February 2026 / (Revenue / Deferred Debts Or Expenses)
A9: Date | B9: Name | D9: Description | F9: Amount
B10: Social Welfare | D10: N/A | F10: 2435
A11: 31st January 2026 | B11: Salary | D11: Deduct 5% MPF | F11: 0
B12: Cigarette Egg | D12: Brought in Advance | F12: 0
F13: 0
F14: 0
F15: 0
D16: Total Revenue | F16: =SUM(F10:G15) -> 2435
A20: =IF(Main!B2,TEXT(EDATE(Main!B3,22),"dd mmmm yyyy"),TEXT(Main!B3+((Main!B5-Main!B3)*22+22),"dd mmmm yyyy"))&" - "&IF(Main!B2,TEXT(EDATE(Main!B3,23)-1,"dd mmmm yyyy"),TEXT(Main!B3+((Main!B5-Main!B3)*23+22),"dd mmmm yyyy"))&" / "&" (Revenue / Deferred Debts Or Expenses)" -> 20 February 2026 - 19 March 2026 / (Revenue / Deferred Debts Or Expenses)
A21: Date | B21: Name | D21: Description | F21: Amount
B22: Social Welfare | D22: N/A | F22: 2435
A23: 28th February 2026 | B23: Salary | D23: Deduct 5% MPF | F23: 0
B24: Cigarette Egg | D24: Brought in Advance | F24: 0
F25: 0
F26: 0
F27: 0
D28: Total Revenue | F28: =SUM(F22:G27) -> 2435
A32: =IF(Main!B2,TEXT(EDATE(Main!B3,23),"dd mmmm yyyy"),TEXT(Main!B3+((Main!B5-Main!B3)*23+23),"dd mmmm yyyy"))&" - "&IF(Main!B2,TEXT(EDATE(Main!B3,24)-1,"dd mmmm yyyy"),TEXT(Main!B3+((Main!B5-Main!B3)*24+23),"dd mmmm yyyy"))&" / "&" (Revenue / Deferred Debts Or Expenses)" -> 20 March 2026 - 19 April 2026 / (Revenue / Deferred Debts Or Expenses)
A33: Date | B33: Name | D33: Description | F33: Amount
B34: Social Welfare | D34: N/A | F34: 2435
A35: 31th March 2026 | B35: Salary | D35: Deduct 5% MPF | F35: 0
B36: Cigarette Egg | D36: Brought in Advance | F36: 0
F37: 0
F38: 0
F39: 0
D40: Total Revenue | F40: =SUM(F34:G39) -> 2435
A44: ="Fixed Expense For the Year "&IF(Main!B2,TEXT(EDATE(Main!B3,21),"mmmm yyyy"),TEXT(Main!B3+((Main!B5-Main!B3)*21+21),"mmmm yyyy"))&" to "&IF(Main!B2,TEXT(EDATE(Main!B3,24)-1,"mmmm yyyy"),TEXT(Main!B3+((Main!B5-Main!B3)*24+23),"mmmm yyyy")) -> Fixed Expense For the Year January 2026 to April 2026
A45: Name | B45: Description | C45: Amount
A46: Mobile And Communications/ Housing Expenses
A47: {=IF((INDIRECT("'"&INDIRECT("Main!B9")&"'!A61"))=0,"",(INDIRECT("'"&INDIRECT("Main!B9")&"'!A61")))} -> Broadband | B47: {=IF((INDIRECT("'"&INDIRECT("Main!B9")&"'!B61"))=0,"",(INDIRECT("'"&INDIRECT("Main!B9")&"'!B61")))} | C47: 78
A48: {=IF((INDIRECT("'"&INDIRECT("Main!B9")&"'!A62"))=0,"",(INDIRECT("'"&INDIRECT("Main!B9")&"'!A62")))} -> China Mobile | B48: {=IF((INDIRECT("'"&INDIRECT("Main!B9")&"'!B62"))=0,"",(INDIRECT("'"&INDIRECT("Main!B9")&"'!B62")))} | C48: 149
A49: {=IF((INDIRECT("'"&INDIRECT("Main!B9")&"'!A63"))=0,"",(INDIRECT("'"&INDIRECT("Main!B9")&"'!A63")))} -> Telephone (Fixed Line) | B49: {=IF((INDIRECT("'"&INDIRECT("Main!B9")&"'!B63"))=0,"",(INDIRECT("'"&INDIRECT("Main!B9")&"'!B63")))} | C49: 0
A50: {=IF((INDIRECT("'"&INDIRECT("Main!B9")&"'!A64"))=0,"",(INDIRECT("'"&INDIRECT("Main!B9")&"'!A64")))} -> Sosim | B50: {=IF((INDIRECT("'"&INDIRECT("Main!B9")&"'!B64"))=0,"",(INDIRECT("'"&INDIRECT("Main!B9")&"'!B64")))} | C50: 0
A51: {=IF((INDIRECT("'"&INDIRECT("Main!B9")&"'!A65"))=0,"",(INDIRECT("'"&INDIRECT("Main!B9")&"'!A65")))} -> Birdie Sim Card Pay date (7th Of Each Month) | B51: {=IF((INDIRECT("'"&INDIRECT("Main!B9")&"'!B65"))=0,"",(INDIRECT("'"&INDIRECT("Main!B9")&"'!B65")))} | C51: 50
A52: {=IF((INDIRECT("'"&INDIRECT("Main!B9")&"'!A66"))=0,"",(INDIRECT("'"&INDIRECT("Main!B9")&"'!A66")))} | B52: {=IF((INDIRECT("'"&INDIRECT("Main!B9")&"'!B66"))=0,"",(INDIRECT("'"&INDIRECT("Main!B9")&"'!B66")))} | C52: 0
A53: {=IF((INDIRECT("'"&INDIRECT("Main!B9")&"'!A67"))=0,"",(INDIRECT("'"&INDIRECT("Main!B9")&"'!A67")))} | B53: {=IF((INDIRECT("'"&INDIRECT("Main!B9")&"'!B67"))=0,"",(INDIRECT("'"&INDIRECT("Main!B9")&"'!B67")))} | C53: 0
A54: {=IF((INDIRECT("'"&INDIRECT("Main!B9")&"'!A68"))=0,"",(INDIRECT("'"&INDIRECT("Main!B9")&"'!A68")))} | B54: {=IF((INDIRECT("'"&INDIRECT("Main!B9")&"'!B68"))=0,"",(INDIRECT("'"&INDIRECT("Main!B9")&"'!B68")))} | C54: 0
B55: Total Expenses | C55: =SUM(C47:C54) -> 277
A56: Credit Card Installments/Government Installments
A57: {=IF((INDIRECT("'"&INDIRECT("Main!B9")&"'!A71"))=0,"",(INDIRECT("'"&INDIRECT("Main!B9")&"'!A71")))} -> Citi Bank | B57: {=IF((INDIRECT("'"&INDIRECT("Main!B9")&"'!B71"))=0,"",(INDIRECT("'"&INDIRECT("Main!B9")&"'!B71")))} | C57: 0
A58: {=IF((INDIRECT("'"&INDIRECT("Main!B9")&"'!A72"))=0,"",(INDIRECT("'"&INDIRECT("Main!B9")&"'!A72")))} -> SC Bank | B58: {=IF((INDIRECT("'"&INDIRECT("Main!B9")&"'!B72"))=0,"",(INDIRECT("'"&INDIRECT("Main!B9")&"'!B72")))} | C58: 0
A59: {=IF((INDIRECT("'"&INDIRECT("Main!B9")&"'!A73"))=0,"",(INDIRECT("'"&INDIRECT("Main!B9")&"'!A73")))} -> Bank Of China | B59: {=IF((INDIRECT("'"&INDIRECT("Main!B9")&"'!B73"))=0,"",(INDIRECT("'"&INDIRECT("Main!B9")&"'!B73")))} | C59: 0
A60: {=IF((INDIRECT("'"&INDIRECT("Main!B9")&"'!A74"))=0,"",(INDIRECT("'"&INDIRECT("Main!B9")&"'!A74")))} -> HSBC | B60: {=IF((INDIRECT("'"&INDIRECT("Main!B9")&"'!B74"))=0,"",(INDIRECT("'"&INDIRECT("Main!B9")&"'!B74")))} | C60: 0
A61: {=IF((INDIRECT("'"&INDIRECT("Main!B9")&"'!A75"))=0,"",(INDIRECT("'"&INDIRECT("Main!B9")&"'!A75")))} | B61: {=IF((INDIRECT("'"&INDIRECT("Main!B9")&"'!B75"))=0,"",(INDIRECT("'"&INDIRECT("Main!B9")&"'!B75")))} | C61: 0
A62: {=IF((INDIRECT("'"&INDIRECT("Main!B9")&"'!A76"))=0,"",(INDIRECT("'"&INDIRECT("Main!B9")&"'!A76")))} | B62: {=IF((INDIRECT("'"&INDIRECT("Main!B9")&"'!B76"))=0,"",(INDIRECT("'"&INDIRECT("Main!B9")&"'!B76")))} | C62: 0
A63: {=IF((INDIRECT("'"&INDIRECT("Main!B9")&"'!A77"))=0,"",(INDIRECT("'"&INDIRECT("Main!B9")&"'!A77")))} | B63: {=IF((INDIRECT("'"&INDIRECT("Main!B9")&"'!B77"))=0,"",(INDIRECT("'"&INDIRECT("Main!B9")&"'!B77")))} | C63: 0
A64: {=IF((INDIRECT("'"&INDIRECT("Main!B9")&"'!A78"))=0,"",(INDIRECT("'"&INDIRECT("Main!B9")&"'!A78")))} | B64: {=IF((INDIRECT("'"&INDIRECT("Main!B9")&"'!B78"))=0,"",(INDIRECT("'"&INDIRECT("Main!B9")&"'!B78")))} | C64: 0
A65: {=IF((INDIRECT("'"&INDIRECT("Main!B9")&"'!A79"))=0,"",(INDIRECT("'"&INDIRECT("Main!B9")&"'!A79")))} | B65: {=IF((INDIRECT("'"&INDIRECT("Main!B9")&"'!B79"))=0,"",(INDIRECT("'"&INDIRECT("Main!B9")&"'!B79")))} | C65: 0
B66: Total Expenses | C66: =SUM(C57:C65) -> 0
A67: Donation
A68: {=IF((INDIRECT("'"&INDIRECT("Main!B9")&"'!A82"))=0,"",(INDIRECT("'"&INDIRECT("Main!B9")&"'!A82")))} -> Traversy | B68: {=IF((INDIRECT("'"&INDIRECT("Main!B9")&"'!B82"))=0,"",(INDIRECT("'"&INDIRECT("Main!B9")&"'!B82")))} -> Traversy Media | C68: 0
A69: {=IF((INDIRECT("'"&INDIRECT("Main!B9")&"'!A83"))=0,"",(INDIRECT("'"&INDIRECT("Main!B9")&"'!A83")))} -> Orbis | B69: {=IF((INDIRECT("'"&INDIRECT("Main!B9")&"'!B83"))=0,"",(INDIRECT("'"&INDIRECT("Main!B9")&"'!B83")))} -> Orbis Eye Flight | C69: 0
A70: {=IF((INDIRECT("'"&INDIRECT("Main!B9")&"'!A84"))=0,"",(INDIRECT("'"&INDIRECT("Main!B9")&"'!A84")))} | B70: {=IF((INDIRECT("'"&INDIRECT("Main!B9")&"'!B84"))=0,"",(INDIRECT("'"&INDIRECT("Main!B9")&"'!B84")))} | C70: 0
A71: {=IF((INDIRECT("'"&INDIRECT("Main!B9")&"'!A85"))=0,"",(INDIRECT("'"&INDIRECT("Main!B9")&"'!A85")))} | B71: {=IF((INDIRECT("'"&INDIRECT("Main!B9")&"'!B85"))=0,"",(INDIRECT("'"&INDIRECT("Main!B9")&"'!B85")))} | C71: 0
A72: {=IF((INDIRECT("'"&INDIRECT("Main!B9")&"'!A86"))=0,"",(INDIRECT("'"&INDIRECT("Main!B9")&"'!A86")))} | B72: {=IF((INDIRECT("'"&INDIRECT("Main!B9")&"'!B86"))=0,"",(INDIRECT("'"&INDIRECT("Main!B9")&"'!B86")))} | C72: 0
A73: {=IF((INDIRECT("'"&INDIRECT("Main!B9")&"'!A87"))=0,"",(INDIRECT("'"&INDIRECT("Main!B9")&"'!A87")))} | B73: {=IF((INDIRECT("'"&INDIRECT("Main!B9")&"'!B87"))=0,"",(INDIRECT("'"&INDIRECT("Main!B9")&"'!B87")))} | C73: 0
A74: {=IF((INDIRECT("'"&INDIRECT("Main!B9")&"'!A88"))=0,"",(INDIRECT("'"&INDIRECT("Main!B9")&"'!A88")))} | B74: {=IF((INDIRECT("'"&INDIRECT("Main!B9")&"'!B88"))=0,"",(INDIRECT("'"&INDIRECT("Main!B9")&"'!B88")))} | C74: 0
B75: Total Expenses | C75: =SUM(C68:C74) -> 0
A76: Insurance (Personal / Properties / Medical)
A77: {=IF((INDIRECT("'"&INDIRECT("Main!B9")&"'!A91"))=0,"",(INDIRECT("'"&INDIRECT("Main!B9")&"'!A91")))} -> AIA | B77: {=IF((INDIRECT("'"&INDIRECT("Main!B9")&"'!B91"))=0,"",(INDIRECT("'"&INDIRECT("Main!B9")&"'!B91")))} | C77: 0
A78: {=IF((INDIRECT("'"&INDIRECT("Main!B9")&"'!A92"))=0,"",(INDIRECT("'"&INDIRECT("Main!B9")&"'!A92")))} | B78: {=IF((INDIRECT("'"&INDIRECT("Main!B9")&"'!B92"))=0,"",(INDIRECT("'"&INDIRECT("Main!B9")&"'!B92")))} | C78: 0
A79: {=IF((INDIRECT("'"&INDIRECT("Main!B9")&"'!A93"))=0,"",(INDIRECT("'"&INDIRECT("Main!B9")&"'!A93")))} | B79: {=IF((INDIRECT("'"&INDIRECT("Main!B9")&"'!B93"))=0,"",(INDIRECT("'"&INDIRECT("Main!B9")&"'!B93")))} | C79: 0
A80: {=IF((INDIRECT("'"&INDIRECT("Main!B9")&"'!A94"))=0,"",(INDIRECT("'"&INDIRECT("Main!B9")&"'!A94")))} | B80: {=IF((INDIRECT("'"&INDIRECT("Main!B9")&"'!B94"))=0,"",(INDIRECT("'"&INDIRECT("Main!B9")&"'!B94")))} | C80: 0
A81: {=IF((INDIRECT("'"&INDIRECT("Main!B9")&"'!A95"))=0,"",(INDIRECT("'"&INDIRECT("Main!B9")&"'!A95")))} | B81: {=IF((INDIRECT("'"&INDIRECT("Main!B9")&"'!B95"))=0,"",(INDIRECT("'"&INDIRECT("Main!B9")&"'!B95")))} | C81: 0
A82: {=IF((INDIRECT("'"&INDIRECT("Main!B9")&"'!A96"))=0,"",(INDIRECT("'"&INDIRECT("Main!B9")&"'!A96")))} | B82: {=IF((INDIRECT("'"&INDIRECT("Main!B9")&"'!B96"))=0,"",(INDIRECT("'"&INDIRECT("Main!B9")&"'!B96")))} | C82: 0
A83: {=IF((INDIRECT("'"&INDIRECT("Main!B9")&"'!A97"))=0,"",(INDIRECT("'"&INDIRECT("Main!B9")&"'!A97")))} | B83: {=IF((INDIRECT("'"&INDIRECT("Main!B9")&"'!B97"))=0,"",(INDIRECT("'"&INDIRECT("Main!B9")&"'!B97")))} | C83: 0
A84: {=IF((INDIRECT("'"&INDIRECT("Main!B9")&"'!A98"))=0,"",(INDIRECT("'"&INDIRECT("Main!B9")&"'!A98")))} | B84: {=IF((INDIRECT("'"&INDIRECT("Main!B9")&"'!B98"))=0,"",(INDIRECT("'"&INDIRECT("Main!B9")&"'!B98")))} | C84: 0
B85: Total Expenses | C85: =SUM(C77:C84) -> 0
A86: Other Expenses
A87: {=IF((INDIRECT("'"&INDIRECT("Main!B9")&"'!A101"))=0,"",(INDIRECT("'"&INDIRECT("Main!B9")&"'!A101")))} -> Other Stuff | B87: {=IF((INDIRECT("'"&INDIRECT("Main!B9")&"'!B101"))=0,"",(INDIRECT("'"&INDIRECT("Main!B9")&"'!B101")))} -> Food, Transport…. | C87: 0
A88: {=IF((INDIRECT("'"&INDIRECT("Main!B9")&"'!A102"))=0,"",(INDIRECT("'"&INDIRECT("Main!B9")&"'!A102")))} -> Entertainment | B88: {=IF((INDIRECT("'"&INDIRECT("Main!B9")&"'!B102"))=0,"",(INDIRECT("'"&INDIRECT("Main!B9")&"'!B102")))} -> Sportify Music / Changed to Apple Music on 13th May 2025 | C88: 68
A89: {=IF((INDIRECT("'"&INDIRECT("Main!B9")&"'!A103"))=0,"",(INDIRECT("'"&INDIRECT("Main!B9")&"'!A103")))} -> Hair Cutting | B89: {=IF((INDIRECT("'"&INDIRECT("Main!B9")&"'!B103"))=0,"",(INDIRECT("'"&INDIRECT("Main!B9")&"'!B103")))} -> Hair Cut not Include Color treatment | C89: 55
A90: {=IF((INDIRECT("'"&INDIRECT("Main!B9")&"'!A104"))=0,"",(INDIRECT("'"&INDIRECT("Main!B9")&"'!A104")))} -> Cigarettes | B90: {=IF((INDIRECT("'"&INDIRECT("Main!B9")&"'!B104"))=0,"",(INDIRECT("'"&INDIRECT("Main!B9")&"'!B104")))} -> 30 packets | C90: 0
A91: {=IF((INDIRECT("'"&INDIRECT("Main!B9")&"'!A105"))=0,"",(INDIRECT("'"&INDIRECT("Main!B9")&"'!A105")))} | B91: {=IF((INDIRECT("'"&INDIRECT("Main!B9")&"'!B105"))=0,"",(INDIRECT("'"&INDIRECT("Main!B9")&"'!B105")))} | C91: 0
A92: {=IF((INDIRECT("'"&INDIRECT("Main!B9")&"'!A106"))=0,"",(INDIRECT("'"&INDIRECT("Main!B9")&"'!A106")))} | B92: {=IF((INDIRECT("'"&INDIRECT("Main!B9")&"'!B106"))=0,"",(INDIRECT("'"&INDIRECT("Main!B9")&"'!B106")))} | C92: 0
A93: {=IF((INDIRECT("'"&INDIRECT("Main!B9")&"'!A107"))=0,"",(INDIRECT("'"&INDIRECT("Main!B9")&"'!A107")))} | B93: {=IF((INDIRECT("'"&INDIRECT("Main!B9")&"'!B107"))=0,"",(INDIRECT("'"&INDIRECT("Main!B9")&"'!B107")))} | C93: 0
A94: {=IF((INDIRECT("'"&INDIRECT("Main!B9")&"'!A108"))=0,"",(INDIRECT("'"&INDIRECT("Main!B9")&"'!A108")))} | B94: {=IF((INDIRECT("'"&INDIRECT("Main!B9")&"'!B108"))=0,"",(INDIRECT("'"&INDIRECT("Main!B9")&"'!B108")))} | C94: 0
B95: Total Expenses | C95: =SUM(C87:C94) -> 123
B96: Grand Expenses Total | C96: =C55+C66+C75+C85+C95 -> 400
A97: Debts
A98: {=IF((INDIRECT("'"&INDIRECT("Main!B9")&"'!A112"))=0,"",(INDIRECT("'"&INDIRECT("Main!B9")&"'!A112")))} -> Mother | B98: {=IF((INDIRECT("'"&INDIRECT("Main!B9")&"'!B112"))=0,"",(INDIRECT("'"&INDIRECT("Main!B9")&"'!B112")))} | C98: {=INDIRECT("'"&INDIRECT("Main!B27")&"'!C98")+SUM(E118+E145+E172)} -> 0
A99: {=IF((INDIRECT("'"&INDIRECT("Main!B9")&"'!A113"))=0,"",(INDIRECT("'"&INDIRECT("Main!B9")&"'!A113")))} -> Ng Wing Lam | B99: {=IF((INDIRECT("'"&INDIRECT("Main!B9")&"'!B113"))=0,"",(INDIRECT("'"&INDIRECT("Main!B9")&"'!B113")))} | C99: {=INDIRECT("'"&INDIRECT("Main!B27")&"'!C99")+SUM(E119+E146+E173)} -> 0
A100: {=IF((INDIRECT("'"&INDIRECT("Main!B9")&"'!A114"))=0,"",(INDIRECT("'"&INDIRECT("Main!B9")&"'!A114")))} -> Lawrence | B100: {=IF((INDIRECT("'"&INDIRECT("Main!B9")&"'!B114"))=0,"",(INDIRECT("'"&INDIRECT("Main!B9")&"'!B114")))} | C100: {=INDIRECT("'"&INDIRECT("Main!B27")&"'!C100")+SUM(E120+E147+E174)} -> 0
A101: {=IF((INDIRECT("'"&INDIRECT("Main!B9")&"'!A115"))=0,"",(INDIRECT("'"&INDIRECT("Main!B9")&"'!A115")))} -> Hong Kong Government Hospital Authority | B101: {=IF((INDIRECT("'"&INDIRECT("Main!B9")&"'!B115"))=0,"",(INDIRECT("'"&INDIRECT("Main!B9")&"'!B115")))} | C101: {=INDIRECT("'"&INDIRECT("Main!B27")&"'!C101")+SUM(E121+E148+E175)} -> 0
A102: {=IF((INDIRECT("'"&INDIRECT("Main!B9")&"'!A116"))=0,"",(INDIRECT("'"&INDIRECT("Main!B9")&"'!A116")))} -> Bankruptcy Department / Bank | B102: {=IF((INDIRECT("'"&INDIRECT("Main!B9")&"'!B116"))=0,"",(INDIRECT("'"&INDIRECT("Main!B9")&"'!B116")))} | C102: {=INDIRECT("'"&INDIRECT("Main!B27")&"'!C102")+SUM(E122+E149+E176)} -> 0
A103: {=IF((INDIRECT("'"&INDIRECT("Main!B9")&"'!A117"))=0,"",(INDIRECT("'"&INDIRECT("Main!B9")&"'!A117")))} -> Mother Air Ticket | B103: {=IF((INDIRECT("'"&INDIRECT("Main!B9")&"'!B117"))=0,"",(INDIRECT("'"&INDIRECT("Main!B9")&"'!B117")))} | C103: {=INDIRECT("'"&INDIRECT("Main!B27")&"'!C103")+SUM(E123+E150+E177)} -> 0
A104: {=IF((INDIRECT("'"&INDIRECT("Main!B9")&"'!A118"))=0,"",(INDIRECT("'"&INDIRECT("Main!B9")&"'!A118")))} | B104: {=IF((INDIRECT("'"&INDIRECT("Main!B9")&"'!B118"))=0,"",(INDIRECT("'"&INDIRECT("Main!B9")&"'!B118")))} | C104: {=INDIRECT("'"&INDIRECT("Main!B27")&"'!C104")+SUM(E124+E151+E178)} -> 0
A105: {=IF((INDIRECT("'"&INDIRECT("Main!B9")&"'!A119"))=0,"",(INDIRECT("'"&INDIRECT("Main!B9")&"'!A119")))} | B105: {=IF((INDIRECT("'"&INDIRECT("Main!B9")&"'!B119"))=0,"",(INDIRECT("'"&INDIRECT("Main!B9")&"'!B119")))} | C105: {=INDIRECT("'"&INDIRECT("Main!B27")&"'!C105")+SUM(E125+E152+E179)} -> 0
A106: {=IF((INDIRECT("'"&INDIRECT("Main!B9")&"'!A120"))=0,"",(INDIRECT("'"&INDIRECT("Main!B9")&"'!A120")))} | B106: {=IF((INDIRECT("'"&INDIRECT("Main!B9")&"'!B120"))=0,"",(INDIRECT("'"&INDIRECT("Main!B9")&"'!B120")))} | C106: {=INDIRECT("'"&INDIRECT("Main!B27")&"'!C106")+SUM(E126+E153+E180)} -> 0
A107: {=IF((INDIRECT("'"&INDIRECT("Main!B9")&"'!A121"))=0,"",(INDIRECT("'"&INDIRECT("Main!B9")&"'!A121")))} | B107: {=IF((INDIRECT("'"&INDIRECT("Main!B9")&"'!B121"))=0,"",(INDIRECT("'"&INDIRECT("Main!B9")&"'!B121")))} | C107: {=INDIRECT("'"&INDIRECT("Main!B27")&"'!C107")+SUM(E127+E154+E181)} -> 0
B108: Total Debts | C108: =SUM(C98:C107) -> 0
B109: Grand Total | C109: =C108-C96 -> -400
A114: ="Debts Or Credits For the Comming "&IF(Main!B2,TEXT(EDATE(Main!B3,21),"mmmm dd yyyy"),TEXT(Main!B3+((Main!B5-Main!B3)*21+21),"mmmm dd yyyy"))&" to "&IF(Main!B2,TEXT(EDATE(Main!B3,22)-1,"mmmm dd yyyy"),TEXT(Main!B3+((Main!B5-Main!B3)*22+21),"mmmm dd yyyy")) -> Debts Or Credits For the Comming January 20 2026 to February 19 2026
A115: Principal | C115: Description | E115: Amount
...

Sheet April 2026 - June 2026
A1: ="Forecasts For the Year "&IF(Main!B2,TEXT(EDATE(Main!B3,24),"mmmm yyyy"),TEXT(Main!B3+((Main!B5-Main!B3)*24+24),"mmmm yyyy"))&" to "&IF(Main!B2,TEXT(EDATE(Main!B3,27)-1,"mmmm yyyy"),TEXT(Main!B3+((Main!B5-Main!B3)*27+26),"mmmm yyyy")) -> Forecasts For the Year April 2026 to July 2026
A2: Assets | B2: Overall | C2: {=INDIRECT("'"&Main!B9&"'!$C$16")} -> 1181.5
B3: Forecasts | C3: =E190 -> 6570.8
A4: Total | C4: =SUM(C2:G3) -> 7752.3
A5: Net Debts: | C5: =C108 -> 0
A8: =IF(Main!B2,TEXT(EDATE(Main!B3,24),"dd mmmm yyyy"),TEXT(Main!B3+((Main!B5-Main!B3)*24+24),"dd mmmm yyyy"))&" - "&IF(Main!B2,TEXT(EDATE(Main!B3,25)-1,"dd mmmm yyyy"),TEXT(Main!B3+((Main!B5-Main!B3)*25+24),"dd mmmm yyyy"))&" / "&" (Revenue / Deferred Debts Or Expenses)" -> 20 April 2026 - 19 May 2026 / (Revenue / Deferred Debts Or Expenses)
A9: Date | B9: Name | D9: Description | F9: Amount
B10: Social Welfare | D10: N/A | F10: 2435
A11: 30th April 2026 | B11: Salary | D11: Deduct 5% MPF | F11: 0
B12: Cigarette Egg | D12: Brought in Advance | F12: 0
F13: 0
F14: 0
F15: 0
D16: Total Revenue | F16: =SUM(F10:G15) -> 2435
A20: =IF(Main!B2,TEXT(EDATE(Main!B3,25),"dd mmmm yyyy"),TEXT(Main!B3+((Main!B5-Main!B3)*25+25),"dd mmmm yyyy"))&" - "&IF(Main!B2,TEXT(EDATE(Main!B3,26)-1,"dd mmmm yyyy"),TEXT(Main!B3+((Main!B5-Main!B3)*26+25),"dd mmmm yyyy"))&" / "&" (Revenue / Deferred Debts Or Expenses)" -> 20 May 2026 - 19 June 2026 / (Revenue / Deferred Debts Or Expenses)
A21: Date | B21: Name | D21: Description | F21: Amount
B22: Social Welfare | D22: N/A | F22: 2435
A23: 31st May 2026 | B23: Salary | D23: Deduct 5% MPF | F23: 0
B24: Cigarette Egg | D24: Brought in Advance | F24: 0
F25: 0
F26: 0
F27: 0
D28: Total Revenue | F28: =SUM(F22:G27) -> 2435
A32: =IF(Main!B2,TEXT(EDATE(Main!B3,26),"dd mmmm yyyy"),TEXT(Main!B3+((Main!B5-Main!B3)*26+26),"dd mmmm yyyy"))&" - "&IF(Main!B2,TEXT(EDATE(Main!B3,27)-1,"dd mmmm yyyy"),TEXT(Main!B3+((Main!B5-Main!B3)*27+26),"dd mmmm yyyy"))&" / "&" (Revenue / Deferred Debts Or Expenses)" -> 20 June 2026 - 19 July 2026 / (Revenue / Deferred Debts Or Expenses)
A33: Date | B33: Name | D33: Description | F33: Amount
B34: Social Welfare | D34: N/A | F34: 2435
A35: 30th June 2026 | B35: Salary | D35: Deduct 5% MPF | F35: 0
B36: Cigarette Egg | D36: Brought in Advance | F36: 0
F37: 0
F38: 0
F39: 0
D40: Total Revenue | F40: =SUM(F34:G39) -> 2435
A44: ="Fixed Expense For the Year "&IF(Main!B2,TEXT(EDATE(Main!B3,24),"mmmm yyyy"),TEXT(Main!B3+((Main!B5-Main!B3)*24+24),"mmmm yyyy"))&" to "&IF(Main!B2,TEXT(EDATE(Main!B3,27)-1,"mmmm yyyy"),TEXT(Main!B3+((Main!B5-Main!B3)*27+26),"mmmm yyyy")) -> Fixed Expense For the Year April 2026 to July 2026
A45: Name | B45: Description | C45: Amount
A46: Mobile And Communications/ Housing Expenses
A47: {=IF((INDIRECT("'"&INDIRECT("Main!B9")&"'!A61"))=0,"",(INDIRECT("'"&INDIRECT("Main!B9")&"'!A61")))} -> Broadband | B47: {=IF((INDIRECT("'"&INDIRECT("Main!B9")&"'!B61"))=0,"",(INDIRECT("'"&INDIRECT("Main!B9")&"'!B61")))} | C47: 78
A48: {=IF((INDIRECT("'"&INDIRECT("Main!B9")&"'!A62"))=0,"",(INDIRECT("'"&INDIRECT("Main!B9")&"'!A62")))} -> China Mobile | B48: {=IF((INDIRECT("'"&INDIRECT("Main!B9")&"'!B62"))=0,"",(INDIRECT("'"&INDIRECT("Main!B9")&"'!B62")))} | C48: 149
A49: {=IF((INDIRECT("'"&INDIRECT("Main!B9")&"'!A63"))=0,"",(INDIRECT("'"&INDIRECT("Main!B9")&"'!A63")))} -> Telephone (Fixed Line) | B49: {=IF((INDIRECT("'"&INDIRECT("Main!B9")&"'!B63"))=0,"",(INDIRECT("'"&INDIRECT("Main!B9")&"'!B63")))} | C49: 0
A50: {=IF((INDIRECT("'"&INDIRECT("Main!B9")&"'!A64"))=0,"",(INDIRECT("'"&INDIRECT("Main!B9")&"'!A64")))} -> Sosim | B50: {=IF((INDIRECT("'"&INDIRECT("Main!B9")&"'!B64"))=0,"",(INDIRECT("'"&INDIRECT("Main!B9")&"'!B64")))} | C50: 0
A51: {=IF((INDIRECT("'"&INDIRECT("Main!B9")&"'!A65"))=0,"",(INDIRECT("'"&INDIRECT("Main!B9")&"'!A65")))} -> Birdie Sim Card Pay date (7th Of Each Month) | B51: {=IF((INDIRECT("'"&INDIRECT("Main!B9")&"'!B65"))=0,"",(INDIRECT("'"&INDIRECT("Main!B9")&"'!B65")))} | C51: 50
A52: {=IF((INDIRECT("'"&INDIRECT("Main!B9")&"'!A66"))=0,"",(INDIRECT("'"&INDIRECT("Main!B9")&"'!A66")))} | B52: {=IF((INDIRECT("'"&INDIRECT("Main!B9")&"'!B66"))=0,"",(INDIRECT("'"&INDIRECT("Main!B9")&"'!B66")))} | C52: 0
A53: {=IF((INDIRECT("'"&INDIRECT("Main!B9")&"'!A67"))=0,"",(INDIRECT("'"&INDIRECT("Main!B9")&"'!A67")))} | B53: {=IF((INDIRECT("'"&INDIRECT("Main!B9")&"'!B67"))=0,"",(INDIRECT("'"&INDIRECT("Main!B9")&"'!B67")))} | C53: 0
A54: {=IF((INDIRECT("'"&INDIRECT("Main!B9")&"'!A68"))=0,"",(INDIRECT("'"&INDIRECT("Main!B9")&"'!A68")))} | B54: {=IF((INDIRECT("'"&INDIRECT("Main!B9")&"'!B68"))=0,"",(INDIRECT("'"&INDIRECT("Main!B9")&"'!B68")))} | C54: 0
B55: Total Expenses | C55: =SUM(C47:C54) -> 277
A56: Credit Card Installments/Government Installments
A57: {=IF((INDIRECT("'"&INDIRECT("Main!B9")&"'!A71"))=0,"",(INDIRECT("'"&INDIRECT("Main!B9")&"'!A71")))} -> Citi Bank | B57: {=IF((INDIRECT("'"&INDIRECT("Main!B9")&"'!B71"))=0,"",(INDIRECT("'"&INDIRECT("Main!B9")&"'!B71")))} | C57: 0
A58: {=IF((INDIRECT("'"&INDIRECT("Main!B9")&"'!A72"))=0,"",(INDIRECT("'"&INDIRECT("Main!B9")&"'!A72")))} -> SC Bank | B58: {=IF((INDIRECT("'"&INDIRECT("Main!B9")&"'!B72"))=0,"",(INDIRECT("'"&INDIRECT("Main!B9")&"'!B72")))} | C58: 0
A59: {=IF((INDIRECT("'"&INDIRECT("Main!B9")&"'!A73"))=0,"",(INDIRECT("'"&INDIRECT("Main!B9")&"'!A73")))} -> Bank Of China | B59: {=IF((INDIRECT("'"&INDIRECT("Main!B9")&"'!B73"))=0,"",(INDIRECT("'"&INDIRECT("Main!B9")&"'!B73")))} | C59: 0
A60: {=IF((INDIRECT("'"&INDIRECT("Main!B9")&"'!A74"))=0,"",(INDIRECT("'"&INDIRECT("Main!B9")&"'!A74")))} -> HSBC | B60: {=IF((INDIRECT("'"&INDIRECT("Main!B9")&"'!B74"))=0,"",(INDIRECT("'"&INDIRECT("Main!B9")&"'!B74")))} | C60: 0
A61: {=IF((INDIRECT("'"&INDIRECT("Main!B9")&"'!A75"))=0,"",(INDIRECT("'"&INDIRECT("Main!B9")&"'!A75")))} | B61: {=IF((INDIRECT("'"&INDIRECT("Main!B9")&"'!B75"))=0,"",(INDIRECT("'"&INDIRECT("Main!B9")&"'!B75")))} | C61: 0
A62: {=IF((INDIRECT("'"&INDIRECT("Main!B9")&"'!A76"))=0,"",(INDIRECT("'"&INDIRECT("Main!B9")&"'!A76")))} | B62: {=IF((INDIRECT("'"&INDIRECT("Main!B9")&"'!B76"))=0,"",(INDIRECT("'"&INDIRECT("Main!B9")&"'!B76")))} | C62: 0
A63: {=IF((INDIRECT("'"&INDIRECT("Main!B9")&"'!A77"))=0,"",(INDIRECT("'"&INDIRECT("Main!B9")&"'!A77")))} | B63: {=IF((INDIRECT("'"&INDIRECT("Main!B9")&"'!B77"))=0,"",(INDIRECT("'"&INDIRECT("Main!B9")&"'!B77")))} | C63: 0
A64: {=IF((INDIRECT("'"&INDIRECT("Main!B9")&"'!A78"))=0,"",(INDIRECT("'"&INDIRECT("Main!B9")&"'!A78")))} | B64: {=IF((INDIRECT("'"&INDIRECT("Main!B9")&"'!B78"))=0,"",(INDIRECT("'"&INDIRECT("Main!B9")&"'!B78")))} | C64: 0
A65: {=IF((INDIRECT("'"&INDIRECT("Main!B9")&"'!A79"))=0,"",(INDIRECT("'"&INDIRECT("Main!B9")&"'!A79")))} | B65: {=IF((INDIRECT("'"&INDIRECT("Main!B9")&"'!B79"))=0,"",(INDIRECT("'"&INDIRECT("Main!B9")&"'!B79")))} | C65: 0
B66: Total Expenses | C66: =SUM(C57:C65) -> 0
A67: Donation
A68: {=IF((INDIRECT("'"&INDIRECT("Main!B9")&"'!A82"))=0,"",(INDIRECT("'"&INDIRECT("Main!B9")&"'!A82")))} -> Traversy | B68: {=IF((INDIRECT("'"&INDIRECT("Main!B9")&"'!B82"))=0,"",(INDIRECT("'"&INDIRECT("Main!B9")&"'!B82")))} -> Traversy Media | C68: 0
A69: {=IF((INDIRECT("'"&INDIRECT("Main!B9")&"'!A83"))=0,"",(INDIRECT("'"&INDIRECT("Main!B9")&"'!A83")))} -> Orbis | B69: {=IF((INDIRECT("'"&INDIRECT("Main!B9")&"'!B83"))=0,"",(INDIRECT("'"&INDIRECT("Main!B9")&"'!B83")))} -> Orbis Eye Flight | C69: 0
A70: {=IF((INDIRECT("'"&INDIRECT("Main!B9")&"'!A84"))=0,"",(INDIRECT("'"&INDIRECT("Main!B9")&"'!A84")))} | B70: {=IF((INDIRECT("'"&INDIRECT("Main!B9")&"'!B84"))=0,"",(INDIRECT("'"&INDIRECT("Main!B9")&"'!B84")))} | C70: 0
A71: {=IF((INDIRECT("'"&INDIRECT("Main!B9")&"'!A85"))=0,"",(INDIRECT("'"&INDIRECT("Main!B9")&"'!A85")))} | B71: {=IF((INDIRECT("'"&INDIRECT("Main!B9")&"'!B85"))=0,"",(INDIRECT("'"&INDIRECT("Main!B9")&"'!B85")))} | C71: 0
A72: {=IF((INDIRECT("'"&INDIRECT("Main!B9")&"'!A86"))=0,"",(INDIRECT("'"&INDIRECT("Main!B9")&"'!A86")))} | B72: {=IF((INDIRECT("'"&INDIRECT("Main!B9")&"'!B86"))=0,"",(INDIRECT("'"&INDIRECT("Main!B9")&"'!B86")))} | C72: 0
A73: {=IF((INDIRECT("'"&INDIRECT("Main!B9")&"'!A87"))=0,"",(INDIRECT("'"&INDIRECT("Main!B9")&"'!A87")))} | B73: {=IF((INDIRECT("'"&INDIRECT("Main!B9")&"'!B87"))=0,"",(INDIRECT("'"&INDIRECT("Main!B9")&"'!B87")))} | C73: 0
A74: {=IF((INDIRECT("'"&INDIRECT("Main!B9")&"'!A88"))=0,"",(INDIRECT("'"&INDIRECT("Main!B9")&"'!A88")))} | B74: {=IF((INDIRECT("'"&INDIRECT("Main!B9")&"'!B88"))=0,"",(INDIRECT("'"&INDIRECT("Main!B9")&"'!B88")))} | C74: 0
B75: Total Expenses | C75: =SUM(C68:C74) -> 0
A76: Insurance (Personal / Properties / Medical)
A77: {=IF((INDIRECT("'"&INDIRECT("Main!B9")&"'!A91"))=0,"",(INDIRECT("'"&INDIRECT("Main!B9")&"'!A91")))} -> AIA | B77: {=IF((INDIRECT("'"&INDIRECT("Main!B9")&"'!B91"))=0,"",(INDIRECT("'"&INDIRECT("Main!B9")&"'!B91")))} | C77: 0
A78: {=IF((INDIRECT("'"&INDIRECT("Main!B9")&"'!A92"))=0,"",(INDIRECT("'"&INDIRECT("Main!B9")&"'!A92")))} | B78: {=IF((INDIRECT("'"&INDIRECT("Main!B9")&"'!B92"))=0,"",(INDIRECT("'"&INDIRECT("Main!B9")&"'!B92")))} | C78: 0
A79: {=IF((INDIRECT("'"&INDIRECT("Main!B9")&"'!A93"))=0,"",(INDIRECT("'"&INDIRECT("Main!B9")&"'!A93")))} | B79: {=IF((INDIRECT("'"&INDIRECT("Main!B9")&"'!B93"))=0,"",(INDIRECT("'"&INDIRECT("Main!B9")&"'!B93")))} | C79: 0
A80: {=IF((INDIRECT("'"&INDIRECT("Main!B9")&"'!A94"))=0,"",(INDIRECT("'"&INDIRECT("Main!B9")&"'!A94")))} | B80: {=IF((INDIRECT("'"&INDIRECT("Main!B9")&"'!B94"))=0,"",(INDIRECT("'"&INDIRECT("Main!B9")&"'!B94")))} | C80: 0
A81: {=IF((INDIRECT("'"&INDIRECT("Main!B9")&"'!A95"))=0,"",(INDIRECT("'"&INDIRECT("Main!B9")&"'!A95")))} | B81: {=IF((INDIRECT("'"&INDIRECT("Main!B9")&"'!B95"))=0,"",(INDIRECT("'"&INDIRECT("Main!B9")&"'!B95")))} | C81: 0
A82: {=IF((INDIRECT("'"&INDIRECT("Main!B9")&"'!A96"))=0,"",(INDIRECT("'"&INDIRECT("Main!B9")&"'!A96")))} | B82: {=IF((INDIRECT("'"&INDIRECT("Main!B9")&"'!B96"))=0,"",(INDIRECT("'"&INDIRECT("Main!B9")&"'!B96")))} | C82: 0
A83: {=IF((INDIRECT("'"&INDIRECT("Main!B9")&"'!A97"))=0,"",(INDIRECT("'"&INDIRECT("Main!B9")&"'!A97")))} | B83: {=IF((INDIRECT("'"&INDIRECT("Main!B9")&"'!B97"))=0,"",(INDIRECT("'"&INDIRECT("Main!B9")&"'!B97")))} | C83: 0
A84: {=IF((INDIRECT("'"&INDIRECT("Main!B9")&"'!A98"))=0,"",(INDIRECT("'"&INDIRECT("Main!B9")&"'!A98")))} | B84: {=IF((INDIRECT("'"&INDIRECT("Main!B9")&"'!B98"))=0,"",(INDIRECT("'"&INDIRECT("Main!B9")&"'!B98")))} | C84: 0
B85: Total Expenses | C85: =SUM(C77:C84) -> 0
A86: Other Expenses
A87: {=IF((INDIRECT("'"&INDIRECT("Main!B9")&"'!A101"))=0,"",(INDIRECT("'"&INDIRECT("Main!B9")&"'!A101")))} -> Other Stuff | B87: {=IF((INDIRECT("'"&INDIRECT("Main!B9")&"'!B101"))=0,"",(INDIRECT("'"&INDIRECT("Main!B9")&"'!B101")))} -> Food, Transport…. | C87: 0
A88: {=IF((INDIRECT("'"&INDIRECT("Main!B9")&"'!A102"))=0,"",(INDIRECT("'"&INDIRECT("Main!B9")&"'!A102")))} -> Entertainment | B88: {=IF((INDIRECT("'"&INDIRECT("Main!B9")&"'!B102"))=0,"",(INDIRECT("'"&INDIRECT("Main!B9")&"'!B102")))} -> Sportify Music / Changed to Apple Music on 13th May 2025 | C88: 68
A89: {=IF((INDIRECT("'"&INDIRECT("Main!B9")&"'!A103"))=0,"",(INDIRECT("'"&INDIRECT("Main!B9")&"'!A103")))} -> Hair Cutting | B89: {=IF((INDIRECT("'"&INDIRECT("Main!B9")&"'!B103"))=0,"",(INDIRECT("'"&INDIRECT("Main!B9")&"'!B103")))} -> Hair Cut not Include Color treatment | C89: 55
A90: {=IF((INDIRECT("'"&INDIRECT("Main!B9")&"'!A104"))=0,"",(INDIRECT("'"&INDIRECT("Main!B9")&"'!A104")))} -> Cigarettes | B90: {=IF((INDIRECT("'"&INDIRECT("Main!B9")&"'!B104"))=0,"",(INDIRECT("'"&INDIRECT("Main!B9")&"'!B104")))} -> 30 packets | C90: 0
A91: {=IF((INDIRECT("'"&INDIRECT("Main!B9")&"'!A105"))=0,"",(INDIRECT("'"&INDIRECT("Main!B9")&"'!A105")))} | B91: {=IF((INDIRECT("'"&INDIRECT("Main!B9")&"'!B105"))=0,"",(INDIRECT("'"&INDIRECT("Main!B9")&"'!B105")))} | C91: 0
A92: {=IF((INDIRECT("'"&INDIRECT("Main!B9")&"'!A106"))=0,"",(INDIRECT("'"&INDIRECT("Main!B9")&"'!A106")))} | B92: {=IF((INDIRECT("'"&INDIRECT("Main!B9")&"'!B106"))=0,"",(INDIRECT("'"&INDIRECT("Main!B9")&"'!B106")))} | C92: 0
A93: {=IF((INDIRECT("'"&INDIRECT("Main!B9")&"'!A107"))=0,"",(INDIRECT("'"&INDIRECT("Main!B9")&"'!A107")))} | B93: {=IF((INDIRECT("'"&INDIRECT("Main!B9")&"'!B107"))=0,"",(INDIRECT("'"&INDIRECT("Main!B9")&"'!B107")))} | C93: 0
A94: {=IF((INDIRECT("'"&INDIRECT("Main!B9")&"'!A108"))=0,"",(INDIRECT("'"&INDIRECT("Main!B9")&"'!A108")))} | B94: {=IF((INDIRECT("'"&INDIRECT("Main!B9")&"'!B108"))=0,"",(INDIRECT("'"&INDIRECT("Main!B9")&"'!B108")))} | C94: 0
B95: Total Expenses | C95: =SUM(C87:C94) -> 123
B96: Grand Expenses Total | C96: =C55+C66+C75+C85+C95 -> 400
A97: Debts
A98: {=IF((INDIRECT("'"&INDIRECT("Main!B9")&"'!A112"))=0,"",(INDIRECT("'"&INDIRECT("Main!B9")&"'!A112")))} -> Mother | B98: {=IF((INDIRECT("'"&INDIRECT("Main!B9")&"'!B112"))=0,"",(INDIRECT("'"&INDIRECT("Main!B9")&"'!B112")))} | C98: {=INDIRECT("'"&INDIRECT("Main!B30")&"'!C98")+SUM(E118+E145+E172)} -> 0
A99: {=IF((INDIRECT("'"&INDIRECT("Main!B9")&"'!A113"))=0,"",(INDIRECT("'"&INDIRECT("Main!B9")&"'!A113")))} -> Ng Wing Lam | B99: {=IF((INDIRECT("'"&INDIRECT("Main!B9")&"'!B113"))=0,"",(INDIRECT("'"&INDIRECT("Main!B9")&"'!B113")))} | C99: {=INDIRECT("'"&INDIRECT("Main!B30")&"'!C99")+SUM(E119+E146+E173)} -> 0
A100: {=IF((INDIRECT("'"&INDIRECT("Main!B9")&"'!A114"))=0,"",(INDIRECT("'"&INDIRECT("Main!B9")&"'!A114")))} -> Lawrence | B100: {=IF((INDIRECT("'"&INDIRECT("Main!B9")&"'!B114"))=0,"",(INDIRECT("'"&INDIRECT("Main!B9")&"'!B114")))} | C100: {=INDIRECT("'"&INDIRECT("Main!B30")&"'!C100")+SUM(E120+E147+E174)} -> 0
A101: {=IF((INDIRECT("'"&INDIRECT("Main!B9")&"'!A115"))=0,"",(INDIRECT("'"&INDIRECT("Main!B9")&"'!A115")))} -> Hong Kong Government Hospital Authority | B101: {=IF((INDIRECT("'"&INDIRECT("Main!B9")&"'!B115"))=0,"",(INDIRECT("'"&INDIRECT("Main!B9")&"'!B115")))} | C101: {=INDIRECT("'"&INDIRECT("Main!B30")&"'!C101")+SUM(E121+E148+E175)} -> 0
A102: {=IF((INDIRECT("'"&INDIRECT("Main!B9")&"'!A116"))=0,"",(INDIRECT("'"&INDIRECT("Main!B9")&"'!A116")))} -> Bankruptcy Department / Bank | B102: {=IF((INDIRECT("'"&INDIRECT("Main!B9")&"'!B116"))=0,"",(INDIRECT("'"&INDIRECT("Main!B9")&"'!B116")))} | C102: {=INDIRECT("'"&INDIRECT("Main!B30")&"'!C102")+SUM(E122+E149+E176)} -> 0
A103: {=IF((INDIRECT("'"&INDIRECT("Main!B9")&"'!A117"))=0,"",(INDIRECT("'"&INDIRECT("Main!B9")&"'!A117")))} -> Mother Air Ticket | B103: {=IF((INDIRECT("'"&INDIRECT("Main!B9")&"'!B117"))=0,"",(INDIRECT("'"&INDIRECT("Main!B9")&"'!B117")))} | C103: {=INDIRECT("'"&INDIRECT("Main!B30")&"'!C103")+SUM(E123+E150+E177)} -> 0
A104: {=IF((INDIRECT("'"&INDIRECT("Main!B9")&"'!A118"))=0,"",(INDIRECT("'"&INDIRECT("Main!B9")&"'!A118")))} | B104: {=IF((INDIRECT("'"&INDIRECT("Main!B9")&"'!B118"))=0,"",(INDIRECT("'"&INDIRECT("Main!B9")&"'!B118")))} | C104: {=INDIRECT("'"&INDIRECT("Main!B30")&"'!C104")+SUM(E124+E151+E178)} -> 0
A105: {=IF((INDIRECT("'"&INDIRECT("Main!B9")&"'!A119"))=0,"",(INDIRECT("'"&INDIRECT("Main!B9")&"'!A119")))} | B105: {=IF((INDIRECT("'"&INDIRECT("Main!B9")&"'!B119"))=0,"",(INDIRECT("'"&INDIRECT("Main!B9")&"'!B119")))} | C105: {=INDIRECT("'"&INDIRECT("Main!B30")&"'!C105")+SUM(E125+E152+E179)} -> 0
A106: {=IF((INDIRECT("'"&INDIRECT("Main!B9")&"'!A120"))=0,"",(INDIRECT("'"&INDIRECT("Main!B9")&"'!A120")))} | B106: {=IF((INDIRECT("'"&INDIRECT("Main!B9")&"'!B120"))=0,"",(INDIRECT("'"&INDIRECT("Main!B9")&"'!B120")))} | C106: {=INDIRECT("'"&INDIRECT("Main!B30")&"'!C106")+SUM(E126+E153+E180)} -> 0
A107: {=IF((INDIRECT("'"&INDIRECT("Main!B9")&"'!A121"))=0,"",(INDIRECT("'"&INDIRECT("Main!B9")&"'!A121")))} | B107: {=IF((INDIRECT("'"&INDIRECT("Main!B9")&"'!B121"))=0,"",(INDIRECT("'"&INDIRECT("Main!B9")&"'!B121")))} | C107: {=INDIRECT("'"&INDIRECT("Main!B30")&"'!C107")+SUM(E127+E154+E181)} -> 0
B108: Total Debts | C108: =SUM(C98:C107) -> 0
B109: Grand Total | C109: =C108-C96 -> -400
A114: ="Debts Or Credits For the Comming "&IF(Main!B2,TEXT(EDATE(Main!B3,24),"mmmm dd yyyy"),TEXT(Main!B3+((Main!B5-Main!B3)*24+24),"mmmm dd yyyy"))&" to "&IF(Main!B2,TEXT(EDATE(Main!B3,25)-1,"mmmm dd yyyy"),TEXT(Main!B3+((Main!B5-Main!B3)*25+24),"mmmm dd yyyy")) -> Debts Or Credits For the Comming April 20 2026 to May 19 2026
A115: Principal | C115: Description | E115: Amount
...

Sheet July 2026 - September 2026
A1: ="Forecasts For the Year "&IF(Main!B2,TEXT(EDATE(Main!B3,27),"mmmm yyyy"),TEXT(Main!B3+((Main!B5-Main!B3)*27+27),"mmmm yyyy"))&" to "&IF(Main!B2,TEXT(EDATE(Main!B3,30)-1,"mmmm yyyy"),TEXT(Main!B3+((Main!B5-Main!B3)*30+29),"mmmm yyyy")) -> Forecasts For the Year July 2026 to October 2026
A2: Assets | B2: Overall | C2: {=INDIRECT("'"&Main!B9&"'!$C$16")} -> 1181.5
B3: Forecasts | C3: =E190 -> 8585
A4: Total | C4: =SUM(C2:G3) -> 9766.5
A5: Net Debts: | C5: =C108 -> 0
A8: =IF(Main!B2,TEXT(EDATE(Main!B3,27),"dd mmmm yyyy"),TEXT(Main!B3+((Main!B5-Main!B3)*27+27),"dd mmmm yyyy"))&" - "&IF(Main!B2,TEXT(EDATE(Main!B3,28)-1,"dd mmmm yyyy"),TEXT(Main!B3+((Main!B5-Main!B3)*28+27),"dd mmmm yyyy"))&" / "&" (Revenue / Deferred Debts Or Expenses)" -> 20 July 2026 - 19 August 2026 / (Revenue / Deferred Debts Or Expenses)
A9: Date | B9: Name | D9: Description | F9: Amount
B10: Social Welfare | D10: N/A | F10: 2435
A11: 31st July 2026 | B11: Salary | D11: Deduct 5% MPF | F11: 0
B12: Cigarette Egg | D12: Brought in Advance | F12: 0
F13: 0
F14: 0
F15: 0
D16: Total Revenue | F16: =SUM(F10:G15) -> 2435
A20: =IF(Main!B2,TEXT(EDATE(Main!B3,28),"dd mmmm yyyy"),TEXT(Main!B3+((Main!B5-Main!B3)*28+28),"dd mmmm yyyy"))&" - "&IF(Main!B2,TEXT(EDATE(Main!B3,29)-1,"dd mmmm yyyy"),TEXT(Main!B3+((Main!B5-Main!B3)*29+28),"dd mmmm yyyy"))&" / "&" (Revenue / Deferred Debts Or Expenses)" -> 20 August 2026 - 19 September 2026 / (Revenue / Deferred Debts Or Expenses)
A21: Date | B21: Name | D21: Description | F21: Amount
B22: Social Welfare | D22: N/A | F22: 2435
A23: 31st August 2026 | B23: Salary | D23: Deduct 5% MPF | F23: 0
B24: Cigarette Egg | D24: Brought in Advance | F24: 0
F25: 0
F26: 0
F27: 0
D28: Total Revenue | F28: =SUM(F22:G27) -> 2435
A32: =IF(Main!B2,TEXT(EDATE(Main!B3,29),"dd mmmm yyyy"),TEXT(Main!B3+((Main!B5-Main!B3)*29+29),"dd mmmm yyyy"))&" - "&IF(Main!B2,TEXT(EDATE(Main!B3,30)-1,"dd mmmm yyyy"),TEXT(Main!B3+((Main!B5-Main!B3)*30+29),"dd mmmm yyyy"))&" / "&" (Revenue / Deferred Debts Or Expenses)" -> 20 September 2026 - 19 October 2026 / (Revenue / Deferred Debts Or Expenses)
A33: Date | B33: Name | D33: Description | F33: Amount
B34: Social Welfare | D34: N/A | F34: 2435
A35: 30th September 2026 | B35: Salary | D35: Deduct 5% MPF | F35: 0
B36: Cigarette Egg | D36: Brought in Advance | F36: 0
F37: 0
F38: 0
F39: 0
D40: Total Revenue | F40: =SUM(F34:G39) -> 2435
A44: ="Fixed Expense For the Year "&IF(Main!B2,TEXT(EDATE(Main!B3,27),"mmmm yyyy"),TEXT(Main!B3+((Main!B5-Main!B3)*27+27),"mmmm yyyy"))&" to "&IF(Main!B2,TEXT(EDATE(Main!B3,30)-1,"mmmm yyyy"),TEXT(Main!B3+((Main!B5-Main!B3)*30+29),"mmmm yyyy")) -> Fixed Expense For the Year July 2026 to October 2026
A45: Name | B45: Description | C45: Amount
A46: Mobile And Communications/ Housing Expenses
A47: {=IF((INDIRECT("'"&INDIRECT("Main!B9")&"'!A61"))=0,"",(INDIRECT("'"&INDIRECT("Main!B9")&"'!A61")))} -> Broadband | B47: {=IF((INDIRECT("'"&INDIRECT("Main!B9")&"'!B61"))=0,"",(INDIRECT("'"&INDIRECT("Main!B9")&"'!B61")))} | C47: 78
A48: {=IF((INDIRECT("'"&INDIRECT("Main!B9")&"'!A62"))=0,"",(INDIRECT("'"&INDIRECT("Main!B9")&"'!A62")))} -> China Mobile | B48: {=IF((INDIRECT("'"&INDIRECT("Main!B9")&"'!B62"))=0,"",(INDIRECT("'"&INDIRECT("Main!B9")&"'!B62")))} | C48: 149
A49: {=IF((INDIRECT("'"&INDIRECT("Main!B9")&"'!A63"))=0,"",(INDIRECT("'"&INDIRECT("Main!B9")&"'!A63")))} -> Telephone (Fixed Line) | B49: {=IF((INDIRECT("'"&INDIRECT("Main!B9")&"'!B63"))=0,"",(INDIRECT("'"&INDIRECT("Main!B9")&"'!B63")))} | C49: 0
A50: {=IF((INDIRECT("'"&INDIRECT("Main!B9")&"'!A64"))=0,"",(INDIRECT("'"&INDIRECT("Main!B9")&"'!A64")))} -> Sosim | B50: {=IF((INDIRECT("'"&INDIRECT("Main!B9")&"'!B64"))=0,"",(INDIRECT("'"&INDIRECT("Main!B9")&"'!B64")))} | C50: 0
A51: {=IF((INDIRECT("'"&INDIRECT("Main!B9")&"'!A65"))=0,"",(INDIRECT("'"&INDIRECT("Main!B9")&"'!A65")))} -> Birdie Sim Card Pay date (7th Of Each Month) | B51: {=IF((INDIRECT("'"&INDIRECT("Main!B9")&"'!B65"))=0,"",(INDIRECT("'"&INDIRECT("Main!B9")&"'!B65")))} | C51: 50
A52: {=IF((INDIRECT("'"&INDIRECT("Main!B9")&"'!A66"))=0,"",(INDIRECT("'"&INDIRECT("Main!B9")&"'!A66")))} | B52: {=IF((INDIRECT("'"&INDIRECT("Main!B9")&"'!B66"))=0,"",(INDIRECT("'"&INDIRECT("Main!B9")&"'!B66")))} | C52: 0
A53: {=IF((INDIRECT("'"&INDIRECT("Main!B9")&"'!A67"))=0,"",(INDIRECT("'"&INDIRECT("Main!B9")&"'!A67")))} | B53: {=IF((INDIRECT("'"&INDIRECT("Main!B9")&"'!B67"))=0,"",(INDIRECT("'"&INDIRECT("Main!B9")&"'!B67")))} | C53: 0
A54: {=IF((INDIRECT("'"&INDIRECT("Main!B9")&"'!A68"))=0,"",(INDIRECT("'"&INDIRECT("Main!B9")&"'!A68")))} | B54: {=IF((INDIRECT("'"&INDIRECT("Main!B9")&"'!B68"))=0,"",(INDIRECT("'"&INDIRECT("Main!B9")&"'!B68")))} | C54: 0
B55: Total Expenses | C55: =SUM(C47:C54) -> 277
A56: Credit Card Installments/Government Installments
A57: {=IF((INDIRECT("'"&INDIRECT("Main!B9")&"'!A71"))=0,"",(INDIRECT("'"&INDIRECT("Main!B9")&"'!A71")))} -> Citi Bank | B57: {=IF((INDIRECT("'"&INDIRECT("Main!B9")&"'!B71"))=0,"",(INDIRECT("'"&INDIRECT("Main!B9")&"'!B71")))} | C57: 0
A58: {=IF((INDIRECT("'"&INDIRECT("Main!B9")&"'!A72"))=0,"",(INDIRECT("'"&INDIRECT("Main!B9")&"'!A72")))} -> SC Bank | B58: {=IF((INDIRECT("'"&INDIRECT("Main!B9")&"'!B72"))=0,"",(INDIRECT("'"&INDIRECT("Main!B9")&"'!B72")))} | C58: 0
A59: {=IF((INDIRECT("'"&INDIRECT("Main!B9")&"'!A73"))=0,"",(INDIRECT("'"&INDIRECT("Main!B9")&"'!A73")))} -> Bank Of China | B59: {=IF((INDIRECT("'"&INDIRECT("Main!B9")&"'!B73"))=0,"",(INDIRECT("'"&INDIRECT("Main!B9")&"'!B73")))} | C59: 0
A60: {=IF((INDIRECT("'"&INDIRECT("Main!B9")&"'!A74"))=0,"",(INDIRECT("'"&INDIRECT("Main!B9")&"'!A74")))} -> HSBC | B60: {=IF((INDIRECT("'"&INDIRECT("Main!B9")&"'!B74"))=0,"",(INDIRECT("'"&INDIRECT("Main!B9")&"'!B74")))} | C60: 0
A61: {=IF((INDIRECT("'"&INDIRECT("Main!B9")&"'!A75"))=0,"",(INDIRECT("'"&INDIRECT("Main!B9")&"'!A75")))} | B61: {=IF((INDIRECT("'"&INDIRECT("Main!B9")&"'!B75"))=0,"",(INDIRECT("'"&INDIRECT("Main!B9")&"'!B75")))} | C61: 0
A62: {=IF((INDIRECT("'"&INDIRECT("Main!B9")&"'!A76"))=0,"",(INDIRECT("'"&INDIRECT("Main!B9")&"'!A76")))} | B62: {=IF((INDIRECT("'"&INDIRECT("Main!B9")&"'!B76"))=0,"",(INDIRECT("'"&INDIRECT("Main!B9")&"'!B76")))} | C62: 0
A63: {=IF((INDIRECT("'"&INDIRECT("Main!B9")&"'!A77"))=0,"",(INDIRECT("'"&INDIRECT("Main!B9")&"'!A77")))} | B63: {=IF((INDIRECT("'"&INDIRECT("Main!B9")&"'!B77"))=0,"",(INDIRECT("'"&INDIRECT("Main!B9")&"'!B77")))} | C63: 0
A64: {=IF((INDIRECT("'"&INDIRECT("Main!B9")&"'!A78"))=0,"",(INDIRECT("'"&INDIRECT("Main!B9")&"'!A78")))} | B64: {=IF((INDIRECT("'"&INDIRECT("Main!B9")&"'!B78"))=0,"",(INDIRECT("'"&INDIRECT("Main!B9")&"'!B78")))} | C64: 0
A65: {=IF((INDIRECT("'"&INDIRECT("Main!B9")&"'!A79"))=0,"",(INDIRECT("'"&INDIRECT("Main!B9")&"'!A79")))} | B65: {=IF((INDIRECT("'"&INDIRECT("Main!B9")&"'!B79"))=0,"",(INDIRECT("'"&INDIRECT("Main!B9")&"'!B79")))} | C65: 0
B66: Total Expenses | C66: =SUM(C57:C65) -> 0
A67: Donation
A68: {=IF((INDIRECT("'"&INDIRECT("Main!B9")&"'!A82"))=0,"",(INDIRECT("'"&INDIRECT("Main!B9")&"'!A82")))} -> Traversy | B68: {=IF((INDIRECT("'"&INDIRECT("Main!B9")&"'!B82"))=0,"",(INDIRECT("'"&INDIRECT("Main!B9")&"'!B82")))} -> Traversy Media | C68: 0
A69: {=IF((INDIRECT("'"&INDIRECT("Main!B9")&"'!A83"))=0,"",(INDIRECT("'"&INDIRECT("Main!B9")&"'!A83")))} -> Orbis | B69: {=IF((INDIRECT("'"&INDIRECT("Main!B9")&"'!B83"))=0,"",(INDIRECT("'"&INDIRECT("Main!B9")&"'!B83")))} -> Orbis Eye Flight | C69: 0
A70: {=IF((INDIRECT("'"&INDIRECT("Main!B9")&"'!A84"))=0,"",(INDIRECT("'"&INDIRECT("Main!B9")&"'!A84")))} | B70: {=IF((INDIRECT("'"&INDIRECT("Main!B9")&"'!B84"))=0,"",(INDIRECT("'"&INDIRECT("Main!B9")&"'!B84")))} | C70: 0
A71: {=IF((INDIRECT("'"&INDIRECT("Main!B9")&"'!A85"))=0,"",(INDIRECT("'"&INDIRECT("Main!B9")&"'!A85")))} | B71: {=IF((INDIRECT("'"&INDIRECT("Main!B9")&"'!B85"))=0,"",(INDIRECT("'"&INDIRECT("Main!B9")&"'!B85")))} | C71: 0
A72: {=IF((INDIRECT("'"&INDIRECT("Main!B9")&"'!A86"))=0,"",(INDIRECT("'"&INDIRECT("Main!B9")&"'!A86")))} | B72: {=IF((INDIRECT("'"&INDIRECT("Main!B9")&"'!B86"))=0,"",(INDIRECT("'"&INDIRECT("Main!B9")&"'!B86")))} | C72: 0
A73: {=IF((INDIRECT("'"&INDIRECT("Main!B9")&"'!A87"))=0,"",(INDIRECT("'"&INDIRECT("Main!B9")&"'!A87")))} | B73: {=IF((INDIRECT("'"&INDIRECT("Main!B9")&"'!B87"))=0,"",(INDIRECT("'"&INDIRECT("Main!B9")&"'!B87")))} | C73: 0
A74: {=IF((INDIRECT("'"&INDIRECT("Main!B9")&"'!A88"))=0,"",(INDIRECT("'"&INDIRECT("Main!B9")&"'!A88")))} | B74: {=IF((INDIRECT("'"&INDIRECT("Main!B9")&"'!B88"))=0,"",(INDIRECT("'"&INDIRECT("Main!B9")&"'!B88")))} | C74: 0
B75: Total Expenses | C75: =SUM(C68:C74) -> 0
A76: Insurance (Personal / Properties / Medical)
A77: {=IF((INDIRECT("'"&INDIRECT("Main!B9")&"'!A91"))=0,"",(INDIRECT("'"&INDIRECT("Main!B9")&"'!A91")))} -> AIA | B77: {=IF((INDIRECT("'"&INDIRECT("Main!B9")&"'!B91"))=0,"",(INDIRECT("'"&INDIRECT("Main!B9")&"'!B91")))} | C77: 0
A78: {=IF((INDIRECT("'"&INDIRECT("Main!B9")&"'!A92"))=0,"",(INDIRECT("'"&INDIRECT("Main!B9")&"'!A92")))} | B78: {=IF((INDIRECT("'"&INDIRECT("Main!B9")&"'!B92"))=0,"",(INDIRECT("'"&INDIRECT("Main!B9")&"'!B92")))} | C78: 0
A79: {=IF((INDIRECT("'"&INDIRECT("Main!B9")&"'!A93"))=0,"",(INDIRECT("'"&INDIRECT("Main!B9")&"'!A93")))} | B79: {=IF((INDIRECT("'"&INDIRECT("Main!B9")&"'!B93"))=0,"",(INDIRECT("'"&INDIRECT("Main!B9")&"'!B93")))} | C79: 0
A80: {=IF((INDIRECT("'"&INDIRECT("Main!B9")&"'!A94"))=0,"",(INDIRECT("'"&INDIRECT("Main!B9")&"'!A94")))} | B80: {=IF((INDIRECT("'"&INDIRECT("Main!B9")&"'!B94"))=0,"",(INDIRECT("'"&INDIRECT("Main!B9")&"'!B94")))} | C80: 0
A81: {=IF((INDIRECT("'"&INDIRECT("Main!B9")&"'!A95"))=0,"",(INDIRECT("'"&INDIRECT("Main!B9")&"'!A95")))} | B81: {=IF((INDIRECT("'"&INDIRECT("Main!B9")&"'!B95"))=0,"",(INDIRECT("'"&INDIRECT("Main!B9")&"'!B95")))} | C81: 0
A82: {=IF((INDIRECT("'"&INDIRECT("Main!B9")&"'!A96"))=0,"",(INDIRECT("'"&INDIRECT("Main!B9")&"'!A96")))} | B82: {=IF((INDIRECT("'"&INDIRECT("Main!B9")&"'!B96"))=0,"",(INDIRECT("'"&INDIRECT("Main!B9")&"'!B96")))} | C82: 0
A83: {=IF((INDIRECT("'"&INDIRECT("Main!B9")&"'!A97"))=0,"",(INDIRECT("'"&INDIRECT("Main!B9")&"'!A97")))} | B83: {=IF((INDIRECT("'"&INDIRECT("Main!B9")&"'!B97"))=0,"",(INDIRECT("'"&INDIRECT("Main!B9")&"'!B97")))} | C83: 0
A84: {=IF((INDIRECT("'"&INDIRECT("Main!B9")&"'!A98"))=0,"",(INDIRECT("'"&INDIRECT("Main!B9")&"'!A98")))} | B84: {=IF((INDIRECT("'"&INDIRECT("Main!B9")&"'!B98"))=0,"",(INDIRECT("'"&INDIRECT("Main!B9")&"'!B98")))} | C84: 0
B85: Total Expenses | C85: =SUM(C77:C84) -> 0
A86: Other Expenses
A87: {=IF((INDIRECT("'"&INDIRECT("Main!B9")&"'!A101"))=0,"",(INDIRECT("'"&INDIRECT("Main!B9")&"'!A101")))} -> Other Stuff | B87: {=IF((INDIRECT("'"&INDIRECT("Main!B9")&"'!B101"))=0,"",(INDIRECT("'"&INDIRECT("Main!B9")&"'!B101")))} -> Food, Transport…. | C87: 0
A88: {=IF((INDIRECT("'"&INDIRECT("Main!B9")&"'!A102"))=0,"",(INDIRECT("'"&INDIRECT("Main!B9")&"'!A102")))} -> Entertainment | B88: {=IF((INDIRECT("'"&INDIRECT("Main!B9")&"'!B102"))=0,"",(INDIRECT("'"&INDIRECT("Main!B9")&"'!B102")))} -> Sportify Music / Changed to Apple Music on 13th May 2025 | C88: 68
A89: {=IF((INDIRECT("'"&INDIRECT("Main!B9")&"'!A103"))=0,"",(INDIRECT("'"&INDIRECT("Main!B9")&"'!A103")))} -> Hair Cutting | B89: {=IF((INDIRECT("'"&INDIRECT("Main!B9")&"'!B103"))=0,"",(INDIRECT("'"&INDIRECT("Main!B9")&"'!B103")))} -> Hair Cut not Include Color treatment | C89: 55
A90: {=IF((INDIRECT("'"&INDIRECT("Main!B9")&"'!A104"))=0,"",(INDIRECT("'"&INDIRECT("Main!B9")&"'!A104")))} -> Cigarettes | B90: {=IF((INDIRECT("'"&INDIRECT("Main!B9")&"'!B104"))=0,"",(INDIRECT("'"&INDIRECT("Main!B9")&"'!B104")))} -> 30 packets | C90: 0
A91: {=IF((INDIRECT("'"&INDIRECT("Main!B9")&"'!A105"))=0,"",(INDIRECT("'"&INDIRECT("Main!B9")&"'!A105")))} | B91: {=IF((INDIRECT("'"&INDIRECT("Main!B9")&"'!B105"))=0,"",(INDIRECT("'"&INDIRECT("Main!B9")&"'!B105")))} | C91: 0
A92: {=IF((INDIRECT("'"&INDIRECT("Main!B9")&"'!A106"))=0,"",(INDIRECT("'"&INDIRECT("Main!B9")&"'!A106")))} | B92: {=IF((INDIRECT("'"&INDIRECT("Main!B9")&"'!B106"))=0,"",(INDIRECT("'"&INDIRECT("Main!B9")&"'!B106")))} | C92: 0
A93: {=IF((INDIRECT("'"&INDIRECT("Main!B9")&"'!A107"))=0,"",(INDIRECT("'"&INDIRECT("Main!B9")&"'!A107")))} | B93: {=IF((INDIRECT("'"&INDIRECT("Main!B9")&"'!B107"))=0,"",(INDIRECT("'"&INDIRECT("Main!B9")&"'!B107")))} | C93: 0
A94: {=IF((INDIRECT("'"&INDIRECT("Main!B9")&"'!A108"))=0,"",(INDIRECT("'"&INDIRECT("Main!B9")&"'!A108")))} | B94: {=IF((INDIRECT("'"&INDIRECT("Main!B9")&"'!B108"))=0,"",(INDIRECT("'"&INDIRECT("Main!B9")&"'!B108")))} | C94: 0
B95: Total Expenses | C95: =SUM(C87:C94) -> 123
B96: Grand Expenses Total | C96: =C55+C66+C75+C85+C95 -> 400
A97: Debts
A98: {=IF((INDIRECT("'"&INDIRECT("Main!B9")&"'!A112"))=0,"",(INDIRECT("'"&INDIRECT("Main!B9")&"'!A112")))} -> Mother | B98: {=IF((INDIRECT("'"&INDIRECT("Main!B9")&"'!B112"))=0,"",(INDIRECT("'"&INDIRECT("Main!B9")&"'!B112")))} | C98: {=INDIRECT("'"&INDIRECT("Main!B33")&"'!C98")+SUM(E118+E145+E172)} -> 0
A99: {=IF((INDIRECT("'"&INDIRECT("Main!B9")&"'!A113"))=0,"",(INDIRECT("'"&INDIRECT("Main!B9")&"'!A113")))} -> Ng Wing Lam | B99: {=IF((INDIRECT("'"&INDIRECT("Main!B9")&"'!B113"))=0,"",(INDIRECT("'"&INDIRECT("Main!B9")&"'!B113")))} | C99: {=INDIRECT("'"&INDIRECT("Main!B33")&"'!C99")+SUM(E119+E146+E173)} -> 0
A100: {=IF((INDIRECT("'"&INDIRECT("Main!B9")&"'!A114"))=0,"",(INDIRECT("'"&INDIRECT("Main!B9")&"'!A114")))} -> Lawrence | B100: {=IF((INDIRECT("'"&INDIRECT("Main!B9")&"'!B114"))=0,"",(INDIRECT("'"&INDIRECT("Main!B9")&"'!B114")))} | C100: {=INDIRECT("'"&INDIRECT("Main!B33")&"'!C100")+SUM(E120+E147+E174)} -> 0
A101: {=IF((INDIRECT("'"&INDIRECT("Main!B9")&"'!A115"))=0,"",(INDIRECT("'"&INDIRECT("Main!B9")&"'!A115")))} -> Hong Kong Government Hospital Authority | B101: {=IF((INDIRECT("'"&INDIRECT("Main!B9")&"'!B115"))=0,"",(INDIRECT("'"&INDIRECT("Main!B9")&"'!B115")))} | C101: {=INDIRECT("'"&INDIRECT("Main!B33")&"'!C101")+SUM(E121+E148+E175)} -> 0
A102: {=IF((INDIRECT("'"&INDIRECT("Main!B9")&"'!A116"))=0,"",(INDIRECT("'"&INDIRECT("Main!B9")&"'!A116")))} -> Bankruptcy Department / Bank | B102: {=IF((INDIRECT("'"&INDIRECT("Main!B9")&"'!B116"))=0,"",(INDIRECT("'"&INDIRECT("Main!B9")&"'!B116")))} | C102: {=INDIRECT("'"&INDIRECT("Main!B33")&"'!C102")+SUM(E122+E149+E176)} -> 0
A103: {=IF((INDIRECT("'"&INDIRECT("Main!B9")&"'!A117"))=0,"",(INDIRECT("'"&INDIRECT("Main!B9")&"'!A117")))} -> Mother Air Ticket | B103: {=IF((INDIRECT("'"&INDIRECT("Main!B9")&"'!B117"))=0,"",(INDIRECT("'"&INDIRECT("Main!B9")&"'!B117")))} | C103: {=INDIRECT("'"&INDIRECT("Main!B33")&"'!C103")+SUM(E123+E150+E177)} -> 0
A104: {=IF((INDIRECT("'"&INDIRECT("Main!B9")&"'!A118"))=0,"",(INDIRECT("'"&INDIRECT("Main!B9")&"'!A118")))} | B104: {=IF((INDIRECT("'"&INDIRECT("Main!B9")&"'!B118"))=0,"",(INDIRECT("'"&INDIRECT("Main!B9")&"'!B118")))} | C104: {=INDIRECT("'"&INDIRECT("Main!B33")&"'!C104")+SUM(E124+E151+E178)} -> 0
A105: {=IF((INDIRECT("'"&INDIRECT("Main!B9")&"'!A119"))=0,"",(INDIRECT("'"&INDIRECT("Main!B9")&"'!A119")))} | B105: {=IF((INDIRECT("'"&INDIRECT("Main!B9")&"'!B119"))=0,"",(INDIRECT("'"&INDIRECT("Main!B9")&"'!B119")))} | C105: {=INDIRECT("'"&INDIRECT("Main!B33")&"'!C105")+SUM(E125+E152+E179)} -> 0
A106: {=IF((INDIRECT("'"&INDIRECT("Main!B9")&"'!A120"))=0,"",(INDIRECT("'"&INDIRECT("Main!B9")&"'!A120")))} | B106: {=IF((INDIRECT("'"&INDIRECT("Main!B9")&"'!B120"))=0,"",(INDIRECT("'"&INDIRECT("Main!B9")&"'!B120")))} | C106: {=INDIRECT("'"&INDIRECT("Main!B33")&"'!C106")+SUM(E126+E153+E180)} -> 0
A107: {=IF((INDIRECT("'"&INDIRECT("Main!B9")&"'!A121"))=0,"",(INDIRECT("'"&INDIRECT("Main!B9")&"'!A121")))} | B107: {=IF((INDIRECT("'"&INDIRECT("Main!B9")&"'!B121"))=0,"",(INDIRECT("'"&INDIRECT("Main!B9")&"'!B121")))} | C107: {=INDIRECT("'"&INDIRECT("Main!B33")&"'!C107")+SUM(E127+E154+E181)} -> 0
B108: Total Debts | C108: =SUM(C98:C107) -> 0
B109: Grand Total | C109: =C108-C96 -> -400
A114: ="Debts Or Credits For the Comming "&IF(Main!B2,TEXT(EDATE(Main!B3,27),"mmmm dd yyyy"),TEXT(Main!B3+((Main!B5-Main!B3)*27+27),"mmmm dd yyyy"))&" to "&IF(Main!B2,TEXT(EDATE(Main!B3,28)-1,"mmmm dd yyyy"),TEXT(Main!B3+((Main!B5-Main!B3)*28+27),"mmmm dd yyyy")) -> Debts Or Credits For the Comming July 20 2026 to August 19 2026
A115: Principal | C115: Description | E115: Amount
...

Sheet October 2026 - December 2026
A1: ="Forecasts For the Year "&IF(Main!B2,TEXT(EDATE(Main!B3,30),"mmmm yyyy"),TEXT(Main!B3+((Main!B5-Main!B3)*30+30),"mmmm yyyy"))&" to "&IF(Main!B2,TEXT(EDATE(Main!B3,33)-1,"mmmm yyyy"),TEXT(Main!B3+((Main!B5-Main!B3)*33+32),"mmmm yyyy")) -> Forecasts For the Year October 2026 to January 2027
A2: Assets | B2: Overall | C2: {=INDIRECT("'"&Main!B9&"'!$C$16")} -> 1181.5
B3: Forecasts | C3: =E190 -> 10371.1
A4: Total | C4: =SUM(C2:G3) -> 11552.6
A5: Net Debts: | C5: =C108 -> 0
A8: =IF(Main!B2,TEXT(EDATE(Main!B3,30),"dd mmmm yyyy"),TEXT(Main!B3+((Main!B5-Main!B3)*30+30),"dd mmmm yyyy"))&" - "&IF(Main!B2,TEXT(EDATE(Main!B3,31)-1,"dd mmmm yyyy"),TEXT(Main!B3+((Main!B5-Main!B3)*31+30),"dd mmmm yyyy"))&" / "&" (Revenue / Deferred Debts Or Expenses)" -> 20 October 2026 - 19 November 2026 / (Revenue / Deferred Debts Or Expenses)
A9: Date | B9: Name | D9: Description | F9: Amount
B10: Social Welfare | D10: N/A | F10: 2435
A11: 31st October 2026 | B11: Salary | D11: Deduct 5% MPF | F11: 0
B12: Cigarette Egg | D12: Brought in Advance | F12: 0
F13: 0
F14: 0
F15: 0
D16: Total Revenue | F16: =SUM(F10:G15) -> 2435
A20: =IF(Main!B2,TEXT(EDATE(Main!B3,31),"dd mmmm yyyy"),TEXT(Main!B3+((Main!B5-Main!B3)*31+31),"dd mmmm yyyy"))&" - "&IF(Main!B2,TEXT(EDATE(Main!B3,32)-1,"dd mmmm yyyy"),TEXT(Main!B3+((Main!B5-Main!B3)*32+31),"dd mmmm yyyy"))&" / "&" (Revenue / Deferred Debts Or Expenses)" -> 20 November 2026 - 19 December 2026 / (Revenue / Deferred Debts Or Expenses)
A21: Date | B21: Name | D21: Description | F21: Amount
B22: Social Welfare | D22: N/A | F22: 2435
A23: 30th November 2026 | B23: Salary | D23: Deduct 5% MPF | F23: 0
B24: Cigarette Egg | D24: Brought in Advance | F24: 0
F25: 0
F26: 0
F27: 0
D28: Total Revenue | F28: =SUM(F22:G27) -> 2435
A32: =IF(Main!B2,TEXT(EDATE(Main!B3,32),"dd mmmm yyyy"),TEXT(Main!B3+((Main!B5-Main!B3)*32+32),"dd mmmm yyyy"))&" - "&IF(Main!B2,TEXT(EDATE(Main!B3,33)-1,"dd mmmm yyyy"),TEXT(Main!B3+((Main!B5-Main!B3)*33+32),"dd mmmm yyyy"))&" / "&" (Revenue / Deferred Debts Or Expenses)" -> 20 December 2026 - 19 January 2027 / (Revenue / Deferred Debts Or Expenses)
A33: Date | B33: Name | D33: Description | F33: Amount
B34: Social Welfare | D34: N/A | F34: 2435
A35: 31st December 2026 | B35: Salary | D35: Deduct 5% MPF | F35: 0
B36: Cigarette Egg | D36: Brought in Advance | F36: 0
F37: 0
F38: 0
F39: 0
D40: Total Revenue | F40: =SUM(F34:G39) -> 2435
A44: ="Fixed Expense For the Year "&IF(Main!B2,TEXT(EDATE(Main!B3,30),"mmmm yyyy"),TEXT(Main!B3+((Main!B5-Main!B3)*30+30),"mmmm yyyy"))&" to "&IF(Main!B2,TEXT(EDATE(Main!B3,33)-1,"mmmm yyyy"),TEXT(Main!B3+((Main!B5-Main!B3)*33+32),"mmmm yyyy")) -> Fixed Expense For the Year October 2026 to January 2027
A45: Name | B45: Description | C45: Amount
A46: Mobile And Communications/ Housing Expenses
A47: {=IF((INDIRECT("'"&INDIRECT("Main!B9")&"'!A61"))=0,"",(INDIRECT("'"&INDIRECT("Main!B9")&"'!A61")))} -> Broadband | B47: {=IF((INDIRECT("'"&INDIRECT("Main!B9")&"'!B61"))=0,"",(INDIRECT("'"&INDIRECT("Main!B9")&"'!B61")))} | C47: 78
A48: {=IF((INDIRECT("'"&INDIRECT("Main!B9")&"'!A62"))=0,"",(INDIRECT("'"&INDIRECT("Main!B9")&"'!A62")))} -> China Mobile | B48: {=IF((INDIRECT("'"&INDIRECT("Main!B9")&"'!B62"))=0,"",(INDIRECT("'"&INDIRECT("Main!B9")&"'!B62")))} | C48: 149
A49: {=IF((INDIRECT("'"&INDIRECT("Main!B9")&"'!A63"))=0,"",(INDIRECT("'"&INDIRECT("Main!B9")&"'!A63")))} -> Telephone (Fixed Line) | B49: {=IF((INDIRECT("'"&INDIRECT("Main!B9")&"'!B63"))=0,"",(INDIRECT("'"&INDIRECT("Main!B9")&"'!B63")))} | C49: 0
A50: {=IF((INDIRECT("'"&INDIRECT("Main!B9")&"'!A64"))=0,"",(INDIRECT("'"&INDIRECT("Main!B9")&"'!A64")))} -> Sosim | B50: {=IF((INDIRECT("'"&INDIRECT("Main!B9")&"'!B64"))=0,"",(INDIRECT("'"&INDIRECT("Main!B9")&"'!B64")))} | C50: 0
A51: {=IF((INDIRECT("'"&INDIRECT("Main!B9")&"'!A65"))=0,"",(INDIRECT("'"&INDIRECT("Main!B9")&"'!A65")))} -> Birdie Sim Card Pay date (7th Of Each Month) | B51: {=IF((INDIRECT("'"&INDIRECT("Main!B9")&"'!B65"))=0,"",(INDIRECT("'"&INDIRECT("Main!B9")&"'!B65")))} | C51: 50
A52: {=IF((INDIRECT("'"&INDIRECT("Main!B9")&"'!A66"))=0,"",(INDIRECT("'"&INDIRECT("Main!B9")&"'!A66")))} | B52: {=IF((INDIRECT("'"&INDIRECT("Main!B9")&"'!B66"))=0,"",(INDIRECT("'"&INDIRECT("Main!B9")&"'!B66")))} | C52: 0
A53: {=IF((INDIRECT("'"&INDIRECT("Main!B9")&"'!A67"))=0,"",(INDIRECT("'"&INDIRECT("Main!B9")&"'!A67")))} | B53: {=IF((INDIRECT("'"&INDIRECT("Main!B9")&"'!B67"))=0,"",(INDIRECT("'"&INDIRECT("Main!B9")&"'!B67")))} | C53: 0
A54: {=IF((INDIRECT("'"&INDIRECT("Main!B9")&"'!A68"))=0,"",(INDIRECT("'"&INDIRECT("Main!B9")&"'!A68")))} | B54: {=IF((INDIRECT("'"&INDIRECT("Main!B9")&"'!B68"))=0,"",(INDIRECT("'"&INDIRECT("Main!B9")&"'!B68")))} | C54: 0
B55: Total Expenses | C55: =SUM(C47:C54) -> 277
A56: Credit Card Installments/Government Installments
A57: {=IF((INDIRECT("'"&INDIRECT("Main!B9")&"'!A71"))=0,"",(INDIRECT("'"&INDIRECT("Main!B9")&"'!A71")))} -> Citi Bank | B57: {=IF((INDIRECT("'"&INDIRECT("Main!B9")&"'!B71"))=0,"",(INDIRECT("'"&INDIRECT("Main!B9")&"'!B71")))} | C57: 0
A58: {=IF((INDIRECT("'"&INDIRECT("Main!B9")&"'!A72"))=0,"",(INDIRECT("'"&INDIRECT("Main!B9")&"'!A72")))} -> SC Bank | B58: {=IF((INDIRECT("'"&INDIRECT("Main!B9")&"'!B72"))=0,"",(INDIRECT("'"&INDIRECT("Main!B9")&"'!B72")))} | C58: 0
A59: {=IF((INDIRECT("'"&INDIRECT("Main!B9")&"'!A73"))=0,"",(INDIRECT("'"&INDIRECT("Main!B9")&"'!A73")))} -> Bank Of China | B59: {=IF((INDIRECT("'"&INDIRECT("Main!B9")&"'!B73"))=0,"",(INDIRECT("'"&INDIRECT("Main!B9")&"'!B73")))} | C59: 0
A60: {=IF((INDIRECT("'"&INDIRECT("Main!B9")&"'!A74"))=0,"",(INDIRECT("'"&INDIRECT("Main!B9")&"'!A74")))} -> HSBC | B60: {=IF((INDIRECT("'"&INDIRECT("Main!B9")&"'!B74"))=0,"",(INDIRECT("'"&INDIRECT("Main!B9")&"'!B74")))} | C60: 0
A61: {=IF((INDIRECT("'"&INDIRECT("Main!B9")&"'!A75"))=0,"",(INDIRECT("'"&INDIRECT("Main!B9")&"'!A75")))} | B61: {=IF((INDIRECT("'"&INDIRECT("Main!B9")&"'!B75"))=0,"",(INDIRECT("'"&INDIRECT("Main!B9")&"'!B75")))} | C61: 0
A62: {=IF((INDIRECT("'"&INDIRECT("Main!B9")&"'!A76"))=0,"",(INDIRECT("'"&INDIRECT("Main!B9")&"'!A76")))} | B62: {=IF((INDIRECT("'"&INDIRECT("Main!B9")&"'!B76"))=0,"",(INDIRECT("'"&INDIRECT("Main!B9")&"'!B76")))} | C62: 0
A63: {=IF((INDIRECT("'"&INDIRECT("Main!B9")&"'!A77"))=0,"",(INDIRECT("'"&INDIRECT("Main!B9")&"'!A77")))} | B63: {=IF((INDIRECT("'"&INDIRECT("Main!B9")&"'!B77"))=0,"",(INDIRECT("'"&INDIRECT("Main!B9")&"'!B77")))} | C63: 0
A64: {=IF((INDIRECT("'"&INDIRECT("Main!B9")&"'!A78"))=0,"",(INDIRECT("'"&INDIRECT("Main!B9")&"'!A78")))} | B64: {=IF((INDIRECT("'"&INDIRECT("Main!B9")&"'!B78"))=0,"",(INDIRECT("'"&INDIRECT("Main!B9")&"'!B78")))} | C64: 0
A65: {=IF((INDIRECT("'"&INDIRECT("Main!B9")&"'!A79"))=0,"",(INDIRECT("'"&INDIRECT("Main!B9")&"'!A79")))} | B65: {=IF((INDIRECT("'"&INDIRECT("Main!B9")&"'!B79"))=0,"",(INDIRECT("'"&INDIRECT("Main!B9")&"'!B79")))} | C65: 0
B66: Total Expenses | C66: =SUM(C57:C65) -> 0
A67: Donation
A68: {=IF((INDIRECT("'"&INDIRECT("Main!B9")&"'!A82"))=0,"",(INDIRECT("'"&INDIRECT("Main!B9")&"'!A82")))} -> Traversy | B68: {=IF((INDIRECT("'"&INDIRECT("Main!B9")&"'!B82"))=0,"",(INDIRECT("'"&INDIRECT("Main!B9")&"'!B82")))} -> Traversy Media | C68: 0
A69: {=IF((INDIRECT("'"&INDIRECT("Main!B9")&"'!A83"))=0,"",(INDIRECT("'"&INDIRECT("Main!B9")&"'!A83")))} -> Orbis | B69: {=IF((INDIRECT("'"&INDIRECT("Main!B9")&"'!B83"))=0,"",(INDIRECT("'"&INDIRECT("Main!B9")&"'!B83")))} -> Orbis Eye Flight | C69: 0
A70: {=IF((INDIRECT("'"&INDIRECT("Main!B9")&"'!A84"))=0,"",(INDIRECT("'"&INDIRECT("Main!B9")&"'!A84")))} | B70: {=IF((INDIRECT("'"&INDIRECT("Main!B9")&"'!B84"))=0,"",(INDIRECT("'"&INDIRECT("Main!B9")&"'!B84")))} | C70: 0
A71: {=IF((INDIRECT("'"&INDIRECT("Main!B9")&"'!A85"))=0,"",(INDIRECT("'"&INDIRECT("Main!B9")&"'!A85")))} | B71: {=IF((INDIRECT("'"&INDIRECT("Main!B9")&"'!B85"))=0,"",(INDIRECT("'"&INDIRECT("Main!B9")&"'!B85")))} | C71: 0
A72: {=IF((INDIRECT("'"&INDIRECT("Main!B9")&"'!A86"))=0,"",(INDIRECT("'"&INDIRECT("Main!B9")&"'!A86")))} | B72: {=IF((INDIRECT("'"&INDIRECT("Main!B9")&"'!B86"))=0,"",(INDIRECT("'"&INDIRECT("Main!B9")&"'!B86")))} | C72: 0
A73: {=IF((INDIRECT("'"&INDIRECT("Main!B9")&"'!A87"))=0,"",(INDIRECT("'"&INDIRECT("Main!B9")&"'!A87")))} | B73: {=IF((INDIRECT("'"&INDIRECT("Main!B9")&"'!B87"))=0,"",(INDIRECT("'"&INDIRECT("Main!B9")&"'!B87")))} | C73: 0
A74: {=IF((INDIRECT("'"&INDIRECT("Main!B9")&"'!A88"))=0,"",(INDIRECT("'"&INDIRECT("Main!B9")&"'!A88")))} | B74: {=IF((INDIRECT("'"&INDIRECT("Main!B9")&"'!B88"))=0,"",(INDIRECT("'"&INDIRECT("Main!B9")&"'!B88")))} | C74: 0
B75: Total Expenses | C75: =SUM(C68:C74) -> 0
A76: Insurance (Personal / Properties / Medical)
A77: {=IF((INDIRECT("'"&INDIRECT("Main!B9")&"'!A91"))=0,"",(INDIRECT("'"&INDIRECT("Main!B9")&"'!A91")))} -> AIA | B77: {=IF((INDIRECT("'"&INDIRECT("Main!B9")&"'!B91"))=0,"",(INDIRECT("'"&INDIRECT("Main!B9")&"'!B91")))} | C77: 0
A78: {=IF((INDIRECT("'"&INDIRECT("Main!B9")&"'!A92"))=0,"",(INDIRECT("'"&INDIRECT("Main!B9")&"'!A92")))} | B78: {=IF((INDIRECT("'"&INDIRECT("Main!B9")&"'!B92"))=0,"",(INDIRECT("'"&INDIRECT("Main!B9")&"'!B92")))} | C78: 0
A79: {=IF((INDIRECT("'"&INDIRECT("Main!B9")&"'!A93"))=0,"",(INDIRECT("'"&INDIRECT("Main!B9")&"'!A93")))} | B79: {=IF((INDIRECT("'"&INDIRECT("Main!B9")&"'!B93"))=0,"",(INDIRECT("'"&INDIRECT("Main!B9")&"'!B93")))} | C79: 0
A80: {=IF((INDIRECT("'"&INDIRECT("Main!B9")&"'!A94"))=0,"",(INDIRECT("'"&INDIRECT("Main!B9")&"'!A94")))} | B80: {=IF((INDIRECT("'"&INDIRECT("Main!B9")&"'!B94"))=0,"",(INDIRECT("'"&INDIRECT("Main!B9")&"'!B94")))} | C80: 0
A81: {=IF((INDIRECT("'"&INDIRECT("Main!B9")&"'!A95"))=0,"",(INDIRECT("'"&INDIRECT("Main!B9")&"'!A95")))} | B81: {=IF((INDIRECT("'"&INDIRECT("Main!B9")&"'!B95"))=0,"",(INDIRECT("'"&INDIRECT("Main!B9")&"'!B95")))} | C81: 0
A82: {=IF((INDIRECT("'"&INDIRECT("Main!B9")&"'!A96"))=0,"",(INDIRECT("'"&INDIRECT("Main!B9")&"'!A96")))} | B82: {=IF((INDIRECT("'"&INDIRECT("Main!B9")&"'!B96"))=0,"",(INDIRECT("'"&INDIRECT("Main!B9")&"'!B96")))} | C82: 0
A83: {=IF((INDIRECT("'"&INDIRECT("Main!B9")&"'!A97"))=0,"",(INDIRECT("'"&INDIRECT("Main!B9")&"'!A97")))} | B83: {=IF((INDIRECT("'"&INDIRECT("Main!B9")&"'!B97"))=0,"",(INDIRECT("'"&INDIRECT("Main!B9")&"'!B97")))} | C83: 0
A84: {=IF((INDIRECT("'"&INDIRECT("Main!B9")&"'!A98"))=0,"",(INDIRECT("'"&INDIRECT("Main!B9")&"'!A98")))} | B84: {=IF((INDIRECT("'"&INDIRECT("Main!B9")&"'!B98"))=0,"",(INDIRECT("'"&INDIRECT("Main!B9")&"'!B98")))} | C84: 0
B85: Total Expenses | C85: =SUM(C77:C84) -> 0
A86: Other Expenses
A87: {=IF((INDIRECT("'"&INDIRECT("Main!B9")&"'!A101"))=0,"",(INDIRECT("'"&INDIRECT("Main!B9")&"'!A101")))} -> Other Stuff | B87: {=IF((INDIRECT("'"&INDIRECT("Main!B9")&"'!B101"))=0,"",(INDIRECT("'"&INDIRECT("Main!B9")&"'!B101")))} -> Food, Transport…. | C87: 0
A88: {=IF((INDIRECT("'"&INDIRECT("Main!B9")&"'!A102"))=0,"",(INDIRECT("'"&INDIRECT("Main!B9")&"'!A102")))} -> Entertainment | B88: {=IF((INDIRECT("'"&INDIRECT("Main!B9")&"'!B102"))=0,"",(INDIRECT("'"&INDIRECT("Main!B9")&"'!B102")))} -> Sportify Music / Changed to Apple Music on 13th May 2025 | C88: 68
A89: {=IF((INDIRECT("'"&INDIRECT("Main!B9")&"'!A103"))=0,"",(INDIRECT("'"&INDIRECT("Main!B9")&"'!A103")))} -> Hair Cutting | B89: {=IF((INDIRECT("'"&INDIRECT("Main!B9")&"'!B103"))=0,"",(INDIRECT("'"&INDIRECT("Main!B9")&"'!B103")))} -> Hair Cut not Include Color treatment | C89: 55
A90: {=IF((INDIRECT("'"&INDIRECT("Main!B9")&"'!A104"))=0,"",(INDIRECT("'"&INDIRECT("Main!B9")&"'!A104")))} -> Cigarettes | B90: {=IF((INDIRECT("'"&INDIRECT("Main!B9")&"'!B104"))=0,"",(INDIRECT("'"&INDIRECT("Main!B9")&"'!B104")))} -> 30 packets | C90: 0
A91: {=IF((INDIRECT("'"&INDIRECT("Main!B9")&"'!A105"))=0,"",(INDIRECT("'"&INDIRECT("Main!B9")&"'!A105")))} | B91: {=IF((INDIRECT("'"&INDIRECT("Main!B9")&"'!B105"))=0,"",(INDIRECT("'"&INDIRECT("Main!B9")&"'!B105")))} | C91: 0
A92: {=IF((INDIRECT("'"&INDIRECT("Main!B9")&"'!A106"))=0,"",(INDIRECT("'"&INDIRECT("Main!B9")&"'!A106")))} | B92: {=IF((INDIRECT("'"&INDIRECT("Main!B9")&"'!B106"))=0,"",(INDIRECT("'"&INDIRECT("Main!B9")&"'!B106")))} | C92: 0
A93: {=IF((INDIRECT("'"&INDIRECT("Main!B9")&"'!A107"))=0,"",(INDIRECT("'"&INDIRECT("Main!B9")&"'!A107")))} | B93: {=IF((INDIRECT("'"&INDIRECT("Main!B9")&"'!B107"))=0,"",(INDIRECT("'"&INDIRECT("Main!B9")&"'!B107")))} | C93: 0
A94: {=IF((INDIRECT("'"&INDIRECT("Main!B9")&"'!A108"))=0,"",(INDIRECT("'"&INDIRECT("Main!B9")&"'!A108")))} | B94: {=IF((INDIRECT("'"&INDIRECT("Main!B9")&"'!B108"))=0,"",(INDIRECT("'"&INDIRECT("Main!B9")&"'!B108")))} | C94: 0
B95: Total Expenses | C95: =SUM(C87:C94) -> 123
