Workbook

Sheet Cover Page
A1: Income Forecast
A32: Your Personal Finance Organizer

Sheet Main
A1: Money In Terms Of (tens, hundred, thousands, millions) | B1: tens
A2: A Month TRUE or FALSE | B2: TRUE
A3: Date Range Start From (dd/mm/yyyy) | B3: 45758
A4: Date Range End To (A month dd/mm/yyyy) | B4: =IF(B2,TEXT(EDATE(B3,1)-1,"dd-mmm-yyyy"),B4) -> 10-May-2025
A5: Specify Date Range End To (dd/mm/yyyy) (If a month is not checked) | B5: 45761
A8: Work Sheet Name
A9: =TEXT(B3,"dd mmmm yyyy")&" - "&IF(B2,TEXT(EDATE(B3,1)-1,"dd mmmm yyyy"),TEXT(B3+B5-B3,"dd mmmm yyyy")) -> 11 April 2025 - 10 May 2025 | B9: Forecast_1
A10: =IF(B2,TEXT(EDATE(B3,1),"dd mmmm yyyy"),TEXT(B3+(B5-B3)+1,"dd mmmm yyyy"))&" - "&IF(B2,TEXT(EDATE(B3,2)-1,"dd mmmm yyyy"),TEXT(B3+(B5-B3)*2+1,"dd mmmm yyyy")) -> 11 May 2025 - 10 June 2025
A11: =IF(B2,TEXT(EDATE(B3,2),"dd mmmm yyyy"),TEXT(B3+((B5-B3)*2)+2,"dd mmmm yyyy"))&" - "&IF(B2,TEXT(EDATE(B3,3)-1,"dd mmmm yyyy"),TEXT(B3+((B5-B3)*3+2),"dd mmmm yyyy")) -> 11 June 2025 - 10 July 2025
A12: =IF(B2,TEXT(EDATE(B3,3),"dd mmmm yyyy"),TEXT(B3+((B5-B3)*3)+3,"dd mmmm yyyy"))&" - "&IF(B2,TEXT(EDATE(B3,4)-1,"dd mmmm yyyy"),TEXT(B3+(((B5-B3)*4)+3),"dd mmmm yyyy")) -> 11 July 2025 - 10 August 2025 | B12: Forecast_2
A13: =IF(B2,TEXT(EDATE(B3,4),"dd mmmm yyyy"),TEXT(B3+((B5-B3)*4)+4,"dd mmmm yyyy"))&" - "&IF(B2,TEXT(EDATE(B3,5)-1,"dd mmmm yyyy"),TEXT(B3+(((B5-B3)*5)+4),"dd mmmm yyyy")) -> 11 August 2025 - 10 September 2025
A14: =IF(B2,TEXT(EDATE(B3,5),"dd mmmm yyyy"),TEXT(B3+((B5-B3)*5)+5,"dd mmmm yyyy"))&" - "&IF(B2,TEXT(EDATE(B3,6)-1,"dd mmmm yyyy"),TEXT(B3+(((B5-B3)*6)+5),"dd mmmm yyyy")) -> 11 September 2025 - 10 October 2025
A15: =IF(B2,TEXT(EDATE(B3,6),"dd mmmm yyyy"),TEXT(B3+((B5-B3)*6)+6,"dd mmmm yyyy"))&" - "&IF(B2,TEXT(EDATE(B3,7)-1,"dd mmmm yyyy"),TEXT(B3+(((B5-B3)*7)+6),"dd mmmm yyyy")) -> 11 October 2025 - 10 November 2025 | B15: Forecast_3
A16: =IF(B2,TEXT(EDATE(B3,7),"dd mmmm yyyy"),TEXT(B3+((B5-B3)*7)+7,"dd mmmm yyyy"))&" - "&IF(B2,TEXT(EDATE(B3,8)-1,"dd mmmm yyyy"),TEXT(B3+(((B5-B3)*8)+7),"dd mmmm yyyy")) -> 11 November 2025 - 10 December 2025
A17: =IF(B2,TEXT(EDATE(B3,8),"dd mmmm yyyy"),TEXT(B3+((B5-B3)*8)+8,"dd mmmm yyyy"))&" - "&IF(B2,TEXT(EDATE(B3,9)-1,"dd mmmm yyyy"),TEXT(B3+(((B5-B3)*9)+8),"dd mmmm yyyy")) -> 11 December 2025 - 10 January 2026
A18: =IF(B2,TEXT(EDATE(B3,9),"dd mmmm yyyy"),TEXT(B3+((B5-B3)*9)+9,"dd mmmm yyyy"))&" - "&IF(B2,TEXT(EDATE(B3,10)-1,"dd mmmm yyyy"),TEXT(B3+(((B5-B3)*10)+9),"dd mmmm yyyy")) -> 11 January 2026 - 10 February 2026 | B18: Forecast_4
A19: =IF(B2,TEXT(EDATE(B3,10),"dd mmmm yyyy"),TEXT(B3+((B5-B3)*10)+10,"dd mmmm yyyy"))&" - "&IF(B2,TEXT(EDATE(B3,11)-1,"dd mmmm yyyy"),TEXT(B3+(((B5-B3)*11)+10),"dd mmmm yyyy")) -> 11 February 2026 - 10 March 2026
A20: =IF(B2,TEXT(EDATE(B3,11),"dd mmmm yyyy"),TEXT(B3+((B5-B3)*11)+11,"dd mmmm yyyy"))&" - "&IF(B2,TEXT(EDATE(B3,12)-1,"dd mmmm yyyy"),TEXT(B3+(((B5-B3)*12)+11),"dd mmmm yyyy")) -> 11 March 2026 - 10 April 2026
A21: =IF(B2,TEXT(EDATE(B3,12),"dd mmmm yyyy"),TEXT(B3+((B5-B3)*12)+12,"dd mmmm yyyy"))&" - "&IF(B2,TEXT(EDATE(B3,13)-1,"dd mmmm yyyy"),TEXT(B3+(((B5-B3)*13)+12),"dd mmmm yyyy")) -> 11 April 2026 - 10 May 2026 | B21: Forecast_5
A22: =IF(B2,TEXT(EDATE(B3,13),"dd mmmm yyyy"),TEXT(B3+((B5-B3)*13)+13,"dd mmmm yyyy"))&" - "&IF(B2,TEXT(EDATE(B3,14)-1,"dd mmmm yyyy"),TEXT(B3+(((B5-B3)*14)+13),"dd mmmm yyyy")) -> 11 May 2026 - 10 June 2026
A23: =IF(B2,TEXT(EDATE(B3,14),"dd mmmm yyyy"),TEXT(B3+((B5-B3)*14)+14,"dd mmmm yyyy"))&" - "&IF(B2,TEXT(EDATE(B3,15)-1,"dd mmmm yyyy"),TEXT(B3+(((B5-B3)*15)+14),"dd mmmm yyyy")) -> 11 June 2026 - 10 July 2026
A24: =IF(B2,TEXT(EDATE(B3,15),"dd mmmm yyyy"),TEXT(B3+((B5-B3)*15)+15,"dd mmmm yyyy"))&" - "&IF(B2,TEXT(EDATE(B3,16)-1,"dd mmmm yyyy"),TEXT(B3+(((B5-B3)*16)+15),"dd mmmm yyyy")) -> 11 July 2026 - 10 August 2026 | B24: Forecast_6
A25: =IF(B2,TEXT(EDATE(B3,16),"dd mmmm yyyy"),TEXT(B3+((B5-B3)*16)+16,"dd mmmm yyyy"))&" - "&IF(B2,TEXT(EDATE(B3,17)-1,"dd mmmm yyyy"),TEXT(B3+(((B5-B3)*17)+16),"dd mmmm yyyy")) -> 11 August 2026 - 10 September 2026
A26: =IF(B2,TEXT(EDATE(B3,17),"dd mmmm yyyy"),TEXT(B3+((B5-B3)*17)+17,"dd mmmm yyyy"))&" - "&IF(B2,TEXT(EDATE(B3,18)-1,"dd mmmm yyyy"),TEXT(B3+(((B5-B3)*18)+17),"dd mmmm yyyy")) -> 11 September 2026 - 10 October 2026
A27: =IF(B2,TEXT(EDATE(B3,18),"dd mmmm yyyy"),TEXT(B3+((B5-B3)*18)+18,"dd mmmm yyyy"))&" - "&IF(B2,TEXT(EDATE(B3,19)-1,"dd mmmm yyyy"),TEXT(B3+(((B5-B3)*19)+18),"dd mmmm yyyy")) -> 11 October 2026 - 10 November 2026 | B27: Forecast_7
A28: =IF(B2,TEXT(EDATE(B3,19),"dd mmmm yyyy"),TEXT(B3+((B5-B3)*19)+19,"dd mmmm yyyy"))&" - "&IF(B2,TEXT(EDATE(B3,20)-1,"dd mmmm yyyy"),TEXT(B3+(((B5-B3)*20)+19),"dd mmmm yyyy")) -> 11 November 2026 - 10 December 2026
A29: =IF(B2,TEXT(EDATE(B3,20),"dd mmmm yyyy"),TEXT(B3+((B5-B3)*20)+20,"dd mmmm yyyy"))&" - "&IF(B2,TEXT(EDATE(B3,21)-1,"dd mmmm yyyy"),TEXT(B3+(((B5-B3)*21)+20),"dd mmmm yyyy")) -> 11 December 2026 - 10 January 2027
A30: =IF(B2,TEXT(EDATE(B3,21),"dd mmmm yyyy"),TEXT(B3+((B5-B3)*21)+21,"dd mmmm yyyy"))&" - "&IF(B2,TEXT(EDATE(B3,22)-1,"dd mmmm yyyy"),TEXT(B3+(((B5-B3)*22)+21),"dd mmmm yyyy")) -> 11 January 2027 - 10 February 2027 | B30: Forecast_8
A31: =IF(B2,TEXT(EDATE(B3,22),"dd mmmm yyyy"),TEXT(B3+((B5-B3)*22)+22,"dd mmmm yyyy"))&" - "&IF(B2,TEXT(EDATE(B3,23)-1,"dd mmmm yyyy"),TEXT(B3+(((B5-B3)*23)+22),"dd mmmm yyyy")) -> 11 February 2027 - 10 March 2027
A32: =IF(B2,TEXT(EDATE(B3,23),"dd mmmm yyyy"),TEXT(B3+((B5-B3)*23)+23,"dd mmmm yyyy"))&" - "&IF(B2,TEXT(EDATE(B3,24)-1,"dd mmmm yyyy"),TEXT(B3+(((B5-B3)*24)+23),"dd mmmm yyyy")) -> 11 March 2027 - 10 April 2027
A33: =IF(B2,TEXT(EDATE(B3,24),"dd mmmm yyyy"),TEXT(B3+((B5-B3)*24)+24,"dd mmmm yyyy"))&" - "&IF(B2,TEXT(EDATE(B3,25)-1,"dd mmmm yyyy"),TEXT(B3+(((B5-B3)*25)+24),"dd mmmm yyyy")) -> 11 April 2027 - 10 May 2027 | B33: Forecast_9
A34: =IF(B2,TEXT(EDATE(B3,25),"dd mmmm yyyy"),TEXT(B3+((B5-B3)*25)+25,"dd mmmm yyyy"))&" - "&IF(B2,TEXT(EDATE(B3,26)-1,"dd mmmm yyyy"),TEXT(B3+(((B5-B3)*26)+25),"dd mmmm yyyy")) -> 11 May 2027 - 10 June 2027
A35: =IF(B2,TEXT(EDATE(B3,26),"dd mmmm yyyy"),TEXT(B3+((B5-B3)*26)+26,"dd mmmm yyyy"))&" - "&IF(B2,TEXT(EDATE(B3,27)-1,"dd mmmm yyyy"),TEXT(B3+(((B5-B3)*27)+26),"dd mmmm yyyy")) -> 11 June 2027 - 10 July 2027
A36: =IF(B2,TEXT(EDATE(B3,27),"dd mmmm yyyy"),TEXT(B3+((B5-B3)*27)+27,"dd mmmm yyyy"))&" - "&IF(B2,TEXT(EDATE(B3,28)-1,"dd mmmm yyyy"),TEXT(B3+(((B5-B3)*28)+27),"dd mmmm yyyy")) -> 11 July 2027 - 10 August 2027 | B36: Forecast_10
A37: =IF(B2,TEXT(EDATE(B3,28),"dd mmmm yyyy"),TEXT(B3+((B5-B3)*28)+28,"dd mmmm yyyy"))&" - "&IF(B2,TEXT(EDATE(B3,29)-1,"dd mmmm yyyy"),TEXT(B3+(((B5-B3)*29)+28),"dd mmmm yyyy")) -> 11 August 2027 - 10 September 2027
A38: =IF(B2,TEXT(EDATE(B3,29),"dd mmmm yyyy"),TEXT(B3+((B5-B3)*29)+29,"dd mmmm yyyy"))&" - "&IF(B2,TEXT(EDATE(B3,30)-1,"dd mmmm yyyy"),TEXT(B3+(((B5-B3)*30)+29),"dd mmmm yyyy")) -> 11 September 2027 - 10 October 2027
A39: =IF(B2,TEXT(EDATE(B3,30),"dd mmmm yyyy"),TEXT(B3+((B5-B3)*30)+30,"dd mmmm yyyy"))&" - "&IF(B2,TEXT(EDATE(B3,31)-1,"dd mmmm yyyy"),TEXT(B3+(((B5-B3)*31)+30),"dd mmmm yyyy")) -> 11 October 2027 - 10 November 2027 | B39: Forecast_11
A40: =IF(B2,TEXT(EDATE(B3,31),"dd mmmm yyyy"),TEXT(B3+((B5-B3)*31)+31,"dd mmmm yyyy"))&" - "&IF(B2,TEXT(EDATE(B3,32)-1,"dd mmmm yyyy"),TEXT(B3+(((B5-B3)*32)+31),"dd mmmm yyyy")) -> 11 November 2027 - 10 December 2027
A41: =IF(B2,TEXT(EDATE(B3,32),"dd mmmm yyyy"),TEXT(B3+((B5-B3)*32)+32,"dd mmmm yyyy"))&" - "&IF(B2,TEXT(EDATE(B3,33)-1,"dd mmmm yyyy"),TEXT(B3+(((B5-B3)*33)+32),"dd mmmm yyyy")) -> 11 December 2027 - 10 January 2028
A42: =IF(B2,TEXT(EDATE(B3,33),"dd mmmm yyyy"),TEXT(B3+((B5-B3)*33)+33,"dd mmmm yyyy"))&" - "&IF(B2,TEXT(EDATE(B3,34)-1,"dd mmmm yyyy"),TEXT(B3+(((B5-B3)*34)+33),"dd mmmm yyyy")) -> 11 January 2028 - 10 February 2028 | B42: Forecast_12
A43: =IF(B2,TEXT(EDATE(B3,34),"dd mmmm yyyy"),TEXT(B3+((B5-B3)*34)+34,"dd mmmm yyyy"))&" - "&IF(B2,TEXT(EDATE(B3,35)-1,"dd mmmm yyyy"),TEXT(B3+(((B5-B3)*35)+34),"dd mmmm yyyy")) -> 11 February 2028 - 10 March 2028
A44: =IF(B2,TEXT(EDATE(B3,35),"dd mmmm yyyy"),TEXT(B3+((B5-B3)*35)+35,"dd mmmm yyyy"))&" - "&IF(B2,TEXT(EDATE(B3,36)-1,"dd mmmm yyyy"),TEXT(B3+(((B5-B3)*36)+35),"dd mmmm yyyy")) -> 11 March 2028 - 10 April 2028
A45: =IF(B2,TEXT(EDATE(B3,36),"dd mmmm yyyy"),TEXT(B3+((B5-B3)*36)+36,"dd mmmm yyyy"))&" - "&IF(B2,TEXT(EDATE(B3,37)-1,"dd mmmm yyyy"),TEXT(B3+(((B5-B3)*37)+36),"dd mmmm yyyy")) -> 11 April 2028 - 10 May 2028 | B45: Forecast_13
A46: =IF(B2,TEXT(EDATE(B3,37),"dd mmmm yyyy"),TEXT(B3+((B5-B3)*37)+37,"dd mmmm yyyy"))&" - "&IF(B2,TEXT(EDATE(B3,38)-1,"dd mmmm yyyy"),TEXT(B3+(((B5-B3)*38)+37),"dd mmmm yyyy")) -> 11 May 2028 - 10 June 2028
A47: =IF(B2,TEXT(EDATE(B3,38),"dd mmmm yyyy"),TEXT(B3+((B5-B3)*38)+38,"dd mmmm yyyy"))&" - "&IF(B2,TEXT(EDATE(B3,39)-1,"dd mmmm yyyy"),TEXT(B3+(((B5-B3)*39)+38),"dd mmmm yyyy")) -> 11 June 2028 - 10 July 2028
A48: =IF(B2,TEXT(EDATE(B3,39),"dd mmmm yyyy"),TEXT(B3+((B5-B3)*39)+39,"dd mmmm yyyy"))&" - "&IF(B2,TEXT(EDATE(B3,40)-1,"dd mmmm yyyy"),TEXT(B3+(((B5-B3)*40)+39),"dd mmmm yyyy")) -> 11 July 2028 - 10 August 2028 | B48: Forecast_14
A49: =IF(B2,TEXT(EDATE(B3,40),"dd mmmm yyyy"),TEXT(B3+((B5-B3)*40)+40,"dd mmmm yyyy"))&" - "&IF(B2,TEXT(EDATE(B3,41)-1,"dd mmmm yyyy"),TEXT(B3+(((B5-B3)*41)+40),"dd mmmm yyyy")) -> 11 August 2028 - 10 September 2028
A50: =IF(B2,TEXT(EDATE(B3,41),"dd mmmm yyyy"),TEXT(B3+((B5-B3)*41)+41,"dd mmmm yyyy"))&" - "&IF(B2,TEXT(EDATE(B3,42)-1,"dd mmmm yyyy"),TEXT(B3+(((B5-B3)*42)+41),"dd mmmm yyyy")) -> 11 September 2028 - 10 October 2028
A51: =IF(B2,TEXT(EDATE(B3,42),"dd mmmm yyyy"),TEXT(B3+((B5-B3)*42)+42,"dd mmmm yyyy"))&" - "&IF(B2,TEXT(EDATE(B3,43)-1,"dd mmmm yyyy"),TEXT(B3+(((B5-B3)*43)+42),"dd mmmm yyyy")) -> 11 October 2028 - 10 November 2028 | B51: Forecast_15
A52: =IF(B2,TEXT(EDATE(B3,43),"dd mmmm yyyy"),TEXT(B3+((B5-B3)*43)+43,"dd mmmm yyyy"))&" - "&IF(B2,TEXT(EDATE(B3,44)-1,"dd mmmm yyyy"),TEXT(B3+(((B5-B3)*44)+43),"dd mmmm yyyy")) -> 11 November 2028 - 10 December 2028
A53: =IF(B2,TEXT(EDATE(B3,44),"dd mmmm yyyy"),TEXT(B3+((B5-B3)*44)+44,"dd mmmm yyyy"))&" - "&IF(B2,TEXT(EDATE(B3,45)-1,"dd mmmm yyyy"),TEXT(B3+(((B5-B3)*45)+44),"dd mmmm yyyy")) -> 11 December 2028 - 10 January 2029
A54: =IF(B2,TEXT(EDATE(B3,45),"dd mmmm yyyy"),TEXT(B3+((B5-B3)*45)+45,"dd mmmm yyyy"))&" - "&IF(B2,TEXT(EDATE(B3,46)-1,"dd mmmm yyyy"),TEXT(B3+(((B5-B3)*46)+45),"dd mmmm yyyy")) -> 11 January 2029 - 10 February 2029 | B54: Forecast_16
A55: =IF(B2,TEXT(EDATE(B3,46),"dd mmmm yyyy"),TEXT(B3+((B5-B3)*46)+46,"dd mmmm yyyy"))&" - "&IF(B2,TEXT(EDATE(B3,47)-1,"dd mmmm yyyy"),TEXT(B3+(((B5-B3)*47)+46),"dd mmmm yyyy")) -> 11 February 2029 - 10 March 2029
A56: =IF(B2,TEXT(EDATE(B3,47),"dd mmmm yyyy"),TEXT(B3+((B5-B3)*47)+47,"dd mmmm yyyy"))&" - "&IF(B2,TEXT(EDATE(B3,48)-1,"dd mmmm yyyy"),TEXT(B3+(((B5-B3)*48)+47),"dd mmmm yyyy")) -> 11 March 2029 - 10 April 2029

Sheet Forecast_1
A1: ="Forecasts For the Year "&TEXT(Main!B3,"mmmm yyyy")&" to "&IF(Main!B2,TEXT(EDATE(Main!B3,3)-1,"mmmm yyyy"),TEXT(Main!B3+((Main!B5-Main!B3)*3+2),"mmmm yyyy")) -> Forecasts For the Year April 2025 to July 2025 | I1: Monthly Balance | M1: Quarterly Debts
A2: Current | D2: Previous | I2: Date | J2: Last Balance | M2: Quarter | N2: Debts Amount
A3: Assets | B3: Bank Account | C3: 0 | D3: Assets | E3: Bank Account | F3: 0 | I3: =TEXT(Main!B3,"dd mmmm yyyy")&" - "&IF(Main!B2,TEXT(EDATE(Main!B3,1)-1,"dd mmmm yyyy"),TEXT(Main!B3+(Main!B5-Main!B3)*1,"dd mmmm yyyy")) -> 11 April 2025 - 10 May 2025 | J3: =E149 -> 0 | M3: =TEXT(Main!B3,"dd mmmm yyyy")&" - "&IF(Main!B2,TEXT(EDATE(Main!B3,3)-1,"dd mmmm yyyy"),TEXT(Main!B3+((Main!B5-Main!B3)*3+2),"dd mmmm yyyy")) -> 11 April 2025 - 10 July 2025 | N3: =-D17 -> 0
B4: cash | C4: 0 | E4: cash | F4: 0 | I4: =IF(Main!B2,TEXT(EDATE(Main!B3,1),"dd mmmm yyyy"),TEXT(Main!B3+(Main!B5-Main!B3)+1,"dd mmmm yyyy"))&" - "&IF(Main!B2,TEXT(EDATE(Main!B3,2)-1,"dd mmmm yyyy"),TEXT(Main!B3+(Main!B5-Main!B3)*2+1,"dd mmmm yyyy")) -> 11 May 2025 - 10 June 2025 | J4: =E176 -> 0 | M4: =IF(Main!B2,TEXT(EDATE(Main!B3,3),"dd mmmm yyyy"),TEXT(Main!B3+((Main!B5-Main!B3)*3+3),"dd mmmm yyyy"))&" - "&IF(Main!B2,TEXT(EDATE(Main!B3,6)-1,"dd mmmm yyyy"),TEXT(Main!B3+((Main!B5-Main!B3)*6+5),"dd mmmm yyyy")) -> 11 July 2025 - 10 October 2025 | N4: {=(INDIRECT("'"&INDIRECT("Main!B12")&"'!C5"))} -> 0
B5: Unit Trusts / Charity Trusts | C5: 0 | E5: Unit Trusts / Charity Trusts | F5: 0 | I5: =IF(Main!B2,TEXT(EDATE(Main!B3,2),"dd mmmm yyyy"),TEXT(Main!B3+((Main!B5-Main!B3)*2)+2,"dd mmmm yyyy"))&" - "&IF(Main!B2,TEXT(EDATE(Main!B3,3)-1,"dd mmmm yyyy"),TEXT(Main!B3+((Main!B5-Main!B3)*3+2),"dd mmmm yyyy")) -> 11 June 2025 - 10 July 2025 | J5: =E203 -> 0 | M5: =IF(Main!B2,TEXT(EDATE(Main!B3,6),"dd mmmm yyyy"),TEXT(Main!B3+((Main!B5-Main!B3)*6+6),"dd mmmm yyyy"))&" - "&IF(Main!B2,TEXT(EDATE(Main!B3,9)-1,"dd mmmm yyyy"),TEXT(Main!B3+((Main!B5-Main!B3)*9+8),"dd mmmm yyyy")) -> 11 October 2025 - 10 January 2026 | N5: {=(INDIRECT("'"&INDIRECT("Main!B15")&"'!C5"))} -> 0
B6: Bank Cheque From Tax | C6: 0 | E6: Bank Cheque From Tax | F6: 0 | I6: =IF(Main!B2,TEXT(EDATE(Main!B3,3),"dd mmmm yyyy"),TEXT(Main!B3+((Main!B5-Main!B3)*3)+3,"dd mmmm yyyy"))&" - "&IF(Main!B2,TEXT(EDATE(Main!B3,4)-1,"dd mmmm yyyy"),TEXT(Main!B3+((Main!B5-Main!B3)*4+3),"dd mmmm yyyy")) -> 11 July 2025 - 10 August 2025 | J6: {=(INDIRECT("'"&INDIRECT("Main!B12")&"'!E136"))} -> 0 | M6: =IF(Main!B2,TEXT(EDATE(Main!B3,9),"dd mmmm yyyy"),TEXT(Main!B3+((Main!B5-Main!B3)*9+9),"dd mmmm yyyy"))&" - "&IF(Main!B2,TEXT(EDATE(Main!B3,12)-1,"dd mmmm yyyy"),TEXT(Main!B3+((Main!B5-Main!B3)*12+11),"dd mmmm yyyy")) -> 11 January 2026 - 10 April 2026 | N6: {=(INDIRECT("'"&INDIRECT("Main!B18")&"'!C5"))} -> 0
B7: Payment System (Apps) | C7: 0 | E7: Payment System (Apps) | F7: 0 | I7: =IF(Main!B2,TEXT(EDATE(Main!B3,4),"dd mmmm yyyy"),TEXT(Main!B3+((Main!B5-Main!B3)*4)+4,"dd mmmm yyyy"))&" - "&IF(Main!B2,TEXT(EDATE(Main!B3,5)-1,"dd mmmm yyyy"),TEXT(Main!B3+((Main!B5-Main!B3)*5+4),"dd mmmm yyyy")) -> 11 August 2025 - 10 September 2025 | J7: {=(INDIRECT("'"&INDIRECT("Main!B12")&"'!E163"))} -> 0 | M7: =IF(Main!B2,TEXT(EDATE(Main!B3,12),"dd mmmm yyyy"),TEXT(Main!B3+((Main!B5-Main!B3)*12+12),"dd mmmm yyyy"))&" - "&IF(Main!B2,TEXT(EDATE(Main!B3,15)-1,"dd mmmm yyyy"),TEXT(Main!B3+((Main!B5-Main!B3)*15+14),"dd mmmm yyyy")) -> 11 April 2026 - 10 July 2026 | N7: {=(INDIRECT("'"&INDIRECT("Main!B21")&"'!C5"))} -> 0
B8: Payment System (internet) | C8: 0 | E8: Payment System (internet) | F8: 0 | I8: =IF(Main!B2,TEXT(EDATE(Main!B3,5),"dd mmmm yyyy"),TEXT(Main!B3+((Main!B5-Main!B3)*5)+5,"dd mmmm yyyy"))&" - "&IF(Main!B2,TEXT(EDATE(Main!B3,6)-1,"dd mmmm yyyy"),TEXT(Main!B3+((Main!B5-Main!B3)*6+5),"dd mmmm yyyy")) -> 11 September 2025 - 10 October 2025 | J8: {=(INDIRECT("'"&INDIRECT("Main!B12")&"'!E190"))} -> 0 | M8: =IF(Main!B2,TEXT(EDATE(Main!B3,15),"dd mmmm yyyy"),TEXT(Main!B3+((Main!B5-Main!B3)*15+15),"dd mmmm yyyy"))&" - "&IF(Main!B2,TEXT(EDATE(Main!B3,18)-1,"dd mmmm yyyy"),TEXT(Main!B3+((Main!B5-Main!B3)*18+17),"dd mmmm yyyy")) -> 11 July 2026 - 10 October 2026 | N8: {=(INDIRECT("'"&INDIRECT("Main!B24")&"'!C5"))} -> 0
B9: Fixed Assest Properties / Data Centers | C9: 0 | E9: Fixed Assest Properties / Data Centers | F9: 0 | I9: =IF(Main!B2,TEXT(EDATE(Main!B3,6),"dd mmmm yyyy"),TEXT(Main!B3+((Main!B5-Main!B3)*6)+6,"dd mmmm yyyy"))&" - "&IF(Main!B2,TEXT(EDATE(Main!B3,7)-1,"dd mmmm yyyy"),TEXT(Main!B3+((Main!B5-Main!B3)*7+6),"dd mmmm yyyy")) -> 11 October 2025 - 10 November 2025 | J9: {=(INDIRECT("'"&INDIRECT("Main!B15")&"'!E136"))} -> 0 | M9: =IF(Main!B2,TEXT(EDATE(Main!B3,18),"dd mmmm yyyy"),TEXT(Main!B3+((Main!B5-Main!B3)*18+18),"dd mmmm yyyy"))&" - "&IF(Main!B2,TEXT(EDATE(Main!B3,21)-1,"dd mmmm yyyy"),TEXT(Main!B3+((Main!B5-Main!B3)*21+20),"dd mmmm yyyy")) -> 11 October 2026 - 10 January 2027 | N9: {=(INDIRECT("'"&INDIRECT("Main!B27")&"'!C5"))} -> 0
B10: Removable Assets | C10: 0 | E10: Removable Assets | F10: 0 | I10: =IF(Main!B2,TEXT(EDATE(Main!B3,7),"dd mmmm yyyy"),TEXT(Main!B3+((Main!B5-Main!B3)*7)+7,"dd mmmm yyyy"))&" - "&IF(Main!B2,TEXT(EDATE(Main!B3,8)-1,"dd mmmm yyyy"),TEXT(Main!B3+((Main!B5-Main!B3)*8+7),"dd mmmm yyyy")) -> 11 November 2025 - 10 December 2025 | J10: {=(INDIRECT("'"&INDIRECT("Main!B15")&"'!E163"))} -> 0 | M10: =IF(Main!B2,TEXT(EDATE(Main!B3,21),"dd mmmm yyyy"),TEXT(Main!B3+((Main!B5-Main!B3)*21+21),"dd mmmm yyyy"))&" - "&IF(Main!B2,TEXT(EDATE(Main!B3,24)-1,"dd mmmm yyyy"),TEXT(Main!B3+((Main!B5-Main!B3)*24+23),"dd mmmm yyyy")) -> 11 January 2027 - 10 April 2027 | N10: {=(INDIRECT("'"&INDIRECT("Main!B30")&"'!C5"))} -> 0
C11: 0 | F11: 0 | I11: =IF(Main!B2,TEXT(EDATE(Main!B3,8),"dd mmmm yyyy"),TEXT(Main!B3+((Main!B5-Main!B3)*8)+8,"dd mmmm yyyy"))&" - "&IF(Main!B2,TEXT(EDATE(Main!B3,9)-1,"dd mmmm yyyy"),TEXT(Main!B3+((Main!B5-Main!B3)*9+8),"dd mmmm yyyy")) -> 11 December 2025 - 10 January 2026 | J11: {=(INDIRECT("'"&INDIRECT("Main!B15")&"'!E190"))} -> 0 | M11: =IF(Main!B2,TEXT(EDATE(Main!B3,24),"dd mmmm yyyy"),TEXT(Main!B3+((Main!B5-Main!B3)*24+24),"dd mmmm yyyy"))&" - "&IF(Main!B2,TEXT(EDATE(Main!B3,27)-1,"dd mmmm yyyy"),TEXT(Main!B3+((Main!B5-Main!B3)*27+26),"dd mmmm yyyy")) -> 11 April 2027 - 10 July 2027 | N11: {=(INDIRECT("'"&INDIRECT("Main!B33")&"'!C5"))} -> 0
C12: 0 | F12: 0 | I12: =IF(Main!B2,TEXT(EDATE(Main!B3,9),"dd mmmm yyyy"),TEXT(Main!B3+((Main!B5-Main!B3)*9)+9,"dd mmmm yyyy"))&" - "&IF(Main!B2,TEXT(EDATE(Main!B3,10)-1,"dd mmmm yyyy"),TEXT(Main!B3+((Main!B5-Main!B3)*10+9),"dd mmmm yyyy")) -> 11 January 2026 - 10 February 2026 | J12: {=(INDIRECT("'"&INDIRECT("Main!B18")&"'!E136"))} -> 0 | M12: =IF(Main!B2,TEXT(EDATE(Main!B3,27),"dd mmmm yyyy"),TEXT(Main!B3+((Main!B5-Main!B3)*27+27),"dd mmmm yyyy"))&" - "&IF(Main!B2,TEXT(EDATE(Main!B3,30)-1,"dd mmmm yyyy"),TEXT(Main!B3+((Main!B5-Main!B3)*30+29),"dd mmmm yyyy")) -> 11 July 2027 - 10 October 2027 | N12: {=(INDIRECT("'"&INDIRECT("Main!B36")&"'!C5"))} -> 0
C13: 0 | F13: 0 | I13: =IF(Main!B2,TEXT(EDATE(Main!B3,10),"dd mmmm yyyy"),TEXT(Main!B3+((Main!B5-Main!B3)*10)+10,"dd mmmm yyyy"))&" - "&IF(Main!B2,TEXT(EDATE(Main!B3,11)-1,"dd mmmm yyyy"),TEXT(Main!B3+((Main!B5-Main!B3)*11+10),"dd mmmm yyyy")) -> 11 February 2026 - 10 March 2026 | J13: {=(INDIRECT("'"&INDIRECT("Main!B18")&"'!E163"))} -> 0 | M13: =IF(Main!B2,TEXT(EDATE(Main!B3,30),"dd mmmm yyyy"),TEXT(Main!B3+((Main!B5-Main!B3)*30+30),"dd mmmm yyyy"))&" - "&IF(Main!B2,TEXT(EDATE(Main!B3,33)-1,"dd mmmm yyyy"),TEXT(Main!B3+((Main!B5-Main!B3)*33+32),"dd mmmm yyyy")) -> 11 October 2027 - 10 January 2028 | N13: {=(INDIRECT("'"&INDIRECT("Main!B39")&"'!C5"))} -> 0
C14: 0 | F14: 0 | I14: =IF(Main!B2,TEXT(EDATE(Main!B3,11),"dd mmmm yyyy"),TEXT(Main!B3+((Main!B5-Main!B3)*11)+11,"dd mmmm yyyy"))&" - "&IF(Main!B2,TEXT(EDATE(Main!B3,12)-1,"dd mmmm yyyy"),TEXT(Main!B3+((Main!B5-Main!B3)*12+11),"dd mmmm yyyy")) -> 11 March 2026 - 10 April 2026 | J14: {=(INDIRECT("'"&INDIRECT("Main!B18")&"'!E190"))} -> 0 | M14: =IF(Main!B2,TEXT(EDATE(Main!B3,33),"dd mmmm yyyy"),TEXT(Main!B3+((Main!B5-Main!B3)*33+33),"dd mmmm yyyy"))&" - "&IF(Main!B2,TEXT(EDATE(Main!B3,36)-1,"dd mmmm yyyy"),TEXT(Main!B3+((Main!B5-Main!B3)*36+35),"dd mmmm yyyy")) -> 11 January 2028 - 10 April 2028 | N14: {=(INDIRECT("'"&INDIRECT("Main!B42")&"'!C5"))} -> 0
C15: 0 | F15: 0 | I15: =IF(Main!B2,TEXT(EDATE(Main!B3,12),"dd mmmm yyyy"),TEXT(Main!B3+((Main!B5-Main!B3)*12)+12,"dd mmmm yyyy"))&" - "&IF(Main!B2,TEXT(EDATE(Main!B3,13)-1,"dd mmmm yyyy"),TEXT(Main!B3+((Main!B5-Main!B3)*13+12),"dd mmmm yyyy")) -> 11 April 2026 - 10 May 2026 | J15: {=(INDIRECT("'"&INDIRECT("Main!B21")&"'!E136"))} -> 0 | M15: =IF(Main!B2,TEXT(EDATE(Main!B3,36),"dd mmmm yyyy"),TEXT(Main!B3+((Main!B5-Main!B3)*36+36),"dd mmmm yyyy"))&" - "&IF(Main!B2,TEXT(EDATE(Main!B3,39)-1,"dd mmmm yyyy"),TEXT(Main!B3+((Main!B5-Main!B3)*39+38),"dd mmmm yyyy")) -> 11 April 2028 - 10 July 2028 | N15: {=(INDIRECT("'"&INDIRECT("Main!B45")&"'!C5"))} -> 0
B16: Total | C16: =SUM(C3:C15) -> 0 | E16: Total | F16: =SUM(F3:F15) -> 0 | I16: =IF(Main!B2,TEXT(EDATE(Main!B3,13),"dd mmmm yyyy"),TEXT(Main!B3+((Main!B5-Main!B3)*13)+13,"dd mmmm yyyy"))&" - "&IF(Main!B2,TEXT(EDATE(Main!B3,14)-1,"dd mmmm yyyy"),TEXT(Main!B3+((Main!B5-Main!B3)*14+13),"dd mmmm yyyy")) -> 11 May 2026 - 10 June 2026 | J16: {=(INDIRECT("'"&INDIRECT("Main!B21")&"'!E163"))} -> 0 | M16: =IF(Main!B2,TEXT(EDATE(Main!B3,39),"dd mmmm yyyy"),TEXT(Main!B3+((Main!B5-Main!B3)*39+39),"dd mmmm yyyy"))&" - "&IF(Main!B2,TEXT(EDATE(Main!B3,42)-1,"dd mmmm yyyy"),TEXT(Main!B3+((Main!B5-Main!B3)*42+41),"dd mmmm yyyy")) -> 11 July 2028 - 10 October 2028 | N16: {=(INDIRECT("'"&INDIRECT("Main!B48")&"'!C5"))} -> 0
I17: =IF(Main!B2,TEXT(EDATE(Main!B3,14),"dd mmmm yyyy"),TEXT(Main!B3+((Main!B5-Main!B3)*14)+14,"dd mmmm yyyy"))&" - "&IF(Main!B2,TEXT(EDATE(Main!B3,15)-1,"dd mmmm yyyy"),TEXT(Main!B3+((Main!B5-Main!B3)*15+14),"dd mmmm yyyy")) -> 11 June 2026 - 10 July 2026 | J17: {=(INDIRECT("'"&INDIRECT("Main!B21")&"'!E190"))} -> 0 | M17: =IF(Main!B2,TEXT(EDATE(Main!B3,42),"dd mmmm yyyy"),TEXT(Main!B3+((Main!B5-Main!B3)*42+42),"dd mmmm yyyy"))&" - "&IF(Main!B2,TEXT(EDATE(Main!B3,45)-1,"dd mmmm yyyy"),TEXT(Main!B3+((Main!B5-Main!B3)*45+44),"dd mmmm yyyy")) -> 11 October 2028 - 10 January 2029 | N17: {=(INDIRECT("'"&INDIRECT("Main!B51")&"'!C5"))} -> 0
I18: =IF(Main!B2,TEXT(EDATE(Main!B3,15),"dd mmmm yyyy"),TEXT(Main!B3+((Main!B5-Main!B3)*15)+15,"dd mmmm yyyy"))&" - "&IF(Main!B2,TEXT(EDATE(Main!B3,16)-1,"dd mmmm yyyy"),TEXT(Main!B3+((Main!B5-Main!B3)*16+15),"dd mmmm yyyy")) -> 11 July 2026 - 10 August 2026 | J18: {=(INDIRECT("'"&INDIRECT("Main!B24")&"'!E136"))} -> 0 | M18: =IF(Main!B2,TEXT(EDATE(Main!B3,45),"dd mmmm yyyy"),TEXT(Main!B3+((Main!B5-Main!B3)*45+45),"dd mmmm yyyy"))&" - "&IF(Main!B2,TEXT(EDATE(Main!B3,48)-1,"dd mmmm yyyy"),TEXT(Main!B3+((Main!B5-Main!B3)*48+47),"dd mmmm yyyy")) -> 11 January 2029 - 10 April 2029 | N18: {=(INDIRECT("'"&INDIRECT("Main!B54")&"'!C5"))} -> 0
I19: =IF(Main!B2,TEXT(EDATE(Main!B3,16),"dd mmmm yyyy"),TEXT(Main!B3+((Main!B5-Main!B3)*16)+16,"dd mmmm yyyy"))&" - "&IF(Main!B2,TEXT(EDATE(Main!B3,17)-1,"dd mmmm yyyy"),TEXT(Main!B3+((Main!B5-Main!B3)*17+16),"dd mmmm yyyy")) -> 11 August 2026 - 10 September 2026 | J19: {=(INDIRECT("'"&INDIRECT("Main!B24")&"'!E163"))} -> 0
I20: =IF(Main!B2,TEXT(EDATE(Main!B3,17),"dd mmmm yyyy"),TEXT(Main!B3+((Main!B5-Main!B3)*17)+17,"dd mmmm yyyy"))&" - "&IF(Main!B2,TEXT(EDATE(Main!B3,18)-1,"dd mmmm yyyy"),TEXT(Main!B3+((Main!B5-Main!B3)*18+17),"dd mmmm yyyy")) -> 11 September 2026 - 10 October 2026 | J20: {=(INDIRECT("'"&INDIRECT("Main!B24")&"'!E190"))} -> 0
I21: =IF(Main!B2,TEXT(EDATE(Main!B3,18),"dd mmmm yyyy"),TEXT(Main!B3+((Main!B5-Main!B3)*18)+18,"dd mmmm yyyy"))&" - "&IF(Main!B2,TEXT(EDATE(Main!B3,19)-1,"dd mmmm yyyy"),TEXT(Main!B3+((Main!B5-Main!B3)*19+18),"dd mmmm yyyy")) -> 11 October 2026 - 10 November 2026 | J21: {=(INDIRECT("'"&INDIRECT("Main!B27")&"'!E136"))} -> 0
A22: =TEXT(Main!B3,"dd mmmm yyyy")&" - "&IF(Main!B2,TEXT(EDATE(Main!B3,1)-1,"dd mmmm yyyy"),TEXT(Main!B3+Main!B5-Main!B3,"dd mmmm yyyy"))&" / "&" (Revenue / Deferred Debts Or Expenses)" -> 11 April 2025 - 10 May 2025 / (Revenue / Deferred Debts Or Expenses) | I22: =IF(Main!B2,TEXT(EDATE(Main!B3,19),"dd mmmm yyyy"),TEXT(Main!B3+((Main!B5-Main!B3)*19)+19,"dd mmmm yyyy"))&" - "&IF(Main!B2,TEXT(EDATE(Main!B3,20)-1,"dd mmmm yyyy"),TEXT(Main!B3+((Main!B5-Main!B3)*20+19),"dd mmmm yyyy")) -> 11 November 2026 - 10 December 2026 | J22: {=(INDIRECT("'"&INDIRECT("Main!B27")&"'!E163"))} -> 0
A23: Date | B23: Name | D23: Description | F23: Amount | I23: =IF(Main!B2,TEXT(EDATE(Main!B3,20),"dd mmmm yyyy"),TEXT(Main!B3+((Main!B5-Main!B3)*20)+20,"dd mmmm yyyy"))&" - "&IF(Main!B2,TEXT(EDATE(Main!B3,21)-1,"dd mmmm yyyy"),TEXT(Main!B3+((Main!B5-Main!B3)*21+20),"dd mmmm yyyy")) -> 11 December 2026 - 10 January 2027 | J23: {=(INDIRECT("'"&INDIRECT("Main!B27")&"'!E190"))} -> 0
F24: 0 | I24: =IF(Main!B2,TEXT(EDATE(Main!B3,21),"dd mmmm yyyy"),TEXT(Main!B3+((Main!B5-Main!B3)*21)+21,"dd mmmm yyyy"))&" - "&IF(Main!B2,TEXT(EDATE(Main!B3,22)-1,"dd mmmm yyyy"),TEXT(Main!B3+((Main!B5-Main!B3)*22+21),"dd mmmm yyyy")) -> 11 January 2027 - 10 February 2027 | J24: {=(INDIRECT("'"&INDIRECT("Main!B30")&"'!E136"))} -> 0
F25: 0 | I25: =IF(Main!B2,TEXT(EDATE(Main!B3,22),"dd mmmm yyyy"),TEXT(Main!B3+((Main!B5-Main!B3)*22)+22,"dd mmmm yyyy"))&" - "&IF(Main!B2,TEXT(EDATE(Main!B3,23)-1,"dd mmmm yyyy"),TEXT(Main!B3+((Main!B5-Main!B3)*23+22),"dd mmmm yyyy")) -> 11 February 2027 - 10 March 2027 | J25: {=(INDIRECT("'"&INDIRECT("Main!B30")&"'!E163"))} -> 0
F26: 0 | I26: =IF(Main!B2,TEXT(EDATE(Main!B3,23),"dd mmmm yyyy"),TEXT(Main!B3+((Main!B5-Main!B3)*23)+23,"dd mmmm yyyy"))&" - "&IF(Main!B2,TEXT(EDATE(Main!B3,24)-1,"dd mmmm yyyy"),TEXT(Main!B3+((Main!B5-Main!B3)*24+23),"dd mmmm yyyy")) -> 11 March 2027 - 10 April 2027 | J26: {=(INDIRECT("'"&INDIRECT("Main!B30")&"'!E190"))} -> 0
F27: 0 | I27: =IF(Main!B2,TEXT(EDATE(Main!B3,24),"dd mmmm yyyy"),TEXT(Main!B3+((Main!B5-Main!B3)*24)+24,"dd mmmm yyyy"))&" - "&IF(Main!B2,TEXT(EDATE(Main!B3,25)-1,"dd mmmm yyyy"),TEXT(Main!B3+((Main!B5-Main!B3)*25+24),"dd mmmm yyyy")) -> 11 April 2027 - 10 May 2027 | J27: {=(INDIRECT("'"&INDIRECT("Main!B33")&"'!E136"))} -> 0
F28: 0 | I28: =IF(Main!B2,TEXT(EDATE(Main!B3,25),"dd mmmm yyyy"),TEXT(Main!B3+((Main!B5-Main!B3)*25)+25,"dd mmmm yyyy"))&" - "&IF(Main!B2,TEXT(EDATE(Main!B3,26)-1,"dd mmmm yyyy"),TEXT(Main!B3+((Main!B5-Main!B3)*26+25),"dd mmmm yyyy")) -> 11 May 2027 - 10 June 2027 | J28: {=(INDIRECT("'"&INDIRECT("Main!B33")&"'!E163"))} -> 0
F29: 0 | I29: =IF(Main!B2,TEXT(EDATE(Main!B3,26),"dd mmmm yyyy"),TEXT(Main!B3+((Main!B5-Main!B3)*26)+26,"dd mmmm yyyy"))&" - "&IF(Main!B2,TEXT(EDATE(Main!B3,27)-1,"dd mmmm yyyy"),TEXT(Main!B3+((Main!B5-Main!B3)*27+26),"dd mmmm yyyy")) -> 11 June 2027 - 10 July 2027 | J29: {=(INDIRECT("'"&INDIRECT("Main!B33")&"'!E190"))} -> 0
D30: Total Revenue | F30: =SUM(F24:G29) -> 0 | I30: =IF(Main!B2,TEXT(EDATE(Main!B3,27),"dd mmmm yyyy"),TEXT(Main!B3+((Main!B5-Main!B3)*27)+27,"dd mmmm yyyy"))&" - "&IF(Main!B2,TEXT(EDATE(Main!B3,28)-1,"dd mmmm yyyy"),TEXT(Main!B3+((Main!B5-Main!B3)*28+27),"dd mmmm yyyy")) -> 11 July 2027 - 10 August 2027 | J30: {=(INDIRECT("'"&INDIRECT("Main!B36")&"'!E136"))} -> 0
I31: =IF(Main!B2,TEXT(EDATE(Main!B3,28),"dd mmmm yyyy"),TEXT(Main!B3+((Main!B5-Main!B3)*28)+28,"dd mmmm yyyy"))&" - "&IF(Main!B2,TEXT(EDATE(Main!B3,29)-1,"dd mmmm yyyy"),TEXT(Main!B3+((Main!B5-Main!B3)*29+28),"dd mmmm yyyy")) -> 11 August 2027 - 10 September 2027 | J31: {=(INDIRECT("'"&INDIRECT("Main!B36")&"'!E163"))} -> 0
I32: =IF(Main!B2,TEXT(EDATE(Main!B3,29),"dd mmmm yyyy"),TEXT(Main!B3+((Main!B5-Main!B3)*29)+29,"dd mmmm yyyy"))&" - "&IF(Main!B2,TEXT(EDATE(Main!B3,30)-1,"dd mmmm yyyy"),TEXT(Main!B3+((Main!B5-Main!B3)*30+29),"dd mmmm yyyy")) -> 11 September 2027 - 10 October 2027 | J32: {=(INDIRECT("'"&INDIRECT("Main!B36")&"'!E190"))} -> 0
I33: =IF(Main!B2,TEXT(EDATE(Main!B3,30),"dd mmmm yyyy"),TEXT(Main!B3+((Main!B5-Main!B3)*30)+30,"dd mmmm yyyy"))&" - "&IF(Main!B2,TEXT(EDATE(Main!B3,31)-1,"dd mmmm yyyy"),TEXT(Main!B3+((Main!B5-Main!B3)*31+30),"dd mmmm yyyy")) -> 11 October 2027 - 10 November 2027 | J33: {=(INDIRECT("'"&INDIRECT("Main!B39")&"'!E136"))} -> 0
A34: =IF(Main!B2,TEXT(EDATE(Main!B3,1),"dd mmmm yyyy"),TEXT(Main!B3+(Main!B5-Main!B3)+1,"dd mmmm yyyy"))&" - "&IF(Main!B2,TEXT(EDATE(Main!B3,2)-1,"dd mmmm yyyy"),TEXT(Main!B3+(Main!B5-Main!B3)*2+1,"dd mmmm yyyy"))&" (Revenue / Deferred Debts Or Expenses)" -> 11 May 2025 - 10 June 2025 (Revenue / Deferred Debts Or Expenses) | I34: =IF(Main!B2,TEXT(EDATE(Main!B3,31),"dd mmmm yyyy"),TEXT(Main!B3+((Main!B5-Main!B3)*31)+31,"dd mmmm yyyy"))&" - "&IF(Main!B2,TEXT(EDATE(Main!B3,32)-1,"dd mmmm yyyy"),TEXT(Main!B3+((Main!B5-Main!B3)*32+31),"dd mmmm yyyy")) -> 11 November 2027 - 10 December 2027 | J34: {=(INDIRECT("'"&INDIRECT("Main!B39")&"'!E163"))} -> 0
A35: Date | B35: Name | D35: Description | F35: Amount | I35: =IF(Main!B2,TEXT(EDATE(Main!B3,32),"dd mmmm yyyy"),TEXT(Main!B3+((Main!B5-Main!B3)*32)+32,"dd mmmm yyyy"))&" - "&IF(Main!B2,TEXT(EDATE(Main!B3,33)-1,"dd mmmm yyyy"),TEXT(Main!B3+((Main!B5-Main!B3)*33+32),"dd mmmm yyyy")) -> 11 December 2027 - 10 January 2028 | J35: {=(INDIRECT("'"&INDIRECT("Main!B39")&"'!E190"))} -> 0
F36: 0 | I36: =IF(Main!B2,TEXT(EDATE(Main!B3,33),"dd mmmm yyyy"),TEXT(Main!B3+((Main!B5-Main!B3)*33)+33,"dd mmmm yyyy"))&" - "&IF(Main!B2,TEXT(EDATE(Main!B3,34)-1,"dd mmmm yyyy"),TEXT(Main!B3+((Main!B5-Main!B3)*34+33),"dd mmmm yyyy")) -> 11 January 2028 - 10 February 2028 | J36: {=(INDIRECT("'"&INDIRECT("Main!B42")&"'!E136"))} -> 0
F37: 0 | I37: =IF(Main!B2,TEXT(EDATE(Main!B3,34),"dd mmmm yyyy"),TEXT(Main!B3+((Main!B5-Main!B3)*34)+34,"dd mmmm yyyy"))&" - "&IF(Main!B2,TEXT(EDATE(Main!B3,35)-1,"dd mmmm yyyy"),TEXT(Main!B3+((Main!B5-Main!B3)*35+34),"dd mmmm yyyy")) -> 11 February 2028 - 10 March 2028 | J37: {=(INDIRECT("'"&INDIRECT("Main!B42")&"'!E163"))} -> 0
F38: 0 | I38: =IF(Main!B2,TEXT(EDATE(Main!B3,35),"dd mmmm yyyy"),TEXT(Main!B3+((Main!B5-Main!B3)*35)+35,"dd mmmm yyyy"))&" - "&IF(Main!B2,TEXT(EDATE(Main!B3,36)-1,"dd mmmm yyyy"),TEXT(Main!B3+((Main!B5-Main!B3)*36+35),"dd mmmm yyyy")) -> 11 March 2028 - 10 April 2028 | J38: {=(INDIRECT("'"&INDIRECT("Main!B42")&"'!E190"))} -> 0
F39: 0 | I39: =IF(Main!B2,TEXT(EDATE(Main!B3,36),"dd mmmm yyyy"),TEXT(Main!B3+((Main!B5-Main!B3)*36)+36,"dd mmmm yyyy"))&" - "&IF(Main!B2,TEXT(EDATE(Main!B3,37)-1,"dd mmmm yyyy"),TEXT(Main!B3+((Main!B5-Main!B3)*37+36),"dd mmmm yyyy")) -> 11 April 2028 - 10 May 2028 | J39: {=(INDIRECT("'"&INDIRECT("Main!B45")&"'!E136"))} -> 0
F40: 0 | I40: =IF(Main!B2,TEXT(EDATE(Main!B3,37),"dd mmmm yyyy"),TEXT(Main!B3+((Main!B5-Main!B3)*37)+37,"dd mmmm yyyy"))&" - "&IF(Main!B2,TEXT(EDATE(Main!B3,38)-1,"dd mmmm yyyy"),TEXT(Main!B3+((Main!B5-Main!B3)*38+37),"dd mmmm yyyy")) -> 11 May 2028 - 10 June 2028 | J40: {=(INDIRECT("'"&INDIRECT("Main!B45")&"'!E163"))} -> 0
F41: 0 | I41: =IF(Main!B2,TEXT(EDATE(Main!B3,38),"dd mmmm yyyy"),TEXT(Main!B3+((Main!B5-Main!B3)*38)+38,"dd mmmm yyyy"))&" - "&IF(Main!B2,TEXT(EDATE(Main!B3,39)-1,"dd mmmm yyyy"),TEXT(Main!B3+((Main!B5-Main!B3)*39+38),"dd mmmm yyyy")) -> 11 June 2028 - 10 July 2028 | J41: {=(INDIRECT("'"&INDIRECT("Main!B45")&"'!E190"))} -> 0
D42: Total Revenue | F42: =SUM(F36:G41) -> 0 | I42: =IF(Main!B2,TEXT(EDATE(Main!B3,39),"dd mmmm yyyy"),TEXT(Main!B3+((Main!B5-Main!B3)*39)+39,"dd mmmm yyyy"))&" - "&IF(Main!B2,TEXT(EDATE(Main!B3,40)-1,"dd mmmm yyyy"),TEXT(Main!B3+((Main!B5-Main!B3)*40+39),"dd mmmm yyyy")) -> 11 July 2028 - 10 August 2028 | J42: {=(INDIRECT("'"&INDIRECT("Main!B48")&"'!E136"))} -> 0
I43: =IF(Main!B2,TEXT(EDATE(Main!B3,40),"dd mmmm yyyy"),TEXT(Main!B3+((Main!B5-Main!B3)*40)+40,"dd mmmm yyyy"))&" - "&IF(Main!B2,TEXT(EDATE(Main!B3,41)-1,"dd mmmm yyyy"),TEXT(Main!B3+((Main!B5-Main!B3)*41+40),"dd mmmm yyyy")) -> 11 August 2028 - 10 September 2028 | J43: {=(INDIRECT("'"&INDIRECT("Main!B48")&"'!E163"))} -> 0
I44: =IF(Main!B2,TEXT(EDATE(Main!B3,41),"dd mmmm yyyy"),TEXT(Main!B3+((Main!B5-Main!B3)*41)+41,"dd mmmm yyyy"))&" - "&IF(Main!B2,TEXT(EDATE(Main!B3,42)-1,"dd mmmm yyyy"),TEXT(Main!B3+((Main!B5-Main!B3)*42+41),"dd mmmm yyyy")) -> 11 September 2028 - 10 October 2028 | J44: {=(INDIRECT("'"&INDIRECT("Main!B48")&"'!E190"))} -> 0
I45: =IF(Main!B2,TEXT(EDATE(Main!B3,42),"dd mmmm yyyy"),TEXT(Main!B3+((Main!B5-Main!B3)*42)+42,"dd mmmm yyyy"))&" - "&IF(Main!B2,TEXT(EDATE(Main!B3,43)-1,"dd mmmm yyyy"),TEXT(Main!B3+((Main!B5-Main!B3)*43+42),"dd mmmm yyyy")) -> 11 October 2028 - 10 November 2028 | J45: {=(INDIRECT("'"&INDIRECT("Main!B51")&"'!E136"))} -> 0
A46: =IF(Main!B2,TEXT(EDATE(Main!B3,2),"dd mmmm yyyy"),TEXT(Main!B3+((Main!B5-Main!B3)*2)+2,"dd mmmm yyyy"))&" - "&IF(Main!B2,TEXT(EDATE(Main!B3,3)-1,"dd mmmm yyyy"),TEXT(Main!B3+((Main!B5-Main!B3)*3+2),"dd mmmm yyyy"))&" (Revenue / Deferred Debts Or Expenses)" -> 11 June 2025 - 10 July 2025 (Revenue / Deferred Debts Or Expenses) | I46: =IF(Main!B2,TEXT(EDATE(Main!B3,43),"dd mmmm yyyy"),TEXT(Main!B3+((Main!B5-Main!B3)*43)+43,"dd mmmm yyyy"))&" - "&IF(Main!B2,TEXT(EDATE(Main!B3,44)-1,"dd mmmm yyyy"),TEXT(Main!B3+((Main!B5-Main!B3)*44+43),"dd mmmm yyyy")) -> 11 November 2028 - 10 December 2028 | J46: {=(INDIRECT("'"&INDIRECT("Main!B51")&"'!E163"))} -> 0
A47: Date | B47: Name | D47: Description | F47: Amount | I47: =IF(Main!B2,TEXT(EDATE(Main!B3,44),"dd mmmm yyyy"),TEXT(Main!B3+((Main!B5-Main!B3)*44)+44,"dd mmmm yyyy"))&" - "&IF(Main!B2,TEXT(EDATE(Main!B3,45)-1,"dd mmmm yyyy"),TEXT(Main!B3+((Main!B5-Main!B3)*45+44),"dd mmmm yyyy")) -> 11 December 2028 - 10 January 2029 | J47: {=(INDIRECT("'"&INDIRECT("Main!B51")&"'!E190"))} -> 0
F48: 0 | I48: =IF(Main!B2,TEXT(EDATE(Main!B3,45),"dd mmmm yyyy"),TEXT(Main!B3+((Main!B5-Main!B3)*45)+45,"dd mmmm yyyy"))&" - "&IF(Main!B2,TEXT(EDATE(Main!B3,46)-1,"dd mmmm yyyy"),TEXT(Main!B3+((Main!B5-Main!B3)*46+45),"dd mmmm yyyy")) -> 11 January 2029 - 10 February 2029 | J48: {=(INDIRECT("'"&INDIRECT("Main!B54")&"'!E136"))} -> 0
F49: 0 | I49: =IF(Main!B2,TEXT(EDATE(Main!B3,46),"dd mmmm yyyy"),TEXT(Main!B3+((Main!B5-Main!B3)*46)+46,"dd mmmm yyyy"))&" - "&IF(Main!B2,TEXT(EDATE(Main!B3,47)-1,"dd mmmm yyyy"),TEXT(Main!B3+((Main!B5-Main!B3)*47+46),"dd mmmm yyyy")) -> 11 February 2029 - 10 March 2029 | J49: {=(INDIRECT("'"&INDIRECT("Main!B54")&"'!E163"))} -> 0
F50: 0 | I50: =IF(Main!B2,TEXT(EDATE(Main!B3,47),"dd mmmm yyyy"),TEXT(Main!B3+((Main!B5-Main!B3)*47)+47,"dd mmmm yyyy"))&" - "&IF(Main!B2,TEXT(EDATE(Main!B3,48)-1,"dd mmmm yyyy"),TEXT(Main!B3+((Main!B5-Main!B3)*48+47),"dd mmmm yyyy")) -> 11 March 2029 - 10 April 2029 | J50: {=(INDIRECT("'"&INDIRECT("Main!B54")&"'!E190"))} -> 0
F51: 0
F52: 0
F53: 0
D54: Total Revenue | F54: =SUM(F48:G53) -> 0
A58: ="Fixed Expense For the Year "&TEXT(Main!B3,"mmmm yyyy")&" - "&IF(Main!B2,TEXT(EDATE(Main!B3,3)-1,"mmmm yyyy"),TEXT(Main!B3+((Main!B5-Main!B3)*3+2),"mmmm yyyy")) -> Fixed Expense For the Year April 2025 - July 2025
A59: Name | B59: Description | C59: Amount
A60: Mobile And Communications/ Housing Expenses
C61: 0
C62: 0
C63: 0
C64: 0
C65: 0
C66: 0
C67: 0
C68: 0
B69: Total Expenses | C69: =SUM(C61:C68) -> 0
A70: Credit Card Installments/Government Installments
C71: 0
C72: 0
C73: 0
C74: 0
C75: 0
C76: 0
C77: 0
C78: 0
C79: 0
B80: Total Expenses | C80: =SUM(C71:C79) -> 0
A81: Donation
C82: 0
C83: 0
C84: 0
C85: 0
C86: 0
C87: 0
C88: 0
B89: Total Expenses | C89: =SUM(C82:C88) -> 0
A90: Insurance (Personal / Properties / Medical)
C91: 0
C92: 0
C93: 0
C94: 0
C95: 0
C96: 0
C97: 0
C98: 0
B99: Total Expenses | C99: =SUM(C91:C98) -> 0
A100: Other Expenses
C101: 0
C102: 0
C103: 0
...

Sheet Forecast_2
A1: ="Forecasts For the Year "&IF(Main!B2,TEXT(EDATE(Main!B3,3),"mmmm yyyy"),TEXT(Main!B3+((Main!B5-Main!B3)*3+3),"mmmm yyyy"))&" to "&IF(Main!B2,TEXT(EDATE(Main!B3,6)-1,"mmmm yyyy"),TEXT(Main!B3+((Main!B5-Main!B3)*6+5),"mmmm yyyy")) -> Forecasts For the Year July 2025 to October 2025
A2: Assets | B2: Overall | C2: {=INDIRECT("'"&Main!B9&"'!$C$16")} -> 0
B3: Forecasts | C3: =E190 -> 0
A4: Total | C4: =SUM(C2:G3) -> 0
A5: Net Debts: | C5: =C108 -> 0
A8: =IF(Main!B2,TEXT(EDATE(Main!B3,3),"dd mmmm yyyy"),TEXT(Main!B3+((Main!B5-Main!B3)*3+3),"dd mmmm yyyy"))&" - "&IF(Main!B2,TEXT(EDATE(Main!B3,4)-1,"dd mmmm yyyy"),TEXT(Main!B3+((Main!B5-Main!B3)*4+3),"dd mmmm yyyy"))&" / "&" (Revenue / Deferred Debts Or Expenses)" -> 11 July 2025 - 10 August 2025 / (Revenue / Deferred Debts Or Expenses)
A9: Date | B9: Name | D9: Description | F9: Amount
F10: 0
F11: 0
F12: 0
F13: 0
F14: 0
F15: 0
D16: Total Revenue | F16: =SUM(F10:G15) -> 0
A20: =IF(Main!B2,TEXT(EDATE(Main!B3,4),"dd mmmm yyyy"),TEXT(Main!B3+((Main!B5-Main!B3)*4+4),"dd mmmm yyyy"))&" - "&IF(Main!B2,TEXT(EDATE(Main!B3,5)-1,"dd mmmm yyyy"),TEXT(Main!B3+((Main!B5-Main!B3)*5+4),"dd mmmm yyyy"))&" / "&" (Revenue / Deferred Debts Or Expenses)" -> 11 August 2025 - 10 September 2025 / (Revenue / Deferred Debts Or Expenses)
A21: Date | B21: Name | D21: Description | F21: Amount
F22: 0
F23: 0
F24: 0
F25: 0
F26: 0
F27: 0
D28: Total Revenue | F28: =SUM(F22:G27) -> 0
A32: =IF(Main!B2,TEXT(EDATE(Main!B3,5),"dd mmmm yyyy"),TEXT(Main!B3+((Main!B5-Main!B3)*5+5),"dd mmmm yyyy"))&" - "&IF(Main!B2,TEXT(EDATE(Main!B3,6)-1,"dd mmmm yyyy"),TEXT(Main!B3+((Main!B5-Main!B3)*6+5),"dd mmmm yyyy"))&" / "&" (Revenue / Deferred Debts Or Expenses)" -> 11 September 2025 - 10 October 2025 / (Revenue / Deferred Debts Or Expenses)
A33: Date | B33: Name | D33: Description | F33: Amount
F34: 0
F35: 0
F36: 0
F37: 0
F38: 0
F39: 0
D40: Total Revenue | F40: =SUM(F34:G39) -> 0
A44: ="Fixed Expense For the Year "&IF(Main!B2,TEXT(EDATE(Main!B3,3),"mmmm yyyy"),TEXT(Main!B3+((Main!B5-Main!B3)*3+3),"mmmm yyyy"))&" to "&IF(Main!B2,TEXT(EDATE(Main!B3,6)-1,"mmmm yyyy"),TEXT(Main!B3+((Main!B5-Main!B3)*6+5),"mmmm yyyy")) -> Fixed Expense For the Year July 2025 to October 2025
A45: Name | B45: Description | C45: Amount
A46: {=IF((INDIRECT("'"&INDIRECT("Main!B9")&"'!A60"))=0,"",(INDIRECT("'"&INDIRECT("Main!B9")&"'!A60")))} -> Mobile And Communications/ Housing Expenses
A47: {=IF((INDIRECT("'"&INDIRECT("Main!B9")&"'!A61"))=0,"",(INDIRECT("'"&INDIRECT("Main!B9")&"'!A61")))} | B47: {=IF((INDIRECT("'"&INDIRECT("Main!B9")&"'!B61"))=0,"",(INDIRECT("'"&INDIRECT("Main!B9")&"'!B61")))} | C47: 0
A48: {=IF((INDIRECT("'"&INDIRECT("Main!B9")&"'!A62"))=0,"",(INDIRECT("'"&INDIRECT("Main!B9")&"'!A62")))} | B48: {=IF((INDIRECT("'"&INDIRECT("Main!B9")&"'!B62"))=0,"",(INDIRECT("'"&INDIRECT("Main!B9")&"'!B62")))} | C48: 0
A49: {=IF((INDIRECT("'"&INDIRECT("Main!B9")&"'!A63"))=0,"",(INDIRECT("'"&INDIRECT("Main!B9")&"'!A63")))} | B49: {=IF((INDIRECT("'"&INDIRECT("Main!B9")&"'!B63"))=0,"",(INDIRECT("'"&INDIRECT("Main!B9")&"'!B63")))} | C49: 0
A50: {=IF((INDIRECT("'"&INDIRECT("Main!B9")&"'!A64"))=0,"",(INDIRECT("'"&INDIRECT("Main!B9")&"'!A64")))} | B50: {=IF((INDIRECT("'"&INDIRECT("Main!B9")&"'!B64"))=0,"",(INDIRECT("'"&INDIRECT("Main!B9")&"'!B64")))} | C50: 0
A51: {=IF((INDIRECT("'"&INDIRECT("Main!B9")&"'!A65"))=0,"",(INDIRECT("'"&INDIRECT("Main!B9")&"'!A65")))} | B51: {=IF((INDIRECT("'"&INDIRECT("Main!B9")&"'!B65"))=0,"",(INDIRECT("'"&INDIRECT("Main!B9")&"'!B65")))} | C51: 0
A52: {=IF((INDIRECT("'"&INDIRECT("Main!B9")&"'!A66"))=0,"",(INDIRECT("'"&INDIRECT("Main!B9")&"'!A66")))} | B52: {=IF((INDIRECT("'"&INDIRECT("Main!B9")&"'!B66"))=0,"",(INDIRECT("'"&INDIRECT("Main!B9")&"'!B66")))} | C52: 0
A53: {=IF((INDIRECT("'"&INDIRECT("Main!B9")&"'!A67"))=0,"",(INDIRECT("'"&INDIRECT("Main!B9")&"'!A67")))} | B53: {=IF((INDIRECT("'"&INDIRECT("Main!B9")&"'!B67"))=0,"",(INDIRECT("'"&INDIRECT("Main!B9")&"'!B67")))} | C53: 0
A54: {=IF((INDIRECT("'"&INDIRECT("Main!B9")&"'!A68"))=0,"",(INDIRECT("'"&INDIRECT("Main!B9")&"'!A68")))} | B54: {=IF((INDIRECT("'"&INDIRECT("Main!B9")&"'!B68"))=0,"",(INDIRECT("'"&INDIRECT("Main!B9")&"'!B68")))} | C54: 0
B55: Total Expenses | C55: =SUM(C47:C54) -> 0
A56: {=IF((INDIRECT("'"&INDIRECT("Main!B9")&"'!A70"))=0,"",(INDIRECT("'"&INDIRECT("Main!B9")&"'!A70")))} -> Credit Card Installments/Government Installments
A57: {=IF((INDIRECT("'"&INDIRECT("Main!B9")&"'!A71"))=0,"",(INDIRECT("'"&INDIRECT("Main!B9")&"'!A71")))} | B57: {=IF((INDIRECT("'"&INDIRECT("Main!B9")&"'!B71"))=0,"",(INDIRECT("'"&INDIRECT("Main!B9")&"'!B71")))} | C57: 0
A58: {=IF((INDIRECT("'"&INDIRECT("Main!B9")&"'!A72"))=0,"",(INDIRECT("'"&INDIRECT("Main!B9")&"'!A72")))} | B58: {=IF((INDIRECT("'"&INDIRECT("Main!B9")&"'!B72"))=0,"",(INDIRECT("'"&INDIRECT("Main!B9")&"'!B72")))} | C58: 0
A59: {=IF((INDIRECT("'"&INDIRECT("Main!B9")&"'!A73"))=0,"",(INDIRECT("'"&INDIRECT("Main!B9")&"'!A73")))} | B59: {=IF((INDIRECT("'"&INDIRECT("Main!B9")&"'!B73"))=0,"",(INDIRECT("'"&INDIRECT("Main!B9")&"'!B73")))} | C59: 0
A60: {=IF((INDIRECT("'"&INDIRECT("Main!B9")&"'!A74"))=0,"",(INDIRECT("'"&INDIRECT("Main!B9")&"'!A74")))} | B60: {=IF((INDIRECT("'"&INDIRECT("Main!B9")&"'!B74"))=0,"",(INDIRECT("'"&INDIRECT("Main!B9")&"'!B74")))} | C60: 0
A61: {=IF((INDIRECT("'"&INDIRECT("Main!B9")&"'!A75"))=0,"",(INDIRECT("'"&INDIRECT("Main!B9")&"'!A75")))} | B61: {=IF((INDIRECT("'"&INDIRECT("Main!B9")&"'!B75"))=0,"",(INDIRECT("'"&INDIRECT("Main!B9")&"'!B75")))} | C61: 0
A62: {=IF((INDIRECT("'"&INDIRECT("Main!B9")&"'!A76"))=0,"",(INDIRECT("'"&INDIRECT("Main!B9")&"'!A76")))} | B62: {=IF((INDIRECT("'"&INDIRECT("Main!B9")&"'!B76"))=0,"",(INDIRECT("'"&INDIRECT("Main!B9")&"'!B76")))} | C62: 0
A63: {=IF((INDIRECT("'"&INDIRECT("Main!B9")&"'!A77"))=0,"",(INDIRECT("'"&INDIRECT("Main!B9")&"'!A77")))} | B63: {=IF((INDIRECT("'"&INDIRECT("Main!B9")&"'!B77"))=0,"",(INDIRECT("'"&INDIRECT("Main!B9")&"'!B77")))} | C63: 0
A64: {=IF((INDIRECT("'"&INDIRECT("Main!B9")&"'!A78"))=0,"",(INDIRECT("'"&INDIRECT("Main!B9")&"'!A78")))} | B64: {=IF((INDIRECT("'"&INDIRECT("Main!B9")&"'!B78"))=0,"",(INDIRECT("'"&INDIRECT("Main!B9")&"'!B78")))} | C64: 0
A65: {=IF((INDIRECT("'"&INDIRECT("Main!B9")&"'!A79"))=0,"",(INDIRECT("'"&INDIRECT("Main!B9")&"'!A79")))} | B65: {=IF((INDIRECT("'"&INDIRECT("Main!B9")&"'!B79"))=0,"",(INDIRECT("'"&INDIRECT("Main!B9")&"'!B79")))} | C65: 0
B66: Total Expenses | C66: =SUM(C57:C65) -> 0
A67: {=IF((INDIRECT("'"&INDIRECT("Main!B9")&"'!A81"))=0,"",(INDIRECT("'"&INDIRECT("Main!B9")&"'!A81")))} -> Donation
A68: {=IF((INDIRECT("'"&INDIRECT("Main!B9")&"'!A82"))=0,"",(INDIRECT("'"&INDIRECT("Main!B9")&"'!A82")))} | B68: {=IF((INDIRECT("'"&INDIRECT("Main!B9")&"'!B82"))=0,"",(INDIRECT("'"&INDIRECT("Main!B9")&"'!B82")))} | C68: 0
A69: {=IF((INDIRECT("'"&INDIRECT("Main!B9")&"'!A83"))=0,"",(INDIRECT("'"&INDIRECT("Main!B9")&"'!A83")))} | B69: {=IF((INDIRECT("'"&INDIRECT("Main!B9")&"'!B83"))=0,"",(INDIRECT("'"&INDIRECT("Main!B9")&"'!B83")))} | C69: 0
A70: {=IF((INDIRECT("'"&INDIRECT("Main!B9")&"'!A84"))=0,"",(INDIRECT("'"&INDIRECT("Main!B9")&"'!A84")))} | B70: {=IF((INDIRECT("'"&INDIRECT("Main!B9")&"'!B84"))=0,"",(INDIRECT("'"&INDIRECT("Main!B9")&"'!B84")))} | C70: 0
A71: {=IF((INDIRECT("'"&INDIRECT("Main!B9")&"'!A85"))=0,"",(INDIRECT("'"&INDIRECT("Main!B9")&"'!A85")))} | B71: {=IF((INDIRECT("'"&INDIRECT("Main!B9")&"'!B85"))=0,"",(INDIRECT("'"&INDIRECT("Main!B9")&"'!B85")))} | C71: 0
A72: {=IF((INDIRECT("'"&INDIRECT("Main!B9")&"'!A86"))=0,"",(INDIRECT("'"&INDIRECT("Main!B9")&"'!A86")))} | B72: {=IF((INDIRECT("'"&INDIRECT("Main!B9")&"'!B86"))=0,"",(INDIRECT("'"&INDIRECT("Main!B9")&"'!B86")))} | C72: 0
A73: {=IF((INDIRECT("'"&INDIRECT("Main!B9")&"'!A87"))=0,"",(INDIRECT("'"&INDIRECT("Main!B9")&"'!A87")))} | B73: {=IF((INDIRECT("'"&INDIRECT("Main!B9")&"'!B87"))=0,"",(INDIRECT("'"&INDIRECT("Main!B9")&"'!B87")))} | C73: 0
A74: {=IF((INDIRECT("'"&INDIRECT("Main!B9")&"'!A88"))=0,"",(INDIRECT("'"&INDIRECT("Main!B9")&"'!A88")))} | B74: {=IF((INDIRECT("'"&INDIRECT("Main!B9")&"'!B88"))=0,"",(INDIRECT("'"&INDIRECT("Main!B9")&"'!B88")))} | C74: 0
B75: Total Expenses | C75: =SUM(C68:C74) -> 0
A76: {=IF((INDIRECT("'"&INDIRECT("Main!B9")&"'!A90"))=0,"",(INDIRECT("'"&INDIRECT("Main!B9")&"'!A90")))} -> Insurance (Personal / Properties / Medical)
A77: {=IF((INDIRECT("'"&INDIRECT("Main!B9")&"'!A91"))=0,"",(INDIRECT("'"&INDIRECT("Main!B9")&"'!A91")))} | B77: {=IF((INDIRECT("'"&INDIRECT("Main!B9")&"'!B91"))=0,"",(INDIRECT("'"&INDIRECT("Main!B9")&"'!B91")))} | C77: 0
A78: {=IF((INDIRECT("'"&INDIRECT("Main!B9")&"'!A92"))=0,"",(INDIRECT("'"&INDIRECT("Main!B9")&"'!A92")))} | B78: {=IF((INDIRECT("'"&INDIRECT("Main!B9")&"'!B92"))=0,"",(INDIRECT("'"&INDIRECT("Main!B9")&"'!B92")))} | C78: 0
A79: {=IF((INDIRECT("'"&INDIRECT("Main!B9")&"'!A93"))=0,"",(INDIRECT("'"&INDIRECT("Main!B9")&"'!A93")))} | B79: {=IF((INDIRECT("'"&INDIRECT("Main!B9")&"'!B93"))=0,"",(INDIRECT("'"&INDIRECT("Main!B9")&"'!B93")))} | C79: 0
A80: {=IF((INDIRECT("'"&INDIRECT("Main!B9")&"'!A94"))=0,"",(INDIRECT("'"&INDIRECT("Main!B9")&"'!A94")))} | B80: {=IF((INDIRECT("'"&INDIRECT("Main!B9")&"'!B94"))=0,"",(INDIRECT("'"&INDIRECT("Main!B9")&"'!B94")))} | C80: 0
A81: {=IF((INDIRECT("'"&INDIRECT("Main!B9")&"'!A95"))=0,"",(INDIRECT("'"&INDIRECT("Main!B9")&"'!A95")))} | B81: {=IF((INDIRECT("'"&INDIRECT("Main!B9")&"'!B95"))=0,"",(INDIRECT("'"&INDIRECT("Main!B9")&"'!B95")))} | C81: 0
A82: {=IF((INDIRECT("'"&INDIRECT("Main!B9")&"'!A96"))=0,"",(INDIRECT("'"&INDIRECT("Main!B9")&"'!A96")))} | B82: {=IF((INDIRECT("'"&INDIRECT("Main!B9")&"'!B96"))=0,"",(INDIRECT("'"&INDIRECT("Main!B9")&"'!B96")))} | C82: 0
A83: {=IF((INDIRECT("'"&INDIRECT("Main!B9")&"'!A97"))=0,"",(INDIRECT("'"&INDIRECT("Main!B9")&"'!A97")))} | B83: {=IF((INDIRECT("'"&INDIRECT("Main!B9")&"'!B97"))=0,"",(INDIRECT("'"&INDIRECT("Main!B9")&"'!B97")))} | C83: 0
A84: {=IF((INDIRECT("'"&INDIRECT("Main!B9")&"'!A98"))=0,"",(INDIRECT("'"&INDIRECT("Main!B9")&"'!A98")))} | B84: {=IF((INDIRECT("'"&INDIRECT("Main!B9")&"'!B98"))=0,"",(INDIRECT("'"&INDIRECT("Main!B9")&"'!B98")))} | C84: 0
B85: Total Expenses | C85: =SUM(C77:C84) -> 0
A86: {=IF((INDIRECT("'"&INDIRECT("Main!B9")&"'!A100"))=0,"",(INDIRECT("'"&INDIRECT("Main!B9")&"'!A100")))} -> Other Expenses
A87: {=IF((INDIRECT("'"&INDIRECT("Main!B9")&"'!A101"))=0,"",(INDIRECT("'"&INDIRECT("Main!B9")&"'!A101")))} | B87: {=IF((INDIRECT("'"&INDIRECT("Main!B9")&"'!B101"))=0,"",(INDIRECT("'"&INDIRECT("Main!B9")&"'!B101")))} | C87: 0
A88: {=IF((INDIRECT("'"&INDIRECT("Main!B9")&"'!A102"))=0,"",(INDIRECT("'"&INDIRECT("Main!B9")&"'!A102")))} | B88: {=IF((INDIRECT("'"&INDIRECT("Main!B9")&"'!B102"))=0,"",(INDIRECT("'"&INDIRECT("Main!B9")&"'!B102")))} | C88: 0
A89: {=IF((INDIRECT("'"&INDIRECT("Main!B9")&"'!A103"))=0,"",(INDIRECT("'"&INDIRECT("Main!B9")&"'!A103")))} | B89: {=IF((INDIRECT("'"&INDIRECT("Main!B9")&"'!B103"))=0,"",(INDIRECT("'"&INDIRECT("Main!B9")&"'!B103")))} | C89: 0
A90: {=IF((INDIRECT("'"&INDIRECT("Main!B9")&"'!A104"))=0,"",(INDIRECT("'"&INDIRECT("Main!B9")&"'!A104")))} | B90: {=IF((INDIRECT("'"&INDIRECT("Main!B9")&"'!B104"))=0,"",(INDIRECT("'"&INDIRECT("Main!B9")&"'!B104")))} | C90: 0
A91: {=IF((INDIRECT("'"&INDIRECT("Main!B9")&"'!A105"))=0,"",(INDIRECT("'"&INDIRECT("Main!B9")&"'!A105")))} | B91: {=IF((INDIRECT("'"&INDIRECT("Main!B9")&"'!B105"))=0,"",(INDIRECT("'"&INDIRECT("Main!B9")&"'!B105")))} | C91: 0
A92: {=IF((INDIRECT("'"&INDIRECT("Main!B9")&"'!A106"))=0,"",(INDIRECT("'"&INDIRECT("Main!B9")&"'!A106")))} | B92: {=IF((INDIRECT("'"&INDIRECT("Main!B9")&"'!B106"))=0,"",(INDIRECT("'"&INDIRECT("Main!B9")&"'!B106")))} | C92: 0
A93: {=IF((INDIRECT("'"&INDIRECT("Main!B9")&"'!A107"))=0,"",(INDIRECT("'"&INDIRECT("Main!B9")&"'!A107")))} | B93: {=IF((INDIRECT("'"&INDIRECT("Main!B9")&"'!B107"))=0,"",(INDIRECT("'"&INDIRECT("Main!B9")&"'!B107")))} | C93: 0
A94: {=IF((INDIRECT("'"&INDIRECT("Main!B9")&"'!A108"))=0,"",(INDIRECT("'"&INDIRECT("Main!B9")&"'!A108")))} | B94: {=IF((INDIRECT("'"&INDIRECT("Main!B9")&"'!B108"))=0,"",(INDIRECT("'"&INDIRECT("Main!B9")&"'!B108")))} | C94: 0
B95: Total Expenses | C95: =SUM(C87:C94) -> 0
B96: Grand Expenses Total | C96: =C55+C66+C75+C85+C95 -> 0
A97: {=IF((INDIRECT("'"&INDIRECT("Main!B9")&"'!A111"))=0,"",(INDIRECT("'"&INDIRECT("Main!B9")&"'!A111")))} -> Debts / Borrowed To
A98: {=IF((INDIRECT("'"&INDIRECT("Main!B9")&"'!A112"))=0,"",(INDIRECT("'"&INDIRECT("Main!B9")&"'!A112")))} | B98: {=IF((INDIRECT("'"&INDIRECT("Main!B9")&"'!B112"))=0,"",(INDIRECT("'"&INDIRECT("Main!B9")&"'!B112")))} | C98: {=(((INDIRECT("'"&INDIRECT("Main!B9")&"'!E131")+INDIRECT("'"&INDIRECT("Main!B9")&"'!E158")+INDIRECT("'"&INDIRECT("Main!B9")&"'!E185")))+SUM(E118+E145+E172))-INDIRECT("'"&INDIRECT("Main!B9")&"'!C112")} -> 0
A99: {=IF((INDIRECT("'"&INDIRECT("Main!B9")&"'!A113"))=0,"",(INDIRECT("'"&INDIRECT("Main!B9")&"'!A113")))} | B99: {=IF((INDIRECT("'"&INDIRECT("Main!B9")&"'!B113"))=0,"",(INDIRECT("'"&INDIRECT("Main!B9")&"'!B113")))} | C99: {=(((INDIRECT("'"&INDIRECT("Main!B9")&"'!E132")+INDIRECT("'"&INDIRECT("Main!B9")&"'!E159")+INDIRECT("'"&INDIRECT("Main!B9")&"'!E186")))+SUM(E119+E146+E173))-INDIRECT("'"&INDIRECT("Main!B9")&"'!C113")} -> 0
A100: {=IF((INDIRECT("'"&INDIRECT("Main!B9")&"'!A114"))=0,"",(INDIRECT("'"&INDIRECT("Main!B9")&"'!A114")))} | B100: {=IF((INDIRECT("'"&INDIRECT("Main!B9")&"'!B114"))=0,"",(INDIRECT("'"&INDIRECT("Main!B9")&"'!B114")))} | C100: {=(((INDIRECT("'"&INDIRECT("Main!B9")&"'!E133")+INDIRECT("'"&INDIRECT("Main!B9")&"'!E160")+INDIRECT("'"&INDIRECT("Main!B9")&"'!E187")))+SUM(E120+E147+E174))-INDIRECT("'"&INDIRECT("Main!B9")&"'!C114")} -> 0
A101: {=IF((INDIRECT("'"&INDIRECT("Main!B9")&"'!A115"))=0,"",(INDIRECT("'"&INDIRECT("Main!B9")&"'!A115")))} | B101: {=IF((INDIRECT("'"&INDIRECT("Main!B9")&"'!B115"))=0,"",(INDIRECT("'"&INDIRECT("Main!B9")&"'!B115")))} | C101: {=(((INDIRECT("'"&INDIRECT("Main!B9")&"'!E134")+INDIRECT("'"&INDIRECT("Main!B9")&"'!E161")+INDIRECT("'"&INDIRECT("Main!B9")&"'!E188")))+SUM(E121+E148+E175))-INDIRECT("'"&INDIRECT("Main!B9")&"'!C115")} -> 0
A102: {=IF((INDIRECT("'"&INDIRECT("Main!B9")&"'!A116"))=0,"",(INDIRECT("'"&INDIRECT("Main!B9")&"'!A116")))} | B102: {=IF((INDIRECT("'"&INDIRECT("Main!B9")&"'!B116"))=0,"",(INDIRECT("'"&INDIRECT("Main!B9")&"'!B116")))} | C102: {=(((INDIRECT("'"&INDIRECT("Main!B9")&"'!E135")+INDIRECT("'"&INDIRECT("Main!B9")&"'!E162")+INDIRECT("'"&INDIRECT("Main!B9")&"'!E189")))+SUM(E122+E149+E176))-INDIRECT("'"&INDIRECT("Main!B9")&"'!C116")} -> 0
A103: {=IF((INDIRECT("'"&INDIRECT("Main!B9")&"'!A117"))=0,"",(INDIRECT("'"&INDIRECT("Main!B9")&"'!A117")))} | B103: {=IF((INDIRECT("'"&INDIRECT("Main!B9")&"'!B117"))=0,"",(INDIRECT("'"&INDIRECT("Main!B9")&"'!B117")))} | C103: {=(((INDIRECT("'"&INDIRECT("Main!B9")&"'!E136")+INDIRECT("'"&INDIRECT("Main!B9")&"'!E163")+INDIRECT("'"&INDIRECT("Main!B9")&"'!E190")))+SUM(EE123+E150+E177)-INDIRECT("'"&INDIRECT("Main!B9")&"'!C117"))} -> 0
A104: {=IF((INDIRECT("'"&INDIRECT("Main!B9")&"'!A118"))=0,"",(INDIRECT("'"&INDIRECT("Main!B9")&"'!A118")))} | B104: {=IF((INDIRECT("'"&INDIRECT("Main!B9")&"'!B118"))=0,"",(INDIRECT("'"&INDIRECT("Main!B9")&"'!B118")))} | C104: {=(((INDIRECT("'"&INDIRECT("Main!B9")&"'!E137")+INDIRECT("'"&INDIRECT("Main!B9")&"'!E164")+INDIRECT("'"&INDIRECT("Main!B9")&"'!E191")))+SUM(E124+E151+E178))-INDIRECT("'"&INDIRECT("Main!B9")&"'!C118")} -> 0
A105: {=IF((INDIRECT("'"&INDIRECT("Main!B9")&"'!A119"))=0,"",(INDIRECT("'"&INDIRECT("Main!B9")&"'!A119")))} | B105: {=IF((INDIRECT("'"&INDIRECT("Main!B9")&"'!B119"))=0,"",(INDIRECT("'"&INDIRECT("Main!B9")&"'!B119")))} | C105: {=(((INDIRECT("'"&INDIRECT("Main!B9")&"'!E138")+INDIRECT("'"&INDIRECT("Main!B9")&"'!E165")+INDIRECT("'"&INDIRECT("Main!B9")&"'!E192")))+SUM(E125+E152+E179)-INDIRECT("'"&INDIRECT("Main!B9")&"'!C119"))} -> 0
A106: {=IF((INDIRECT("'"&INDIRECT("Main!B9")&"'!A120"))=0,"",(INDIRECT("'"&INDIRECT("Main!B9")&"'!A120")))} | B106: {=IF((INDIRECT("'"&INDIRECT("Main!B9")&"'!B120"))=0,"",(INDIRECT("'"&INDIRECT("Main!B9")&"'!B120")))} | C106: {=(((INDIRECT("'"&INDIRECT("Main!B9")&"'!E139")+INDIRECT("'"&INDIRECT("Main!B9")&"'!E166")+INDIRECT("'"&INDIRECT("Main!B9")&"'!E193")))+SUM(E126+E153+E180))-INDIRECT("'"&INDIRECT("Main!B9")&"'!C120")} -> 0
A107: {=IF((INDIRECT("'"&INDIRECT("Main!B9")&"'!A121"))=0,"",(INDIRECT("'"&INDIRECT("Main!B9")&"'!A121")))} | B107: {=IF((INDIRECT("'"&INDIRECT("Main!B9")&"'!B121"))=0,"",(INDIRECT("'"&INDIRECT("Main!B9")&"'!B121")))} | C107: {=(((INDIRECT("'"&INDIRECT("Main!B9")&"'!E140")+INDIRECT("'"&INDIRECT("Main!B9")&"'!E167")+INDIRECT("'"&INDIRECT("Main!B9")&"'!E194")))+SUM(E127+E154+E181))-INDIRECT("'"&INDIRECT("Main!B9")&"'!C121")} -> 0
B108: Total Debts | C108: =SUM(C98:C107) -> 0
B109: Grand Total | C109: =C108-C96 -> 0
A114: ="Debts Or Credits For the Comming "&IF(Main!B2,TEXT(EDATE(Main!B3,3),"mmmm dd yyyy"),TEXT(Main!B3+((Main!B5-Main!B3)*3+3),"mmmm dd yyyy"))&" to "&IF(Main!B2,TEXT(EDATE(Main!B3,4)-1,"mmmm dd yyyy"),TEXT(Main!B3+((Main!B5-Main!B3)*4+3),"mmmm dd yyyy")) -> Debts Or Credits For the Comming July 11 2025 to August 10 2025
A115: Principal | C115: Description | E115: Amount
...

Sheet Forecast_3
A1: ="Forecasts For the Year "&IF(Main!B2,TEXT(EDATE(Main!B3,6),"mmmm yyyy"),TEXT(Main!B3+((Main!B5-Main!B3)*6+6),"mmmm yyyy"))&" to "&IF(Main!B2,TEXT(EDATE(Main!B3,9)-1,"mmmm yyyy"),TEXT(Main!B3+((Main!B5-Main!B3)*9+8),"mmmm yyyy")) -> Forecasts For the Year October 2025 to January 2026
A2: Assets | B2: Overall | C2: {=INDIRECT("'"&Main!B9&"'!$C$16")} -> 0
B3: Forecasts | C3: =E190 -> 0
A4: Total | C4: =SUM(C2:G3) -> 0
A5: Net Debts: | C5: =C108 -> 0
A8: =IF(Main!B2,TEXT(EDATE(Main!B3,6),"dd mmmm yyyy"),TEXT(Main!B3+((Main!B5-Main!B3)*6+6),"dd mmmm yyyy"))&" - "&IF(Main!B2,TEXT(EDATE(Main!B3,7)-1,"dd mmmm yyyy"),TEXT(Main!B3+((Main!B5-Main!B3)*7+6),"dd mmmm yyyy"))&" / "&" (Revenue / Deferred Debts Or Expenses)" -> 11 October 2025 - 10 November 2025 / (Revenue / Deferred Debts Or Expenses)
A9: Date | B9: Name | D9: Description | F9: Amount
F10: 0
F11: 0
F12: 0
F13: 0
F14: 0
F15: 0
D16: Total Revenue | F16: =SUM(F10:G15) -> 0
A20: =IF(Main!B2,TEXT(EDATE(Main!B3,7),"dd mmmm yyyy"),TEXT(Main!B3+((Main!B5-Main!B3)*7+7),"dd mmmm yyyy"))&" - "&IF(Main!B2,TEXT(EDATE(Main!B3,8)-1,"dd mmmm yyyy"),TEXT(Main!B3+((Main!B5-Main!B3)*8+7),"dd mmmm yyyy"))&" / "&" (Revenue / Deferred Debts Or Expenses)" -> 11 November 2025 - 10 December 2025 / (Revenue / Deferred Debts Or Expenses)
A21: Date | B21: Name | D21: Description | F21: Amount
F22: 0
F23: 0
F24: 0
F25: 0
F26: 0
F27: 0
D28: Total Revenue | F28: =SUM(F22:G27) -> 0
A32: =IF(Main!B2,TEXT(EDATE(Main!B3,8),"dd mmmm yyyy"),TEXT(Main!B3+((Main!B5-Main!B3)*8+8),"dd mmmm yyyy"))&" - "&IF(Main!B2,TEXT(EDATE(Main!B3,9)-1,"dd mmmm yyyy"),TEXT(Main!B3+((Main!B5-Main!B3)*9+8),"dd mmmm yyyy"))&" / "&" (Revenue / Deferred Debts Or Expenses)" -> 11 December 2025 - 10 January 2026 / (Revenue / Deferred Debts Or Expenses)
A33: Date | B33: Name | D33: Description | F33: Amount
F34: 0
F35: 0
F36: 0
F37: 0
F38: 0
F39: 0
D40: Total Revenue | F40: =SUM(F34:G39) -> 0
A44: ="Fixed Expense For the Year "&IF(Main!B2,TEXT(EDATE(Main!B3,6),"mmmm yyyy"),TEXT(Main!B3+((Main!B5-Main!B3)*6+6),"mmmm yyyy"))&" to "&IF(Main!B2,TEXT(EDATE(Main!B3,9)-1,"mmmm yyyy"),TEXT(Main!B3+((Main!B5-Main!B3)*9+8),"mmmm yyyy")) -> Fixed Expense For the Year October 2025 to January 2026
A45: Name | B45: Description | C45: Amount
A46: {=IF((INDIRECT("'"&INDIRECT("Main!B9")&"'!A60"))=0,"",(INDIRECT("'"&INDIRECT("Main!B9")&"'!A60")))} -> Mobile And Communications/ Housing Expenses
A47: {=IF((INDIRECT("'"&INDIRECT("Main!B9")&"'!A61"))=0,"",(INDIRECT("'"&INDIRECT("Main!B9")&"'!A61")))} | B47: {=IF((INDIRECT("'"&INDIRECT("Main!B9")&"'!B61"))=0,"",(INDIRECT("'"&INDIRECT("Main!B9")&"'!B61")))} | C47: 0
A48: {=IF((INDIRECT("'"&INDIRECT("Main!B9")&"'!A62"))=0,"",(INDIRECT("'"&INDIRECT("Main!B9")&"'!A62")))} | B48: {=IF((INDIRECT("'"&INDIRECT("Main!B9")&"'!B62"))=0,"",(INDIRECT("'"&INDIRECT("Main!B9")&"'!B62")))} | C48: 0
A49: {=IF((INDIRECT("'"&INDIRECT("Main!B9")&"'!A63"))=0,"",(INDIRECT("'"&INDIRECT("Main!B9")&"'!A63")))} | B49: {=IF((INDIRECT("'"&INDIRECT("Main!B9")&"'!B63"))=0,"",(INDIRECT("'"&INDIRECT("Main!B9")&"'!B63")))} | C49: 0
A50: {=IF((INDIRECT("'"&INDIRECT("Main!B9")&"'!A64"))=0,"",(INDIRECT("'"&INDIRECT("Main!B9")&"'!A64")))} | B50: {=IF((INDIRECT("'"&INDIRECT("Main!B9")&"'!B64"))=0,"",(INDIRECT("'"&INDIRECT("Main!B9")&"'!B64")))} | C50: 0
A51: {=IF((INDIRECT("'"&INDIRECT("Main!B9")&"'!A65"))=0,"",(INDIRECT("'"&INDIRECT("Main!B9")&"'!A65")))} | B51: {=IF((INDIRECT("'"&INDIRECT("Main!B9")&"'!B65"))=0,"",(INDIRECT("'"&INDIRECT("Main!B9")&"'!B65")))} | C51: 0
A52: {=IF((INDIRECT("'"&INDIRECT("Main!B9")&"'!A66"))=0,"",(INDIRECT("'"&INDIRECT("Main!B9")&"'!A66")))} | B52: {=IF((INDIRECT("'"&INDIRECT("Main!B9")&"'!B66"))=0,"",(INDIRECT("'"&INDIRECT("Main!B9")&"'!B66")))} | C52: 0
A53: {=IF((INDIRECT("'"&INDIRECT("Main!B9")&"'!A67"))=0,"",(INDIRECT("'"&INDIRECT("Main!B9")&"'!A67")))} | B53: {=IF((INDIRECT("'"&INDIRECT("Main!B9")&"'!B67"))=0,"",(INDIRECT("'"&INDIRECT("Main!B9")&"'!B67")))} | C53: 0
A54: {=IF((INDIRECT("'"&INDIRECT("Main!B9")&"'!A68"))=0,"",(INDIRECT("'"&INDIRECT("Main!B9")&"'!A68")))} | B54: {=IF((INDIRECT("'"&INDIRECT("Main!B9")&"'!B68"))=0,"",(INDIRECT("'"&INDIRECT("Main!B9")&"'!B68")))} | C54: 0
B55: Total Expenses | C55: =SUM(C47:C54) -> 0
A56: {=IF((INDIRECT("'"&INDIRECT("Main!B9")&"'!A70"))=0,"",(INDIRECT("'"&INDIRECT("Main!B9")&"'!A70")))} -> Credit Card Installments/Government Installments
A57: {=IF((INDIRECT("'"&INDIRECT("Main!B9")&"'!A71"))=0,"",(INDIRECT("'"&INDIRECT("Main!B9")&"'!A71")))} | B57: {=IF((INDIRECT("'"&INDIRECT("Main!B9")&"'!B71"))=0,"",(INDIRECT("'"&INDIRECT("Main!B9")&"'!B71")))} | C57: 0
A58: {=IF((INDIRECT("'"&INDIRECT("Main!B9")&"'!A72"))=0,"",(INDIRECT("'"&INDIRECT("Main!B9")&"'!A72")))} | B58: {=IF((INDIRECT("'"&INDIRECT("Main!B9")&"'!B72"))=0,"",(INDIRECT("'"&INDIRECT("Main!B9")&"'!B72")))} | C58: 0
A59: {=IF((INDIRECT("'"&INDIRECT("Main!B9")&"'!A73"))=0,"",(INDIRECT("'"&INDIRECT("Main!B9")&"'!A73")))} | B59: {=IF((INDIRECT("'"&INDIRECT("Main!B9")&"'!B73"))=0,"",(INDIRECT("'"&INDIRECT("Main!B9")&"'!B73")))} | C59: 0
A60: {=IF((INDIRECT("'"&INDIRECT("Main!B9")&"'!A74"))=0,"",(INDIRECT("'"&INDIRECT("Main!B9")&"'!A74")))} | B60: {=IF((INDIRECT("'"&INDIRECT("Main!B9")&"'!B74"))=0,"",(INDIRECT("'"&INDIRECT("Main!B9")&"'!B74")))} | C60: 0
A61: {=IF((INDIRECT("'"&INDIRECT("Main!B9")&"'!A75"))=0,"",(INDIRECT("'"&INDIRECT("Main!B9")&"'!A75")))} | B61: {=IF((INDIRECT("'"&INDIRECT("Main!B9")&"'!B75"))=0,"",(INDIRECT("'"&INDIRECT("Main!B9")&"'!B75")))} | C61: 0
A62: {=IF((INDIRECT("'"&INDIRECT("Main!B9")&"'!A76"))=0,"",(INDIRECT("'"&INDIRECT("Main!B9")&"'!A76")))} | B62: {=IF((INDIRECT("'"&INDIRECT("Main!B9")&"'!B76"))=0,"",(INDIRECT("'"&INDIRECT("Main!B9")&"'!B76")))} | C62: 0
A63: {=IF((INDIRECT("'"&INDIRECT("Main!B9")&"'!A77"))=0,"",(INDIRECT("'"&INDIRECT("Main!B9")&"'!A77")))} | B63: {=IF((INDIRECT("'"&INDIRECT("Main!B9")&"'!B77"))=0,"",(INDIRECT("'"&INDIRECT("Main!B9")&"'!B77")))} | C63: 0
A64: {=IF((INDIRECT("'"&INDIRECT("Main!B9")&"'!A78"))=0,"",(INDIRECT("'"&INDIRECT("Main!B9")&"'!A78")))} | B64: {=IF((INDIRECT("'"&INDIRECT("Main!B9")&"'!B78"))=0,"",(INDIRECT("'"&INDIRECT("Main!B9")&"'!B78")))} | C64: 0
A65: {=IF((INDIRECT("'"&INDIRECT("Main!B9")&"'!A79"))=0,"",(INDIRECT("'"&INDIRECT("Main!B9")&"'!A79")))} | B65: {=IF((INDIRECT("'"&INDIRECT("Main!B9")&"'!B79"))=0,"",(INDIRECT("'"&INDIRECT("Main!B9")&"'!B79")))} | C65: 0
B66: Total Expenses | C66: =SUM(C57:C65) -> 0
A67: {=IF((INDIRECT("'"&INDIRECT("Main!B9")&"'!A81"))=0,"",(INDIRECT("'"&INDIRECT("Main!B9")&"'!A81")))} -> Donation
A68: {=IF((INDIRECT("'"&INDIRECT("Main!B9")&"'!A82"))=0,"",(INDIRECT("'"&INDIRECT("Main!B9")&"'!A82")))} | B68: {=IF((INDIRECT("'"&INDIRECT("Main!B9")&"'!B82"))=0,"",(INDIRECT("'"&INDIRECT("Main!B9")&"'!B82")))} | C68: 0
A69: {=IF((INDIRECT("'"&INDIRECT("Main!B9")&"'!A83"))=0,"",(INDIRECT("'"&INDIRECT("Main!B9")&"'!A83")))} | B69: {=IF((INDIRECT("'"&INDIRECT("Main!B9")&"'!B83"))=0,"",(INDIRECT("'"&INDIRECT("Main!B9")&"'!B83")))} | C69: 0
A70: {=IF((INDIRECT("'"&INDIRECT("Main!B9")&"'!A84"))=0,"",(INDIRECT("'"&INDIRECT("Main!B9")&"'!A84")))} | B70: {=IF((INDIRECT("'"&INDIRECT("Main!B9")&"'!B84"))=0,"",(INDIRECT("'"&INDIRECT("Main!B9")&"'!B84")))} | C70: 0
A71: {=IF((INDIRECT("'"&INDIRECT("Main!B9")&"'!A85"))=0,"",(INDIRECT("'"&INDIRECT("Main!B9")&"'!A85")))} | B71: {=IF((INDIRECT("'"&INDIRECT("Main!B9")&"'!B85"))=0,"",(INDIRECT("'"&INDIRECT("Main!B9")&"'!B85")))} | C71: 0
A72: {=IF((INDIRECT("'"&INDIRECT("Main!B9")&"'!A86"))=0,"",(INDIRECT("'"&INDIRECT("Main!B9")&"'!A86")))} | B72: {=IF((INDIRECT("'"&INDIRECT("Main!B9")&"'!B86"))=0,"",(INDIRECT("'"&INDIRECT("Main!B9")&"'!B86")))} | C72: 0
A73: {=IF((INDIRECT("'"&INDIRECT("Main!B9")&"'!A87"))=0,"",(INDIRECT("'"&INDIRECT("Main!B9")&"'!A87")))} | B73: {=IF((INDIRECT("'"&INDIRECT("Main!B9")&"'!B87"))=0,"",(INDIRECT("'"&INDIRECT("Main!B9")&"'!B87")))} | C73: 0
A74: {=IF((INDIRECT("'"&INDIRECT("Main!B9")&"'!A88"))=0,"",(INDIRECT("'"&INDIRECT("Main!B9")&"'!A88")))} | B74: {=IF((INDIRECT("'"&INDIRECT("Main!B9")&"'!B88"))=0,"",(INDIRECT("'"&INDIRECT("Main!B9")&"'!B88")))} | C74: 0
B75: Total Expenses | C75: =SUM(C68:C74) -> 0
A76: {=IF((INDIRECT("'"&INDIRECT("Main!B9")&"'!A90"))=0,"",(INDIRECT("'"&INDIRECT("Main!B9")&"'!A90")))} -> Insurance (Personal / Properties / Medical)
A77: {=IF((INDIRECT("'"&INDIRECT("Main!B9")&"'!A91"))=0,"",(INDIRECT("'"&INDIRECT("Main!B9")&"'!A91")))} | B77: {=IF((INDIRECT("'"&INDIRECT("Main!B9")&"'!B91"))=0,"",(INDIRECT("'"&INDIRECT("Main!B9")&"'!B91")))} | C77: 0
A78: {=IF((INDIRECT("'"&INDIRECT("Main!B9")&"'!A92"))=0,"",(INDIRECT("'"&INDIRECT("Main!B9")&"'!A92")))} | B78: {=IF((INDIRECT("'"&INDIRECT("Main!B9")&"'!B92"))=0,"",(INDIRECT("'"&INDIRECT("Main!B9")&"'!B92")))} | C78: 0
A79: {=IF((INDIRECT("'"&INDIRECT("Main!B9")&"'!A93"))=0,"",(INDIRECT("'"&INDIRECT("Main!B9")&"'!A93")))} | B79: {=IF((INDIRECT("'"&INDIRECT("Main!B9")&"'!B93"))=0,"",(INDIRECT("'"&INDIRECT("Main!B9")&"'!B93")))} | C79: 0
A80: {=IF((INDIRECT("'"&INDIRECT("Main!B9")&"'!A94"))=0,"",(INDIRECT("'"&INDIRECT("Main!B9")&"'!A94")))} | B80: {=IF((INDIRECT("'"&INDIRECT("Main!B9")&"'!B94"))=0,"",(INDIRECT("'"&INDIRECT("Main!B9")&"'!B94")))} | C80: 0
A81: {=IF((INDIRECT("'"&INDIRECT("Main!B9")&"'!A95"))=0,"",(INDIRECT("'"&INDIRECT("Main!B9")&"'!A95")))} | B81: {=IF((INDIRECT("'"&INDIRECT("Main!B9")&"'!B95"))=0,"",(INDIRECT("'"&INDIRECT("Main!B9")&"'!B95")))} | C81: 0
A82: {=IF((INDIRECT("'"&INDIRECT("Main!B9")&"'!A96"))=0,"",(INDIRECT("'"&INDIRECT("Main!B9")&"'!A96")))} | B82: {=IF((INDIRECT("'"&INDIRECT("Main!B9")&"'!B96"))=0,"",(INDIRECT("'"&INDIRECT("Main!B9")&"'!B96")))} | C82: 0
A83: {=IF((INDIRECT("'"&INDIRECT("Main!B9")&"'!A97"))=0,"",(INDIRECT("'"&INDIRECT("Main!B9")&"'!A97")))} | B83: {=IF((INDIRECT("'"&INDIRECT("Main!B9")&"'!B97"))=0,"",(INDIRECT("'"&INDIRECT("Main!B9")&"'!B97")))} | C83: 0
A84: {=IF((INDIRECT("'"&INDIRECT("Main!B9")&"'!A98"))=0,"",(INDIRECT("'"&INDIRECT("Main!B9")&"'!A98")))} | B84: {=IF((INDIRECT("'"&INDIRECT("Main!B9")&"'!B98"))=0,"",(INDIRECT("'"&INDIRECT("Main!B9")&"'!B98")))} | C84: 0
B85: Total Expenses | C85: =SUM(C77:C84) -> 0
A86: {=IF((INDIRECT("'"&INDIRECT("Main!B9")&"'!A100"))=0,"",(INDIRECT("'"&INDIRECT("Main!B9")&"'!A100")))} -> Other Expenses
A87: {=IF((INDIRECT("'"&INDIRECT("Main!B9")&"'!A101"))=0,"",(INDIRECT("'"&INDIRECT("Main!B9")&"'!A101")))} | B87: {=IF((INDIRECT("'"&INDIRECT("Main!B9")&"'!B101"))=0,"",(INDIRECT("'"&INDIRECT("Main!B9")&"'!B101")))} | C87: 0
A88: {=IF((INDIRECT("'"&INDIRECT("Main!B9")&"'!A102"))=0,"",(INDIRECT("'"&INDIRECT("Main!B9")&"'!A102")))} | B88: {=IF((INDIRECT("'"&INDIRECT("Main!B9")&"'!B102"))=0,"",(INDIRECT("'"&INDIRECT("Main!B9")&"'!B102")))} | C88: 0
A89: {=IF((INDIRECT("'"&INDIRECT("Main!B9")&"'!A103"))=0,"",(INDIRECT("'"&INDIRECT("Main!B9")&"'!A103")))} | B89: {=IF((INDIRECT("'"&INDIRECT("Main!B9")&"'!B103"))=0,"",(INDIRECT("'"&INDIRECT("Main!B9")&"'!B103")))} | C89: 0
A90: {=IF((INDIRECT("'"&INDIRECT("Main!B9")&"'!A104"))=0,"",(INDIRECT("'"&INDIRECT("Main!B9")&"'!A104")))} | B90: {=IF((INDIRECT("'"&INDIRECT("Main!B9")&"'!B104"))=0,"",(INDIRECT("'"&INDIRECT("Main!B9")&"'!B104")))} | C90: 0
A91: {=IF((INDIRECT("'"&INDIRECT("Main!B9")&"'!A105"))=0,"",(INDIRECT("'"&INDIRECT("Main!B9")&"'!A105")))} | B91: {=IF((INDIRECT("'"&INDIRECT("Main!B9")&"'!B105"))=0,"",(INDIRECT("'"&INDIRECT("Main!B9")&"'!B105")))} | C91: 0
A92: {=IF((INDIRECT("'"&INDIRECT("Main!B9")&"'!A106"))=0,"",(INDIRECT("'"&INDIRECT("Main!B9")&"'!A106")))} | B92: {=IF((INDIRECT("'"&INDIRECT("Main!B9")&"'!B106"))=0,"",(INDIRECT("'"&INDIRECT("Main!B9")&"'!B106")))} | C92: 0
A93: {=IF((INDIRECT("'"&INDIRECT("Main!B9")&"'!A107"))=0,"",(INDIRECT("'"&INDIRECT("Main!B9")&"'!A107")))} | B93: {=IF((INDIRECT("'"&INDIRECT("Main!B9")&"'!B107"))=0,"",(INDIRECT("'"&INDIRECT("Main!B9")&"'!B107")))} | C93: 0
A94: {=IF((INDIRECT("'"&INDIRECT("Main!B9")&"'!A108"))=0,"",(INDIRECT("'"&INDIRECT("Main!B9")&"'!A108")))} | B94: {=IF((INDIRECT("'"&INDIRECT("Main!B9")&"'!B108"))=0,"",(INDIRECT("'"&INDIRECT("Main!B9")&"'!B108")))} | C94: 0
B95: Total Expenses | C95: =SUM(C87:C94) -> 0
B96: Grand Expenses Total | C96: =C55+C66+C75+C85+C95 -> 0
A97: {=IF((INDIRECT("'"&INDIRECT("Main!B9")&"'!A111"))=0,"",(INDIRECT("'"&INDIRECT("Main!B9")&"'!A111")))} -> Debts / Borrowed To
A98: {=IF((INDIRECT("'"&INDIRECT("Main!B9")&"'!A112"))=0,"",(INDIRECT("'"&INDIRECT("Main!B9")&"'!A112")))} | B98: {=IF((INDIRECT("'"&INDIRECT("Main!B9")&"'!B112"))=0,"",(INDIRECT("'"&INDIRECT("Main!B9")&"'!B112")))} | C98: {=INDIRECT("'"&INDIRECT("Main!B12")&"'!C98")+SUM(E118+E145+E172)} -> 0
A99: {=IF((INDIRECT("'"&INDIRECT("Main!B9")&"'!A113"))=0,"",(INDIRECT("'"&INDIRECT("Main!B9")&"'!A113")))} | B99: {=IF((INDIRECT("'"&INDIRECT("Main!B9")&"'!B113"))=0,"",(INDIRECT("'"&INDIRECT("Main!B9")&"'!B113")))} | C99: {=INDIRECT("'"&INDIRECT("Main!B12")&"'!C99")+SUM(E119+E146+E173)} -> 0
A100: {=IF((INDIRECT("'"&INDIRECT("Main!B9")&"'!A114"))=0,"",(INDIRECT("'"&INDIRECT("Main!B9")&"'!A114")))} | B100: {=IF((INDIRECT("'"&INDIRECT("Main!B9")&"'!B114"))=0,"",(INDIRECT("'"&INDIRECT("Main!B9")&"'!B114")))} | C100: {=INDIRECT("'"&INDIRECT("Main!B12")&"'!C100")+SUM(E120+E147+E174)} -> 0
A101: {=IF((INDIRECT("'"&INDIRECT("Main!B9")&"'!A115"))=0,"",(INDIRECT("'"&INDIRECT("Main!B9")&"'!A115")))} | B101: {=IF((INDIRECT("'"&INDIRECT("Main!B9")&"'!B115"))=0,"",(INDIRECT("'"&INDIRECT("Main!B9")&"'!B115")))} | C101: {=INDIRECT("'"&INDIRECT("Main!B12")&"'!C101")+SUM(E121+E148+E175)} -> 0
A102: {=IF((INDIRECT("'"&INDIRECT("Main!B9")&"'!A116"))=0,"",(INDIRECT("'"&INDIRECT("Main!B9")&"'!A116")))} | B102: {=IF((INDIRECT("'"&INDIRECT("Main!B9")&"'!B116"))=0,"",(INDIRECT("'"&INDIRECT("Main!B9")&"'!B116")))} | C102: {=INDIRECT("'"&INDIRECT("Main!B12")&"'!C102")+SUM(E122+E149+E176)} -> 0
A103: {=IF((INDIRECT("'"&INDIRECT("Main!B9")&"'!A117"))=0,"",(INDIRECT("'"&INDIRECT("Main!B9")&"'!A117")))} | B103: {=IF((INDIRECT("'"&INDIRECT("Main!B9")&"'!B117"))=0,"",(INDIRECT("'"&INDIRECT("Main!B9")&"'!B117")))} | C103: {=INDIRECT("'"&INDIRECT("Main!B12")&"'!C103")+SUM(E123+E150+E177)} -> 0
A104: {=IF((INDIRECT("'"&INDIRECT("Main!B9")&"'!A118"))=0,"",(INDIRECT("'"&INDIRECT("Main!B9")&"'!A118")))} | B104: {=IF((INDIRECT("'"&INDIRECT("Main!B9")&"'!B118"))=0,"",(INDIRECT("'"&INDIRECT("Main!B9")&"'!B118")))} | C104: {=INDIRECT("'"&INDIRECT("Main!B12")&"'!C104")+SUM(E124+E151+E178)} -> 0
A105: {=IF((INDIRECT("'"&INDIRECT("Main!B9")&"'!A119"))=0,"",(INDIRECT("'"&INDIRECT("Main!B9")&"'!A119")))} | B105: {=IF((INDIRECT("'"&INDIRECT("Main!B9")&"'!B119"))=0,"",(INDIRECT("'"&INDIRECT("Main!B9")&"'!B119")))} | C105: {=INDIRECT("'"&INDIRECT("Main!B12")&"'!C105")+SUM(E125+E152+E179)} -> 0
A106: {=IF((INDIRECT("'"&INDIRECT("Main!B9")&"'!A120"))=0,"",(INDIRECT("'"&INDIRECT("Main!B9")&"'!A120")))} | B106: {=IF((INDIRECT("'"&INDIRECT("Main!B9")&"'!B120"))=0,"",(INDIRECT("'"&INDIRECT("Main!B9")&"'!B120")))} | C106: {=INDIRECT("'"&INDIRECT("Main!B12")&"'!C106")+SUM(E126+E153+E180)} -> 0
A107: {=IF((INDIRECT("'"&INDIRECT("Main!B9")&"'!A121"))=0,"",(INDIRECT("'"&INDIRECT("Main!B9")&"'!A121")))} | B107: {=IF((INDIRECT("'"&INDIRECT("Main!B9")&"'!B121"))=0,"",(INDIRECT("'"&INDIRECT("Main!B9")&"'!B121")))} | C107: {=INDIRECT("'"&INDIRECT("Main!B12")&"'!C107")+SUM(E127+E154+E181)} -> 0
B108: Total Debts | C108: =SUM(C98:C107) -> 0
B109: Grand Total | C109: =C108-C96 -> 0
A114: ="Debts Or Credits For the Comming "&IF(Main!B2,TEXT(EDATE(Main!B3,6),"mmmm dd yyyy"),TEXT(Main!B3+((Main!B5-Main!B3)*6+6),"mmmm dd yyyy"))&" to "&IF(Main!B2,TEXT(EDATE(Main!B3,7)-1,"mmmm dd yyyy"),TEXT(Main!B3+((Main!B5-Main!B3)*7+6),"mmmm dd yyyy")) -> Debts Or Credits For the Comming October 11 2025 to November 10 2025
A115: Principal | C115: Description | E115: Amount
...

Sheet Forecast_4
A1: ="Forecasts For the Year "&IF(Main!B2,TEXT(EDATE(Main!B3,9),"mmmm yyyy"),TEXT(Main!B3+((Main!B5-Main!B3)*9+9),"mmmm yyyy"))&" to "&IF(Main!B2,TEXT(EDATE(Main!B3,12)-1,"mmmm yyyy"),TEXT(Main!B3+((Main!B5-Main!B3)*12+11),"mmmm yyyy")) -> Forecasts For the Year January 2026 to April 2026
A2: Assets | B2: Overall | C2: {=INDIRECT("'"&Main!B9&"'!$C$16")} -> 0
B3: Forecasts | C3: =E190 -> 0
A4: Total | C4: =SUM(C2:G3) -> 0
A5: Net Debts: | C5: =C108 -> 0
A8: =IF(Main!B2,TEXT(EDATE(Main!B3,9),"dd mmmm yyyy"),TEXT(Main!B3+((Main!B5-Main!B3)*9+9),"dd mmmm yyyy"))&" - "&IF(Main!B2,TEXT(EDATE(Main!B3,10)-1,"dd mmmm yyyy"),TEXT(Main!B3+((Main!B5-Main!B3)*10+9),"dd mmmm yyyy"))&" / "&" (Revenue / Deferred Debts Or Expenses)" -> 11 January 2026 - 10 February 2026 / (Revenue / Deferred Debts Or Expenses)
A9: Date | B9: Name | D9: Description | F9: Amount
F10: 0
F11: 0
F12: 0
F13: 0
F14: 0
F15: 0
D16: Total Revenue | F16: =SUM(F10:G15) -> 0
A20: =IF(Main!B2,TEXT(EDATE(Main!B3,10),"dd mmmm yyyy"),TEXT(Main!B3+((Main!B5-Main!B3)*10+10),"dd mmmm yyyy"))&" - "&IF(Main!B2,TEXT(EDATE(Main!B3,11)-1,"dd mmmm yyyy"),TEXT(Main!B3+((Main!B5-Main!B3)*11+10),"dd mmmm yyyy"))&" / "&" (Revenue / Deferred Debts Or Expenses)" -> 11 February 2026 - 10 March 2026 / (Revenue / Deferred Debts Or Expenses)
A21: Date | B21: Name | D21: Description | F21: Amount
F22: 0
F23: 0
F24: 0
F25: 0
F26: 0
F27: 0
D28: Total Revenue | F28: =SUM(F22:G27) -> 0
A32: =IF(Main!B2,TEXT(EDATE(Main!B3,11),"dd mmmm yyyy"),TEXT(Main!B3+((Main!B5-Main!B3)*11+11),"dd mmmm yyyy"))&" - "&IF(Main!B2,TEXT(EDATE(Main!B3,12)-1,"dd mmmm yyyy"),TEXT(Main!B3+((Main!B5-Main!B3)*12+11),"dd mmmm yyyy"))&" / "&" (Revenue / Deferred Debts Or Expenses)" -> 11 March 2026 - 10 April 2026 / (Revenue / Deferred Debts Or Expenses)
A33: Date | B33: Name | D33: Description | F33: Amount
F34: 0
F35: 0
F36: 0
F37: 0
F38: 0
F39: 0
D40: Total Revenue | F40: =SUM(F34:G39) -> 0
A44: ="Fixed Expense For the Year "&IF(Main!B2,TEXT(EDATE(Main!B3,9),"mmmm yyyy"),TEXT(Main!B3+((Main!B5-Main!B3)*9+9),"mmmm yyyy"))&" to "&IF(Main!B2,TEXT(EDATE(Main!B3,12)-1,"mmmm yyyy"),TEXT(Main!B3+((Main!B5-Main!B3)*12+11),"mmmm yyyy")) -> Fixed Expense For the Year January 2026 to April 2026
A45: Name | B45: Description | C45: Amount
A46: {=IF((INDIRECT("'"&INDIRECT("Main!B9")&"'!A60"))=0,"",(INDIRECT("'"&INDIRECT("Main!B9")&"'!A60")))} -> Mobile And Communications/ Housing Expenses
A47: {=IF((INDIRECT("'"&INDIRECT("Main!B9")&"'!A61"))=0,"",(INDIRECT("'"&INDIRECT("Main!B9")&"'!A61")))} | B47: {=IF((INDIRECT("'"&INDIRECT("Main!B9")&"'!B61"))=0,"",(INDIRECT("'"&INDIRECT("Main!B9")&"'!B61")))} | C47: 0
A48: {=IF((INDIRECT("'"&INDIRECT("Main!B9")&"'!A62"))=0,"",(INDIRECT("'"&INDIRECT("Main!B9")&"'!A62")))} | B48: {=IF((INDIRECT("'"&INDIRECT("Main!B9")&"'!B62"))=0,"",(INDIRECT("'"&INDIRECT("Main!B9")&"'!B62")))} | C48: 0
A49: {=IF((INDIRECT("'"&INDIRECT("Main!B9")&"'!A63"))=0,"",(INDIRECT("'"&INDIRECT("Main!B9")&"'!A63")))} | B49: {=IF((INDIRECT("'"&INDIRECT("Main!B9")&"'!B63"))=0,"",(INDIRECT("'"&INDIRECT("Main!B9")&"'!B63")))} | C49: 0
A50: {=IF((INDIRECT("'"&INDIRECT("Main!B9")&"'!A64"))=0,"",(INDIRECT("'"&INDIRECT("Main!B9")&"'!A64")))} | B50: {=IF((INDIRECT("'"&INDIRECT("Main!B9")&"'!B64"))=0,"",(INDIRECT("'"&INDIRECT("Main!B9")&"'!B64")))} | C50: 0
A51: {=IF((INDIRECT("'"&INDIRECT("Main!B9")&"'!A65"))=0,"",(INDIRECT("'"&INDIRECT("Main!B9")&"'!A65")))} | B51: {=IF((INDIRECT("'"&INDIRECT("Main!B9")&"'!B65"))=0,"",(INDIRECT("'"&INDIRECT("Main!B9")&"'!B65")))} | C51: 0
A52: {=IF((INDIRECT("'"&INDIRECT("Main!B9")&"'!A66"))=0,"",(INDIRECT("'"&INDIRECT("Main!B9")&"'!A66")))} | B52: {=IF((INDIRECT("'"&INDIRECT("Main!B9")&"'!B66"))=0,"",(INDIRECT("'"&INDIRECT("Main!B9")&"'!B66")))} | C52: 0
A53: {=IF((INDIRECT("'"&INDIRECT("Main!B9")&"'!A67"))=0,"",(INDIRECT("'"&INDIRECT("Main!B9")&"'!A67")))} | B53: {=IF((INDIRECT("'"&INDIRECT("Main!B9")&"'!B67"))=0,"",(INDIRECT("'"&INDIRECT("Main!B9")&"'!B67")))} | C53: 0
A54: {=IF((INDIRECT("'"&INDIRECT("Main!B9")&"'!A68"))=0,"",(INDIRECT("'"&INDIRECT("Main!B9")&"'!A68")))} | B54: {=IF((INDIRECT("'"&INDIRECT("Main!B9")&"'!B68"))=0,"",(INDIRECT("'"&INDIRECT("Main!B9")&"'!B68")))} | C54: 0
B55: Total Expenses | C55: =SUM(C47:C54) -> 0
A56: {=IF((INDIRECT("'"&INDIRECT("Main!B9")&"'!A70"))=0,"",(INDIRECT("'"&INDIRECT("Main!B9")&"'!A70")))} -> Credit Card Installments/Government Installments
A57: {=IF((INDIRECT("'"&INDIRECT("Main!B9")&"'!A71"))=0,"",(INDIRECT("'"&INDIRECT("Main!B9")&"'!A71")))} | B57: {=IF((INDIRECT("'"&INDIRECT("Main!B9")&"'!B71"))=0,"",(INDIRECT("'"&INDIRECT("Main!B9")&"'!B71")))} | C57: 0
A58: {=IF((INDIRECT("'"&INDIRECT("Main!B9")&"'!A72"))=0,"",(INDIRECT("'"&INDIRECT("Main!B9")&"'!A72")))} | B58: {=IF((INDIRECT("'"&INDIRECT("Main!B9")&"'!B72"))=0,"",(INDIRECT("'"&INDIRECT("Main!B9")&"'!B72")))} | C58: 0
A59: {=IF((INDIRECT("'"&INDIRECT("Main!B9")&"'!A73"))=0,"",(INDIRECT("'"&INDIRECT("Main!B9")&"'!A73")))} | B59: {=IF((INDIRECT("'"&INDIRECT("Main!B9")&"'!B73"))=0,"",(INDIRECT("'"&INDIRECT("Main!B9")&"'!B73")))} | C59: 0
A60: {=IF((INDIRECT("'"&INDIRECT("Main!B9")&"'!A74"))=0,"",(INDIRECT("'"&INDIRECT("Main!B9")&"'!A74")))} | B60: {=IF((INDIRECT("'"&INDIRECT("Main!B9")&"'!B74"))=0,"",(INDIRECT("'"&INDIRECT("Main!B9")&"'!B74")))} | C60: 0
A61: {=IF((INDIRECT("'"&INDIRECT("Main!B9")&"'!A75"))=0,"",(INDIRECT("'"&INDIRECT("Main!B9")&"'!A75")))} | B61: {=IF((INDIRECT("'"&INDIRECT("Main!B9")&"'!B75"))=0,"",(INDIRECT("'"&INDIRECT("Main!B9")&"'!B75")))} | C61: 0
A62: {=IF((INDIRECT("'"&INDIRECT("Main!B9")&"'!A76"))=0,"",(INDIRECT("'"&INDIRECT("Main!B9")&"'!A76")))} | B62: {=IF((INDIRECT("'"&INDIRECT("Main!B9")&"'!B76"))=0,"",(INDIRECT("'"&INDIRECT("Main!B9")&"'!B76")))} | C62: 0
A63: {=IF((INDIRECT("'"&INDIRECT("Main!B9")&"'!A77"))=0,"",(INDIRECT("'"&INDIRECT("Main!B9")&"'!A77")))} | B63: {=IF((INDIRECT("'"&INDIRECT("Main!B9")&"'!B77"))=0,"",(INDIRECT("'"&INDIRECT("Main!B9")&"'!B77")))} | C63: 0
A64: {=IF((INDIRECT("'"&INDIRECT("Main!B9")&"'!A78"))=0,"",(INDIRECT("'"&INDIRECT("Main!B9")&"'!A78")))} | B64: {=IF((INDIRECT("'"&INDIRECT("Main!B9")&"'!B78"))=0,"",(INDIRECT("'"&INDIRECT("Main!B9")&"'!B78")))} | C64: 0
A65: {=IF((INDIRECT("'"&INDIRECT("Main!B9")&"'!A79"))=0,"",(INDIRECT("'"&INDIRECT("Main!B9")&"'!A79")))} | B65: {=IF((INDIRECT("'"&INDIRECT("Main!B9")&"'!B79"))=0,"",(INDIRECT("'"&INDIRECT("Main!B9")&"'!B79")))} | C65: 0
B66: Total Expenses | C66: =SUM(C57:C65) -> 0
A67: {=IF((INDIRECT("'"&INDIRECT("Main!B9")&"'!A81"))=0,"",(INDIRECT("'"&INDIRECT("Main!B9")&"'!A81")))} -> Donation
A68: {=IF((INDIRECT("'"&INDIRECT("Main!B9")&"'!A82"))=0,"",(INDIRECT("'"&INDIRECT("Main!B9")&"'!A82")))} | B68: {=IF((INDIRECT("'"&INDIRECT("Main!B9")&"'!B82"))=0,"",(INDIRECT("'"&INDIRECT("Main!B9")&"'!B82")))} | C68: 0
A69: {=IF((INDIRECT("'"&INDIRECT("Main!B9")&"'!A83"))=0,"",(INDIRECT("'"&INDIRECT("Main!B9")&"'!A83")))} | B69: {=IF((INDIRECT("'"&INDIRECT("Main!B9")&"'!B83"))=0,"",(INDIRECT("'"&INDIRECT("Main!B9")&"'!B83")))} | C69: 0
A70: {=IF((INDIRECT("'"&INDIRECT("Main!B9")&"'!A84"))=0,"",(INDIRECT("'"&INDIRECT("Main!B9")&"'!A84")))} | B70: {=IF((INDIRECT("'"&INDIRECT("Main!B9")&"'!B84"))=0,"",(INDIRECT("'"&INDIRECT("Main!B9")&"'!B84")))} | C70: 0
A71: {=IF((INDIRECT("'"&INDIRECT("Main!B9")&"'!A85"))=0,"",(INDIRECT("'"&INDIRECT("Main!B9")&"'!A85")))} | B71: {=IF((INDIRECT("'"&INDIRECT("Main!B9")&"'!B85"))=0,"",(INDIRECT("'"&INDIRECT("Main!B9")&"'!B85")))} | C71: 0
A72: {=IF((INDIRECT("'"&INDIRECT("Main!B9")&"'!A86"))=0,"",(INDIRECT("'"&INDIRECT("Main!B9")&"'!A86")))} | B72: {=IF((INDIRECT("'"&INDIRECT("Main!B9")&"'!B86"))=0,"",(INDIRECT("'"&INDIRECT("Main!B9")&"'!B86")))} | C72: 0
A73: {=IF((INDIRECT("'"&INDIRECT("Main!B9")&"'!A87"))=0,"",(INDIRECT("'"&INDIRECT("Main!B9")&"'!A87")))} | B73: {=IF((INDIRECT("'"&INDIRECT("Main!B9")&"'!B87"))=0,"",(INDIRECT("'"&INDIRECT("Main!B9")&"'!B87")))} | C73: 0
A74: {=IF((INDIRECT("'"&INDIRECT("Main!B9")&"'!A88"))=0,"",(INDIRECT("'"&INDIRECT("Main!B9")&"'!A88")))} | B74: {=IF((INDIRECT("'"&INDIRECT("Main!B9")&"'!B88"))=0,"",(INDIRECT("'"&INDIRECT("Main!B9")&"'!B88")))} | C74: 0
B75: Total Expenses | C75: =SUM(C68:C74) -> 0
A76: {=IF((INDIRECT("'"&INDIRECT("Main!B9")&"'!A90"))=0,"",(INDIRECT("'"&INDIRECT("Main!B9")&"'!A90")))} -> Insurance (Personal / Properties / Medical)
A77: {=IF((INDIRECT("'"&INDIRECT("Main!B9")&"'!A91"))=0,"",(INDIRECT("'"&INDIRECT("Main!B9")&"'!A91")))} | B77: {=IF((INDIRECT("'"&INDIRECT("Main!B9")&"'!B91"))=0,"",(INDIRECT("'"&INDIRECT("Main!B9")&"'!B91")))} | C77: 0
A78: {=IF((INDIRECT("'"&INDIRECT("Main!B9")&"'!A92"))=0,"",(INDIRECT("'"&INDIRECT("Main!B9")&"'!A92")))} | B78: {=IF((INDIRECT("'"&INDIRECT("Main!B9")&"'!B92"))=0,"",(INDIRECT("'"&INDIRECT("Main!B9")&"'!B92")))} | C78: 0
A79: {=IF((INDIRECT("'"&INDIRECT("Main!B9")&"'!A93"))=0,"",(INDIRECT("'"&INDIRECT("Main!B9")&"'!A93")))} | B79: {=IF((INDIRECT("'"&INDIRECT("Main!B9")&"'!B93"))=0,"",(INDIRECT("'"&INDIRECT("Main!B9")&"'!B93")))} | C79: 0
A80: {=IF((INDIRECT("'"&INDIRECT("Main!B9")&"'!A94"))=0,"",(INDIRECT("'"&INDIRECT("Main!B9")&"'!A94")))} | B80: {=IF((INDIRECT("'"&INDIRECT("Main!B9")&"'!B94"))=0,"",(INDIRECT("'"&INDIRECT("Main!B9")&"'!B94")))} | C80: 0
A81: {=IF((INDIRECT("'"&INDIRECT("Main!B9")&"'!A95"))=0,"",(INDIRECT("'"&INDIRECT("Main!B9")&"'!A95")))} | B81: {=IF((INDIRECT("'"&INDIRECT("Main!B9")&"'!B95"))=0,"",(INDIRECT("'"&INDIRECT("Main!B9")&"'!B95")))} | C81: 0
A82: {=IF((INDIRECT("'"&INDIRECT("Main!B9")&"'!A96"))=0,"",(INDIRECT("'"&INDIRECT("Main!B9")&"'!A96")))} | B82: {=IF((INDIRECT("'"&INDIRECT("Main!B9")&"'!B96"))=0,"",(INDIRECT("'"&INDIRECT("Main!B9")&"'!B96")))} | C82: 0
A83: {=IF((INDIRECT("'"&INDIRECT("Main!B9")&"'!A97"))=0,"",(INDIRECT("'"&INDIRECT("Main!B9")&"'!A97")))} | B83: {=IF((INDIRECT("'"&INDIRECT("Main!B9")&"'!B97"))=0,"",(INDIRECT("'"&INDIRECT("Main!B9")&"'!B97")))} | C83: 0
A84: {=IF((INDIRECT("'"&INDIRECT("Main!B9")&"'!A98"))=0,"",(INDIRECT("'"&INDIRECT("Main!B9")&"'!A98")))} | B84: {=IF((INDIRECT("'"&INDIRECT("Main!B9")&"'!B98"))=0,"",(INDIRECT("'"&INDIRECT("Main!B9")&"'!B98")))} | C84: 0
B85: Total Expenses | C85: =SUM(C77:C84) -> 0
A86: {=IF((INDIRECT("'"&INDIRECT("Main!B9")&"'!A100"))=0,"",(INDIRECT("'"&INDIRECT("Main!B9")&"'!A100")))} -> Other Expenses
A87: {=IF((INDIRECT("'"&INDIRECT("Main!B9")&"'!A101"))=0,"",(INDIRECT("'"&INDIRECT("Main!B9")&"'!A101")))} | B87: {=IF((INDIRECT("'"&INDIRECT("Main!B9")&"'!B101"))=0,"",(INDIRECT("'"&INDIRECT("Main!B9")&"'!B101")))} | C87: 0
A88: {=IF((INDIRECT("'"&INDIRECT("Main!B9")&"'!A102"))=0,"",(INDIRECT("'"&INDIRECT("Main!B9")&"'!A102")))} | B88: {=IF((INDIRECT("'"&INDIRECT("Main!B9")&"'!B102"))=0,"",(INDIRECT("'"&INDIRECT("Main!B9")&"'!B102")))} | C88: 0
A89: {=IF((INDIRECT("'"&INDIRECT("Main!B9")&"'!A103"))=0,"",(INDIRECT("'"&INDIRECT("Main!B9")&"'!A103")))} | B89: {=IF((INDIRECT("'"&INDIRECT("Main!B9")&"'!B103"))=0,"",(INDIRECT("'"&INDIRECT("Main!B9")&"'!B103")))} | C89: 0
A90: {=IF((INDIRECT("'"&INDIRECT("Main!B9")&"'!A104"))=0,"",(INDIRECT("'"&INDIRECT("Main!B9")&"'!A104")))} | B90: {=IF((INDIRECT("'"&INDIRECT("Main!B9")&"'!B104"))=0,"",(INDIRECT("'"&INDIRECT("Main!B9")&"'!B104")))} | C90: 0
A91: {=IF((INDIRECT("'"&INDIRECT("Main!B9")&"'!A105"))=0,"",(INDIRECT("'"&INDIRECT("Main!B9")&"'!A105")))} | B91: {=IF((INDIRECT("'"&INDIRECT("Main!B9")&"'!B105"))=0,"",(INDIRECT("'"&INDIRECT("Main!B9")&"'!B105")))} | C91: 0
A92: {=IF((INDIRECT("'"&INDIRECT("Main!B9")&"'!A106"))=0,"",(INDIRECT("'"&INDIRECT("Main!B9")&"'!A106")))} | B92: {=IF((INDIRECT("'"&INDIRECT("Main!B9")&"'!B106"))=0,"",(INDIRECT("'"&INDIRECT("Main!B9")&"'!B106")))} | C92: 0
A93: {=IF((INDIRECT("'"&INDIRECT("Main!B9")&"'!A107"))=0,"",(INDIRECT("'"&INDIRECT("Main!B9")&"'!A107")))} | B93: {=IF((INDIRECT("'"&INDIRECT("Main!B9")&"'!B107"))=0,"",(INDIRECT("'"&INDIRECT("Main!B9")&"'!B107")))} | C93: 0
A94: {=IF((INDIRECT("'"&INDIRECT("Main!B9")&"'!A108"))=0,"",(INDIRECT("'"&INDIRECT("Main!B9")&"'!A108")))} | B94: {=IF((INDIRECT("'"&INDIRECT("Main!B9")&"'!B108"))=0,"",(INDIRECT("'"&INDIRECT("Main!B9")&"'!B108")))} | C94: 0
B95: Total Expenses | C95: =SUM(C87:C94) -> 0
B96: Grand Expenses Total | C96: =C55+C66+C75+C85+C95 -> 0
A97: {=IF((INDIRECT("'"&INDIRECT("Main!B9")&"'!A111"))=0,"",(INDIRECT("'"&INDIRECT("Main!B9")&"'!A111")))} -> Debts / Borrowed To
A98: {=IF((INDIRECT("'"&INDIRECT("Main!B9")&"'!A112"))=0,"",(INDIRECT("'"&INDIRECT("Main!B9")&"'!A112")))} | B98: {=IF((INDIRECT("'"&INDIRECT("Main!B9")&"'!B112"))=0,"",(INDIRECT("'"&INDIRECT("Main!B9")&"'!B112")))} | C98: {=INDIRECT("'"&INDIRECT("Main!B15")&"'!C98")+SUM(E118+E145+E172)} -> 0
A99: {=IF((INDIRECT("'"&INDIRECT("Main!B9")&"'!A113"))=0,"",(INDIRECT("'"&INDIRECT("Main!B9")&"'!A113")))} | B99: {=IF((INDIRECT("'"&INDIRECT("Main!B9")&"'!B113"))=0,"",(INDIRECT("'"&INDIRECT("Main!B9")&"'!B113")))} | C99: {=INDIRECT("'"&INDIRECT("Main!B15")&"'!C99")+SUM(E119+E146+E173)} -> 0
A100: {=IF((INDIRECT("'"&INDIRECT("Main!B9")&"'!A114"))=0,"",(INDIRECT("'"&INDIRECT("Main!B9")&"'!A114")))} | B100: {=IF((INDIRECT("'"&INDIRECT("Main!B9")&"'!B114"))=0,"",(INDIRECT("'"&INDIRECT("Main!B9")&"'!B114")))} | C100: {=INDIRECT("'"&INDIRECT("Main!B15")&"'!C100")+SUM(E120+E147+E174)} -> 0
A101: {=IF((INDIRECT("'"&INDIRECT("Main!B9")&"'!A115"))=0,"",(INDIRECT("'"&INDIRECT("Main!B9")&"'!A115")))} | B101: {=IF((INDIRECT("'"&INDIRECT("Main!B9")&"'!B115"))=0,"",(INDIRECT("'"&INDIRECT("Main!B9")&"'!B115")))} | C101: {=INDIRECT("'"&INDIRECT("Main!B15")&"'!C101")+SUM(E121+E148+E175)} -> 0
A102: {=IF((INDIRECT("'"&INDIRECT("Main!B9")&"'!A116"))=0,"",(INDIRECT("'"&INDIRECT("Main!B9")&"'!A116")))} | B102: {=IF((INDIRECT("'"&INDIRECT("Main!B9")&"'!B116"))=0,"",(INDIRECT("'"&INDIRECT("Main!B9")&"'!B116")))} | C102: {=INDIRECT("'"&INDIRECT("Main!B15")&"'!C102")+SUM(E122+E149+E176)} -> 0
A103: {=IF((INDIRECT("'"&INDIRECT("Main!B9")&"'!A117"))=0,"",(INDIRECT("'"&INDIRECT("Main!B9")&"'!A117")))} | B103: {=IF((INDIRECT("'"&INDIRECT("Main!B9")&"'!B117"))=0,"",(INDIRECT("'"&INDIRECT("Main!B9")&"'!B117")))} | C103: {=INDIRECT("'"&INDIRECT("Main!B15")&"'!C103")+SUM(E123+E150+E177)} -> 0
A104: {=IF((INDIRECT("'"&INDIRECT("Main!B9")&"'!A118"))=0,"",(INDIRECT("'"&INDIRECT("Main!B9")&"'!A118")))} | B104: {=IF((INDIRECT("'"&INDIRECT("Main!B9")&"'!B118"))=0,"",(INDIRECT("'"&INDIRECT("Main!B9")&"'!B118")))} | C104: {=INDIRECT("'"&INDIRECT("Main!B15")&"'!C104")+SUM(E124+E151+E178)} -> 0
A105: {=IF((INDIRECT("'"&INDIRECT("Main!B9")&"'!A119"))=0,"",(INDIRECT("'"&INDIRECT("Main!B9")&"'!A119")))} | B105: {=IF((INDIRECT("'"&INDIRECT("Main!B9")&"'!B119"))=0,"",(INDIRECT("'"&INDIRECT("Main!B9")&"'!B119")))} | C105: {=INDIRECT("'"&INDIRECT("Main!B15")&"'!C105")+SUM(E125+E152+E179)} -> 0
A106: {=IF((INDIRECT("'"&INDIRECT("Main!B9")&"'!A120"))=0,"",(INDIRECT("'"&INDIRECT("Main!B9")&"'!A120")))} | B106: {=IF((INDIRECT("'"&INDIRECT("Main!B9")&"'!B120"))=0,"",(INDIRECT("'"&INDIRECT("Main!B9")&"'!B120")))} | C106: {=INDIRECT("'"&INDIRECT("Main!B15")&"'!C106")+SUM(E126+E153+E180)} -> 0
A107: {=IF((INDIRECT("'"&INDIRECT("Main!B9")&"'!A121"))=0,"",(INDIRECT("'"&INDIRECT("Main!B9")&"'!A121")))} | B107: {=IF((INDIRECT("'"&INDIRECT("Main!B9")&"'!B121"))=0,"",(INDIRECT("'"&INDIRECT("Main!B9")&"'!B121")))} | C107: {=INDIRECT("'"&INDIRECT("Main!B15")&"'!C107")+SUM(E127+E154+E181)} -> 0
B108: Total Debts | C108: =SUM(C98:C107) -> 0
B109: Grand Total | C109: =C108-C96 -> 0
A114: ="Debts Or Credits For the Comming "&IF(Main!B2,TEXT(EDATE(Main!B3,9),"mmmm dd yyyy"),TEXT(Main!B3+((Main!B5-Main!B3)*9+9),"mmmm dd yyyy"))&" to "&IF(Main!B2,TEXT(EDATE(Main!B3,10)-1,"mmmm dd yyyy"),TEXT(Main!B3+((Main!B5-Main!B3)*10+9),"mmmm dd yyyy")) -> Debts Or Credits For the Comming January 11 2026 to February 10 2026
A115: Principal | C115: Description | E115: Amount
...

Sheet Forecast_5
A1: ="Forecasts For the Year "&IF(Main!B2,TEXT(EDATE(Main!B3,12),"mmmm yyyy"),TEXT(Main!B3+((Main!B5-Main!B3)*12+12),"mmmm yyyy"))&" to "&IF(Main!B2,TEXT(EDATE(Main!B3,15)-1,"mmmm yyyy"),TEXT(Main!B3+((Main!B5-Main!B3)*15+14),"mmmm yyyy")) -> Forecasts For the Year April 2026 to July 2026
A2: Assets | B2: Overall | C2: {=INDIRECT("'"&Main!B9&"'!$C$16")} -> 0
B3: Forecasts | C3: =E190 -> 0
A4: Total | C4: =SUM(C2:G3) -> 0
A5: Net Debts: | C5: =C108 -> 0
A8: =IF(Main!B2,TEXT(EDATE(Main!B3,12),"dd mmmm yyyy"),TEXT(Main!B3+((Main!B5-Main!B3)*12+12),"dd mmmm yyyy"))&" - "&IF(Main!B2,TEXT(EDATE(Main!B3,13)-1,"dd mmmm yyyy"),TEXT(Main!B3+((Main!B5-Main!B3)*13+12),"dd mmmm yyyy"))&" / "&" (Revenue / Deferred Debts Or Expenses)" -> 11 April 2026 - 10 May 2026 / (Revenue / Deferred Debts Or Expenses)
A9: Date | B9: Name | D9: Description | F9: Amount
F10: 0
F11: 0
F12: 0
F13: 0
F14: 0
F15: 0
D16: Total Revenue | F16: =SUM(F10:G15) -> 0
A20: =IF(Main!B2,TEXT(EDATE(Main!B3,13),"dd mmmm yyyy"),TEXT(Main!B3+((Main!B5-Main!B3)*13+13),"dd mmmm yyyy"))&" - "&IF(Main!B2,TEXT(EDATE(Main!B3,14)-1,"dd mmmm yyyy"),TEXT(Main!B3+((Main!B5-Main!B3)*14+13),"dd mmmm yyyy"))&" / "&" (Revenue / Deferred Debts Or Expenses)" -> 11 May 2026 - 10 June 2026 / (Revenue / Deferred Debts Or Expenses)
A21: Date | B21: Name | D21: Description | F21: Amount
F22: 0
F23: 0
F24: 0
F25: 0
F26: 0
F27: 0
D28: Total Revenue | F28: =SUM(F22:G27) -> 0
A32: =IF(Main!B2,TEXT(EDATE(Main!B3,14),"dd mmmm yyyy"),TEXT(Main!B3+((Main!B5-Main!B3)*14+14),"dd mmmm yyyy"))&" - "&IF(Main!B2,TEXT(EDATE(Main!B3,15)-1,"dd mmmm yyyy"),TEXT(Main!B3+((Main!B5-Main!B3)*15+14),"dd mmmm yyyy"))&" / "&" (Revenue / Deferred Debts Or Expenses)" -> 11 June 2026 - 10 July 2026 / (Revenue / Deferred Debts Or Expenses)
A33: Date | B33: Name | D33: Description | F33: Amount
F34: 0
F35: 0
F36: 0
F37: 0
F38: 0
F39: 0
D40: Total Revenue | F40: =SUM(F34:G39) -> 0
A44: ="Fixed Expense For the Year "&IF(Main!B2,TEXT(EDATE(Main!B3,12),"mmmm yyyy"),TEXT(Main!B3+((Main!B5-Main!B3)*12+12),"mmmm yyyy"))&" to "&IF(Main!B2,TEXT(EDATE(Main!B3,15)-1,"mmmm yyyy"),TEXT(Main!B3+((Main!B5-Main!B3)*15+14),"mmmm yyyy")) -> Fixed Expense For the Year April 2026 to July 2026
A45: Name | B45: Description | C45: Amount
A46: {=IF((INDIRECT("'"&INDIRECT("Main!B9")&"'!A60"))=0,"",(INDIRECT("'"&INDIRECT("Main!B9")&"'!A60")))} -> Mobile And Communications/ Housing Expenses
A47: {=IF((INDIRECT("'"&INDIRECT("Main!B9")&"'!A61"))=0,"",(INDIRECT("'"&INDIRECT("Main!B9")&"'!A61")))} | B47: {=IF((INDIRECT("'"&INDIRECT("Main!B9")&"'!B61"))=0,"",(INDIRECT("'"&INDIRECT("Main!B9")&"'!B61")))} | C47: 0
A48: {=IF((INDIRECT("'"&INDIRECT("Main!B9")&"'!A62"))=0,"",(INDIRECT("'"&INDIRECT("Main!B9")&"'!A62")))} | B48: {=IF((INDIRECT("'"&INDIRECT("Main!B9")&"'!B62"))=0,"",(INDIRECT("'"&INDIRECT("Main!B9")&"'!B62")))} | C48: 0
A49: {=IF((INDIRECT("'"&INDIRECT("Main!B9")&"'!A63"))=0,"",(INDIRECT("'"&INDIRECT("Main!B9")&"'!A63")))} | B49: {=IF((INDIRECT("'"&INDIRECT("Main!B9")&"'!B63"))=0,"",(INDIRECT("'"&INDIRECT("Main!B9")&"'!B63")))} | C49: 0
A50: {=IF((INDIRECT("'"&INDIRECT("Main!B9")&"'!A64"))=0,"",(INDIRECT("'"&INDIRECT("Main!B9")&"'!A64")))} | B50: {=IF((INDIRECT("'"&INDIRECT("Main!B9")&"'!B64"))=0,"",(INDIRECT("'"&INDIRECT("Main!B9")&"'!B64")))} | C50: 0
A51: {=IF((INDIRECT("'"&INDIRECT("Main!B9")&"'!A65"))=0,"",(INDIRECT("'"&INDIRECT("Main!B9")&"'!A65")))} | B51: {=IF((INDIRECT("'"&INDIRECT("Main!B9")&"'!B65"))=0,"",(INDIRECT("'"&INDIRECT("Main!B9")&"'!B65")))} | C51: 0
A52: {=IF((INDIRECT("'"&INDIRECT("Main!B9")&"'!A66"))=0,"",(INDIRECT("'"&INDIRECT("Main!B9")&"'!A66")))} | B52: {=IF((INDIRECT("'"&INDIRECT("Main!B9")&"'!B66"))=0,"",(INDIRECT("'"&INDIRECT("Main!B9")&"'!B66")))} | C52: 0
A53: {=IF((INDIRECT("'"&INDIRECT("Main!B9")&"'!A67"))=0,"",(INDIRECT("'"&INDIRECT("Main!B9")&"'!A67")))} | B53: {=IF((INDIRECT("'"&INDIRECT("Main!B9")&"'!B67"))=0,"",(INDIRECT("'"&INDIRECT("Main!B9")&"'!B67")))} | C53: 0
A54: {=IF((INDIRECT("'"&INDIRECT("Main!B9")&"'!A68"))=0,"",(INDIRECT("'"&INDIRECT("Main!B9")&"'!A68")))} | B54: {=IF((INDIRECT("'"&INDIRECT("Main!B9")&"'!B68"))=0,"",(INDIRECT("'"&INDIRECT("Main!B9")&"'!B68")))} | C54: 0
B55: Total Expenses | C55: =SUM(C47:C54) -> 0
A56: {=IF((INDIRECT("'"&INDIRECT("Main!B9")&"'!A70"))=0,"",(INDIRECT("'"&INDIRECT("Main!B9")&"'!A70")))} -> Credit Card Installments/Government Installments
A57: {=IF((INDIRECT("'"&INDIRECT("Main!B9")&"'!A71"))=0,"",(INDIRECT("'"&INDIRECT("Main!B9")&"'!A71")))} | B57: {=IF((INDIRECT("'"&INDIRECT("Main!B9")&"'!B71"))=0,"",(INDIRECT("'"&INDIRECT("Main!B9")&"'!B71")))} | C57: 0
A58: {=IF((INDIRECT("'"&INDIRECT("Main!B9")&"'!A72"))=0,"",(INDIRECT("'"&INDIRECT("Main!B9")&"'!A72")))} | B58: {=IF((INDIRECT("'"&INDIRECT("Main!B9")&"'!B72"))=0,"",(INDIRECT("'"&INDIRECT("Main!B9")&"'!B72")))} | C58: 0
A59: {=IF((INDIRECT("'"&INDIRECT("Main!B9")&"'!A73"))=0,"",(INDIRECT("'"&INDIRECT("Main!B9")&"'!A73")))} | B59: {=IF((INDIRECT("'"&INDIRECT("Main!B9")&"'!B73"))=0,"",(INDIRECT("'"&INDIRECT("Main!B9")&"'!B73")))} | C59: 0
A60: {=IF((INDIRECT("'"&INDIRECT("Main!B9")&"'!A74"))=0,"",(INDIRECT("'"&INDIRECT("Main!B9")&"'!A74")))} | B60: {=IF((INDIRECT("'"&INDIRECT("Main!B9")&"'!B74"))=0,"",(INDIRECT("'"&INDIRECT("Main!B9")&"'!B74")))} | C60: 0
A61: {=IF((INDIRECT("'"&INDIRECT("Main!B9")&"'!A75"))=0,"",(INDIRECT("'"&INDIRECT("Main!B9")&"'!A75")))} | B61: {=IF((INDIRECT("'"&INDIRECT("Main!B9")&"'!B75"))=0,"",(INDIRECT("'"&INDIRECT("Main!B9")&"'!B75")))} | C61: 0
A62: {=IF((INDIRECT("'"&INDIRECT("Main!B9")&"'!A76"))=0,"",(INDIRECT("'"&INDIRECT("Main!B9")&"'!A76")))} | B62: {=IF((INDIRECT("'"&INDIRECT("Main!B9")&"'!B76"))=0,"",(INDIRECT("'"&INDIRECT("Main!B9")&"'!B76")))} | C62: 0
A63: {=IF((INDIRECT("'"&INDIRECT("Main!B9")&"'!A77"))=0,"",(INDIRECT("'"&INDIRECT("Main!B9")&"'!A77")))} | B63: {=IF((INDIRECT("'"&INDIRECT("Main!B9")&"'!B77"))=0,"",(INDIRECT("'"&INDIRECT("Main!B9")&"'!B77")))} | C63: 0
A64: {=IF((INDIRECT("'"&INDIRECT("Main!B9")&"'!A78"))=0,"",(INDIRECT("'"&INDIRECT("Main!B9")&"'!A78")))} | B64: {=IF((INDIRECT("'"&INDIRECT("Main!B9")&"'!B78"))=0,"",(INDIRECT("'"&INDIRECT("Main!B9")&"'!B78")))} | C64: 0
A65: {=IF((INDIRECT("'"&INDIRECT("Main!B9")&"'!A79"))=0,"",(INDIRECT("'"&INDIRECT("Main!B9")&"'!A79")))} | B65: {=IF((INDIRECT("'"&INDIRECT("Main!B9")&"'!B79"))=0,"",(INDIRECT("'"&INDIRECT("Main!B9")&"'!B79")))} | C65: 0
B66: Total Expenses | C66: =SUM(C57:C65) -> 0
A67: {=IF((INDIRECT("'"&INDIRECT("Main!B9")&"'!A81"))=0,"",(INDIRECT("'"&INDIRECT("Main!B9")&"'!A81")))} -> Donation
A68: {=IF((INDIRECT("'"&INDIRECT("Main!B9")&"'!A82"))=0,"",(INDIRECT("'"&INDIRECT("Main!B9")&"'!A82")))} | B68: {=IF((INDIRECT("'"&INDIRECT("Main!B9")&"'!B82"))=0,"",(INDIRECT("'"&INDIRECT("Main!B9")&"'!B82")))} | C68: 0
A69: {=IF((INDIRECT("'"&INDIRECT("Main!B9")&"'!A83"))=0,"",(INDIRECT("'"&INDIRECT("Main!B9")&"'!A83")))} | B69: {=IF((INDIRECT("'"&INDIRECT("Main!B9")&"'!B83"))=0,"",(INDIRECT("'"&INDIRECT("Main!B9")&"'!B83")))} | C69: 0
A70: {=IF((INDIRECT("'"&INDIRECT("Main!B9")&"'!A84"))=0,"",(INDIRECT("'"&INDIRECT("Main!B9")&"'!A84")))} | B70: {=IF((INDIRECT("'"&INDIRECT("Main!B9")&"'!B84"))=0,"",(INDIRECT("'"&INDIRECT("Main!B9")&"'!B84")))} | C70: 0
A71: {=IF((INDIRECT("'"&INDIRECT("Main!B9")&"'!A85"))=0,"",(INDIRECT("'"&INDIRECT("Main!B9")&"'!A85")))} | B71: {=IF((INDIRECT("'"&INDIRECT("Main!B9")&"'!B85"))=0,"",(INDIRECT("'"&INDIRECT("Main!B9")&"'!B85")))} | C71: 0
A72: {=IF((INDIRECT("'"&INDIRECT("Main!B9")&"'!A86"))=0,"",(INDIRECT("'"&INDIRECT("Main!B9")&"'!A86")))} | B72: {=IF((INDIRECT("'"&INDIRECT("Main!B9")&"'!B86"))=0,"",(INDIRECT("'"&INDIRECT("Main!B9")&"'!B86")))} | C72: 0
A73: {=IF((INDIRECT("'"&INDIRECT("Main!B9")&"'!A87"))=0,"",(INDIRECT("'"&INDIRECT("Main!B9")&"'!A87")))} | B73: {=IF((INDIRECT("'"&INDIRECT("Main!B9")&"'!B87"))=0,"",(INDIRECT("'"&INDIRECT("Main!B9")&"'!B87")))} | C73: 0
A74: {=IF((INDIRECT("'"&INDIRECT("Main!B9")&"'!A88"))=0,"",(INDIRECT("'"&INDIRECT("Main!B9")&"'!A88")))} | B74: {=IF((INDIRECT("'"&INDIRECT("Main!B9")&"'!B88"))=0,"",(INDIRECT("'"&INDIRECT("Main!B9")&"'!B88")))} | C74: 0
B75: Total Expenses | C75: =SUM(C68:C74) -> 0
A76: {=IF((INDIRECT("'"&INDIRECT("Main!B9")&"'!A90"))=0,"",(INDIRECT("'"&INDIRECT("Main!B9")&"'!A90")))} -> Insurance (Personal / Properties / Medical)
A77: {=IF((INDIRECT("'"&INDIRECT("Main!B9")&"'!A91"))=0,"",(INDIRECT("'"&INDIRECT("Main!B9")&"'!A91")))} | B77: {=IF((INDIRECT("'"&INDIRECT("Main!B9")&"'!B91"))=0,"",(INDIRECT("'"&INDIRECT("Main!B9")&"'!B91")))} | C77: 0
A78: {=IF((INDIRECT("'"&INDIRECT("Main!B9")&"'!A92"))=0,"",(INDIRECT("'"&INDIRECT("Main!B9")&"'!A92")))} | B78: {=IF((INDIRECT("'"&INDIRECT("Main!B9")&"'!B92"))=0,"",(INDIRECT("'"&INDIRECT("Main!B9")&"'!B92")))} | C78: 0
A79: {=IF((INDIRECT("'"&INDIRECT("Main!B9")&"'!A93"))=0,"",(INDIRECT("'"&INDIRECT("Main!B9")&"'!A93")))} | B79: {=IF((INDIRECT("'"&INDIRECT("Main!B9")&"'!B93"))=0,"",(INDIRECT("'"&INDIRECT("Main!B9")&"'!B93")))} | C79: 0
A80: {=IF((INDIRECT("'"&INDIRECT("Main!B9")&"'!A94"))=0,"",(INDIRECT("'"&INDIRECT("Main!B9")&"'!A94")))} | B80: {=IF((INDIRECT("'"&INDIRECT("Main!B9")&"'!B94"))=0,"",(INDIRECT("'"&INDIRECT("Main!B9")&"'!B94")))} | C80: 0
A81: {=IF((INDIRECT("'"&INDIRECT("Main!B9")&"'!A95"))=0,"",(INDIRECT("'"&INDIRECT("Main!B9")&"'!A95")))} | B81: {=IF((INDIRECT("'"&INDIRECT("Main!B9")&"'!B95"))=0,"",(INDIRECT("'"&INDIRECT("Main!B9")&"'!B95")))} | C81: 0
A82: {=IF((INDIRECT("'"&INDIRECT("Main!B9")&"'!A96"))=0,"",(INDIRECT("'"&INDIRECT("Main!B9")&"'!A96")))} | B82: {=IF((INDIRECT("'"&INDIRECT("Main!B9")&"'!B96"))=0,"",(INDIRECT("'"&INDIRECT("Main!B9")&"'!B96")))} | C82: 0
A83: {=IF((INDIRECT("'"&INDIRECT("Main!B9")&"'!A97"))=0,"",(INDIRECT("'"&INDIRECT("Main!B9")&"'!A97")))} | B83: {=IF((INDIRECT("'"&INDIRECT("Main!B9")&"'!B97"))=0,"",(INDIRECT("'"&INDIRECT("Main!B9")&"'!B97")))} | C83: 0
A84: {=IF((INDIRECT("'"&INDIRECT("Main!B9")&"'!A98"))=0,"",(INDIRECT("'"&INDIRECT("Main!B9")&"'!A98")))} | B84: {=IF((INDIRECT("'"&INDIRECT("Main!B9")&"'!B98"))=0,"",(INDIRECT("'"&INDIRECT("Main!B9")&"'!B98")))} | C84: 0
B85: Total Expenses | C85: =SUM(C77:C84) -> 0
A86: {=IF((INDIRECT("'"&INDIRECT("Main!B9")&"'!A100"))=0,"",(INDIRECT("'"&INDIRECT("Main!B9")&"'!A100")))} -> Other Expenses
A87: {=IF((INDIRECT("'"&INDIRECT("Main!B9")&"'!A101"))=0,"",(INDIRECT("'"&INDIRECT("Main!B9")&"'!A101")))} | B87: {=IF((INDIRECT("'"&INDIRECT("Main!B9")&"'!B101"))=0,"",(INDIRECT("'"&INDIRECT("Main!B9")&"'!B101")))} | C87: 0
A88: {=IF((INDIRECT("'"&INDIRECT("Main!B9")&"'!A102"))=0,"",(INDIRECT("'"&INDIRECT("Main!B9")&"'!A102")))} | B88: {=IF((INDIRECT("'"&INDIRECT("Main!B9")&"'!B102"))=0,"",(INDIRECT("'"&INDIRECT("Main!B9")&"'!B102")))} | C88: 0
A89: {=IF((INDIRECT("'"&INDIRECT("Main!B9")&"'!A103"))=0,"",(INDIRECT("'"&INDIRECT("Main!B9")&"'!A103")))} | B89: {=IF((INDIRECT("'"&INDIRECT("Main!B9")&"'!B103"))=0,"",(INDIRECT("'"&INDIRECT("Main!B9")&"'!B103")))} | C89: 0
A90: {=IF((INDIRECT("'"&INDIRECT("Main!B9")&"'!A104"))=0,"",(INDIRECT("'"&INDIRECT("Main!B9")&"'!A104")))} | B90: {=IF((INDIRECT("'"&INDIRECT("Main!B9")&"'!B104"))=0,"",(INDIRECT("'"&INDIRECT("Main!B9")&"'!B104")))} | C90: 0
A91: {=IF((INDIRECT("'"&INDIRECT("Main!B9")&"'!A105"))=0,"",(INDIRECT("'"&INDIRECT("Main!B9")&"'!A105")))} | B91: {=IF((INDIRECT("'"&INDIRECT("Main!B9")&"'!B105"))=0,"",(INDIRECT("'"&INDIRECT("Main!B9")&"'!B105")))} | C91: 0
A92: {=IF((INDIRECT("'"&INDIRECT("Main!B9")&"'!A106"))=0,"",(INDIRECT("'"&INDIRECT("Main!B9")&"'!A106")))} | B92: {=IF((INDIRECT("'"&INDIRECT("Main!B9")&"'!B106"))=0,"",(INDIRECT("'"&INDIRECT("Main!B9")&"'!B106")))} | C92: 0
A93: {=IF((INDIRECT("'"&INDIRECT("Main!B9")&"'!A107"))=0,"",(INDIRECT("'"&INDIRECT("Main!B9")&"'!A107")))} | B93: {=IF((INDIRECT("'"&INDIRECT("Main!B9")&"'!B107"))=0,"",(INDIRECT("'"&INDIRECT("Main!B9")&"'!B107")))} | C93: 0
A94: {=IF((INDIRECT("'"&INDIRECT("Main!B9")&"'!A108"))=0,"",(INDIRECT("'"&INDIRECT("Main!B9")&"'!A108")))} | B94: {=IF((INDIRECT("'"&INDIRECT("Main!B9")&"'!B108"))=0,"",(INDIRECT("'"&INDIRECT("Main!B9")&"'!B108")))} | C94: 0
B95: Total Expenses | C95: =SUM(C87:C94) -> 0
B96: Grand Expenses Total | C96: =C55+C66+C75+C85+C95 -> 0
A97: {=IF((INDIRECT("'"&INDIRECT("Main!B9")&"'!A111"))=0,"",(INDIRECT("'"&INDIRECT("Main!B9")&"'!A111")))} -> Debts / Borrowed To
A98: {=IF((INDIRECT("'"&INDIRECT("Main!B9")&"'!A112"))=0,"",(INDIRECT("'"&INDIRECT("Main!B9")&"'!A112")))} | B98: {=IF((INDIRECT("'"&INDIRECT("Main!B9")&"'!B112"))=0,"",(INDIRECT("'"&INDIRECT("Main!B9")&"'!B112")))} | C98: {=INDIRECT("'"&INDIRECT("Main!B18")&"'!C98")+SUM(E118+E145+E172)} -> 0
A99: {=IF((INDIRECT("'"&INDIRECT("Main!B9")&"'!A113"))=0,"",(INDIRECT("'"&INDIRECT("Main!B9")&"'!A113")))} | B99: {=IF((INDIRECT("'"&INDIRECT("Main!B9")&"'!B113"))=0,"",(INDIRECT("'"&INDIRECT("Main!B9")&"'!B113")))} | C99: {=INDIRECT("'"&INDIRECT("Main!B18")&"'!C99")+SUM(E119+E146+E173)} -> 0
A100: {=IF((INDIRECT("'"&INDIRECT("Main!B9")&"'!A114"))=0,"",(INDIRECT("'"&INDIRECT("Main!B9")&"'!A114")))} | B100: {=IF((INDIRECT("'"&INDIRECT("Main!B9")&"'!B114"))=0,"",(INDIRECT("'"&INDIRECT("Main!B9")&"'!B114")))} | C100: {=INDIRECT("'"&INDIRECT("Main!B18")&"'!C100")+SUM(E120+E147+E174)} -> 0
A101: {=IF((INDIRECT("'"&INDIRECT("Main!B9")&"'!A115"))=0,"",(INDIRECT("'"&INDIRECT("Main!B9")&"'!A115")))} | B101: {=IF((INDIRECT("'"&INDIRECT("Main!B9")&"'!B115"))=0,"",(INDIRECT("'"&INDIRECT("Main!B9")&"'!B115")))} | C101: {=INDIRECT("'"&INDIRECT("Main!B18")&"'!C101")+SUM(E121+E148+E175)} -> 0
A102: {=IF((INDIRECT("'"&INDIRECT("Main!B9")&"'!A116"))=0,"",(INDIRECT("'"&INDIRECT("Main!B9")&"'!A116")))} | B102: {=IF((INDIRECT("'"&INDIRECT("Main!B9")&"'!B116"))=0,"",(INDIRECT("'"&INDIRECT("Main!B9")&"'!B116")))} | C102: {=INDIRECT("'"&INDIRECT("Main!B18")&"'!C102")+SUM(E122+E149+E176)} -> 0
A103: {=IF((INDIRECT("'"&INDIRECT("Main!B9")&"'!A117"))=0,"",(INDIRECT("'"&INDIRECT("Main!B9")&"'!A117")))} | B103: {=IF((INDIRECT("'"&INDIRECT("Main!B9")&"'!B117"))=0,"",(INDIRECT("'"&INDIRECT("Main!B9")&"'!B117")))} | C103: {=INDIRECT("'"&INDIRECT("Main!B18")&"'!C103")+SUM(E123+E150+E177)} -> 0
A104: {=IF((INDIRECT("'"&INDIRECT("Main!B9")&"'!A118"))=0,"",(INDIRECT("'"&INDIRECT("Main!B9")&"'!A118")))} | B104: {=IF((INDIRECT("'"&INDIRECT("Main!B9")&"'!B118"))=0,"",(INDIRECT("'"&INDIRECT("Main!B9")&"'!B118")))} | C104: {=INDIRECT("'"&INDIRECT("Main!B18")&"'!C104")+SUM(E124+E151+E178)} -> 0
A105: {=IF((INDIRECT("'"&INDIRECT("Main!B9")&"'!A119"))=0,"",(INDIRECT("'"&INDIRECT("Main!B9")&"'!A119")))} | B105: {=IF((INDIRECT("'"&INDIRECT("Main!B9")&"'!B119"))=0,"",(INDIRECT("'"&INDIRECT("Main!B9")&"'!B119")))} | C105: {=INDIRECT("'"&INDIRECT("Main!B18")&"'!C105")+SUM(E125+E152+E179)} -> 0
A106: {=IF((INDIRECT("'"&INDIRECT("Main!B9")&"'!A120"))=0,"",(INDIRECT("'"&INDIRECT("Main!B9")&"'!A120")))} | B106: {=IF((INDIRECT("'"&INDIRECT("Main!B9")&"'!B120"))=0,"",(INDIRECT("'"&INDIRECT("Main!B9")&"'!B120")))} | C106: {=INDIRECT("'"&INDIRECT("Main!B18")&"'!C106")+SUM(E126+E153+E180)} -> 0
A107: {=IF((INDIRECT("'"&INDIRECT("Main!B9")&"'!A121"))=0,"",(INDIRECT("'"&INDIRECT("Main!B9")&"'!A121")))} | B107: {=IF((INDIRECT("'"&INDIRECT("Main!B9")&"'!B121"))=0,"",(INDIRECT("'"&INDIRECT("Main!B9")&"'!B121")))} | C107: {=INDIRECT("'"&INDIRECT("Main!B18")&"'!C107")+SUM(E127+E154+E181)} -> 0
B108: Total Debts | C108: =SUM(C98:C107) -> 0
B109: Grand Total | C109: =C108-C96 -> 0
A114: ="Debts Or Credits For the Comming "&IF(Main!B2,TEXT(EDATE(Main!B3,12),"mmmm dd yyyy"),TEXT(Main!B3+((Main!B5-Main!B3)*12+12),"mmmm dd yyyy"))&" to "&IF(Main!B2,TEXT(EDATE(Main!B3,13)-1,"mmmm dd yyyy"),TEXT(Main!B3+((Main!B5-Main!B3)*13+12),"mmmm dd yyyy")) -> Debts Or Credits For the Comming April 11 2026 to May 10 2026
A115: Principal | C115: Description | E115: Amount
...

Sheet Forecast_6
A1: ="Forecasts For the Year "&IF(Main!B2,TEXT(EDATE(Main!B3,15),"mmmm yyyy"),TEXT(Main!B3+((Main!B5-Main!B3)*15+15),"mmmm yyyy"))&" to "&IF(Main!B2,TEXT(EDATE(Main!B3,18)-1,"mmmm yyyy"),TEXT(Main!B3+((Main!B5-Main!B3)*18+17),"mmmm yyyy")) -> Forecasts For the Year July 2026 to October 2026
A2: Assets | B2: Overall | C2: {=INDIRECT("'"&Main!B9&"'!$C$16")} -> 0
B3: Forecasts | C3: =E190 -> 0
A4: Total | C4: =SUM(C2:G3) -> 0
A5: Net Debts: | C5: =C108 -> 0
A8: =IF(Main!B2,TEXT(EDATE(Main!B3,15),"dd mmmm yyyy"),TEXT(Main!B3+((Main!B5-Main!B3)*15+15),"dd mmmm yyyy"))&" - "&IF(Main!B2,TEXT(EDATE(Main!B3,16)-1,"dd mmmm yyyy"),TEXT(Main!B3+((Main!B5-Main!B3)*16+15),"dd mmmm yyyy"))&" / "&" (Revenue / Deferred Debts Or Expenses)" -> 11 July 2026 - 10 August 2026 / (Revenue / Deferred Debts Or Expenses)
A9: Date | B9: Name | D9: Description | F9: Amount
F10: 0
F11: 0
F12: 0
F13: 0
F14: 0
F15: 0
D16: Total Revenue | F16: =SUM(F10:G15) -> 0
A20: =IF(Main!B2,TEXT(EDATE(Main!B3,16),"dd mmmm yyyy"),TEXT(Main!B3+((Main!B5-Main!B3)*16+16),"dd mmmm yyyy"))&" - "&IF(Main!B2,TEXT(EDATE(Main!B3,17)-1,"dd mmmm yyyy"),TEXT(Main!B3+((Main!B5-Main!B3)*17+16),"dd mmmm yyyy"))&" / "&" (Revenue / Deferred Debts Or Expenses)" -> 11 August 2026 - 10 September 2026 / (Revenue / Deferred Debts Or Expenses)
A21: Date | B21: Name | D21: Description | F21: Amount
F22: 0
F23: 0
F24: 0
F25: 0
F26: 0
F27: 0
D28: Total Revenue | F28: =SUM(F22:G27) -> 0
A32: =IF(Main!B2,TEXT(EDATE(Main!B3,17),"dd mmmm yyyy"),TEXT(Main!B3+((Main!B5-Main!B3)*17+17),"dd mmmm yyyy"))&" - "&IF(Main!B2,TEXT(EDATE(Main!B3,18)-1,"dd mmmm yyyy"),TEXT(Main!B3+((Main!B5-Main!B3)*18+17),"dd mmmm yyyy"))&" / "&" (Revenue / Deferred Debts Or Expenses)" -> 11 September 2026 - 10 October 2026 / (Revenue / Deferred Debts Or Expenses)
A33: Date | B33: Name | D33: Description | F33: Amount
F34: 0
F35: 0
F36: 0
F37: 0
F38: 0
F39: 0
D40: Total Revenue | F40: =SUM(F34:G39) -> 0
A44: ="Fixed Expense For the Year "&IF(Main!B2,TEXT(EDATE(Main!B3,15),"mmmm yyyy"),TEXT(Main!B3+((Main!B5-Main!B3)*15+15),"mmmm yyyy"))&" to "&IF(Main!B2,TEXT(EDATE(Main!B3,18)-1,"mmmm yyyy"),TEXT(Main!B3+((Main!B5-Main!B3)*18+17),"mmmm yyyy")) -> Fixed Expense For the Year July 2026 to October 2026
A45: Name | B45: Description | C45: Amount
A46: {=IF((INDIRECT("'"&INDIRECT("Main!B9")&"'!A60"))=0,"",(INDIRECT("'"&INDIRECT("Main!B9")&"'!A60")))} -> Mobile And Communications/ Housing Expenses
A47: {=IF((INDIRECT("'"&INDIRECT("Main!B9")&"'!A61"))=0,"",(INDIRECT("'"&INDIRECT("Main!B9")&"'!A61")))} | B47: {=IF((INDIRECT("'"&INDIRECT("Main!B9")&"'!B61"))=0,"",(INDIRECT("'"&INDIRECT("Main!B9")&"'!B61")))} | C47: 0
A48: {=IF((INDIRECT("'"&INDIRECT("Main!B9")&"'!A62"))=0,"",(INDIRECT("'"&INDIRECT("Main!B9")&"'!A62")))} | B48: {=IF((INDIRECT("'"&INDIRECT("Main!B9")&"'!B62"))=0,"",(INDIRECT("'"&INDIRECT("Main!B9")&"'!B62")))} | C48: 0
A49: {=IF((INDIRECT("'"&INDIRECT("Main!B9")&"'!A63"))=0,"",(INDIRECT("'"&INDIRECT("Main!B9")&"'!A63")))} | B49: {=IF((INDIRECT("'"&INDIRECT("Main!B9")&"'!B63"))=0,"",(INDIRECT("'"&INDIRECT("Main!B9")&"'!B63")))} | C49: 0
A50: {=IF((INDIRECT("'"&INDIRECT("Main!B9")&"'!A64"))=0,"",(INDIRECT("'"&INDIRECT("Main!B9")&"'!A64")))} | B50: {=IF((INDIRECT("'"&INDIRECT("Main!B9")&"'!B64"))=0,"",(INDIRECT("'"&INDIRECT("Main!B9")&"'!B64")))} | C50: 0
A51: {=IF((INDIRECT("'"&INDIRECT("Main!B9")&"'!A65"))=0,"",(INDIRECT("'"&INDIRECT("Main!B9")&"'!A65")))} | B51: {=IF((INDIRECT("'"&INDIRECT("Main!B9")&"'!B65"))=0,"",(INDIRECT("'"&INDIRECT("Main!B9")&"'!B65")))} | C51: 0
A52: {=IF((INDIRECT("'"&INDIRECT("Main!B9")&"'!A66"))=0,"",(INDIRECT("'"&INDIRECT("Main!B9")&"'!A66")))} | B52: {=IF((INDIRECT("'"&INDIRECT("Main!B9")&"'!B66"))=0,"",(INDIRECT("'"&INDIRECT("Main!B9")&"'!B66")))} | C52: 0
A53: {=IF((INDIRECT("'"&INDIRECT("Main!B9")&"'!A67"))=0,"",(INDIRECT("'"&INDIRECT("Main!B9")&"'!A67")))} | B53: {=IF((INDIRECT("'"&INDIRECT("Main!B9")&"'!B67"))=0,"",(INDIRECT("'"&INDIRECT("Main!B9")&"'!B67")))} | C53: 0
A54: {=IF((INDIRECT("'"&INDIRECT("Main!B9")&"'!A68"))=0,"",(INDIRECT("'"&INDIRECT("Main!B9")&"'!A68")))} | B54: {=IF((INDIRECT("'"&INDIRECT("Main!B9")&"'!B68"))=0,"",(INDIRECT("'"&INDIRECT("Main!B9")&"'!B68")))} | C54: 0
B55: Total Expenses | C55: =SUM(C47:C54) -> 0
A56: {=IF((INDIRECT("'"&INDIRECT("Main!B9")&"'!A70"))=0,"",(INDIRECT("'"&INDIRECT("Main!B9")&"'!A70")))} -> Credit Card Installments/Government Installments
A57: {=IF((INDIRECT("'"&INDIRECT("Main!B9")&"'!A71"))=0,"",(INDIRECT("'"&INDIRECT("Main!B9")&"'!A71")))} | B57: {=IF((INDIRECT("'"&INDIRECT("Main!B9")&"'!B71"))=0,"",(INDIRECT("'"&INDIRECT("Main!B9")&"'!B71")))} | C57: 0
A58: {=IF((INDIRECT("'"&INDIRECT("Main!B9")&"'!A72"))=0,"",(INDIRECT("'"&INDIRECT("Main!B9")&"'!A72")))} | B58: {=IF((INDIRECT("'"&INDIRECT("Main!B9")&"'!B72"))=0,"",(INDIRECT("'"&INDIRECT("Main!B9")&"'!B72")))} | C58: 0
A59: {=IF((INDIRECT("'"&INDIRECT("Main!B9")&"'!A73"))=0,"",(INDIRECT("'"&INDIRECT("Main!B9")&"'!A73")))} | B59: {=IF((INDIRECT("'"&INDIRECT("Main!B9")&"'!B73"))=0,"",(INDIRECT("'"&INDIRECT("Main!B9")&"'!B73")))} | C59: 0
A60: {=IF((INDIRECT("'"&INDIRECT("Main!B9")&"'!A74"))=0,"",(INDIRECT("'"&INDIRECT("Main!B9")&"'!A74")))} | B60: {=IF((INDIRECT("'"&INDIRECT("Main!B9")&"'!B74"))=0,"",(INDIRECT("'"&INDIRECT("Main!B9")&"'!B74")))} | C60: 0
A61: {=IF((INDIRECT("'"&INDIRECT("Main!B9")&"'!A75"))=0,"",(INDIRECT("'"&INDIRECT("Main!B9")&"'!A75")))} | B61: {=IF((INDIRECT("'"&INDIRECT("Main!B9")&"'!B75"))=0,"",(INDIRECT("'"&INDIRECT("Main!B9")&"'!B75")))} | C61: 0
A62: {=IF((INDIRECT("'"&INDIRECT("Main!B9")&"'!A76"))=0,"",(INDIRECT("'"&INDIRECT("Main!B9")&"'!A76")))} | B62: {=IF((INDIRECT("'"&INDIRECT("Main!B9")&"'!B76"))=0,"",(INDIRECT("'"&INDIRECT("Main!B9")&"'!B76")))} | C62: 0
A63: {=IF((INDIRECT("'"&INDIRECT("Main!B9")&"'!A77"))=0,"",(INDIRECT("'"&INDIRECT("Main!B9")&"'!A77")))} | B63: {=IF((INDIRECT("'"&INDIRECT("Main!B9")&"'!B77"))=0,"",(INDIRECT("'"&INDIRECT("Main!B9")&"'!B77")))} | C63: 0
A64: {=IF((INDIRECT("'"&INDIRECT("Main!B9")&"'!A78"))=0,"",(INDIRECT("'"&INDIRECT("Main!B9")&"'!A78")))} | B64: {=IF((INDIRECT("'"&INDIRECT("Main!B9")&"'!B78"))=0,"",(INDIRECT("'"&INDIRECT("Main!B9")&"'!B78")))} | C64: 0
A65: {=IF((INDIRECT("'"&INDIRECT("Main!B9")&"'!A79"))=0,"",(INDIRECT("'"&INDIRECT("Main!B9")&"'!A79")))} | B65: {=IF((INDIRECT("'"&INDIRECT("Main!B9")&"'!B79"))=0,"",(INDIRECT("'"&INDIRECT("Main!B9")&"'!B79")))} | C65: 0
B66: Total Expenses | C66: =SUM(C57:C65) -> 0
A67: {=IF((INDIRECT("'"&INDIRECT("Main!B9")&"'!A81"))=0,"",(INDIRECT("'"&INDIRECT("Main!B9")&"'!A81")))} -> Donation
A68: {=IF((INDIRECT("'"&INDIRECT("Main!B9")&"'!A82"))=0,"",(INDIRECT("'"&INDIRECT("Main!B9")&"'!A82")))} | B68: {=IF((INDIRECT("'"&INDIRECT("Main!B9")&"'!B82"))=0,"",(INDIRECT("'"&INDIRECT("Main!B9")&"'!B82")))} | C68: 0
A69: {=IF((INDIRECT("'"&INDIRECT("Main!B9")&"'!A83"))=0,"",(INDIRECT("'"&INDIRECT("Main!B9")&"'!A83")))} | B69: {=IF((INDIRECT("'"&INDIRECT("Main!B9")&"'!B83"))=0,"",(INDIRECT("'"&INDIRECT("Main!B9")&"'!B83")))} | C69: 0
A70: {=IF((INDIRECT("'"&INDIRECT("Main!B9")&"'!A84"))=0,"",(INDIRECT("'"&INDIRECT("Main!B9")&"'!A84")))} | B70: {=IF((INDIRECT("'"&INDIRECT("Main!B9")&"'!B84"))=0,"",(INDIRECT("'"&INDIRECT("Main!B9")&"'!B84")))} | C70: 0
A71: {=IF((INDIRECT("'"&INDIRECT("Main!B9")&"'!A85"))=0,"",(INDIRECT("'"&INDIRECT("Main!B9")&"'!A85")))} | B71: {=IF((INDIRECT("'"&INDIRECT("Main!B9")&"'!B85"))=0,"",(INDIRECT("'"&INDIRECT("Main!B9")&"'!B85")))} | C71: 0
A72: {=IF((INDIRECT("'"&INDIRECT("Main!B9")&"'!A86"))=0,"",(INDIRECT("'"&INDIRECT("Main!B9")&"'!A86")))} | B72: {=IF((INDIRECT("'"&INDIRECT("Main!B9")&"'!B86"))=0,"",(INDIRECT("'"&INDIRECT("Main!B9")&"'!B86")))} | C72: 0
A73: {=IF((INDIRECT("'"&INDIRECT("Main!B9")&"'!A87"))=0,"",(INDIRECT("'"&INDIRECT("Main!B9")&"'!A87")))} | B73: {=IF((INDIRECT("'"&INDIRECT("Main!B9")&"'!B87"))=0,"",(INDIRECT("'"&INDIRECT("Main!B9")&"'!B87")))} | C73: 0
A74: {=IF((INDIRECT("'"&INDIRECT("Main!B9")&"'!A88"))=0,"",(INDIRECT("'"&INDIRECT("Main!B9")&"'!A88")))} | B74: {=IF((INDIRECT("'"&INDIRECT("Main!B9")&"'!B88"))=0,"",(INDIRECT("'"&INDIRECT("Main!B9")&"'!B88")))} | C74: 0
B75: Total Expenses | C75: =SUM(C68:C74) -> 0
A76: {=IF((INDIRECT("'"&INDIRECT("Main!B9")&"'!A90"))=0,"",(INDIRECT("'"&INDIRECT("Main!B9")&"'!A90")))} -> Insurance (Personal / Properties / Medical)
A77: {=IF((INDIRECT("'"&INDIRECT("Main!B9")&"'!A91"))=0,"",(INDIRECT("'"&INDIRECT("Main!B9")&"'!A91")))} | B77: {=IF((INDIRECT("'"&INDIRECT("Main!B9")&"'!B91"))=0,"",(INDIRECT("'"&INDIRECT("Main!B9")&"'!B91")))} | C77: 0
A78: {=IF((INDIRECT("'"&INDIRECT("Main!B9")&"'!A92"))=0,"",(INDIRECT("'"&INDIRECT("Main!B9")&"'!A92")))} | B78: {=IF((INDIRECT("'"&INDIRECT("Main!B9")&"'!B92"))=0,"",(INDIRECT("'"&INDIRECT("Main!B9")&"'!B92")))} | C78: 0
A79: {=IF((INDIRECT("'"&INDIRECT("Main!B9")&"'!A93"))=0,"",(INDIRECT("'"&INDIRECT("Main!B9")&"'!A93")))} | B79: {=IF((INDIRECT("'"&INDIRECT("Main!B9")&"'!B93"))=0,"",(INDIRECT("'"&INDIRECT("Main!B9")&"'!B93")))} | C79: 0
A80: {=IF((INDIRECT("'"&INDIRECT("Main!B9")&"'!A94"))=0,"",(INDIRECT("'"&INDIRECT("Main!B9")&"'!A94")))} | B80: {=IF((INDIRECT("'"&INDIRECT("Main!B9")&"'!B94"))=0,"",(INDIRECT("'"&INDIRECT("Main!B9")&"'!B94")))} | C80: 0
A81: {=IF((INDIRECT("'"&INDIRECT("Main!B9")&"'!A95"))=0,"",(INDIRECT("'"&INDIRECT("Main!B9")&"'!A95")))} | B81: {=IF((INDIRECT("'"&INDIRECT("Main!B9")&"'!B95"))=0,"",(INDIRECT("'"&INDIRECT("Main!B9")&"'!B95")))} | C81: 0
A82: {=IF((INDIRECT("'"&INDIRECT("Main!B9")&"'!A96"))=0,"",(INDIRECT("'"&INDIRECT("Main!B9")&"'!A96")))} | B82: {=IF((INDIRECT("'"&INDIRECT("Main!B9")&"'!B96"))=0,"",(INDIRECT("'"&INDIRECT("Main!B9")&"'!B96")))} | C82: 0
A83: {=IF((INDIRECT("'"&INDIRECT("Main!B9")&"'!A97"))=0,"",(INDIRECT("'"&INDIRECT("Main!B9")&"'!A97")))} | B83: {=IF((INDIRECT("'"&INDIRECT("Main!B9")&"'!B97"))=0,"",(INDIRECT("'"&INDIRECT("Main!B9")&"'!B97")))} | C83: 0
A84: {=IF((INDIRECT("'"&INDIRECT("Main!B9")&"'!A98"))=0,"",(INDIRECT("'"&INDIRECT("Main!B9")&"'!A98")))} | B84: {=IF((INDIRECT("'"&INDIRECT("Main!B9")&"'!B98"))=0,"",(INDIRECT("'"&INDIRECT("Main!B9")&"'!B98")))} | C84: 0
B85: Total Expenses | C85: =SUM(C77:C84) -> 0
A86: {=IF((INDIRECT("'"&INDIRECT("Main!B9")&"'!A100"))=0,"",(INDIRECT("'"&INDIRECT("Main!B9")&"'!A100")))} -> Other Expenses
A87: {=IF((INDIRECT("'"&INDIRECT("Main!B9")&"'!A101"))=0,"",(INDIRECT("'"&INDIRECT("Main!B9")&"'!A101")))} | B87: {=IF((INDIRECT("'"&INDIRECT("Main!B9")&"'!B101"))=0,"",(INDIRECT("'"&INDIRECT("Main!B9")&"'!B101")))} | C87: 0
A88: {=IF((INDIRECT("'"&INDIRECT("Main!B9")&"'!A102"))=0,"",(INDIRECT("'"&INDIRECT("Main!B9")&"'!A102")))} | B88: {=IF((INDIRECT("'"&INDIRECT("Main!B9")&"'!B102"))=0,"",(INDIRECT("'"&INDIRECT("Main!B9")&"'!B102")))} | C88: 0
A89: {=IF((INDIRECT("'"&INDIRECT("Main!B9")&"'!A103"))=0,"",(INDIRECT("'"&INDIRECT("Main!B9")&"'!A103")))} | B89: {=IF((INDIRECT("'"&INDIRECT("Main!B9")&"'!B103"))=0,"",(INDIRECT("'"&INDIRECT("Main!B9")&"'!B103")))} | C89: 0
A90: {=IF((INDIRECT("'"&INDIRECT("Main!B9")&"'!A104"))=0,"",(INDIRECT("'"&INDIRECT("Main!B9")&"'!A104")))} | B90: {=IF((INDIRECT("'"&INDIRECT("Main!B9")&"'!B104"))=0,"",(INDIRECT("'"&INDIRECT("Main!B9")&"'!B104")))} | C90: 0
A91: {=IF((INDIRECT("'"&INDIRECT("Main!B9")&"'!A105"))=0,"",(INDIRECT("'"&INDIRECT("Main!B9")&"'!A105")))} | B91: {=IF((INDIRECT("'"&INDIRECT("Main!B9")&"'!B105"))=0,"",(INDIRECT("'"&INDIRECT("Main!B9")&"'!B105")))} | C91: 0
A92: {=IF((INDIRECT("'"&INDIRECT("Main!B9")&"'!A106"))=0,"",(INDIRECT("'"&INDIRECT("Main!B9")&"'!A106")))} | B92: {=IF((INDIRECT("'"&INDIRECT("Main!B9")&"'!B106"))=0,"",(INDIRECT("'"&INDIRECT("Main!B9")&"'!B106")))} | C92: 0
A93: {=IF((INDIRECT("'"&INDIRECT("Main!B9")&"'!A107"))=0,"",(INDIRECT("'"&INDIRECT("Main!B9")&"'!A107")))} | B93: {=IF((INDIRECT("'"&INDIRECT("Main!B9")&"'!B107"))=0,"",(INDIRECT("'"&INDIRECT("Main!B9")&"'!B107")))} | C93: 0
A94: {=IF((INDIRECT("'"&INDIRECT("Main!B9")&"'!A108"))=0,"",(INDIRECT("'"&INDIRECT("Main!B9")&"'!A108")))} | B94: {=IF((INDIRECT("'"&INDIRECT("Main!B9")&"'!B108"))=0,"",(INDIRECT("'"&INDIRECT("Main!B9")&"'!B108")))} | C94: 0
B95: Total Expenses | C95: =SUM(C87:C94) -> 0
B96: Grand Expenses Total | C96: =C55+C66+C75+C85+C95 -> 0
A97: {=IF((INDIRECT("'"&INDIRECT("Main!B9")&"'!A111"))=0,"",(INDIRECT("'"&INDIRECT("Main!B9")&"'!A111")))} -> Debts / Borrowed To
A98: {=IF((INDIRECT("'"&INDIRECT("Main!B9")&"'!A112"))=0,"",(INDIRECT("'"&INDIRECT("Main!B9")&"'!A112")))} | B98: {=IF((INDIRECT("'"&INDIRECT("Main!B9")&"'!B112"))=0,"",(INDIRECT("'"&INDIRECT("Main!B9")&"'!B112")))} | C98: {=INDIRECT("'"&INDIRECT("Main!B21")&"'!C98")+SUM(E118+E145+E172)} -> 0
A99: {=IF((INDIRECT("'"&INDIRECT("Main!B9")&"'!A113"))=0,"",(INDIRECT("'"&INDIRECT("Main!B9")&"'!A113")))} | B99: {=IF((INDIRECT("'"&INDIRECT("Main!B9")&"'!B113"))=0,"",(INDIRECT("'"&INDIRECT("Main!B9")&"'!B113")))} | C99: {=INDIRECT("'"&INDIRECT("Main!B21")&"'!C99")+SUM(E119+E146+E173)} -> 0
A100: {=IF((INDIRECT("'"&INDIRECT("Main!B9")&"'!A114"))=0,"",(INDIRECT("'"&INDIRECT("Main!B9")&"'!A114")))} | B100: {=IF((INDIRECT("'"&INDIRECT("Main!B9")&"'!B114"))=0,"",(INDIRECT("'"&INDIRECT("Main!B9")&"'!B114")))} | C100: {=INDIRECT("'"&INDIRECT("Main!B21")&"'!C100")+SUM(E120+E147+E174)} -> 0
A101: {=IF((INDIRECT("'"&INDIRECT("Main!B9")&"'!A115"))=0,"",(INDIRECT("'"&INDIRECT("Main!B9")&"'!A115")))} | B101: {=IF((INDIRECT("'"&INDIRECT("Main!B9")&"'!B115"))=0,"",(INDIRECT("'"&INDIRECT("Main!B9")&"'!B115")))} | C101: {=INDIRECT("'"&INDIRECT("Main!B21")&"'!C101")+SUM(E121+E148+E175)} -> 0
A102: {=IF((INDIRECT("'"&INDIRECT("Main!B9")&"'!A116"))=0,"",(INDIRECT("'"&INDIRECT("Main!B9")&"'!A116")))} | B102: {=IF((INDIRECT("'"&INDIRECT("Main!B9")&"'!B116"))=0,"",(INDIRECT("'"&INDIRECT("Main!B9")&"'!B116")))} | C102: {=INDIRECT("'"&INDIRECT("Main!B21")&"'!C102")+SUM(E122+E149+E176)} -> 0
A103: {=IF((INDIRECT("'"&INDIRECT("Main!B9")&"'!A117"))=0,"",(INDIRECT("'"&INDIRECT("Main!B9")&"'!A117")))} | B103: {=IF((INDIRECT("'"&INDIRECT("Main!B9")&"'!B117"))=0,"",(INDIRECT("'"&INDIRECT("Main!B9")&"'!B117")))} | C103: {=INDIRECT("'"&INDIRECT("Main!B21")&"'!C103")+SUM(E123+E150+E177)} -> 0
A104: {=IF((INDIRECT("'"&INDIRECT("Main!B9")&"'!A118"))=0,"",(INDIRECT("'"&INDIRECT("Main!B9")&"'!A118")))} | B104: {=IF((INDIRECT("'"&INDIRECT("Main!B9")&"'!B118"))=0,"",(INDIRECT("'"&INDIRECT("Main!B9")&"'!B118")))} | C104: {=INDIRECT("'"&INDIRECT("Main!B21")&"'!C104")+SUM(E124+E151+E178)} -> 0
A105: {=IF((INDIRECT("'"&INDIRECT("Main!B9")&"'!A119"))=0,"",(INDIRECT("'"&INDIRECT("Main!B9")&"'!A119")))} | B105: {=IF((INDIRECT("'"&INDIRECT("Main!B9")&"'!B119"))=0,"",(INDIRECT("'"&INDIRECT("Main!B9")&"'!B119")))} | C105: {=INDIRECT("'"&INDIRECT("Main!B21")&"'!C105")+SUM(E125+E152+E179)} -> 0
A106: {=IF((INDIRECT("'"&INDIRECT("Main!B9")&"'!A120"))=0,"",(INDIRECT("'"&INDIRECT("Main!B9")&"'!A120")))} | B106: {=IF((INDIRECT("'"&INDIRECT("Main!B9")&"'!B120"))=0,"",(INDIRECT("'"&INDIRECT("Main!B9")&"'!B120")))} | C106: {=INDIRECT("'"&INDIRECT("Main!B21")&"'!C106")+SUM(E126+E153+E180)} -> 0
A107: {=IF((INDIRECT("'"&INDIRECT("Main!B9")&"'!A121"))=0,"",(INDIRECT("'"&INDIRECT("Main!B9")&"'!A121")))} | B107: {=IF((INDIRECT("'"&INDIRECT("Main!B9")&"'!B121"))=0,"",(INDIRECT("'"&INDIRECT("Main!B9")&"'!B121")))} | C107: {=INDIRECT("'"&INDIRECT("Main!B21")&"'!C107")+SUM(E127+E154+E181)} -> 0
B108: Total Debts | C108: =SUM(C98:C107) -> 0
B109: Grand Total | C109: =C108-C96 -> 0
A114: ="Debts Or Credits For the Comming "&IF(Main!B2,TEXT(EDATE(Main!B3,15),"mmmm dd yyyy"),TEXT(Main!B3+((Main!B5-Main!B3)*15+15),"mmmm dd yyyy"))&" to "&IF(Main!B2,TEXT(EDATE(Main!B3,16)-1,"mmmm dd yyyy"),TEXT(Main!B3+((Main!B5-Main!B3)*16+15),"mmmm dd yyyy")) -> Debts Or Credits For the Comming July 11 2026 to August 10 2026
A115: Principal | C115: Description | E115: Amount
...

Sheet Forecast_7
A1: ="Forecasts For the Year "&IF(Main!B2,TEXT(EDATE(Main!B3,18),"mmmm yyyy"),TEXT(Main!B3+((Main!B5-Main!B3)*18+18),"mmmm yyyy"))&" to "&IF(Main!B2,TEXT(EDATE(Main!B3,21)-1,"mmmm yyyy"),TEXT(Main!B3+((Main!B5-Main!B3)*21+20),"mmmm yyyy")) -> Forecasts For the Year October 2026 to January 2027
A2: Assets | B2: Overall | C2: {=INDIRECT("'"&Main!B9&"'!$C$16")} -> 0
B3: Forecasts | C3: =E190 -> 0
A4: Total | C4: =SUM(C2:G3) -> 0
A5: Net Debts: | C5: =C108 -> 0
A8: =IF(Main!B2,TEXT(EDATE(Main!B3,18),"dd mmmm yyyy"),TEXT(Main!B3+((Main!B5-Main!B3)*18+18),"dd mmmm yyyy"))&" - "&IF(Main!B2,TEXT(EDATE(Main!B3,19)-1,"dd mmmm yyyy"),TEXT(Main!B3+((Main!B5-Main!B3)*19+18),"dd mmmm yyyy"))&" / "&" (Revenue / Deferred Debts Or Expenses)" -> 11 October 2026 - 10 November 2026 / (Revenue / Deferred Debts Or Expenses)
A9: Date | B9: Name | D9: Description | F9: Amount
F10: 0
F11: 0
F12: 0
F13: 0
F14: 0
F15: 0
D16: Total Revenue | F16: =SUM(F10:G15) -> 0
A20: =IF(Main!B2,TEXT(EDATE(Main!B3,19),"dd mmmm yyyy"),TEXT(Main!B3+((Main!B5-Main!B3)*19+19),"dd mmmm yyyy"))&" - "&IF(Main!B2,TEXT(EDATE(Main!B3,20)-1,"dd mmmm yyyy"),TEXT(Main!B3+((Main!B5-Main!B3)*20+19),"dd mmmm yyyy"))&" / "&" (Revenue / Deferred Debts Or Expenses)" -> 11 November 2026 - 10 December 2026 / (Revenue / Deferred Debts Or Expenses)
A21: Date | B21: Name | D21: Description | F21: Amount
F22: 0
F23: 0
F24: 0
F25: 0
F26: 0
F27: 0
D28: Total Revenue | F28: =SUM(F22:G27) -> 0
A32: =IF(Main!B2,TEXT(EDATE(Main!B3,20),"dd mmmm yyyy"),TEXT(Main!B3+((Main!B5-Main!B3)*20+20),"dd mmmm yyyy"))&" - "&IF(Main!B2,TEXT(EDATE(Main!B3,21)-1,"dd mmmm yyyy"),TEXT(Main!B3+((Main!B5-Main!B3)*21+20),"dd mmmm yyyy"))&" / "&" (Revenue / Deferred Debts Or Expenses)" -> 11 December 2026 - 10 January 2027 / (Revenue / Deferred Debts Or Expenses)
A33: Date | B33: Name | D33: Description | F33: Amount
F34: 0
F35: 0
F36: 0
F37: 0
F38: 0
F39: 0
D40: Total Revenue | F40: =SUM(F34:G39) -> 0
A44: ="Fixed Expense For the Year "&IF(Main!B2,TEXT(EDATE(Main!B3,18),"mmmm yyyy"),TEXT(Main!B3+((Main!B5-Main!B3)*18+18),"mmmm yyyy"))&" to "&IF(Main!B2,TEXT(EDATE(Main!B3,21)-1,"mmmm yyyy"),TEXT(Main!B3+((Main!B5-Main!B3)*21+20),"mmmm yyyy")) -> Fixed Expense For the Year October 2026 to January 2027
A45: Name | B45: Description | C45: Amount
A46: {=IF((INDIRECT("'"&INDIRECT("Main!B9")&"'!A60"))=0,"",(INDIRECT("'"&INDIRECT("Main!B9")&"'!A60")))} -> Mobile And Communications/ Housing Expenses
A47: {=IF((INDIRECT("'"&INDIRECT("Main!B9")&"'!A61"))=0,"",(INDIRECT("'"&INDIRECT("Main!B9")&"'!A61")))} | B47: {=IF((INDIRECT("'"&INDIRECT("Main!B9")&"'!B61"))=0,"",(INDIRECT("'"&INDIRECT("Main!B9")&"'!B61")))} | C47: 0
A48: {=IF((INDIRECT("'"&INDIRECT("Main!B9")&"'!A62"))=0,"",(INDIRECT("'"&INDIRECT("Main!B9")&"'!A62")))} | B48: {=IF((INDIRECT("'"&INDIRECT("Main!B9")&"'!B62"))=0,"",(INDIRECT("'"&INDIRECT("Main!B9")&"'!B62")))} | C48: 0
A49: {=IF((INDIRECT("'"&INDIRECT("Main!B9")&"'!A63"))=0,"",(INDIRECT("'"&INDIRECT("Main!B9")&"'!A63")))} | B49: {=IF((INDIRECT("'"&INDIRECT("Main!B9")&"'!B63"))=0,"",(INDIRECT("'"&INDIRECT("Main!B9")&"'!B63")))} | C49: 0
A50: {=IF((INDIRECT("'"&INDIRECT("Main!B9")&"'!A64"))=0,"",(INDIRECT("'"&INDIRECT("Main!B9")&"'!A64")))} | B50: {=IF((INDIRECT("'"&INDIRECT("Main!B9")&"'!B64"))=0,"",(INDIRECT("'"&INDIRECT("Main!B9")&"'!B64")))} | C50: 0
A51: {=IF((INDIRECT("'"&INDIRECT("Main!B9")&"'!A65"))=0,"",(INDIRECT("'"&INDIRECT("Main!B9")&"'!A65")))} | B51: {=IF((INDIRECT("'"&INDIRECT("Main!B9")&"'!B65"))=0,"",(INDIRECT("'"&INDIRECT("Main!B9")&"'!B65")))} | C51: 0
A52: {=IF((INDIRECT("'"&INDIRECT("Main!B9")&"'!A66"))=0,"",(INDIRECT("'"&INDIRECT("Main!B9")&"'!A66")))} | B52: {=IF((INDIRECT("'"&INDIRECT("Main!B9")&"'!B66"))=0,"",(INDIRECT("'"&INDIRECT("Main!B9")&"'!B66")))} | C52: 0
A53: {=IF((INDIRECT("'"&INDIRECT("Main!B9")&"'!A67"))=0,"",(INDIRECT("'"&INDIRECT("Main!B9")&"'!A67")))} | B53: {=IF((INDIRECT("'"&INDIRECT("Main!B9")&"'!B67"))=0,"",(INDIRECT("'"&INDIRECT("Main!B9")&"'!B67")))} | C53: 0
A54: {=IF((INDIRECT("'"&INDIRECT("Main!B9")&"'!A68"))=0,"",(INDIRECT("'"&INDIRECT("Main!B9")&"'!A68")))} | B54: {=IF((INDIRECT("'"&INDIRECT("Main!B9")&"'!B68"))=0,"",(INDIRECT("'"&INDIRECT("Main!B9")&"'!B68")))} | C54: 0
B55: Total Expenses | C55: =SUM(C47:C54) -> 0
A56: {=IF((INDIRECT("'"&INDIRECT("Main!B9")&"'!A70"))=0,"",(INDIRECT("'"&INDIRECT("Main!B9")&"'!A70")))} -> Credit Card Installments/Government Installments
A57: {=IF((INDIRECT("'"&INDIRECT("Main!B9")&"'!A71"))=0,"",(INDIRECT("'"&INDIRECT("Main!B9")&"'!A71")))} | B57: {=IF((INDIRECT("'"&INDIRECT("Main!B9")&"'!B71"))=0,"",(INDIRECT("'"&INDIRECT("Main!B9")&"'!B71")))} | C57: 0
A58: {=IF((INDIRECT("'"&INDIRECT("Main!B9")&"'!A72"))=0,"",(INDIRECT("'"&INDIRECT("Main!B9")&"'!A72")))} | B58: {=IF((INDIRECT("'"&INDIRECT("Main!B9")&"'!B72"))=0,"",(INDIRECT("'"&INDIRECT("Main!B9")&"'!B72")))} | C58: 0
A59: {=IF((INDIRECT("'"&INDIRECT("Main!B9")&"'!A73"))=0,"",(INDIRECT("'"&INDIRECT("Main!B9")&"'!A73")))} | B59: {=IF((INDIRECT("'"&INDIRECT("Main!B9")&"'!B73"))=0,"",(INDIRECT("'"&INDIRECT("Main!B9")&"'!B73")))} | C59: 0
A60: {=IF((INDIRECT("'"&INDIRECT("Main!B9")&"'!A74"))=0,"",(INDIRECT("'"&INDIRECT("Main!B9")&"'!A74")))} | B60: {=IF((INDIRECT("'"&INDIRECT("Main!B9")&"'!B74"))=0,"",(INDIRECT("'"&INDIRECT("Main!B9")&"'!B74")))} | C60: 0
A61: {=IF((INDIRECT("'"&INDIRECT("Main!B9")&"'!A75"))=0,"",(INDIRECT("'"&INDIRECT("Main!B9")&"'!A75")))} | B61: {=IF((INDIRECT("'"&INDIRECT("Main!B9")&"'!B75"))=0,"",(INDIRECT("'"&INDIRECT("Main!B9")&"'!B75")))} | C61: 0
A62: {=IF((INDIRECT("'"&INDIRECT("Main!B9")&"'!A76"))=0,"",(INDIRECT("'"&INDIRECT("Main!B9")&"'!A76")))} | B62: {=IF((INDIRECT("'"&INDIRECT("Main!B9")&"'!B76"))=0,"",(INDIRECT("'"&INDIRECT("Main!B9")&"'!B76")))} | C62: 0
A63: {=IF((INDIRECT("'"&INDIRECT("Main!B9")&"'!A77"))=0,"",(INDIRECT("'"&INDIRECT("Main!B9")&"'!A77")))} | B63: {=IF((INDIRECT("'"&INDIRECT("Main!B9")&"'!B77"))=0,"",(INDIRECT("'"&INDIRECT("Main!B9")&"'!B77")))} | C63: 0
A64: {=IF((INDIRECT("'"&INDIRECT("Main!B9")&"'!A78"))=0,"",(INDIRECT("'"&INDIRECT("Main!B9")&"'!A78")))} | B64: {=IF((INDIRECT("'"&INDIRECT("Main!B9")&"'!B78"))=0,"",(INDIRECT("'"&INDIRECT("Main!B9")&"'!B78")))} | C64: 0
A65: {=IF((INDIRECT("'"&INDIRECT("Main!B9")&"'!A79"))=0,"",(INDIRECT("'"&INDIRECT("Main!B9")&"'!A79")))} | B65: {=IF((INDIRECT("'"&INDIRECT("Main!B9")&"'!B79"))=0,"",(INDIRECT("'"&INDIRECT("Main!B9")&"'!B79")))} | C65: 0
B66: Total Expenses | C66: =SUM(C57:C65) -> 0
A67: {=IF((INDIRECT("'"&INDIRECT("Main!B9")&"'!A81"))=0,"",(INDIRECT("'"&INDIRECT("Main!B9")&"'!A81")))} -> Donation
A68: {=IF((INDIRECT("'"&INDIRECT("Main!B9")&"'!A82"))=0,"",(INDIRECT("'"&INDIRECT("Main!B9")&"'!A82")))} | B68: {=IF((INDIRECT("'"&INDIRECT("Main!B9")&"'!B82"))=0,"",(INDIRECT("'"&INDIRECT("Main!B9")&"'!B82")))} | C68: 0
A69: {=IF((INDIRECT("'"&INDIRECT("Main!B9")&"'!A83"))=0,"",(INDIRECT("'"&INDIRECT("Main!B9")&"'!A83")))} | B69: {=IF((INDIRECT("'"&INDIRECT("Main!B9")&"'!B83"))=0,"",(INDIRECT("'"&INDIRECT("Main!B9")&"'!B83")))} | C69: 0
A70: {=IF((INDIRECT("'"&INDIRECT("Main!B9")&"'!A84"))=0,"",(INDIRECT("'"&INDIRECT("Main!B9")&"'!A84")))} | B70: {=IF((INDIRECT("'"&INDIRECT("Main!B9")&"'!B84"))=0,"",(INDIRECT("'"&INDIRECT("Main!B9")&"'!B84")))} | C70: 0
A71: {=IF((INDIRECT("'"&INDIRECT("Main!B9")&"'!A85"))=0,"",(INDIRECT("'"&INDIRECT("Main!B9")&"'!A85")))} | B71: {=IF((INDIRECT("'"&INDIRECT("Main!B9")&"'!B85"))=0,"",(INDIRECT("'"&INDIRECT("Main!B9")&"'!B85")))} | C71: 0
A72: {=IF((INDIRECT("'"&INDIRECT("Main!B9")&"'!A86"))=0,"",(INDIRECT("'"&INDIRECT("Main!B9")&"'!A86")))} | B72: {=IF((INDIRECT("'"&INDIRECT("Main!B9")&"'!B86"))=0,"",(INDIRECT("'"&INDIRECT("Main!B9")&"'!B86")))} | C72: 0
A73: {=IF((INDIRECT("'"&INDIRECT("Main!B9")&"'!A87"))=0,"",(INDIRECT("'"&INDIRECT("Main!B9")&"'!A87")))} | B73: {=IF((INDIRECT("'"&INDIRECT("Main!B9")&"'!B87"))=0,"",(INDIRECT("'"&INDIRECT("Main!B9")&"'!B87")))} | C73: 0
A74: {=IF((INDIRECT("'"&INDIRECT("Main!B9")&"'!A88"))=0,"",(INDIRECT("'"&INDIRECT("Main!B9")&"'!A88")))} | B74: {=IF((INDIRECT("'"&INDIRECT("Main!B9")&"'!B88"))=0,"",(INDIRECT("'"&INDIRECT("Main!B9")&"'!B88")))} | C74: 0
B75: Total Expenses | C75: =SUM(C68:C74) -> 0
A76: {=IF((INDIRECT("'"&INDIRECT("Main!B9")&"'!A90"))=0,"",(INDIRECT("'"&INDIRECT("Main!B9")&"'!A90")))} -> Insurance (Personal / Properties / Medical)
A77: {=IF((INDIRECT("'"&INDIRECT("Main!B9")&"'!A91"))=0,"",(INDIRECT("'"&INDIRECT("Main!B9")&"'!A91")))} | B77: {=IF((INDIRECT("'"&INDIRECT("Main!B9")&"'!B91"))=0,"",(INDIRECT("'"&INDIRECT("Main!B9")&"'!B91")))} | C77: 0
A78: {=IF((INDIRECT("'"&INDIRECT("Main!B9")&"'!A92"))=0,"",(INDIRECT("'"&INDIRECT("Main!B9")&"'!A92")))} | B78: {=IF((INDIRECT("'"&INDIRECT("Main!B9")&"'!B92"))=0,"",(INDIRECT("'"&INDIRECT("Main!B9")&"'!B92")))} | C78: 0
A79: {=IF((INDIRECT("'"&INDIRECT("Main!B9")&"'!A93"))=0,"",(INDIRECT("'"&INDIRECT("Main!B9")&"'!A93")))} | B79: {=IF((INDIRECT("'"&INDIRECT("Main!B9")&"'!B93"))=0,"",(INDIRECT("'"&INDIRECT("Main!B9")&"'!B93")))} | C79: 0
A80: {=IF((INDIRECT("'"&INDIRECT("Main!B9")&"'!A94"))=0,"",(INDIRECT("'"&INDIRECT("Main!B9")&"'!A94")))} | B80: {=IF((INDIRECT("'"&INDIRECT("Main!B9")&"'!B94"))=0,"",(INDIRECT("'"&INDIRECT("Main!B9")&"'!B94")))} | C80: 0
A81: {=IF((INDIRECT("'"&INDIRECT("Main!B9")&"'!A95"))=0,"",(INDIRECT("'"&INDIRECT("Main!B9")&"'!A95")))} | B81: {=IF((INDIRECT("'"&INDIRECT("Main!B9")&"'!B95"))=0,"",(INDIRECT("'"&INDIRECT("Main!B9")&"'!B95")))} | C81: 0
A82: {=IF((INDIRECT("'"&INDIRECT("Main!B9")&"'!A96"))=0,"",(INDIRECT("'"&INDIRECT("Main!B9")&"'!A96")))} | B82: {=IF((INDIRECT("'"&INDIRECT("Main!B9")&"'!B96"))=0,"",(INDIRECT("'"&INDIRECT("Main!B9")&"'!B96")))} | C82: 0
A83: {=IF((INDIRECT("'"&INDIRECT("Main!B9")&"'!A97"))=0,"",(INDIRECT("'"&INDIRECT("Main!B9")&"'!A97")))} | B83: {=IF((INDIRECT("'"&INDIRECT("Main!B9")&"'!B97"))=0,"",(INDIRECT("'"&INDIRECT("Main!B9")&"'!B97")))} | C83: 0
A84: {=IF((INDIRECT("'"&INDIRECT("Main!B9")&"'!A98"))=0,"",(INDIRECT("'"&INDIRECT("Main!B9")&"'!A98")))} | B84: {=IF((INDIRECT("'"&INDIRECT("Main!B9")&"'!B98"))=0,"",(INDIRECT("'"&INDIRECT("Main!B9")&"'!B98")))} | C84: 0
B85: Total Expenses | C85: =SUM(C77:C84) -> 0
A86: {=IF((INDIRECT("'"&INDIRECT("Main!B9")&"'!A100"))=0,"",(INDIRECT("'"&INDIRECT("Main!B9")&"'!A100")))} -> Other Expenses
A87: {=IF((INDIRECT("'"&INDIRECT("Main!B9")&"'!A101"))=0,"",(INDIRECT("'"&INDIRECT("Main!B9")&"'!A101")))} | B87: {=IF((INDIRECT("'"&INDIRECT("Main!B9")&"'!B101"))=0,"",(INDIRECT("'"&INDIRECT("Main!B9")&"'!B101")))} | C87: 0
A88: {=IF((INDIRECT("'"&INDIRECT("Main!B9")&"'!A102"))=0,"",(INDIRECT("'"&INDIRECT("Main!B9")&"'!A102")))} | B88: {=IF((INDIRECT("'"&INDIRECT("Main!B9")&"'!B102"))=0,"",(INDIRECT("'"&INDIRECT("Main!B9")&"'!B102")))} | C88: 0
A89: {=IF((INDIRECT("'"&INDIRECT("Main!B9")&"'!A103"))=0,"",(INDIRECT("'"&INDIRECT("Main!B9")&"'!A103")))} | B89: {=IF((INDIRECT("'"&INDIRECT("Main!B9")&"'!B103"))=0,"",(INDIRECT("'"&INDIRECT("Main!B9")&"'!B103")))} | C89: 0
A90: {=IF((INDIRECT("'"&INDIRECT("Main!B9")&"'!A104"))=0,"",(INDIRECT("'"&INDIRECT("Main!B9")&"'!A104")))} | B90: {=IF((INDIRECT("'"&INDIRECT("Main!B9")&"'!B104"))=0,"",(INDIRECT("'"&INDIRECT("Main!B9")&"'!B104")))} | C90: 0
A91: {=IF((INDIRECT("'"&INDIRECT("Main!B9")&"'!A105"))=0,"",(INDIRECT("'"&INDIRECT("Main!B9")&"'!A105")))} | B91: {=IF((INDIRECT("'"&INDIRECT("Main!B9")&"'!B105"))=0,"",(INDIRECT("'"&INDIRECT("Main!B9")&"'!B105")))} | C91: 0
A92: {=IF((INDIRECT("'"&INDIRECT("Main!B9")&"'!A106"))=0,"",(INDIRECT("'"&INDIRECT("Main!B9")&"'!A106")))} | B92: {=IF((INDIRECT("'"&INDIRECT("Main!B9")&"'!B106"))=0,"",(INDIRECT("'"&INDIRECT("Main!B9")&"'!B106")))} | C92: 0
A93: {=IF((INDIRECT("'"&INDIRECT("Main!B9")&"'!A107"))=0,"",(INDIRECT("'"&INDIRECT("Main!B9")&"'!A107")))} | B93: {=IF((INDIRECT("'"&INDIRECT("Main!B9")&"'!B107"))=0,"",(INDIRECT("'"&INDIRECT("Main!B9")&"'!B107")))} | C93: 0
A94: {=IF((INDIRECT("'"&INDIRECT("Main!B9")&"'!A108"))=0,"",(INDIRECT("'"&INDIRECT("Main!B9")&"'!A108")))} | B94: {=IF((INDIRECT("'"&INDIRECT("Main!B9")&"'!B108"))=0,"",(INDIRECT("'"&INDIRECT("Main!B9")&"'!B108")))} | C94: 0
B95: Total Expenses | C95: =SUM(C87:C94) -> 0
B96: Grand Expenses Total | C96: =C55+C66+C75+C85+C95 -> 0
A97: {=IF((INDIRECT("'"&INDIRECT("Main!B9")&"'!A111"))=0,"",(INDIRECT("'"&INDIRECT("Main!B9")&"'!A111")))} -> Debts / Borrowed To
A98: {=IF((INDIRECT("'"&INDIRECT("Main!B9")&"'!A112"))=0,"",(INDIRECT("'"&INDIRECT("Main!B9")&"'!A112")))} | B98: {=IF((INDIRECT("'"&INDIRECT("Main!B9")&"'!B112"))=0,"",(INDIRECT("'"&INDIRECT("Main!B9")&"'!B112")))} | C98: {=INDIRECT("'"&INDIRECT("Main!B24")&"'!C98")+SUM(E118+E145+E172)} -> 0
A99: {=IF((INDIRECT("'"&INDIRECT("Main!B9")&"'!A113"))=0,"",(INDIRECT("'"&INDIRECT("Main!B9")&"'!A113")))} | B99: {=IF((INDIRECT("'"&INDIRECT("Main!B9")&"'!B113"))=0,"",(INDIRECT("'"&INDIRECT("Main!B9")&"'!B113")))} | C99: {=INDIRECT("'"&INDIRECT("Main!B24")&"'!C99")+SUM(E119+E146+E173)} -> 0
A100: {=IF((INDIRECT("'"&INDIRECT("Main!B9")&"'!A114"))=0,"",(INDIRECT("'"&INDIRECT("Main!B9")&"'!A114")))} | B100: {=IF((INDIRECT("'"&INDIRECT("Main!B9")&"'!B114"))=0,"",(INDIRECT("'"&INDIRECT("Main!B9")&"'!B114")))} | C100: {=INDIRECT("'"&INDIRECT("Main!B24")&"'!C100")+SUM(E120+E147+E174)} -> 0
A101: {=IF((INDIRECT("'"&INDIRECT("Main!B9")&"'!A115"))=0,"",(INDIRECT("'"&INDIRECT("Main!B9")&"'!A115")))} | B101: {=IF((INDIRECT("'"&INDIRECT("Main!B9")&"'!B115"))=0,"",(INDIRECT("'"&INDIRECT("Main!B9")&"'!B115")))} | C101: {=INDIRECT("'"&INDIRECT("Main!B24")&"'!C101")+SUM(E121+E148+E175)} -> 0
A102: {=IF((INDIRECT("'"&INDIRECT("Main!B9")&"'!A116"))=0,"",(INDIRECT("'"&INDIRECT("Main!B9")&"'!A116")))} | B102: {=IF((INDIRECT("'"&INDIRECT("Main!B9")&"'!B116"))=0,"",(INDIRECT("'"&INDIRECT("Main!B9")&"'!B116")))} | C102: {=INDIRECT("'"&INDIRECT("Main!B24")&"'!C102")+SUM(E122+E149+E176)} -> 0
A103: {=IF((INDIRECT("'"&INDIRECT("Main!B9")&"'!A117"))=0,"",(INDIRECT("'"&INDIRECT("Main!B9")&"'!A117")))} | B103: {=IF((INDIRECT("'"&INDIRECT("Main!B9")&"'!B117"))=0,"",(INDIRECT("'"&INDIRECT("Main!B9")&"'!B117")))} | C103: {=INDIRECT("'"&INDIRECT("Main!B24")&"'!C103")+SUM(E123+E150+E177)} -> 0
A104: {=IF((INDIRECT("'"&INDIRECT("Main!B9")&"'!A118"))=0,"",(INDIRECT("'"&INDIRECT("Main!B9")&"'!A118")))} | B104: {=IF((INDIRECT("'"&INDIRECT("Main!B9")&"'!B118"))=0,"",(INDIRECT("'"&INDIRECT("Main!B9")&"'!B118")))} | C104: {=INDIRECT("'"&INDIRECT("Main!B24")&"'!C104")+SUM(E124+E151+E178)} -> 0
A105: {=IF((INDIRECT("'"&INDIRECT("Main!B9")&"'!A119"))=0,"",(INDIRECT("'"&INDIRECT("Main!B9")&"'!A119")))} | B105: {=IF((INDIRECT("'"&INDIRECT("Main!B9")&"'!B119"))=0,"",(INDIRECT("'"&INDIRECT("Main!B9")&"'!B119")))} | C105: {=INDIRECT("'"&INDIRECT("Main!B24")&"'!C105")+SUM(E125+E152+E179)} -> 0
A106: {=IF((INDIRECT("'"&INDIRECT("Main!B9")&"'!A120"))=0,"",(INDIRECT("'"&INDIRECT("Main!B9")&"'!A120")))} | B106: {=IF((INDIRECT("'"&INDIRECT("Main!B9")&"'!B120"))=0,"",(INDIRECT("'"&INDIRECT("Main!B9")&"'!B120")))} | C106: {=INDIRECT("'"&INDIRECT("Main!B24")&"'!C106")+SUM(E126+E153+E180)} -> 0
A107: {=IF((INDIRECT("'"&INDIRECT("Main!B9")&"'!A121"))=0,"",(INDIRECT("'"&INDIRECT("Main!B9")&"'!A121")))} | B107: {=IF((INDIRECT("'"&INDIRECT("Main!B9")&"'!B121"))=0,"",(INDIRECT("'"&INDIRECT("Main!B9")&"'!B121")))} | C107: {=INDIRECT("'"&INDIRECT("Main!B24")&"'!C107")+SUM(E127+E154+E181)} -> 0
B108: Total Debts | C108: =SUM(C98:C107) -> 0
B109: Grand Total | C109: =C108-C96 -> 0
A114: ="Debts Or Credits For the Comming "&IF(Main!B2,TEXT(EDATE(Main!B3,18),"mmmm dd yyyy"),TEXT(Main!B3+((Main!B5-Main!B3)*18+18),"mmmm dd yyyy"))&" to "&IF(Main!B2,TEXT(EDATE(Main!B3,19)-1,"mmmm dd yyyy"),TEXT(Main!B3+((Main!B5-Main!B3)*19+18),"mmmm dd yyyy")) -> Debts Or Credits For the Comming October 11 2026 to November 10 2026
A115: Principal | C115: Description | E115: Amount
...

Sheet Forecast_8
A1: ="Forecasts For the Year "&IF(Main!B2,TEXT(EDATE(Main!B3,21),"mmmm yyyy"),TEXT(Main!B3+((Main!B5-Main!B3)*21+21),"mmmm yyyy"))&" to "&IF(Main!B2,TEXT(EDATE(Main!B3,24)-1,"mmmm yyyy"),TEXT(Main!B3+((Main!B5-Main!B3)*24+23),"mmmm yyyy")) -> Forecasts For the Year January 2027 to April 2027
A2: Assets | B2: Overall | C2: {=INDIRECT("'"&Main!B9&"'!$C$16")} -> 0
B3: Forecasts | C3: =E190 -> 0
A4: Total | C4: =SUM(C2:G3) -> 0
A5: Net Debts: | C5: =C108 -> 0
A8: =IF(Main!B2,TEXT(EDATE(Main!B3,21),"dd mmmm yyyy"),TEXT(Main!B3+((Main!B5-Main!B3)*21+21),"dd mmmm yyyy"))&" - "&IF(Main!B2,TEXT(EDATE(Main!B3,22)-1,"dd mmmm yyyy"),TEXT(Main!B3+((Main!B5-Main!B3)*22+21),"dd mmmm yyyy"))&" / "&" (Revenue / Deferred Debts Or Expenses)" -> 11 January 2027 - 10 February 2027 / (Revenue / Deferred Debts Or Expenses)
A9: Date | B9: Name | D9: Description | F9: Amount
F10: 0
F11: 0
F12: 0
F13: 0
F14: 0
F15: 0
D16: Total Revenue | F16: =SUM(F10:G15) -> 0
A20: =IF(Main!B2,TEXT(EDATE(Main!B3,22),"dd mmmm yyyy"),TEXT(Main!B3+((Main!B5-Main!B3)*22+22),"dd mmmm yyyy"))&" - "&IF(Main!B2,TEXT(EDATE(Main!B3,23)-1,"dd mmmm yyyy"),TEXT(Main!B3+((Main!B5-Main!B3)*23+22),"dd mmmm yyyy"))&" / "&" (Revenue / Deferred Debts Or Expenses)" -> 11 February 2027 - 10 March 2027 / (Revenue / Deferred Debts Or Expenses)
A21: Date | B21: Name | D21: Description | F21: Amount
F22: 0
F23: 0
F24: 0
F25: 0
F26: 0
F27: 0
D28: Total Revenue | F28: =SUM(F22:G27) -> 0
A32: =IF(Main!B2,TEXT(EDATE(Main!B3,23),"dd mmmm yyyy"),TEXT(Main!B3+((Main!B5-Main!B3)*23+23),"dd mmmm yyyy"))&" - "&IF(Main!B2,TEXT(EDATE(Main!B3,24)-1,"dd mmmm yyyy"),TEXT(Main!B3+((Main!B5-Main!B3)*24+23),"dd mmmm yyyy"))&" / "&" (Revenue / Deferred Debts Or Expenses)" -> 11 March 2027 - 10 April 2027 / (Revenue / Deferred Debts Or Expenses)
A33: Date | B33: Name | D33: Description | F33: Amount
F34: 0
F35: 0
F36: 0
F37: 0
F38: 0
F39: 0
D40: Total Revenue | F40: =SUM(F34:G39) -> 0
A44: ="Fixed Expense For the Year "&IF(Main!B2,TEXT(EDATE(Main!B3,21),"mmmm yyyy"),TEXT(Main!B3+((Main!B5-Main!B3)*21+21),"mmmm yyyy"))&" to "&IF(Main!B2,TEXT(EDATE(Main!B3,24)-1,"mmmm yyyy"),TEXT(Main!B3+((Main!B5-Main!B3)*24+23),"mmmm yyyy")) -> Fixed Expense For the Year January 2027 to April 2027
A45: Name | B45: Description | C45: Amount
A46: {=IF((INDIRECT("'"&INDIRECT("Main!B9")&"'!A60"))=0,"",(INDIRECT("'"&INDIRECT("Main!B9")&"'!A60")))} -> Mobile And Communications/ Housing Expenses
A47: {=IF((INDIRECT("'"&INDIRECT("Main!B9")&"'!A61"))=0,"",(INDIRECT("'"&INDIRECT("Main!B9")&"'!A61")))} | B47: {=IF((INDIRECT("'"&INDIRECT("Main!B9")&"'!B61"))=0,"",(INDIRECT("'"&INDIRECT("Main!B9")&"'!B61")))} | C47: 0
A48: {=IF((INDIRECT("'"&INDIRECT("Main!B9")&"'!A62"))=0,"",(INDIRECT("'"&INDIRECT("Main!B9")&"'!A62")))} | B48: {=IF((INDIRECT("'"&INDIRECT("Main!B9")&"'!B62"))=0,"",(INDIRECT("'"&INDIRECT("Main!B9")&"'!B62")))} | C48: 0
A49: {=IF((INDIRECT("'"&INDIRECT("Main!B9")&"'!A63"))=0,"",(INDIRECT("'"&INDIRECT("Main!B9")&"'!A63")))} | B49: {=IF((INDIRECT("'"&INDIRECT("Main!B9")&"'!B63"))=0,"",(INDIRECT("'"&INDIRECT("Main!B9")&"'!B63")))} | C49: 0
A50: {=IF((INDIRECT("'"&INDIRECT("Main!B9")&"'!A64"))=0,"",(INDIRECT("'"&INDIRECT("Main!B9")&"'!A64")))} | B50: {=IF((INDIRECT("'"&INDIRECT("Main!B9")&"'!B64"))=0,"",(INDIRECT("'"&INDIRECT("Main!B9")&"'!B64")))} | C50: 0
A51: {=IF((INDIRECT("'"&INDIRECT("Main!B9")&"'!A65"))=0,"",(INDIRECT("'"&INDIRECT("Main!B9")&"'!A65")))} | B51: {=IF((INDIRECT("'"&INDIRECT("Main!B9")&"'!B65"))=0,"",(INDIRECT("'"&INDIRECT("Main!B9")&"'!B65")))} | C51: 0
A52: {=IF((INDIRECT("'"&INDIRECT("Main!B9")&"'!A66"))=0,"",(INDIRECT("'"&INDIRECT("Main!B9")&"'!A66")))} | B52: {=IF((INDIRECT("'"&INDIRECT("Main!B9")&"'!B66"))=0,"",(INDIRECT("'"&INDIRECT("Main!B9")&"'!B66")))} | C52: 0
A53: {=IF((INDIRECT("'"&INDIRECT("Main!B9")&"'!A67"))=0,"",(INDIRECT("'"&INDIRECT("Main!B9")&"'!A67")))} | B53: {=IF((INDIRECT("'"&INDIRECT("Main!B9")&"'!B67"))=0,"",(INDIRECT("'"&INDIRECT("Main!B9")&"'!B67")))} | C53: 0
A54: {=IF((INDIRECT("'"&INDIRECT("Main!B9")&"'!A68"))=0,"",(INDIRECT("'"&INDIRECT("Main!B9")&"'!A68")))} | B54: {=IF((INDIRECT("'"&INDIRECT("Main!B9")&"'!B68"))=0,"",(INDIRECT("'"&INDIRECT("Main!B9")&"'!B68")))} | C54: 0
B55: Total Expenses | C55: =SUM(C47:C54) -> 0
A56: {=IF((INDIRECT("'"&INDIRECT("Main!B9")&"'!A70"))=0,"",(INDIRECT("'"&INDIRECT("Main!B9")&"'!A70")))} -> Credit Card Installments/Government Installments
A57: {=IF((INDIRECT("'"&INDIRECT("Main!B9")&"'!A71"))=0,"",(INDIRECT("'"&INDIRECT("Main!B9")&"'!A71")))} | B57: {=IF((INDIRECT("'"&INDIRECT("Main!B9")&"'!B71"))=0,"",(INDIRECT("'"&INDIRECT("Main!B9")&"'!B71")))} | C57: 0
A58: {=IF((INDIRECT("'"&INDIRECT("Main!B9")&"'!A72"))=0,"",(INDIRECT("'"&INDIRECT("Main!B9")&"'!A72")))} | B58: {=IF((INDIRECT("'"&INDIRECT("Main!B9")&"'!B72"))=0,"",(INDIRECT("'"&INDIRECT("Main!B9")&"'!B72")))} | C58: 0
A59: {=IF((INDIRECT("'"&INDIRECT("Main!B9")&"'!A73"))=0,"",(INDIRECT("'"&INDIRECT("Main!B9")&"'!A73")))} | B59: {=IF((INDIRECT("'"&INDIRECT("Main!B9")&"'!B73"))=0,"",(INDIRECT("'"&INDIRECT("Main!B9")&"'!B73")))} | C59: 0
A60: {=IF((INDIRECT("'"&INDIRECT("Main!B9")&"'!A74"))=0,"",(INDIRECT("'"&INDIRECT("Main!B9")&"'!A74")))} | B60: {=IF((INDIRECT("'"&INDIRECT("Main!B9")&"'!B74"))=0,"",(INDIRECT("'"&INDIRECT("Main!B9")&"'!B74")))} | C60: 0
A61: {=IF((INDIRECT("'"&INDIRECT("Main!B9")&"'!A75"))=0,"",(INDIRECT("'"&INDIRECT("Main!B9")&"'!A75")))} | B61: {=IF((INDIRECT("'"&INDIRECT("Main!B9")&"'!B75"))=0,"",(INDIRECT("'"&INDIRECT("Main!B9")&"'!B75")))} | C61: 0
A62: {=IF((INDIRECT("'"&INDIRECT("Main!B9")&"'!A76"))=0,"",(INDIRECT("'"&INDIRECT("Main!B9")&"'!A76")))} | B62: {=IF((INDIRECT("'"&INDIRECT("Main!B9")&"'!B76"))=0,"",(INDIRECT("'"&INDIRECT("Main!B9")&"'!B76")))} | C62: 0
A63: {=IF((INDIRECT("'"&INDIRECT("Main!B9")&"'!A77"))=0,"",(INDIRECT("'"&INDIRECT("Main!B9")&"'!A77")))} | B63: {=IF((INDIRECT("'"&INDIRECT("Main!B9")&"'!B77"))=0,"",(INDIRECT("'"&INDIRECT("Main!B9")&"'!B77")))} | C63: 0
A64: {=IF((INDIRECT("'"&INDIRECT("Main!B9")&"'!A78"))=0,"",(INDIRECT("'"&INDIRECT("Main!B9")&"'!A78")))} | B64: {=IF((INDIRECT("'"&INDIRECT("Main!B9")&"'!B78"))=0,"",(INDIRECT("'"&INDIRECT("Main!B9")&"'!B78")))} | C64: 0
A65: {=IF((INDIRECT("'"&INDIRECT("Main!B9")&"'!A79"))=0,"",(INDIRECT("'"&INDIRECT("Main!B9")&"'!A79")))} | B65: {=IF((INDIRECT("'"&INDIRECT("Main!B9")&"'!B79"))=0,"",(INDIRECT("'"&INDIRECT("Main!B9")&"'!B79")))} | C65: 0
B66: Total Expenses | C66: =SUM(C57:C65) -> 0
A67: {=IF((INDIRECT("'"&INDIRECT("Main!B9")&"'!A81"))=0,"",(INDIRECT("'"&INDIRECT("Main!B9")&"'!A81")))} -> Donation
A68: {=IF((INDIRECT("'"&INDIRECT("Main!B9")&"'!A82"))=0,"",(INDIRECT("'"&INDIRECT("Main!B9")&"'!A82")))} | B68: {=IF((INDIRECT("'"&INDIRECT("Main!B9")&"'!B82"))=0,"",(INDIRECT("'"&INDIRECT("Main!B9")&"'!B82")))} | C68: 0
A69: {=IF((INDIRECT("'"&INDIRECT("Main!B9")&"'!A83"))=0,"",(INDIRECT("'"&INDIRECT("Main!B9")&"'!A83")))} | B69: {=IF((INDIRECT("'"&INDIRECT("Main!B9")&"'!B83"))=0,"",(INDIRECT("'"&INDIRECT("Main!B9")&"'!B83")))} | C69: 0
A70: {=IF((INDIRECT("'"&INDIRECT("Main!B9")&"'!A84"))=0,"",(INDIRECT("'"&INDIRECT("Main!B9")&"'!A84")))} | B70: {=IF((INDIRECT("'"&INDIRECT("Main!B9")&"'!B84"))=0,"",(INDIRECT("'"&INDIRECT("Main!B9")&"'!B84")))} | C70: 0
A71: {=IF((INDIRECT("'"&INDIRECT("Main!B9")&"'!A85"))=0,"",(INDIRECT("'"&INDIRECT("Main!B9")&"'!A85")))} | B71: {=IF((INDIRECT("'"&INDIRECT("Main!B9")&"'!B85"))=0,"",(INDIRECT("'"&INDIRECT("Main!B9")&"'!B85")))} | C71: 0
A72: {=IF((INDIRECT("'"&INDIRECT("Main!B9")&"'!A86"))=0,"",(INDIRECT("'"&INDIRECT("Main!B9")&"'!A86")))} | B72: {=IF((INDIRECT("'"&INDIRECT("Main!B9")&"'!B86"))=0,"",(INDIRECT("'"&INDIRECT("Main!B9")&"'!B86")))} | C72: 0
A73: {=IF((INDIRECT("'"&INDIRECT("Main!B9")&"'!A87"))=0,"",(INDIRECT("'"&INDIRECT("Main!B9")&"'!A87")))} | B73: {=IF((INDIRECT("'"&INDIRECT("Main!B9")&"'!B87"))=0,"",(INDIRECT("'"&INDIRECT("Main!B9")&"'!B87")))} | C73: 0
A74: {=IF((INDIRECT("'"&INDIRECT("Main!B9")&"'!A88"))=0,"",(INDIRECT("'"&INDIRECT("Main!B9")&"'!A88")))} | B74: {=IF((INDIRECT("'"&INDIRECT("Main!B9")&"'!B88"))=0,"",(INDIRECT("'"&INDIRECT("Main!B9")&"'!B88")))} | C74: 0
B75: Total Expenses | C75: =SUM(C68:C74) -> 0
A76: {=IF((INDIRECT("'"&INDIRECT("Main!B9")&"'!A90"))=0,"",(INDIRECT("'"&INDIRECT("Main!B9")&"'!A90")))} -> Insurance (Personal / Properties / Medical)
A77: {=IF((INDIRECT("'"&INDIRECT("Main!B9")&"'!A91"))=0,"",(INDIRECT("'"&INDIRECT("Main!B9")&"'!A91")))} | B77: {=IF((INDIRECT("'"&INDIRECT("Main!B9")&"'!B91"))=0,"",(INDIRECT("'"&INDIRECT("Main!B9")&"'!B91")))} | C77: 0
A78: {=IF((INDIRECT("'"&INDIRECT("Main!B9")&"'!A92"))=0,"",(INDIRECT("'"&INDIRECT("Main!B9")&"'!A92")))} | B78: {=IF((INDIRECT("'"&INDIRECT("Main!B9")&"'!B92"))=0,"",(INDIRECT("'"&INDIRECT("Main!B9")&"'!B92")))} | C78: 0
A79: {=IF((INDIRECT("'"&INDIRECT("Main!B9")&"'!A93"))=0,"",(INDIRECT("'"&INDIRECT("Main!B9")&"'!A93")))} | B79: {=IF((INDIRECT("'"&INDIRECT("Main!B9")&"'!B93"))=0,"",(INDIRECT("'"&INDIRECT("Main!B9")&"'!B93")))} | C79: 0
A80: {=IF((INDIRECT("'"&INDIRECT("Main!B9")&"'!A94"))=0,"",(INDIRECT("'"&INDIRECT("Main!B9")&"'!A94")))} | B80: {=IF((INDIRECT("'"&INDIRECT("Main!B9")&"'!B94"))=0,"",(INDIRECT("'"&INDIRECT("Main!B9")&"'!B94")))} | C80: 0
A81: {=IF((INDIRECT("'"&INDIRECT("Main!B9")&"'!A95"))=0,"",(INDIRECT("'"&INDIRECT("Main!B9")&"'!A95")))} | B81: {=IF((INDIRECT("'"&INDIRECT("Main!B9")&"'!B95"))=0,"",(INDIRECT("'"&INDIRECT("Main!B9")&"'!B95")))} | C81: 0
A82: {=IF((INDIRECT("'"&INDIRECT("Main!B9")&"'!A96"))=0,"",(INDIRECT("'"&INDIRECT("Main!B9")&"'!A96")))} | B82: {=IF((INDIRECT("'"&INDIRECT("Main!B9")&"'!B96"))=0,"",(INDIRECT("'"&INDIRECT("Main!B9")&"'!B96")))} | C82: 0
A83: {=IF((INDIRECT("'"&INDIRECT("Main!B9")&"'!A97"))=0,"",(INDIRECT("'"&INDIRECT("Main!B9")&"'!A97")))} | B83: {=IF((INDIRECT("'"&INDIRECT("Main!B9")&"'!B97"))=0,"",(INDIRECT("'"&INDIRECT("Main!B9")&"'!B97")))} | C83: 0
A84: {=IF((INDIRECT("'"&INDIRECT("Main!B9")&"'!A98"))=0,"",(INDIRECT("'"&INDIRECT("Main!B9")&"'!A98")))} | B84: {=IF((INDIRECT("'"&INDIRECT("Main!B9")&"'!B98"))=0,"",(INDIRECT("'"&INDIRECT("Main!B9")&"'!B98")))} | C84: 0
B85: Total Expenses | C85: =SUM(C77:C84) -> 0
A86: {=IF((INDIRECT("'"&INDIRECT("Main!B9")&"'!A100"))=0,"",(INDIRECT("'"&INDIRECT("Main!B9")&"'!A100")))} -> Other Expenses
A87: {=IF((INDIRECT("'"&INDIRECT("Main!B9")&"'!A101"))=0,"",(INDIRECT("'"&INDIRECT("Main!B9")&"'!A101")))} | B87: {=IF((INDIRECT("'"&INDIRECT("Main!B9")&"'!B101"))=0,"",(INDIRECT("'"&INDIRECT("Main!B9")&"'!B101")))} | C87: 0
A88: {=IF((INDIRECT("'"&INDIRECT("Main!B9")&"'!A102"))=0,"",(INDIRECT("'"&INDIRECT("Main!B9")&"'!A102")))} | B88: {=IF((INDIRECT("'"&INDIRECT("Main!B9")&"'!B102"))=0,"",(INDIRECT("'"&INDIRECT("Main!B9")&"'!B102")))} | C88: 0
A89: {=IF((INDIRECT("'"&INDIRECT("Main!B9")&"'!A103"))=0,"",(INDIRECT("'"&INDIRECT("Main!B9")&"'!A103")))} | B89: {=IF((INDIRECT("'"&INDIRECT("Main!B9")&"'!B103"))=0,"",(INDIRECT("'"&INDIRECT("Main!B9")&"'!B103")))} | C89: 0
A90: {=IF((INDIRECT("'"&INDIRECT("Main!B9")&"'!A104"))=0,"",(INDIRECT("'"&INDIRECT("Main!B9")&"'!A104")))} | B90: {=IF((INDIRECT("'"&INDIRECT("Main!B9")&"'!B104"))=0,"",(INDIRECT("'"&INDIRECT("Main!B9")&"'!B104")))} | C90: 0
A91: {=IF((INDIRECT("'"&INDIRECT("Main!B9")&"'!A105"))=0,"",(INDIRECT("'"&INDIRECT("Main!B9")&"'!A105")))} | B91: {=IF((INDIRECT("'"&INDIRECT("Main!B9")&"'!B105"))=0,"",(INDIRECT("'"&INDIRECT("Main!B9")&"'!B105")))} | C91: 0
A92: {=IF((INDIRECT("'"&INDIRECT("Main!B9")&"'!A106"))=0,"",(INDIRECT("'"&INDIRECT("Main!B9")&"'!A106")))} | B92: {=IF((INDIRECT("'"&INDIRECT("Main!B9")&"'!B106"))=0,"",(INDIRECT("'"&INDIRECT("Main!B9")&"'!B106")))} | C92: 0
A93: {=IF((INDIRECT("'"&INDIRECT("Main!B9")&"'!A107"))=0,"",(INDIRECT("'"&INDIRECT("Main!B9")&"'!A107")))} | B93: {=IF((INDIRECT("'"&INDIRECT("Main!B9")&"'!B107"))=0,"",(INDIRECT("'"&INDIRECT("Main!B9")&"'!B107")))} | C93: 0
A94: {=IF((INDIRECT("'"&INDIRECT("Main!B9")&"'!A108"))=0,"",(INDIRECT("'"&INDIRECT("Main!B9")&"'!A108")))} | B94: {=IF((INDIRECT("'"&INDIRECT("Main!B9")&"'!B108"))=0,"",(INDIRECT("'"&INDIRECT("Main!B9")&"'!B108")))} | C94: 0
B95: Total Expenses | C95: =SUM(C87:C94) -> 0
B96: Grand Expenses Total | C96: =C55+C66+C75+C85+C95 -> 0
A97: {=IF((INDIRECT("'"&INDIRECT("Main!B9")&"'!A111"))=0,"",(INDIRECT("'"&INDIRECT("Main!B9")&"'!A111")))} -> Debts / Borrowed To
A98: {=IF((INDIRECT("'"&INDIRECT("Main!B9")&"'!A112"))=0,"",(INDIRECT("'"&INDIRECT("Main!B9")&"'!A112")))} | B98: {=IF((INDIRECT("'"&INDIRECT("Main!B9")&"'!B112"))=0,"",(INDIRECT("'"&INDIRECT("Main!B9")&"'!B112")))} | C98: {=INDIRECT("'"&INDIRECT("Main!B27")&"'!C98")+SUM(E118+E145+E172)} -> 0
A99: {=IF((INDIRECT("'"&INDIRECT("Main!B9")&"'!A113"))=0,"",(INDIRECT("'"&INDIRECT("Main!B9")&"'!A113")))} | B99: {=IF((INDIRECT("'"&INDIRECT("Main!B9")&"'!B113"))=0,"",(INDIRECT("'"&INDIRECT("Main!B9")&"'!B113")))} | C99: {=INDIRECT("'"&INDIRECT("Main!B27")&"'!C99")+SUM(E119+E146+E173)} -> 0
A100: {=IF((INDIRECT("'"&INDIRECT("Main!B9")&"'!A114"))=0,"",(INDIRECT("'"&INDIRECT("Main!B9")&"'!A114")))} | B100: {=IF((INDIRECT("'"&INDIRECT("Main!B9")&"'!B114"))=0,"",(INDIRECT("'"&INDIRECT("Main!B9")&"'!B114")))} | C100: {=INDIRECT("'"&INDIRECT("Main!B27")&"'!C100")+SUM(E120+E147+E174)} -> 0
A101: {=IF((INDIRECT("'"&INDIRECT("Main!B9")&"'!A115"))=0,"",(INDIRECT("'"&INDIRECT("Main!B9")&"'!A115")))} | B101: {=IF((INDIRECT("'"&INDIRECT("Main!B9")&"'!B115"))=0,"",(INDIRECT("'"&INDIRECT("Main!B9")&"'!B115")))} | C101: {=INDIRECT("'"&INDIRECT("Main!B27")&"'!C101")+SUM(E121+E148+E175)} -> 0
A102: {=IF((INDIRECT("'"&INDIRECT("Main!B9")&"'!A116"))=0,"",(INDIRECT("'"&INDIRECT("Main!B9")&"'!A116")))} | B102: {=IF((INDIRECT("'"&INDIRECT("Main!B9")&"'!B116"))=0,"",(INDIRECT("'"&INDIRECT("Main!B9")&"'!B116")))} | C102: {=INDIRECT("'"&INDIRECT("Main!B27")&"'!C102")+SUM(E122+E149+E176)} -> 0
A103: {=IF((INDIRECT("'"&INDIRECT("Main!B9")&"'!A117"))=0,"",(INDIRECT("'"&INDIRECT("Main!B9")&"'!A117")))} | B103: {=IF((INDIRECT("'"&INDIRECT("Main!B9")&"'!B117"))=0,"",(INDIRECT("'"&INDIRECT("Main!B9")&"'!B117")))} | C103: {=INDIRECT("'"&INDIRECT("Main!B27")&"'!C103")+SUM(E123+E150+E177)} -> 0
A104: {=IF((INDIRECT("'"&INDIRECT("Main!B9")&"'!A118"))=0,"",(INDIRECT("'"&INDIRECT("Main!B9")&"'!A118")))} | B104: {=IF((INDIRECT("'"&INDIRECT("Main!B9")&"'!B118"))=0,"",(INDIRECT("'"&INDIRECT("Main!B9")&"'!B118")))} | C104: {=INDIRECT("'"&INDIRECT("Main!B27")&"'!C104")+SUM(E124+E151+E178)} -> 0
A105: {=IF((INDIRECT("'"&INDIRECT("Main!B9")&"'!A119"))=0,"",(INDIRECT("'"&INDIRECT("Main!B9")&"'!A119")))} | B105: {=IF((INDIRECT("'"&INDIRECT("Main!B9")&"'!B119"))=0,"",(INDIRECT("'"&INDIRECT("Main!B9")&"'!B119")))} | C105: {=INDIRECT("'"&INDIRECT("Main!B27")&"'!C105")+SUM(E125+E152+E179)} -> 0
A106: {=IF((INDIRECT("'"&INDIRECT("Main!B9")&"'!A120"))=0,"",(INDIRECT("'"&INDIRECT("Main!B9")&"'!A120")))} | B106: {=IF((INDIRECT("'"&INDIRECT("Main!B9")&"'!B120"))=0,"",(INDIRECT("'"&INDIRECT("Main!B9")&"'!B120")))} | C106: {=INDIRECT("'"&INDIRECT("Main!B27")&"'!C106")+SUM(E126+E153+E180)} -> 0
A107: {=IF((INDIRECT("'"&INDIRECT("Main!B9")&"'!A121"))=0,"",(INDIRECT("'"&INDIRECT("Main!B9")&"'!A121")))} | B107: {=IF((INDIRECT("'"&INDIRECT("Main!B9")&"'!B121"))=0,"",(INDIRECT("'"&INDIRECT("Main!B9")&"'!B121")))} | C107: {=INDIRECT("'"&INDIRECT("Main!B27")&"'!C107")+SUM(E127+E154+E181)} -> 0
B108: Total Debts | C108: =SUM(C98:C107) -> 0
B109: Grand Total | C109: =C108-C96 -> 0
A114: ="Debts Or Credits For the Comming "&IF(Main!B2,TEXT(EDATE(Main!B3,21),"mmmm dd yyyy"),TEXT(Main!B3+((Main!B5-Main!B3)*21+21),"mmmm dd yyyy"))&" to "&IF(Main!B2,TEXT(EDATE(Main!B3,22)-1,"mmmm dd yyyy"),TEXT(Main!B3+((Main!B5-Main!B3)*22+21),"mmmm dd yyyy")) -> Debts Or Credits For the Comming January 11 2027 to February 10 2027
A115: Principal | C115: Description | E115: Amount
...

Sheet Forecast_9
A1: ="Forecasts For the Year "&IF(Main!B2,TEXT(EDATE(Main!B3,24),"mmmm yyyy"),TEXT(Main!B3+((Main!B5-Main!B3)*24+24),"mmmm yyyy"))&" to "&IF(Main!B2,TEXT(EDATE(Main!B3,27)-1,"mmmm yyyy"),TEXT(Main!B3+((Main!B5-Main!B3)*27+26),"mmmm yyyy")) -> Forecasts For the Year April 2027 to July 2027
A2: Assets | B2: Overall | C2: {=INDIRECT("'"&Main!B9&"'!$C$16")} -> 0
B3: Forecasts | C3: =E190 -> 0
A4: Total | C4: =SUM(C2:G3) -> 0
A5: Net Debts: | C5: =C108 -> 0
A8: =IF(Main!B2,TEXT(EDATE(Main!B3,24),"dd mmmm yyyy"),TEXT(Main!B3+((Main!B5-Main!B3)*24+24),"dd mmmm yyyy"))&" - "&IF(Main!B2,TEXT(EDATE(Main!B3,25)-1,"dd mmmm yyyy"),TEXT(Main!B3+((Main!B5-Main!B3)*25+24),"dd mmmm yyyy"))&" / "&" (Revenue / Deferred Debts Or Expenses)" -> 11 April 2027 - 10 May 2027 / (Revenue / Deferred Debts Or Expenses)
A9: Date | B9: Name | D9: Description | F9: Amount
F10: 0
F11: 0
F12: 0
F13: 0
F14: 0
F15: 0
D16: Total Revenue | F16: =SUM(F10:G15) -> 0
A20: =IF(Main!B2,TEXT(EDATE(Main!B3,25),"dd mmmm yyyy"),TEXT(Main!B3+((Main!B5-Main!B3)*25+25),"dd mmmm yyyy"))&" - "&IF(Main!B2,TEXT(EDATE(Main!B3,26)-1,"dd mmmm yyyy"),TEXT(Main!B3+((Main!B5-Main!B3)*26+25),"dd mmmm yyyy"))&" / "&" (Revenue / Deferred Debts Or Expenses)" -> 11 May 2027 - 10 June 2027 / (Revenue / Deferred Debts Or Expenses)
A21: Date | B21: Name | D21: Description | F21: Amount
F22: 0
F23: 0
F24: 0
F25: 0
F26: 0
F27: 0
D28: Total Revenue | F28: =SUM(F22:G27) -> 0
A32: =IF(Main!B2,TEXT(EDATE(Main!B3,26),"dd mmmm yyyy"),TEXT(Main!B3+((Main!B5-Main!B3)*26+26),"dd mmmm yyyy"))&" - "&IF(Main!B2,TEXT(EDATE(Main!B3,27)-1,"dd mmmm yyyy"),TEXT(Main!B3+((Main!B5-Main!B3)*27+26),"dd mmmm yyyy"))&" / "&" (Revenue / Deferred Debts Or Expenses)" -> 11 June 2027 - 10 July 2027 / (Revenue / Deferred Debts Or Expenses)
A33: Date | B33: Name | D33: Description | F33: Amount
F34: 0
F35: 0
F36: 0
F37: 0
F38: 0
F39: 0
D40: Total Revenue | F40: =SUM(F34:G39) -> 0
A44: ="Fixed Expense For the Year "&IF(Main!B2,TEXT(EDATE(Main!B3,24),"mmmm yyyy"),TEXT(Main!B3+((Main!B5-Main!B3)*24+24),"mmmm yyyy"))&" to "&IF(Main!B2,TEXT(EDATE(Main!B3,27)-1,"mmmm yyyy"),TEXT(Main!B3+((Main!B5-Main!B3)*27+26),"mmmm yyyy")) -> Fixed Expense For the Year April 2027 to July 2027
A45: Name | B45: Description | C45: Amount
A46: {=IF((INDIRECT("'"&INDIRECT("Main!B9")&"'!A60"))=0,"",(INDIRECT("'"&INDIRECT("Main!B9")&"'!A60")))} -> Mobile And Communications/ Housing Expenses
A47: {=IF((INDIRECT("'"&INDIRECT("Main!B9")&"'!A61"))=0,"",(INDIRECT("'"&INDIRECT("Main!B9")&"'!A61")))} | B47: {=IF((INDIRECT("'"&INDIRECT("Main!B9")&"'!B61"))=0,"",(INDIRECT("'"&INDIRECT("Main!B9")&"'!B61")))} | C47: 0
A48: {=IF((INDIRECT("'"&INDIRECT("Main!B9")&"'!A62"))=0,"",(INDIRECT("'"&INDIRECT("Main!B9")&"'!A62")))} | B48: {=IF((INDIRECT("'"&INDIRECT("Main!B9")&"'!B62"))=0,"",(INDIRECT("'"&INDIRECT("Main!B9")&"'!B62")))} | C48: 0
A49: {=IF((INDIRECT("'"&INDIRECT("Main!B9")&"'!A63"))=0,"",(INDIRECT("'"&INDIRECT("Main!B9")&"'!A63")))} | B49: {=IF((INDIRECT("'"&INDIRECT("Main!B9")&"'!B63"))=0,"",(INDIRECT("'"&INDIRECT("Main!B9")&"'!B63")))} | C49: 0
A50: {=IF((INDIRECT("'"&INDIRECT("Main!B9")&"'!A64"))=0,"",(INDIRECT("'"&INDIRECT("Main!B9")&"'!A64")))} | B50: {=IF((INDIRECT("'"&INDIRECT("Main!B9")&"'!B64"))=0,"",(INDIRECT("'"&INDIRECT("Main!B9")&"'!B64")))} | C50: 0
A51: {=IF((INDIRECT("'"&INDIRECT("Main!B9")&"'!A65"))=0,"",(INDIRECT("'"&INDIRECT("Main!B9")&"'!A65")))} | B51: {=IF((INDIRECT("'"&INDIRECT("Main!B9")&"'!B65"))=0,"",(INDIRECT("'"&INDIRECT("Main!B9")&"'!B65")))} | C51: 0
A52: {=IF((INDIRECT("'"&INDIRECT("Main!B9")&"'!A66"))=0,"",(INDIRECT("'"&INDIRECT("Main!B9")&"'!A66")))} | B52: {=IF((INDIRECT("'"&INDIRECT("Main!B9")&"'!B66"))=0,"",(INDIRECT("'"&INDIRECT("Main!B9")&"'!B66")))} | C52: 0
A53: {=IF((INDIRECT("'"&INDIRECT("Main!B9")&"'!A67"))=0,"",(INDIRECT("'"&INDIRECT("Main!B9")&"'!A67")))} | B53: {=IF((INDIRECT("'"&INDIRECT("Main!B9")&"'!B67"))=0,"",(INDIRECT("'"&INDIRECT("Main!B9")&"'!B67")))} | C53: 0
A54: {=IF((INDIRECT("'"&INDIRECT("Main!B9")&"'!A68"))=0,"",(INDIRECT("'"&INDIRECT("Main!B9")&"'!A68")))} | B54: {=IF((INDIRECT("'"&INDIRECT("Main!B9")&"'!B68"))=0,"",(INDIRECT("'"&INDIRECT("Main!B9")&"'!B68")))} | C54: 0
B55: Total Expenses | C55: =SUM(C47:C54) -> 0
A56: {=IF((INDIRECT("'"&INDIRECT("Main!B9")&"'!A70"))=0,"",(INDIRECT("'"&INDIRECT("Main!B9")&"'!A70")))} -> Credit Card Installments/Government Installments
A57: {=IF((INDIRECT("'"&INDIRECT("Main!B9")&"'!A71"))=0,"",(INDIRECT("'"&INDIRECT("Main!B9")&"'!A71")))} | B57: {=IF((INDIRECT("'"&INDIRECT("Main!B9")&"'!B71"))=0,"",(INDIRECT("'"&INDIRECT("Main!B9")&"'!B71")))} | C57: 0
A58: {=IF((INDIRECT("'"&INDIRECT("Main!B9")&"'!A72"))=0,"",(INDIRECT("'"&INDIRECT("Main!B9")&"'!A72")))} | B58: {=IF((INDIRECT("'"&INDIRECT("Main!B9")&"'!B72"))=0,"",(INDIRECT("'"&INDIRECT("Main!B9")&"'!B72")))} | C58: 0
A59: {=IF((INDIRECT("'"&INDIRECT("Main!B9")&"'!A73"))=0,"",(INDIRECT("'"&INDIRECT("Main!B9")&"'!A73")))} | B59: {=IF((INDIRECT("'"&INDIRECT("Main!B9")&"'!B73"))=0,"",(INDIRECT("'"&INDIRECT("Main!B9")&"'!B73")))} | C59: 0
A60: {=IF((INDIRECT("'"&INDIRECT("Main!B9")&"'!A74"))=0,"",(INDIRECT("'"&INDIRECT("Main!B9")&"'!A74")))} | B60: {=IF((INDIRECT("'"&INDIRECT("Main!B9")&"'!B74"))=0,"",(INDIRECT("'"&INDIRECT("Main!B9")&"'!B74")))} | C60: 0
A61: {=IF((INDIRECT("'"&INDIRECT("Main!B9")&"'!A75"))=0,"",(INDIRECT("'"&INDIRECT("Main!B9")&"'!A75")))} | B61: {=IF((INDIRECT("'"&INDIRECT("Main!B9")&"'!B75"))=0,"",(INDIRECT("'"&INDIRECT("Main!B9")&"'!B75")))} | C61: 0
A62: {=IF((INDIRECT("'"&INDIRECT("Main!B9")&"'!A76"))=0,"",(INDIRECT("'"&INDIRECT("Main!B9")&"'!A76")))} | B62: {=IF((INDIRECT("'"&INDIRECT("Main!B9")&"'!B76"))=0,"",(INDIRECT("'"&INDIRECT("Main!B9")&"'!B76")))} | C62: 0
A63: {=IF((INDIRECT("'"&INDIRECT("Main!B9")&"'!A77"))=0,"",(INDIRECT("'"&INDIRECT("Main!B9")&"'!A77")))} | B63: {=IF((INDIRECT("'"&INDIRECT("Main!B9")&"'!B77"))=0,"",(INDIRECT("'"&INDIRECT("Main!B9")&"'!B77")))} | C63: 0
A64: {=IF((INDIRECT("'"&INDIRECT("Main!B9")&"'!A78"))=0,"",(INDIRECT("'"&INDIRECT("Main!B9")&"'!A78")))} | B64: {=IF((INDIRECT("'"&INDIRECT("Main!B9")&"'!B78"))=0,"",(INDIRECT("'"&INDIRECT("Main!B9")&"'!B78")))} | C64: 0
A65: {=IF((INDIRECT("'"&INDIRECT("Main!B9")&"'!A79"))=0,"",(INDIRECT("'"&INDIRECT("Main!B9")&"'!A79")))} | B65: {=IF((INDIRECT("'"&INDIRECT("Main!B9")&"'!B79"))=0,"",(INDIRECT("'"&INDIRECT("Main!B9")&"'!B79")))} | C65: 0
B66: Total Expenses | C66: =SUM(C57:C65) -> 0
A67: {=IF((INDIRECT("'"&INDIRECT("Main!B9")&"'!A81"))=0,"",(INDIRECT("'"&INDIRECT("Main!B9")&"'!A81")))} -> Donation
A68: {=IF((INDIRECT("'"&INDIRECT("Main!B9")&"'!A82"))=0,"",(INDIRECT("'"&INDIRECT("Main!B9")&"'!A82")))} | B68: {=IF((INDIRECT("'"&INDIRECT("Main!B9")&"'!B82"))=0,"",(INDIRECT("'"&INDIRECT("Main!B9")&"'!B82")))} | C68: 0
A69: {=IF((INDIRECT("'"&INDIRECT("Main!B9")&"'!A83"))=0,"",(INDIRECT("'"&INDIRECT("Main!B9")&"'!A83")))} | B69: {=IF((INDIRECT("'"&INDIRECT("Main!B9")&"'!B83"))=0,"",(INDIRECT("'"&INDIRECT("Main!B9")&"'!B83")))} | C69: 0
A70: {=IF((INDIRECT("'"&INDIRECT("Main!B9")&"'!A84"))=0,"",(INDIRECT("'"&INDIRECT("Main!B9")&"'!A84")))} | B70: {=IF((INDIRECT("'"&INDIRECT("Main!B9")&"'!B84"))=0,"",(INDIRECT("'"&INDIRECT("Main!B9")&"'!B84")))} | C70: 0
A71: {=IF((INDIRECT("'"&INDIRECT("Main!B9")&"'!A85"))=0,"",(INDIRECT("'"&INDIRECT("Main!B9")&"'!A85")))} | B71: {=IF((INDIRECT("'"&INDIRECT("Main!B9")&"'!B85"))=0,"",(INDIRECT("'"&INDIRECT("Main!B9")&"'!B85")))} | C71: 0
A72: {=IF((INDIRECT("'"&INDIRECT("Main!B9")&"'!A86"))=0,"",(INDIRECT("'"&INDIRECT("Main!B9")&"'!A86")))} | B72: {=IF((INDIRECT("'"&INDIRECT("Main!B9")&"'!B86"))=0,"",(INDIRECT("'"&INDIRECT("Main!B9")&"'!B86")))} | C72: 0
A73: {=IF((INDIRECT("'"&INDIRECT("Main!B9")&"'!A87"))=0,"",(INDIRECT("'"&INDIRECT("Main!B9")&"'!A87")))} | B73: {=IF((INDIRECT("'"&INDIRECT("Main!B9")&"'!B87"))=0,"",(INDIRECT("'"&INDIRECT("Main!B9")&"'!B87")))} | C73: 0
A74: {=IF((INDIRECT("'"&INDIRECT("Main!B9")&"'!A88"))=0,"",(INDIRECT("'"&INDIRECT("Main!B9")&"'!A88")))} | B74: {=IF((INDIRECT("'"&INDIRECT("Main!B9")&"'!B88"))=0,"",(INDIRECT("'"&INDIRECT("Main!B9")&"'!B88")))} | C74: 0
B75: Total Expenses | C75: =SUM(C68:C74) -> 0
A76: {=IF((INDIRECT("'"&INDIRECT("Main!B9")&"'!A90"))=0,"",(INDIRECT("'"&INDIRECT("Main!B9")&"'!A90")))} -> Insurance (Personal / Properties / Medical)
A77: {=IF((INDIRECT("'"&INDIRECT("Main!B9")&"'!A91"))=0,"",(INDIRECT("'"&INDIRECT("Main!B9")&"'!A91")))} | B77: {=IF((INDIRECT("'"&INDIRECT("Main!B9")&"'!B91"))=0,"",(INDIRECT("'"&INDIRECT("Main!B9")&"'!B91")))} | C77: 0
A78: {=IF((INDIRECT("'"&INDIRECT("Main!B9")&"'!A92"))=0,"",(INDIRECT("'"&INDIRECT("Main!B9")&"'!A92")))} | B78: {=IF((INDIRECT("'"&INDIRECT("Main!B9")&"'!B92"))=0,"",(INDIRECT("'"&INDIRECT("Main!B9")&"'!B92")))} | C78: 0
A79: {=IF((INDIRECT("'"&INDIRECT("Main!B9")&"'!A93"))=0,"",(INDIRECT("'"&INDIRECT("Main!B9")&"'!A93")))} | B79: {=IF((INDIRECT("'"&INDIRECT("Main!B9")&"'!B93"))=0,"",(INDIRECT("'"&INDIRECT("Main!B9")&"'!B93")))} | C79: 0
A80: {=IF((INDIRECT("'"&INDIRECT("Main!B9")&"'!A94"))=0,"",(INDIRECT("'"&INDIRECT("Main!B9")&"'!A94")))} | B80: {=IF((INDIRECT("'"&INDIRECT("Main!B9")&"'!B94"))=0,"",(INDIRECT("'"&INDIRECT("Main!B9")&"'!B94")))} | C80: 0
A81: {=IF((INDIRECT("'"&INDIRECT("Main!B9")&"'!A95"))=0,"",(INDIRECT("'"&INDIRECT("Main!B9")&"'!A95")))} | B81: {=IF((INDIRECT("'"&INDIRECT("Main!B9")&"'!B95"))=0,"",(INDIRECT("'"&INDIRECT("Main!B9")&"'!B95")))} | C81: 0
A82: {=IF((INDIRECT("'"&INDIRECT("Main!B9")&"'!A96"))=0,"",(INDIRECT("'"&INDIRECT("Main!B9")&"'!A96")))} | B82: {=IF((INDIRECT("'"&INDIRECT("Main!B9")&"'!B96"))=0,"",(INDIRECT("'"&INDIRECT("Main!B9")&"'!B96")))} | C82: 0
A83: {=IF((INDIRECT("'"&INDIRECT("Main!B9")&"'!A97"))=0,"",(INDIRECT("'"&INDIRECT("Main!B9")&"'!A97")))} | B83: {=IF((INDIRECT("'"&INDIRECT("Main!B9")&"'!B97"))=0,"",(INDIRECT("'"&INDIRECT("Main!B9")&"'!B97")))} | C83: 0
A84: {=IF((INDIRECT("'"&INDIRECT("Main!B9")&"'!A98"))=0,"",(INDIRECT("'"&INDIRECT("Main!B9")&"'!A98")))} | B84: {=IF((INDIRECT("'"&INDIRECT("Main!B9")&"'!B98"))=0,"",(INDIRECT("'"&INDIRECT("Main!B9")&"'!B98")))} | C84: 0
B85: Total Expenses | C85: =SUM(C77:C84) -> 0
A86: {=IF((INDIRECT("'"&INDIRECT("Main!B9")&"'!A100"))=0,"",(INDIRECT("'"&INDIRECT("Main!B9")&"'!A100")))} -> Other Expenses
A87: {=IF((INDIRECT("'"&INDIRECT("Main!B9")&"'!A101"))=0,"",(INDIRECT("'"&INDIRECT("Main!B9")&"'!A101")))} | B87: {=IF((INDIRECT("'"&INDIRECT("Main!B9")&"'!B101"))=0,"",(INDIRECT("'"&INDIRECT("Main!B9")&"'!B101")))} | C87: 0
A88: {=IF((INDIRECT("'"&INDIRECT("Main!B9")&"'!A102"))=0,"",(INDIRECT("'"&INDIRECT("Main!B9")&"'!A102")))} | B88: {=IF((INDIRECT("'"&INDIRECT("Main!B9")&"'!B102"))=0,"",(INDIRECT("'"&INDIRECT("Main!B9")&"'!B102")))} | C88: 0
A89: {=IF((INDIRECT("'"&INDIRECT("Main!B9")&"'!A103"))=0,"",(INDIRECT("'"&INDIRECT("Main!B9")&"'!A103")))} | B89: {=IF((INDIRECT("'"&INDIRECT("Main!B9")&"'!B103"))=0,"",(INDIRECT("'"&INDIRECT("Main!B9")&"'!B103")))} | C89: 0
A90: {=IF((INDIRECT("'"&INDIRECT("Main!B9")&"'!A104"))=0,"",(INDIRECT("'"&INDIRECT("Main!B9")&"'!A104")))} | B90: {=IF((INDIRECT("'"&INDIRECT("Main!B9")&"'!B104"))=0,"",(INDIRECT("'"&INDIRECT("Main!B9")&"'!B104")))} | C90: 0
A91: {=IF((INDIRECT("'"&INDIRECT("Main!B9")&"'!A105"))=0,"",(INDIRECT("'"&INDIRECT("Main!B9")&"'!A105")))} | B91: {=IF((INDIRECT("'"&INDIRECT("Main!B9")&"'!B105"))=0,"",(INDIRECT("'"&INDIRECT("Main!B9")&"'!B105")))} | C91: 0
A92: {=IF((INDIRECT("'"&INDIRECT("Main!B9")&"'!A106"))=0,"",(INDIRECT("'"&INDIRECT("Main!B9")&"'!A106")))} | B92: {=IF((INDIRECT("'"&INDIRECT("Main!B9")&"'!B106"))=0,"",(INDIRECT("'"&INDIRECT("Main!B9")&"'!B106")))} | C92: 0
A93: {=IF((INDIRECT("'"&INDIRECT("Main!B9")&"'!A107"))=0,"",(INDIRECT("'"&INDIRECT("Main!B9")&"'!A107")))} | B93: {=IF((INDIRECT("'"&INDIRECT("Main!B9")&"'!B107"))=0,"",(INDIRECT("'"&INDIRECT("Main!B9")&"'!B107")))} | C93: 0
A94: {=IF((INDIRECT("'"&INDIRECT("Main!B9")&"'!A108"))=0,"",(INDIRECT("'"&INDIRECT("Main!B9")&"'!A108")))} | B94: {=IF((INDIRECT("'"&INDIRECT("Main!B9")&"'!B108"))=0,"",(INDIRECT("'"&INDIRECT("Main!B9")&"'!B108")))} | C94: 0
B95: Total Expenses | C95: =SUM(C87:C94) -> 0
B96: Grand Expenses Total | C96: =C55+C66+C75+C85+C95 -> 0
A97: {=IF((INDIRECT("'"&INDIRECT("Main!B9")&"'!A111"))=0,"",(INDIRECT("'"&INDIRECT("Main!B9")&"'!A111")))} -> Debts / Borrowed To
A98: {=IF((INDIRECT("'"&INDIRECT("Main!B9")&"'!A112"))=0,"",(INDIRECT("'"&INDIRECT("Main!B9")&"'!A112")))} | B98: {=IF((INDIRECT("'"&INDIRECT("Main!B9")&"'!B112"))=0,"",(INDIRECT("'"&INDIRECT("Main!B9")&"'!B112")))} | C98: {=INDIRECT("'"&INDIRECT("Main!B30")&"'!C98")+SUM(E118+E145+E172)} -> 0
A99: {=IF((INDIRECT("'"&INDIRECT("Main!B9")&"'!A113"))=0,"",(INDIRECT("'"&INDIRECT("Main!B9")&"'!A113")))} | B99: {=IF((INDIRECT("'"&INDIRECT("Main!B9")&"'!B113"))=0,"",(INDIRECT("'"&INDIRECT("Main!B9")&"'!B113")))} | C99: {=INDIRECT("'"&INDIRECT("Main!B30")&"'!C99")+SUM(E119+E146+E173)} -> 0
A100: {=IF((INDIRECT("'"&INDIRECT("Main!B9")&"'!A114"))=0,"",(INDIRECT("'"&INDIRECT("Main!B9")&"'!A114")))} | B100: {=IF((INDIRECT("'"&INDIRECT("Main!B9")&"'!B114"))=0,"",(INDIRECT("'"&INDIRECT("Main!B9")&"'!B114")))} | C100: {=INDIRECT("'"&INDIRECT("Main!B30")&"'!C100")+SUM(E120+E147+E174)} -> 0
A101: {=IF((INDIRECT("'"&INDIRECT("Main!B9")&"'!A115"))=0,"",(INDIRECT("'"&INDIRECT("Main!B9")&"'!A115")))} | B101: {=IF((INDIRECT("'"&INDIRECT("Main!B9")&"'!B115"))=0,"",(INDIRECT("'"&INDIRECT("Main!B9")&"'!B115")))} | C101: {=INDIRECT("'"&INDIRECT("Main!B30")&"'!C101")+SUM(E121+E148+E175)} -> 0
A102: {=IF((INDIRECT("'"&INDIRECT("Main!B9")&"'!A116"))=0,"",(INDIRECT("'"&INDIRECT("Main!B9")&"'!A116")))} | B102: {=IF((INDIRECT("'"&INDIRECT("Main!B9")&"'!B116"))=0,"",(INDIRECT("'"&INDIRECT("Main!B9")&"'!B116")))} | C102: {=INDIRECT("'"&INDIRECT("Main!B30")&"'!C102")+SUM(E122+E149+E176)} -> 0
A103: {=IF((INDIRECT("'"&INDIRECT("Main!B9")&"'!A117"))=0,"",(INDIRECT("'"&INDIRECT("Main!B9")&"'!A117")))} | B103: {=IF((INDIRECT("'"&INDIRECT("Main!B9")&"'!B117"))=0,"",(INDIRECT("'"&INDIRECT("Main!B9")&"'!B117")))} | C103: {=INDIRECT("'"&INDIRECT("Main!B30")&"'!C103")+SUM(E123+E150+E177)} -> 0
A104: {=IF((INDIRECT("'"&INDIRECT("Main!B9")&"'!A118"))=0,"",(INDIRECT("'"&INDIRECT("Main!B9")&"'!A118")))} | B104: {=IF((INDIRECT("'"&INDIRECT("Main!B9")&"'!B118"))=0,"",(INDIRECT("'"&INDIRECT("Main!B9")&"'!B118")))} | C104: {=INDIRECT("'"&INDIRECT("Main!B30")&"'!C104")+SUM(E124+E151+E178)} -> 0
A105: {=IF((INDIRECT("'"&INDIRECT("Main!B9")&"'!A119"))=0,"",(INDIRECT("'"&INDIRECT("Main!B9")&"'!A119")))} | B105: {=IF((INDIRECT("'"&INDIRECT("Main!B9")&"'!B119"))=0,"",(INDIRECT("'"&INDIRECT("Main!B9")&"'!B119")))} | C105: {=INDIRECT("'"&INDIRECT("Main!B30")&"'!C105")+SUM(E125+E152+E179)} -> 0
A106: {=IF((INDIRECT("'"&INDIRECT("Main!B9")&"'!A120"))=0,"",(INDIRECT("'"&INDIRECT("Main!B9")&"'!A120")))} | B106: {=IF((INDIRECT("'"&INDIRECT("Main!B9")&"'!B120"))=0,"",(INDIRECT("'"&INDIRECT("Main!B9")&"'!B120")))} | C106: {=INDIRECT("'"&INDIRECT("Main!B30")&"'!C106")+SUM(E126+E153+E180)} -> 0
A107: {=IF((INDIRECT("'"&INDIRECT("Main!B9")&"'!A121"))=0,"",(INDIRECT("'"&INDIRECT("Main!B9")&"'!A121")))} | B107: {=IF((INDIRECT("'"&INDIRECT("Main!B9")&"'!B121"))=0,"",(INDIRECT("'"&INDIRECT("Main!B9")&"'!B121")))} | C107: {=INDIRECT("'"&INDIRECT("Main!B30")&"'!C107")+SUM(E127+E154+E181)} -> 0
B108: Total Debts | C108: =SUM(C98:C107) -> 0
B109: Grand Total | C109: =C108-C96 -> 0
A114: ="Debts Or Credits For the Comming "&IF(Main!B2,TEXT(EDATE(Main!B3,24),"mmmm dd yyyy"),TEXT(Main!B3+((Main!B5-Main!B3)*24+24),"mmmm dd yyyy"))&" to "&IF(Main!B2,TEXT(EDATE(Main!B3,25)-1,"mmmm dd yyyy"),TEXT(Main!B3+((Main!B5-Main!B3)*25+24),"mmmm dd yyyy")) -> Debts Or Credits For the Comming April 11 2027 to May 10 2027
A115: Principal | C115: Description | E115: Amount
...

Sheet Forecast_10
A1: ="Forecasts For the Year "&IF(Main!B2,TEXT(EDATE(Main!B3,27),"mmmm yyyy"),TEXT(Main!B3+((Main!B5-Main!B3)*27+27),"mmmm yyyy"))&" to "&IF(Main!B2,TEXT(EDATE(Main!B3,30)-1,"mmmm yyyy"),TEXT(Main!B3+((Main!B5-Main!B3)*30+29),"mmmm yyyy")) -> Forecasts For the Year July 2027 to October 2027
A2: Assets | B2: Overall | C2: {=INDIRECT("'"&Main!B9&"'!$C$16")} -> 0
B3: Forecasts | C3: =E190 -> 0
A4: Total | C4: =SUM(C2:G3) -> 0
A5: Net Debts: | C5: =C108 -> 0
A8: =IF(Main!B2,TEXT(EDATE(Main!B3,27),"dd mmmm yyyy"),TEXT(Main!B3+((Main!B5-Main!B3)*27+27),"dd mmmm yyyy"))&" - "&IF(Main!B2,TEXT(EDATE(Main!B3,28)-1,"dd mmmm yyyy"),TEXT(Main!B3+((Main!B5-Main!B3)*28+27),"dd mmmm yyyy"))&" / "&" (Revenue / Deferred Debts Or Expenses)" -> 11 July 2027 - 10 August 2027 / (Revenue / Deferred Debts Or Expenses)
A9: Date | B9: Name | D9: Description | F9: Amount
F10: 0
F11: 0
F12: 0
F13: 0
F14: 0
F15: 0
D16: Total Revenue | F16: =SUM(F10:G15) -> 0
A20: =IF(Main!B2,TEXT(EDATE(Main!B3,28),"dd mmmm yyyy"),TEXT(Main!B3+((Main!B5-Main!B3)*28+28),"dd mmmm yyyy"))&" - "&IF(Main!B2,TEXT(EDATE(Main!B3,29)-1,"dd mmmm yyyy"),TEXT(Main!B3+((Main!B5-Main!B3)*29+28),"dd mmmm yyyy"))&" / "&" (Revenue / Deferred Debts Or Expenses)" -> 11 August 2027 - 10 September 2027 / (Revenue / Deferred Debts Or Expenses)
A21: Date | B21: Name | D21: Description | F21: Amount
F22: 0
F23: 0
F24: 0
F25: 0
F26: 0
F27: 0
D28: Total Revenue | F28: =SUM(F22:G27) -> 0
A32: =IF(Main!B2,TEXT(EDATE(Main!B3,29),"dd mmmm yyyy"),TEXT(Main!B3+((Main!B5-Main!B3)*29+29),"dd mmmm yyyy"))&" - "&IF(Main!B2,TEXT(EDATE(Main!B3,30)-1,"dd mmmm yyyy"),TEXT(Main!B3+((Main!B5-Main!B3)*30+29),"dd mmmm yyyy"))&" / "&" (Revenue / Deferred Debts Or Expenses)" -> 11 September 2027 - 10 October 2027 / (Revenue / Deferred Debts Or Expenses)
A33: Date | B33: Name | D33: Description | F33: Amount
F34: 0
F35: 0
F36: 0
F37: 0
F38: 0
F39: 0
D40: Total Revenue | F40: =SUM(F34:G39) -> 0
A44: ="Fixed Expense For the Year "&IF(Main!B2,TEXT(EDATE(Main!B3,27),"mmmm yyyy"),TEXT(Main!B3+((Main!B5-Main!B3)*27+27),"mmmm yyyy"))&" to "&IF(Main!B2,TEXT(EDATE(Main!B3,30)-1,"mmmm yyyy"),TEXT(Main!B3+((Main!B5-Main!B3)*30+29),"mmmm yyyy")) -> Fixed Expense For the Year July 2027 to October 2027
A45: Name | B45: Description | C45: Amount
A46: {=IF((INDIRECT("'"&INDIRECT("Main!B9")&"'!A60"))=0,"",(INDIRECT("'"&INDIRECT("Main!B9")&"'!A60")))} -> Mobile And Communications/ Housing Expenses
A47: {=IF((INDIRECT("'"&INDIRECT("Main!B9")&"'!A61"))=0,"",(INDIRECT("'"&INDIRECT("Main!B9")&"'!A61")))} | B47: {=IF((INDIRECT("'"&INDIRECT("Main!B9")&"'!B61"))=0,"",(INDIRECT("'"&INDIRECT("Main!B9")&"'!B61")))} | C47: 0
A48: {=IF((INDIRECT("'"&INDIRECT("Main!B9")&"'!A62"))=0,"",(INDIRECT("'"&INDIRECT("Main!B9")&"'!A62")))} | B48: {=IF((INDIRECT("'"&INDIRECT("Main!B9")&"'!B62"))=0,"",(INDIRECT("'"&INDIRECT("Main!B9")&"'!B62")))} | C48: 0
A49: {=IF((INDIRECT("'"&INDIRECT("Main!B9")&"'!A63"))=0,"",(INDIRECT("'"&INDIRECT("Main!B9")&"'!A63")))} | B49: {=IF((INDIRECT("'"&INDIRECT("Main!B9")&"'!B63"))=0,"",(INDIRECT("'"&INDIRECT("Main!B9")&"'!B63")))} | C49: 0
A50: {=IF((INDIRECT("'"&INDIRECT("Main!B9")&"'!A64"))=0,"",(INDIRECT("'"&INDIRECT("Main!B9")&"'!A64")))} | B50: {=IF((INDIRECT("'"&INDIRECT("Main!B9")&"'!B64"))=0,"",(INDIRECT("'"&INDIRECT("Main!B9")&"'!B64")))} | C50: 0
A51: {=IF((INDIRECT("'"&INDIRECT("Main!B9")&"'!A65"))=0,"",(INDIRECT("'"&INDIRECT("Main!B9")&"'!A65")))} | B51: {=IF((INDIRECT("'"&INDIRECT("Main!B9")&"'!B65"))=0,"",(INDIRECT("'"&INDIRECT("Main!B9")&"'!B65")))} | C51: 0
A52: {=IF((INDIRECT("'"&INDIRECT("Main!B9")&"'!A66"))=0,"",(INDIRECT("'"&INDIRECT("Main!B9")&"'!A66")))} | B52: {=IF((INDIRECT("'"&INDIRECT("Main!B9")&"'!B66"))=0,"",(INDIRECT("'"&INDIRECT("Main!B9")&"'!B66")))} | C52: 0
A53: {=IF((INDIRECT("'"&INDIRECT("Main!B9")&"'!A67"))=0,"",(INDIRECT("'"&INDIRECT("Main!B9")&"'!A67")))} | B53: {=IF((INDIRECT("'"&INDIRECT("Main!B9")&"'!B67"))=0,"",(INDIRECT("'"&INDIRECT("Main!B9")&"'!B67")))} | C53: 0
A54: {=IF((INDIRECT("'"&INDIRECT("Main!B9")&"'!A68"))=0,"",(INDIRECT("'"&INDIRECT("Main!B9")&"'!A68")))} | B54: {=IF((INDIRECT("'"&INDIRECT("Main!B9")&"'!B68"))=0,"",(INDIRECT("'"&INDIRECT("Main!B9")&"'!B68")))} | C54: 0
B55: Total Expenses | C55: =SUM(C47:C54) -> 0
A56: {=IF((INDIRECT("'"&INDIRECT("Main!B9")&"'!A70"))=0,"",(INDIRECT("'"&INDIRECT("Main!B9")&"'!A70")))} -> Credit Card Installments/Government Installments
A57: {=IF((INDIRECT("'"&INDIRECT("Main!B9")&"'!A71"))=0,"",(INDIRECT("'"&INDIRECT("Main!B9")&"'!A71")))} | B57: {=IF((INDIRECT("'"&INDIRECT("Main!B9")&"'!B71"))=0,"",(INDIRECT("'"&INDIRECT("Main!B9")&"'!B71")))} | C57: 0
A58: {=IF((INDIRECT("'"&INDIRECT("Main!B9")&"'!A72"))=0,"",(INDIRECT("'"&INDIRECT("Main!B9")&"'!A72")))} | B58: {=IF((INDIRECT("'"&INDIRECT("Main!B9")&"'!B72"))=0,"",(INDIRECT("'"&INDIRECT("Main!B9")&"'!B72")))} | C58: 0
A59: {=IF((INDIRECT("'"&INDIRECT("Main!B9")&"'!A73"))=0,"",(INDIRECT("'"&INDIRECT("Main!B9")&"'!A73")))} | B59: {=IF((INDIRECT("'"&INDIRECT("Main!B9")&"'!B73"))=0,"",(INDIRECT("'"&INDIRECT("Main!B9")&"'!B73")))} | C59: 0
A60: {=IF((INDIRECT("'"&INDIRECT("Main!B9")&"'!A74"))=0,"",(INDIRECT("'"&INDIRECT("Main!B9")&"'!A74")))} | B60: {=IF((INDIRECT("'"&INDIRECT("Main!B9")&"'!B74"))=0,"",(INDIRECT("'"&INDIRECT("Main!B9")&"'!B74")))} | C60: 0
A61: {=IF((INDIRECT("'"&INDIRECT("Main!B9")&"'!A75"))=0,"",(INDIRECT("'"&INDIRECT("Main!B9")&"'!A75")))} | B61: {=IF((INDIRECT("'"&INDIRECT("Main!B9")&"'!B75"))=0,"",(INDIRECT("'"&INDIRECT("Main!B9")&"'!B75")))} | C61: 0
A62: {=IF((INDIRECT("'"&INDIRECT("Main!B9")&"'!A76"))=0,"",(INDIRECT("'"&INDIRECT("Main!B9")&"'!A76")))} | B62: {=IF((INDIRECT("'"&INDIRECT("Main!B9")&"'!B76"))=0,"",(INDIRECT("'"&INDIRECT("Main!B9")&"'!B76")))} | C62: 0
A63: {=IF((INDIRECT("'"&INDIRECT("Main!B9")&"'!A77"))=0,"",(INDIRECT("'"&INDIRECT("Main!B9")&"'!A77")))} | B63: {=IF((INDIRECT("'"&INDIRECT("Main!B9")&"'!B77"))=0,"",(INDIRECT("'"&INDIRECT("Main!B9")&"'!B77")))} | C63: 0
A64: {=IF((INDIRECT("'"&INDIRECT("Main!B9")&"'!A78"))=0,"",(INDIRECT("'"&INDIRECT("Main!B9")&"'!A78")))} | B64: {=IF((INDIRECT("'"&INDIRECT("Main!B9")&"'!B78"))=0,"",(INDIRECT("'"&INDIRECT("Main!B9")&"'!B78")))} | C64: 0
A65: {=IF((INDIRECT("'"&INDIRECT("Main!B9")&"'!A79"))=0,"",(INDIRECT("'"&INDIRECT("Main!B9")&"'!A79")))} | B65: {=IF((INDIRECT("'"&INDIRECT("Main!B9")&"'!B79"))=0,"",(INDIRECT("'"&INDIRECT("Main!B9")&"'!B79")))} | C65: 0
B66: Total Expenses | C66: =SUM(C57:C65) -> 0
A67: {=IF((INDIRECT("'"&INDIRECT("Main!B9")&"'!A81"))=0,"",(INDIRECT("'"&INDIRECT("Main!B9")&"'!A81")))} -> Donation
A68: {=IF((INDIRECT("'"&INDIRECT("Main!B9")&"'!A82"))=0,"",(INDIRECT("'"&INDIRECT("Main!B9")&"'!A82")))} | B68: {=IF((INDIRECT("'"&INDIRECT("Main!B9")&"'!B82"))=0,"",(INDIRECT("'"&INDIRECT("Main!B9")&"'!B82")))} | C68: 0
A69: {=IF((INDIRECT("'"&INDIRECT("Main!B9")&"'!A83"))=0,"",(INDIRECT("'"&INDIRECT("Main!B9")&"'!A83")))} | B69: {=IF((INDIRECT("'"&INDIRECT("Main!B9")&"'!B83"))=0,"",(INDIRECT("'"&INDIRECT("Main!B9")&"'!B83")))} | C69: 0
A70: {=IF((INDIRECT("'"&INDIRECT("Main!B9")&"'!A84"))=0,"",(INDIRECT("'"&INDIRECT("Main!B9")&"'!A84")))} | B70: {=IF((INDIRECT("'"&INDIRECT("Main!B9")&"'!B84"))=0,"",(INDIRECT("'"&INDIRECT("Main!B9")&"'!B84")))} | C70: 0
A71: {=IF((INDIRECT("'"&INDIRECT("Main!B9")&"'!A85"))=0,"",(INDIRECT("'"&INDIRECT("Main!B9")&"'!A85")))} | B71: {=IF((INDIRECT("'"&INDIRECT("Main!B9")&"'!B85"))=0,"",(INDIRECT("'"&INDIRECT("Main!B9")&"'!B85")))} | C71: 0
A72: {=IF((INDIRECT("'"&INDIRECT("Main!B9")&"'!A86"))=0,"",(INDIRECT("'"&INDIRECT("Main!B9")&"'!A86")))} | B72: {=IF((INDIRECT("'"&INDIRECT("Main!B9")&"'!B86"))=0,"",(INDIRECT("'"&INDIRECT("Main!B9")&"'!B86")))} | C72: 0
A73: {=IF((INDIRECT("'"&INDIRECT("Main!B9")&"'!A87"))=0,"",(INDIRECT("'"&INDIRECT("Main!B9")&"'!A87")))} | B73: {=IF((INDIRECT("'"&INDIRECT("Main!B9")&"'!B87"))=0,"",(INDIRECT("'"&INDIRECT("Main!B9")&"'!B87")))} | C73: 0
A74: {=IF((INDIRECT("'"&INDIRECT("Main!B9")&"'!A88"))=0,"",(INDIRECT("'"&INDIRECT("Main!B9")&"'!A88")))} | B74: {=IF((INDIRECT("'"&INDIRECT("Main!B9")&"'!B88"))=0,"",(INDIRECT("'"&INDIRECT("Main!B9")&"'!B88")))} | C74: 0
B75: Total Expenses | C75: =SUM(C68:C74) -> 0
A76: {=IF((INDIRECT("'"&INDIRECT("Main!B9")&"'!A90"))=0,"",(INDIRECT("'"&INDIRECT("Main!B9")&"'!A90")))} -> Insurance (Personal / Properties / Medical)
A77: {=IF((INDIRECT("'"&INDIRECT("Main!B9")&"'!A91"))=0,"",(INDIRECT("'"&INDIRECT("Main!B9")&"'!A91")))} | B77: {=IF((INDIRECT("'"&INDIRECT("Main!B9")&"'!B91"))=0,"",(INDIRECT("'"&INDIRECT("Main!B9")&"'!B91")))} | C77: 0
A78: {=IF((INDIRECT("'"&INDIRECT("Main!B9")&"'!A92"))=0,"",(INDIRECT("'"&INDIRECT("Main!B9")&"'!A92")))} | B78: {=IF((INDIRECT("'"&INDIRECT("Main!B9")&"'!B92"))=0,"",(INDIRECT("'"&INDIRECT("Main!B9")&"'!B92")))} | C78: 0
A79: {=IF((INDIRECT("'"&INDIRECT("Main!B9")&"'!A93"))=0,"",(INDIRECT("'"&INDIRECT("Main!B9")&"'!A93")))} | B79: {=IF((INDIRECT("'"&INDIRECT("Main!B9")&"'!B93"))=0,"",(INDIRECT("'"&INDIRECT("Main!B9")&"'!B93")))} | C79: 0
A80: {=IF((INDIRECT("'"&INDIRECT("Main!B9")&"'!A94"))=0,"",(INDIRECT("'"&INDIRECT("Main!B9")&"'!A94")))} | B80: {=IF((INDIRECT("'"&INDIRECT("Main!B9")&"'!B94"))=0,"",(INDIRECT("'"&INDIRECT("Main!B9")&"'!B94")))} | C80: 0
A81: {=IF((INDIRECT("'"&INDIRECT("Main!B9")&"'!A95"))=0,"",(INDIRECT("'"&INDIRECT("Main!B9")&"'!A95")))} | B81: {=IF((INDIRECT("'"&INDIRECT("Main!B9")&"'!B95"))=0,"",(INDIRECT("'"&INDIRECT("Main!B9")&"'!B95")))} | C81: 0
A82: {=IF((INDIRECT("'"&INDIRECT("Main!B9")&"'!A96"))=0,"",(INDIRECT("'"&INDIRECT("Main!B9")&"'!A96")))} | B82: {=IF((INDIRECT("'"&INDIRECT("Main!B9")&"'!B96"))=0,"",(INDIRECT("'"&INDIRECT("Main!B9")&"'!B96")))} | C82: 0
A83: {=IF((INDIRECT("'"&INDIRECT("Main!B9")&"'!A97"))=0,"",(INDIRECT("'"&INDIRECT("Main!B9")&"'!A97")))} | B83: {=IF((INDIRECT("'"&INDIRECT("Main!B9")&"'!B97"))=0,"",(INDIRECT("'"&INDIRECT("Main!B9")&"'!B97")))} | C83: 0
A84: {=IF((INDIRECT("'"&INDIRECT("Main!B9")&"'!A98"))=0,"",(INDIRECT("'"&INDIRECT("Main!B9")&"'!A98")))} | B84: {=IF((INDIRECT("'"&INDIRECT("Main!B9")&"'!B98"))=0,"",(INDIRECT("'"&INDIRECT("Main!B9")&"'!B98")))} | C84: 0
B85: Total Expenses | C85: =SUM(C77:C84) -> 0
A86: {=IF((INDIRECT("'"&INDIRECT("Main!B9")&"'!A100"))=0,"",(INDIRECT("'"&INDIRECT("Main!B9")&"'!A100")))} -> Other Expenses
A87: {=IF((INDIRECT("'"&INDIRECT("Main!B9")&"'!A101"))=0,"",(INDIRECT("'"&INDIRECT("Main!B9")&"'!A101")))} | B87: {=IF((INDIRECT("'"&INDIRECT("Main!B9")&"'!B101"))=0,"",(INDIRECT("'"&INDIRECT("Main!B9")&"'!B101")))} | C87: 0
A88: {=IF((INDIRECT("'"&INDIRECT("Main!B9")&"'!A102"))=0,"",(INDIRECT("'"&INDIRECT("Main!B9")&"'!A102")))} | B88: {=IF((INDIRECT("'"&INDIRECT("Main!B9")&"'!B102"))=0,"",(INDIRECT("'"&INDIRECT("Main!B9")&"'!B102")))} | C88: 0
A89: {=IF((INDIRECT("'"&INDIRECT("Main!B9")&"'!A103"))=0,"",(INDIRECT("'"&INDIRECT("Main!B9")&"'!A103")))} | B89: {=IF((INDIRECT("'"&INDIRECT("Main!B9")&"'!B103"))=0,"",(INDIRECT("'"&INDIRECT("Main!B9")&"'!B103")))} | C89: 0
A90: {=IF((INDIRECT("'"&INDIRECT("Main!B9")&"'!A104"))=0,"",(INDIRECT("'"&INDIRECT("Main!B9")&"'!A104")))} | B90: {=IF((INDIRECT("'"&INDIRECT("Main!B9")&"'!B104"))=0,"",(INDIRECT("'"&INDIRECT("Main!B9")&"'!B104")))} | C90: 0
A91: {=IF((INDIRECT("'"&INDIRECT("Main!B9")&"'!A105"))=0,"",(INDIRECT("'"&INDIRECT("Main!B9")&"'!A105")))} | B91: {=IF((INDIRECT("'"&INDIRECT("Main!B9")&"'!B105"))=0,"",(INDIRECT("'"&INDIRECT("Main!B9")&"'!B105")))} | C91: 0
A92: {=IF((INDIRECT("'"&INDIRECT("Main!B9")&"'!A106"))=0,"",(INDIRECT("'"&INDIRECT("Main!B9")&"'!A106")))} | B92: {=IF((INDIRECT("'"&INDIRECT("Main!B9")&"'!B106"))=0,"",(INDIRECT("'"&INDIRECT("Main!B9")&"'!B106")))} | C92: 0
A93: {=IF((INDIRECT("'"&INDIRECT("Main!B9")&"'!A107"))=0,"",(INDIRECT("'"&INDIRECT("Main!B9")&"'!A107")))} | B93: {=IF((INDIRECT("'"&INDIRECT("Main!B9")&"'!B107"))=0,"",(INDIRECT("'"&INDIRECT("Main!B9")&"'!B107")))} | C93: 0
A94: {=IF((INDIRECT("'"&INDIRECT("Main!B9")&"'!A108"))=0,"",(INDIRECT("'"&INDIRECT("Main!B9")&"'!A108")))} | B94: {=IF((INDIRECT("'"&INDIRECT("Main!B9")&"'!B108"))=0,"",(INDIRECT("'"&INDIRECT("Main!B9")&"'!B108")))} | C94: 0
B95: Total Expenses | C95: =SUM(C87:C94) -> 0
B96: Grand Expenses Total | C96: =C55+C66+C75+C85+C95 -> 0
A97: {=IF((INDIRECT("'"&INDIRECT("Main!B9")&"'!A111"))=0,"",(INDIRECT("'"&INDIRECT("Main!B9")&"'!A111")))} -> Debts / Borrowed To
A98: {=IF((INDIRECT("'"&INDIRECT("Main!B9")&"'!A112"))=0,"",(INDIRECT("'"&INDIRECT("Main!B9")&"'!A112")))} | B98: {=IF((INDIRECT("'"&INDIRECT("Main!B9")&"'!B112"))=0,"",(INDIRECT("'"&INDIRECT("Main!B9")&"'!B112")))} | C98: {=INDIRECT("'"&INDIRECT("Main!B33")&"'!C98")+SUM(E118+E145+E172)} -> 0
A99: {=IF((INDIRECT("'"&INDIRECT("Main!B9")&"'!A113"))=0,"",(INDIRECT("'"&INDIRECT("Main!B9")&"'!A113")))} | B99: {=IF((INDIRECT("'"&INDIRECT("Main!B9")&"'!B113"))=0,"",(INDIRECT("'"&INDIRECT("Main!B9")&"'!B113")))} | C99: {=INDIRECT("'"&INDIRECT("Main!B33")&"'!C99")+SUM(E119+E146+E173)} -> 0
A100: {=IF((INDIRECT("'"&INDIRECT("Main!B9")&"'!A114"))=0,"",(INDIRECT("'"&INDIRECT("Main!B9")&"'!A114")))} | B100: {=IF((INDIRECT("'"&INDIRECT("Main!B9")&"'!B114"))=0,"",(INDIRECT("'"&INDIRECT("Main!B9")&"'!B114")))} | C100: {=INDIRECT("'"&INDIRECT("Main!B33")&"'!C100")+SUM(E120+E147+E174)} -> 0
A101: {=IF((INDIRECT("'"&INDIRECT("Main!B9")&"'!A115"))=0,"",(INDIRECT("'"&INDIRECT("Main!B9")&"'!A115")))} | B101: {=IF((INDIRECT("'"&INDIRECT("Main!B9")&"'!B115"))=0,"",(INDIRECT("'"&INDIRECT("Main!B9")&"'!B115")))} | C101: {=INDIRECT("'"&INDIRECT("Main!B33")&"'!C101")+SUM(E121+E148+E175)} -> 0
A102: {=IF((INDIRECT("'"&INDIRECT("Main!B9")&"'!A116"))=0,"",(INDIRECT("'"&INDIRECT("Main!B9")&"'!A116")))} | B102: {=IF((INDIRECT("'"&INDIRECT("Main!B9")&"'!B116"))=0,"",(INDIRECT("'"&INDIRECT("Main!B9")&"'!B116")))} | C102: {=INDIRECT("'"&INDIRECT("Main!B33")&"'!C102")+SUM(E122+E149+E176)} -> 0
A103: {=IF((INDIRECT("'"&INDIRECT("Main!B9")&"'!A117"))=0,"",(INDIRECT("'"&INDIRECT("Main!B9")&"'!A117")))} | B103: {=IF((INDIRECT("'"&INDIRECT("Main!B9")&"'!B117"))=0,"",(INDIRECT("'"&INDIRECT("Main!B9")&"'!B117")))} | C103: {=INDIRECT("'"&INDIRECT("Main!B33")&"'!C103")+SUM(E123+E150+E177)} -> 0
A104: {=IF((INDIRECT("'"&INDIRECT("Main!B9")&"'!A118"))=0,"",(INDIRECT("'"&INDIRECT("Main!B9")&"'!A118")))} | B104: {=IF((INDIRECT("'"&INDIRECT("Main!B9")&"'!B118"))=0,"",(INDIRECT("'"&INDIRECT("Main!B9")&"'!B118")))} | C104: {=INDIRECT("'"&INDIRECT("Main!B33")&"'!C104")+SUM(E124+E151+E178)} -> 0
A105: {=IF((INDIRECT("'"&INDIRECT("Main!B9")&"'!A119"))=0,"",(INDIRECT("'"&INDIRECT("Main!B9")&"'!A119")))} | B105: {=IF((INDIRECT("'"&INDIRECT("Main!B9")&"'!B119"))=0,"",(INDIRECT("'"&INDIRECT("Main!B9")&"'!B119")))} | C105: {=INDIRECT("'"&INDIRECT("Main!B33")&"'!C105")+SUM(E125+E152+E179)} -> 0
A106: {=IF((INDIRECT("'"&INDIRECT("Main!B9")&"'!A120"))=0,"",(INDIRECT("'"&INDIRECT("Main!B9")&"'!A120")))} | B106: {=IF((INDIRECT("'"&INDIRECT("Main!B9")&"'!B120"))=0,"",(INDIRECT("'"&INDIRECT("Main!B9")&"'!B120")))} | C106: {=INDIRECT("'"&INDIRECT("Main!B33")&"'!C106")+SUM(E126+E153+E180)} -> 0
A107: {=IF((INDIRECT("'"&INDIRECT("Main!B9")&"'!A121"))=0,"",(INDIRECT("'"&INDIRECT("Main!B9")&"'!A121")))} | B107: {=IF((INDIRECT("'"&INDIRECT("Main!B9")&"'!B121"))=0,"",(INDIRECT("'"&INDIRECT("Main!B9")&"'!B121")))} | C107: {=INDIRECT("'"&INDIRECT("Main!B33")&"'!C107")+SUM(E127+E154+E181)} -> 0
B108: Total Debts | C108: =SUM(C98:C107) -> 0
B109: Grand Total | C109: =C108-C96 -> 0
A114: ="Debts Or Credits For the Comming "&IF(Main!B2,TEXT(EDATE(Main!B3,27),"mmmm dd yyyy"),TEXT(Main!B3+((Main!B5-Main!B3)*27+27),"mmmm dd yyyy"))&" to "&IF(Main!B2,TEXT(EDATE(Main!B3,28)-1,"mmmm dd yyyy"),TEXT(Main!B3+((Main!B5-Main!B3)*28+27),"mmmm dd yyyy")) -> Debts Or Credits For the Comming July 11 2027 to August 10 2027
A115: Principal | C115: Description | E115: Amount
...

Sheet Forecast_11
A1: ="Forecasts For the Year "&IF(Main!B2,TEXT(EDATE(Main!B3,30),"mmmm yyyy"),TEXT(Main!B3+((Main!B5-Main!B3)*30+30),"mmmm yyyy"))&" to "&IF(Main!B2,TEXT(EDATE(Main!B3,33)-1,"mmmm yyyy"),TEXT(Main!B3+((Main!B5-Main!B3)*33+32),"mmmm yyyy")) -> Forecasts For the Year October 2027 to January 2028
A2: Assets | B2: Overall | C2: {=INDIRECT("'"&Main!B9&"'!$C$16")} -> 0
B3: Forecasts | C3: =E190 -> 0
A4: Total | C4: =SUM(C2:G3) -> 0
A5: Net Debts: | C5: =C108 -> 0
A8: =IF(Main!B2,TEXT(EDATE(Main!B3,30),"dd mmmm yyyy"),TEXT(Main!B3+((Main!B5-Main!B3)*30+30),"dd mmmm yyyy"))&" - "&IF(Main!B2,TEXT(EDATE(Main!B3,31)-1,"dd mmmm yyyy"),TEXT(Main!B3+((Main!B5-Main!B3)*31+30),"dd mmmm yyyy"))&" / "&" (Revenue / Deferred Debts Or Expenses)" -> 11 October 2027 - 10 November 2027 / (Revenue / Deferred Debts Or Expenses)
A9: Date | B9: Name | D9: Description | F9: Amount
F10: 0
F11: 0
F12: 0
F13: 0
F14: 0
F15: 0
D16: Total Revenue | F16: =SUM(F10:G15) -> 0
A20: =IF(Main!B2,TEXT(EDATE(Main!B3,31),"dd mmmm yyyy"),TEXT(Main!B3+((Main!B5-Main!B3)*31+31),"dd mmmm yyyy"))&" - "&IF(Main!B2,TEXT(EDATE(Main!B3,32)-1,"dd mmmm yyyy"),TEXT(Main!B3+((Main!B5-Main!B3)*32+31),"dd mmmm yyyy"))&" / "&" (Revenue / Deferred Debts Or Expenses)" -> 11 November 2027 - 10 December 2027 / (Revenue / Deferred Debts Or Expenses)
A21: Date | B21: Name | D21: Description | F21: Amount
F22: 0
F23: 0
F24: 0
F25: 0
F26: 0
F27: 0
D28: Total Revenue | F28: =SUM(F22:G27) -> 0
A32: =IF(Main!B2,TEXT(EDATE(Main!B3,32),"dd mmmm yyyy"),TEXT(Main!B3+((Main!B5-Main!B3)*32+32),"dd mmmm yyyy"))&" - "&IF(Main!B2,TEXT(EDATE(Main!B3,33)-1,"dd mmmm yyyy"),TEXT(Main!B3+((Main!B5-Main!B3)*33+32),"dd mmmm yyyy"))&" / "&" (Revenue / Deferred Debts Or Expenses)" -> 11 December 2027 - 10 January 2028 / (Revenue / Deferred Debts Or Expenses)
A33: Date | B33: Name | D33: Description | F33: Amount
F34: 0
F35: 0
F36: 0
F37: 0
F38: 0
F39: 0
D40: Total Revenue | F40: =SUM(F34:G39) -> 0
A44: ="Fixed Expense For the Year "&IF(Main!B2,TEXT(EDATE(Main!B3,30),"mmmm yyyy"),TEXT(Main!B3+((Main!B5-Main!B3)*30+30),"mmmm yyyy"))&" to "&IF(Main!B2,TEXT(EDATE(Main!B3,33)-1,"mmmm yyyy"),TEXT(Main!B3+((Main!B5-Main!B3)*33+32),"mmmm yyyy")) -> Fixed Expense For the Year October 2027 to January 2028
A45: Name | B45: Description | C45: Amount
A46: {=IF((INDIRECT("'"&INDIRECT("Main!B9")&"'!A60"))=0,"",(INDIRECT("'"&INDIRECT("Main!B9")&"'!A60")))} -> Mobile And Communications/ Housing Expenses
A47: {=IF((INDIRECT("'"&INDIRECT("Main!B9")&"'!A61"))=0,"",(INDIRECT("'"&INDIRECT("Main!B9")&"'!A61")))} | B47: {=IF((INDIRECT("'"&INDIRECT("Main!B9")&"'!B61"))=0,"",(INDIRECT("'"&INDIRECT("Main!B9")&"'!B61")))} | C47: 0
A48: {=IF((INDIRECT("'"&INDIRECT("Main!B9")&"'!A62"))=0,"",(INDIRECT("'"&INDIRECT("Main!B9")&"'!A62")))} | B48: {=IF((INDIRECT("'"&INDIRECT("Main!B9")&"'!B62"))=0,"",(INDIRECT("'"&INDIRECT("Main!B9")&"'!B62")))} | C48: 0
A49: {=IF((INDIRECT("'"&INDIRECT("Main!B9")&"'!A63"))=0,"",(INDIRECT("'"&INDIRECT("Main!B9")&"'!A63")))} | B49: {=IF((INDIRECT("'"&INDIRECT("Main!B9")&"'!B63"))=0,"",(INDIRECT("'"&INDIRECT("Main!B9")&"'!B63")))} | C49: 0
A50: {=IF((INDIRECT("'"&INDIRECT("Main!B9")&"'!A64"))=0,"",(INDIRECT("'"&INDIRECT("Main!B9")&"'!A64")))} | B50: {=IF((INDIRECT("'"&INDIRECT("Main!B9")&"'!B64"))=0,"",(INDIRECT("'"&INDIRECT("Main!B9")&"'!B64")))} | C50: 0
A51: {=IF((INDIRECT("'"&INDIRECT("Main!B9")&"'!A65"))=0,"",(INDIRECT("'"&INDIRECT("Main!B9")&"'!A65")))} | B51: {=IF((INDIRECT("'"&INDIRECT("Main!B9")&"'!B65"))=0,"",(INDIRECT("'"&INDIRECT("Main!B9")&"'!B65")))} | C51: 0
A52: {=IF((INDIRECT("'"&INDIRECT("Main!B9")&"'!A66"))=0,"",(INDIRECT("'"&INDIRECT("Main!B9")&"'!A66")))} | B52: {=IF((INDIRECT("'"&INDIRECT("Main!B9")&"'!B66"))=0,"",(INDIRECT("'"&INDIRECT("Main!B9")&"'!B66")))} | C52: 0
A53: {=IF((INDIRECT("'"&INDIRECT("Main!B9")&"'!A67"))=0,"",(INDIRECT("'"&INDIRECT("Main!B9")&"'!A67")))} | B53: {=IF((INDIRECT("'"&INDIRECT("Main!B9")&"'!B67"))=0,"",(INDIRECT("'"&INDIRECT("Main!B9")&"'!B67")))} | C53: 0
A54: {=IF((INDIRECT("'"&INDIRECT("Main!B9")&"'!A68"))=0,"",(INDIRECT("'"&INDIRECT("Main!B9")&"'!A68")))} | B54: {=IF((INDIRECT("'"&INDIRECT("Main!B9")&"'!B68"))=0,"",(INDIRECT("'"&INDIRECT("Main!B9")&"'!B68")))} | C54: 0
B55: Total Expenses | C55: =SUM(C47:C54) -> 0
A56: {=IF((INDIRECT("'"&INDIRECT("Main!B9")&"'!A70"))=0,"",(INDIRECT("'"&INDIRECT("Main!B9")&"'!A70")))} -> Credit Card Installments/Government Installments
A57: {=IF((INDIRECT("'"&INDIRECT("Main!B9")&"'!A71"))=0,"",(INDIRECT("'"&INDIRECT("Main!B9")&"'!A71")))} | B57: {=IF((INDIRECT("'"&INDIRECT("Main!B9")&"'!B71"))=0,"",(INDIRECT("'"&INDIRECT("Main!B9")&"'!B71")))} | C57: 0
A58: {=IF((INDIRECT("'"&INDIRECT("Main!B9")&"'!A72"))=0,"",(INDIRECT("'"&INDIRECT("Main!B9")&"'!A72")))} | B58: {=IF((INDIRECT("'"&INDIRECT("Main!B9")&"'!B72"))=0,"",(INDIRECT("'"&INDIRECT("Main!B9")&"'!B72")))} | C58: 0
A59: {=IF((INDIRECT("'"&INDIRECT("Main!B9")&"'!A73"))=0,"",(INDIRECT("'"&INDIRECT("Main!B9")&"'!A73")))} | B59: {=IF((INDIRECT("'"&INDIRECT("Main!B9")&"'!B73"))=0,"",(INDIRECT("'"&INDIRECT("Main!B9")&"'!B73")))} | C59: 0
A60: {=IF((INDIRECT("'"&INDIRECT("Main!B9")&"'!A74"))=0,"",(INDIRECT("'"&INDIRECT("Main!B9")&"'!A74")))} | B60: {=IF((INDIRECT("'"&INDIRECT("Main!B9")&"'!B74"))=0,"",(INDIRECT("'"&INDIRECT("Main!B9")&"'!B74")))} | C60: 0
A61: {=IF((INDIRECT("'"&INDIRECT("Main!B9")&"'!A75"))=0,"",(INDIRECT("'"&INDIRECT("Main!B9")&"'!A75")))} | B61: {=IF((INDIRECT("'"&INDIRECT("Main!B9")&"'!B75"))=0,"",(INDIRECT("'"&INDIRECT("Main!B9")&"'!B75")))} | C61: 0
A62: {=IF((INDIRECT("'"&INDIRECT("Main!B9")&"'!A76"))=0,"",(INDIRECT("'"&INDIRECT("Main!B9")&"'!A76")))} | B62: {=IF((INDIRECT("'"&INDIRECT("Main!B9")&"'!B76"))=0,"",(INDIRECT("'"&INDIRECT("Main!B9")&"'!B76")))} | C62: 0
A63: {=IF((INDIRECT("'"&INDIRECT("Main!B9")&"'!A77"))=0,"",(INDIRECT("'"&INDIRECT("Main!B9")&"'!A77")))} | B63: {=IF((INDIRECT("'"&INDIRECT("Main!B9")&"'!B77"))=0,"",(INDIRECT("'"&INDIRECT("Main!B9")&"'!B77")))} | C63: 0
A64: {=IF((INDIRECT("'"&INDIRECT("Main!B9")&"'!A78"))=0,"",(INDIRECT("'"&INDIRECT("Main!B9")&"'!A78")))} | B64: {=IF((INDIRECT("'"&INDIRECT("Main!B9")&"'!B78"))=0,"",(INDIRECT("'"&INDIRECT("Main!B9")&"'!B78")))} | C64: 0
A65: {=IF((INDIRECT("'"&INDIRECT("Main!B9")&"'!A79"))=0,"",(INDIRECT("'"&INDIRECT("Main!B9")&"'!A79")))} | B65: {=IF((INDIRECT("'"&INDIRECT("Main!B9")&"'!B79"))=0,"",(INDIRECT("'"&INDIRECT("Main!B9")&"'!B79")))} | C65: 0
B66: Total Expenses | C66: =SUM(C57:C65) -> 0
A67: {=IF((INDIRECT("'"&INDIRECT("Main!B9")&"'!A81"))=0,"",(INDIRECT("'"&INDIRECT("Main!B9")&"'!A81")))} -> Donation
A68: {=IF((INDIRECT("'"&INDIRECT("Main!B9")&"'!A82"))=0,"",(INDIRECT("'"&INDIRECT("Main!B9")&"'!A82")))} | B68: {=IF((INDIRECT("'"&INDIRECT("Main!B9")&"'!B82"))=0,"",(INDIRECT("'"&INDIRECT("Main!B9")&"'!B82")))} | C68: 0
A69: {=IF((INDIRECT("'"&INDIRECT("Main!B9")&"'!A83"))=0,"",(INDIRECT("'"&INDIRECT("Main!B9")&"'!A83")))} | B69: {=IF((INDIRECT("'"&INDIRECT("Main!B9")&"'!B83"))=0,"",(INDIRECT("'"&INDIRECT("Main!B9")&"'!B83")))} | C69: 0
A70: {=IF((INDIRECT("'"&INDIRECT("Main!B9")&"'!A84"))=0,"",(INDIRECT("'"&INDIRECT("Main!B9")&"'!A84")))} | B70: {=IF((INDIRECT("'"&INDIRECT("Main!B9")&"'!B84"))=0,"",(INDIRECT("'"&INDIRECT("Main!B9")&"'!B84")))} | C70: 0
A71: {=IF((INDIRECT("'"&INDIRECT("Main!B9")&"'!A85"))=0,"",(INDIRECT("'"&INDIRECT("Main!B9")&"'!A85")))} | B71: {=IF((INDIRECT("'"&INDIRECT("Main!B9")&"'!B85"))=0,"",(INDIRECT("'"&INDIRECT("Main!B9")&"'!B85")))} | C71: 0
A72: {=IF((INDIRECT("'"&INDIRECT("Main!B9")&"'!A86"))=0,"",(INDIRECT("'"&INDIRECT("Main!B9")&"'!A86")))} | B72: {=IF((INDIRECT("'"&INDIRECT("Main!B9")&"'!B86"))=0,"",(INDIRECT("'"&INDIRECT("Main!B9")&"'!B86")))} | C72: 0
A73: {=IF((INDIRECT("'"&INDIRECT("Main!B9")&"'!A87"))=0,"",(INDIRECT("'"&INDIRECT("Main!B9")&"'!A87")))} | B73: {=IF((INDIRECT("'"&INDIRECT("Main!B9")&"'!B87"))=0,"",(INDIRECT("'"&INDIRECT("Main!B9")&"'!B87")))} | C73: 0
A74: {=IF((INDIRECT("'"&INDIRECT("Main!B9")&"'!A88"))=0,"",(INDIRECT("'"&INDIRECT("Main!B9")&"'!A88")))} | B74: {=IF((INDIRECT("'"&INDIRECT("Main!B9")&"'!B88"))=0,"",(INDIRECT("'"&INDIRECT("Main!B9")&"'!B88")))} | C74: 0
B75: Total Expenses | C75: =SUM(C68:C74) -> 0
A76: {=IF((INDIRECT("'"&INDIRECT("Main!B9")&"'!A90"))=0,"",(INDIRECT("'"&INDIRECT("Main!B9")&"'!A90")))} -> Insurance (Personal / Properties / Medical)
A77: {=IF((INDIRECT("'"&INDIRECT("Main!B9")&"'!A91"))=0,"",(INDIRECT("'"&INDIRECT("Main!B9")&"'!A91")))} | B77: {=IF((INDIRECT("'"&INDIRECT("Main!B9")&"'!B91"))=0,"",(INDIRECT("'"&INDIRECT("Main!B9")&"'!B91")))} | C77: 0
A78: {=IF((INDIRECT("'"&INDIRECT("Main!B9")&"'!A92"))=0,"",(INDIRECT("'"&INDIRECT("Main!B9")&"'!A92")))} | B78: {=IF((INDIRECT("'"&INDIRECT("Main!B9")&"'!B92"))=0,"",(INDIRECT("'"&INDIRECT("Main!B9")&"'!B92")))} | C78: 0
A79: {=IF((INDIRECT("'"&INDIRECT("Main!B9")&"'!A93"))=0,"",(INDIRECT("'"&INDIRECT("Main!B9")&"'!A93")))} | B79: {=IF((INDIRECT("'"&INDIRECT("Main!B9")&"'!B93"))=0,"",(INDIRECT("'"&INDIRECT("Main!B9")&"'!B93")))} | C79: 0
A80: {=IF((INDIRECT("'"&INDIRECT("Main!B9")&"'!A94"))=0,"",(INDIRECT("'"&INDIRECT("Main!B9")&"'!A94")))} | B80: {=IF((INDIRECT("'"&INDIRECT("Main!B9")&"'!B94"))=0,"",(INDIRECT("'"&INDIRECT("Main!B9")&"'!B94")))} | C80: 0
A81: {=IF((INDIRECT("'"&INDIRECT("Main!B9")&"'!A95"))=0,"",(INDIRECT("'"&INDIRECT("Main!B9")&"'!A95")))} | B81: {=IF((INDIRECT("'"&INDIRECT("Main!B9")&"'!B95"))=0,"",(INDIRECT("'"&INDIRECT("Main!B9")&"'!B95")))} | C81: 0
A82: {=IF((INDIRECT("'"&INDIRECT("Main!B9")&"'!A96"))=0,"",(INDIRECT("'"&INDIRECT("Main!B9")&"'!A96")))} | B82: {=IF((INDIRECT("'"&INDIRECT("Main!B9")&"'!B96"))=0,"",(INDIRECT("'"&INDIRECT("Main!B9")&"'!B96")))} | C82: 0
A83: {=IF((INDIRECT("'"&INDIRECT("Main!B9")&"'!A97"))=0,"",(INDIRECT("'"&INDIRECT("Main!B9")&"'!A97")))} | B83: {=IF((INDIRECT("'"&INDIRECT("Main!B9")&"'!B97"))=0,"",(INDIRECT("'"&INDIRECT("Main!B9")&"'!B97")))} | C83: 0
A84: {=IF((INDIRECT("'"&INDIRECT("Main!B9")&"'!A98"))=0,"",(INDIRECT("'"&INDIRECT("Main!B9")&"'!A98")))} | B84: {=IF((INDIRECT("'"&INDIRECT("Main!B9")&"'!B98"))=0,"",(INDIRECT("'"&INDIRECT("Main!B9")&"'!B98")))} | C84: 0
B85: Total Expenses | C85: =SUM(C77:C84) -> 0
A86: {=IF((INDIRECT("'"&INDIRECT("Main!B9")&"'!A100"))=0,"",(INDIRECT("'"&INDIRECT("Main!B9")&"'!A100")))} -> Other Expenses
A87: {=IF((INDIRECT("'"&INDIRECT("Main!B9")&"'!A101"))=0,"",(INDIRECT("'"&INDIRECT("Main!B9")&"'!A101")))} | B87: {=IF((INDIRECT("'"&INDIRECT("Main!B9")&"'!B101"))=0,"",(INDIRECT("'"&INDIRECT("Main!B9")&"'!B101")))} | C87: 0
A88: {=IF((INDIRECT("'"&INDIRECT("Main!B9")&"'!A102"))=0,"",(INDIRECT("'"&INDIRECT("Main!B9")&"'!A102")))} | B88: {=IF((INDIRECT("'"&INDIRECT("Main!B9")&"'!B102"))=0,"",(INDIRECT("'"&INDIRECT("Main!B9")&"'!B102")))} | C88: 0
A89: {=IF((INDIRECT("'"&INDIRECT("Main!B9")&"'!A103"))=0,"",(INDIRECT("'"&INDIRECT("Main!B9")&"'!A103")))} | B89: {=IF((INDIRECT("'"&INDIRECT("Main!B9")&"'!B103"))=0,"",(INDIRECT("'"&INDIRECT("Main!B9")&"'!B103")))} | C89: 0
A90: {=IF((INDIRECT("'"&INDIRECT("Main!B9")&"'!A104"))=0,"",(INDIRECT("'"&INDIRECT("Main!B9")&"'!A104")))} | B90: {=IF((INDIRECT("'"&INDIRECT("Main!B9")&"'!B104"))=0,"",(INDIRECT("'"&INDIRECT("Main!B9")&"'!B104")))} | C90: 0
A91: {=IF((INDIRECT("'"&INDIRECT("Main!B9")&"'!A105"))=0,"",(INDIRECT("'"&INDIRECT("Main!B9")&"'!A105")))} | B91: {=IF((INDIRECT("'"&INDIRECT("Main!B9")&"'!B105"))=0,"",(INDIRECT("'"&INDIRECT("Main!B9")&"'!B105")))} | C91: 0
A92: {=IF((INDIRECT("'"&INDIRECT("Main!B9")&"'!A106"))=0,"",(INDIRECT("'"&INDIRECT("Main!B9")&"'!A106")))} | B92: {=IF((INDIRECT("'"&INDIRECT("Main!B9")&"'!B106"))=0,"",(INDIRECT("'"&INDIRECT("Main!B9")&"'!B106")))} | C92: 0
A93: {=IF((INDIRECT("'"&INDIRECT("Main!B9")&"'!A107"))=0,"",(INDIRECT("'"&INDIRECT("Main!B9")&"'!A107")))} | B93: {=IF((INDIRECT("'"&INDIRECT("Main!B9")&"'!B107"))=0,"",(INDIRECT("'"&INDIRECT("Main!B9")&"'!B107")))} | C93: 0
A94: {=IF((INDIRECT("'"&INDIRECT("Main!B9")&"'!A108"))=0,"",(INDIRECT("'"&INDIRECT("Main!B9")&"'!A108")))} | B94: {=IF((INDIRECT("'"&INDIRECT("Main!B9")&"'!B108"))=0,"",(INDIRECT("'"&INDIRECT("Main!B9")&"'!B108")))} | C94: 0
B95: Total Expenses | C95: =SUM(C87:C94) -> 0
B96: Grand Expenses Total | C96: =C55+C66+C75+C85+C95 -> 0
A97: {=IF((INDIRECT("'"&INDIRECT("Main!B9")&"'!A111"))=0,"",(INDIRECT("'"&INDIRECT("Main!B9")&"'!A111")))} -> Debts / Borrowed To
A98: {=IF((INDIRECT("'"&INDIRECT("Main!B9")&"'!A112"))=0,"",(INDIRECT("'"&INDIRECT("Main!B9")&"'!A112")))} | B98: {=IF((INDIRECT("'"&INDIRECT("Main!B9")&"'!B112"))=0,"",(INDIRECT("'"&INDIRECT("Main!B9")&"'!B112")))} | C98: {=INDIRECT("'"&INDIRECT("Main!B36")&"'!C98")+SUM(E118+E145+E172)} -> 0
A99: {=IF((INDIRECT("'"&INDIRECT("Main!B9")&"'!A113"))=0,"",(INDIRECT("'"&INDIRECT("Main!B9")&"'!A113")))} | B99: {=IF((INDIRECT("'"&INDIRECT("Main!B9")&"'!B113"))=0,"",(INDIRECT("'"&INDIRECT("Main!B9")&"'!B113")))} | C99: {=INDIRECT("'"&INDIRECT("Main!B36")&"'!C99")+SUM(E119+E146+E173)} -> 0
A100: {=IF((INDIRECT("'"&INDIRECT("Main!B9")&"'!A114"))=0,"",(INDIRECT("'"&INDIRECT("Main!B9")&"'!A114")))} | B100: {=IF((INDIRECT("'"&INDIRECT("Main!B9")&"'!B114"))=0,"",(INDIRECT("'"&INDIRECT("Main!B9")&"'!B114")))} | C100: {=INDIRECT("'"&INDIRECT("Main!B36")&"'!C100")+SUM(E120+E147+E174)} -> 0
A101: {=IF((INDIRECT("'"&INDIRECT("Main!B9")&"'!A115"))=0,"",(INDIRECT("'"&INDIRECT("Main!B9")&"'!A115")))} | B101: {=IF((INDIRECT("'"&INDIRECT("Main!B9")&"'!B115"))=0,"",(INDIRECT("'"&INDIRECT("Main!B9")&"'!B115")))} | C101: {=INDIRECT("'"&INDIRECT("Main!B36")&"'!C101")+SUM(E121+E148+E175)} -> 0
A102: {=IF((INDIRECT("'"&INDIRECT("Main!B9")&"'!A116"))=0,"",(INDIRECT("'"&INDIRECT("Main!B9")&"'!A116")))} | B102: {=IF((INDIRECT("'"&INDIRECT("Main!B9")&"'!B116"))=0,"",(INDIRECT("'"&INDIRECT("Main!B9")&"'!B116")))} | C102: {=INDIRECT("'"&INDIRECT("Main!B36")&"'!C102")+SUM(E122+E149+E176)} -> 0
A103: {=IF((INDIRECT("'"&INDIRECT("Main!B9")&"'!A117"))=0,"",(INDIRECT("'"&INDIRECT("Main!B9")&"'!A117")))} | B103: {=IF((INDIRECT("'"&INDIRECT("Main!B9")&"'!B117"))=0,"",(INDIRECT("'"&INDIRECT("Main!B9")&"'!B117")))} | C103: {=INDIRECT("'"&INDIRECT("Main!B36")&"'!C103")+SUM(E123+E150+E177)} -> 0
A104: {=IF((INDIRECT("'"&INDIRECT("Main!B9")&"'!A118"))=0,"",(INDIRECT("'"&INDIRECT("Main!B9")&"'!A118")))} | B104: {=IF((INDIRECT("'"&INDIRECT("Main!B9")&"'!B118"))=0,"",(INDIRECT("'"&INDIRECT("Main!B9")&"'!B118")))} | C104: {=INDIRECT("'"&INDIRECT("Main!B36")&"'!C104")+SUM(E124+E151+E178)} -> 0
A105: {=IF((INDIRECT("'"&INDIRECT("Main!B9")&"'!A119"))=0,"",(INDIRECT("'"&INDIRECT("Main!B9")&"'!A119")))} | B105: {=IF((INDIRECT("'"&INDIRECT("Main!B9")&"'!B119"))=0,"",(INDIRECT("'"&INDIRECT("Main!B9")&"'!B119")))} | C105: {=INDIRECT("'"&INDIRECT("Main!B36")&"'!C105")+SUM(E125+E152+E179)} -> 0
A106: {=IF((INDIRECT("'"&INDIRECT("Main!B9")&"'!A120"))=0,"",(INDIRECT("'"&INDIRECT("Main!B9")&"'!A120")))} | B106: {=IF((INDIRECT("'"&INDIRECT("Main!B9")&"'!B120"))=0,"",(INDIRECT("'"&INDIRECT("Main!B9")&"'!B120")))} | C106: {=INDIRECT("'"&INDIRECT("Main!B36")&"'!C106")+SUM(E126+E153+E180)} -> 0
A107: {=IF((INDIRECT("'"&INDIRECT("Main!B9")&"'!A121"))=0,"",(INDIRECT("'"&INDIRECT("Main!B9")&"'!A121")))} | B107: {=IF((INDIRECT("'"&INDIRECT("Main!B9")&"'!B121"))=0,"",(INDIRECT("'"&INDIRECT("Main!B9")&"'!B121")))} | C107: {=INDIRECT("'"&INDIRECT("Main!B36")&"'!C107")+SUM(E127+E154+E181)} -> 0
B108: Total Debts | C108: =SUM(C98:C107) -> 0
B109: Grand Total | C109: =C108-C96 -> 0
A114: ="Debts Or Credits For the Comming "&IF(Main!B2,TEXT(EDATE(Main!B3,30),"mmmm dd yyyy"),TEXT(Main!B3+((Main!B5-Main!B3)*30+30),"mmmm dd yyyy"))&" to "&IF(Main!B2,TEXT(EDATE(Main!B3,31)-1,"mmmm dd yyyy"),TEXT(Main!B3+((Main!B5-Main!B3)*31+30),"mmmm dd yyyy")) -> Debts Or Credits For the Comming October 11 2027 to November 10 2027
A115: Principal | C115: Description | E115: Amount
...

Sheet Forecast_12
A1: ="Forecasts For the Year "&IF(Main!B2,TEXT(EDATE(Main!B3,33),"mmmm yyyy"),TEXT(Main!B3+((Main!B5-Main!B3)*33+33),"mmmm yyyy"))&" to "&IF(Main!B2,TEXT(EDATE(Main!B3,36)-1,"mmmm yyyy"),TEXT(Main!B3+((Main!B5-Main!B3)*36+35),"mmmm yyyy")) -> Forecasts For the Year January 2028 to April 2028
A2: Assets | B2: Overall | C2: {=INDIRECT("'"&Main!B9&"'!$C$16")} -> 0
B3: Forecasts | C3: =E190 -> 0
A4: Total | C4: =SUM(C2:G3) -> 0
A5: Net Debts: | C5: =C108 -> 0
A8: =IF(Main!B2,TEXT(EDATE(Main!B3,33),"dd mmmm yyyy"),TEXT(Main!B3+((Main!B5-Main!B3)*33+33),"dd mmmm yyyy"))&" - "&IF(Main!B2,TEXT(EDATE(Main!B3,34)-1,"dd mmmm yyyy"),TEXT(Main!B3+((Main!B5-Main!B3)*34+33),"dd mmmm yyyy"))&" / "&" (Revenue / Deferred Debts Or Expenses)" -> 11 January 2028 - 10 February 2028 / (Revenue / Deferred Debts Or Expenses)
A9: Date | B9: Name | D9: Description | F9: Amount
F10: 0
F11: 0
F12: 0
F13: 0
F14: 0
F15: 0
D16: Total Revenue | F16: =SUM(F10:G15) -> 0
A20: =IF(Main!B2,TEXT(EDATE(Main!B3,34),"dd mmmm yyyy"),TEXT(Main!B3+((Main!B5-Main!B3)*34+34),"dd mmmm yyyy"))&" - "&IF(Main!B2,TEXT(EDATE(Main!B3,35)-1,"dd mmmm yyyy"),TEXT(Main!B3+((Main!B5-Main!B3)*35+34),"dd mmmm yyyy"))&" / "&" (Revenue / Deferred Debts Or Expenses)" -> 11 February 2028 - 10 March 2028 / (Revenue / Deferred Debts Or Expenses)
A21: Date | B21: Name | D21: Description | F21: Amount
F22: 0
F23: 0
F24: 0
F25: 0
F26: 0
F27: 0
D28: Total Revenue | F28: =SUM(F22:G27) -> 0
A32: =IF(Main!B2,TEXT(EDATE(Main!B3,35),"dd mmmm yyyy"),TEXT(Main!B3+((Main!B5-Main!B3)*35+35),"dd mmmm yyyy"))&" - "&IF(Main!B2,TEXT(EDATE(Main!B3,36)-1,"dd mmmm yyyy"),TEXT(Main!B3+((Main!B5-Main!B3)*36+35),"dd mmmm yyyy"))&" / "&" (Revenue / Deferred Debts Or Expenses)" -> 11 March 2028 - 10 April 2028 / (Revenue / Deferred Debts Or Expenses)
A33: Date | B33: Name | D33: Description | F33: Amount
F34: 0
F35: 0
F36: 0
F37: 0
F38: 0
F39: 0
D40: Total Revenue | F40: =SUM(F34:G39) -> 0
A44: ="Fixed Expense For the Year "&IF(Main!B2,TEXT(EDATE(Main!B3,33),"mmmm yyyy"),TEXT(Main!B3+((Main!B5-Main!B3)*33+33),"mmmm yyyy"))&" to "&IF(Main!B2,TEXT(EDATE(Main!B3,36)-1,"mmmm yyyy"),TEXT(Main!B3+((Main!B5-Main!B3)*36+35),"mmmm yyyy")) -> Fixed Expense For the Year January 2028 to April 2028
A45: Name | B45: Description | C45: Amount
A46: {=IF((INDIRECT("'"&INDIRECT("Main!B9")&"'!A60"))=0,"",(INDIRECT("'"&INDIRECT("Main!B9")&"'!A60")))} -> Mobile And Communications/ Housing Expenses
A47: {=IF((INDIRECT("'"&INDIRECT("Main!B9")&"'!A61"))=0,"",(INDIRECT("'"&INDIRECT("Main!B9")&"'!A61")))} | B47: {=IF((INDIRECT("'"&INDIRECT("Main!B9")&"'!B61"))=0,"",(INDIRECT("'"&INDIRECT("Main!B9")&"'!B61")))} | C47: 0
A48: {=IF((INDIRECT("'"&INDIRECT("Main!B9")&"'!A62"))=0,"",(INDIRECT("'"&INDIRECT("Main!B9")&"'!A62")))} | B48: {=IF((INDIRECT("'"&INDIRECT("Main!B9")&"'!B62"))=0,"",(INDIRECT("'"&INDIRECT("Main!B9")&"'!B62")))} | C48: 0
A49: {=IF((INDIRECT("'"&INDIRECT("Main!B9")&"'!A63"))=0,"",(INDIRECT("'"&INDIRECT("Main!B9")&"'!A63")))} | B49: {=IF((INDIRECT("'"&INDIRECT("Main!B9")&"'!B63"))=0,"",(INDIRECT("'"&INDIRECT("Main!B9")&"'!B63")))} | C49: 0
A50: {=IF((INDIRECT("'"&INDIRECT("Main!B9")&"'!A64"))=0,"",(INDIRECT("'"&INDIRECT("Main!B9")&"'!A64")))} | B50: {=IF((INDIRECT("'"&INDIRECT("Main!B9")&"'!B64"))=0,"",(INDIRECT("'"&INDIRECT("Main!B9")&"'!B64")))} | C50: 0
A51: {=IF((INDIRECT("'"&INDIRECT("Main!B9")&"'!A65"))=0,"",(INDIRECT("'"&INDIRECT("Main!B9")&"'!A65")))} | B51: {=IF((INDIRECT("'"&INDIRECT("Main!B9")&"'!B65"))=0,"",(INDIRECT("'"&INDIRECT("Main!B9")&"'!B65")))} | C51: 0
A52: {=IF((INDIRECT("'"&INDIRECT("Main!B9")&"'!A66"))=0,"",(INDIRECT("'"&INDIRECT("Main!B9")&"'!A66")))} | B52: {=IF((INDIRECT("'"&INDIRECT("Main!B9")&"'!B66"))=0,"",(INDIRECT("'"&INDIRECT("Main!B9")&"'!B66")))} | C52: 0
A53: {=IF((INDIRECT("'"&INDIRECT("Main!B9")&"'!A67"))=0,"",(INDIRECT("'"&INDIRECT("Main!B9")&"'!A67")))} | B53: {=IF((INDIRECT("'"&INDIRECT("Main!B9")&"'!B67"))=0,"",(INDIRECT("'"&INDIRECT("Main!B9")&"'!B67")))} | C53: 0
A54: {=IF((INDIRECT("'"&INDIRECT("Main!B9")&"'!A68"))=0,"",(INDIRECT("'"&INDIRECT("Main!B9")&"'!A68")))} | B54: {=IF((INDIRECT("'"&INDIRECT("Main!B9")&"'!B68"))=0,"",(INDIRECT("'"&INDIRECT("Main!B9")&"'!B68")))} | C54: 0
B55: Total Expenses | C55: =SUM(C47:C54) -> 0
A56: {=IF((INDIRECT("'"&INDIRECT("Main!B9")&"'!A70"))=0,"",(INDIRECT("'"&INDIRECT("Main!B9")&"'!A70")))} -> Credit Card Installments/Government Installments
A57: {=IF((INDIRECT("'"&INDIRECT("Main!B9")&"'!A71"))=0,"",(INDIRECT("'"&INDIRECT("Main!B9")&"'!A71")))} | B57: {=IF((INDIRECT("'"&INDIRECT("Main!B9")&"'!B71"))=0,"",(INDIRECT("'"&INDIRECT("Main!B9")&"'!B71")))} | C57: 0
A58: {=IF((INDIRECT("'"&INDIRECT("Main!B9")&"'!A72"))=0,"",(INDIRECT("'"&INDIRECT("Main!B9")&"'!A72")))} | B58: {=IF((INDIRECT("'"&INDIRECT("Main!B9")&"'!B72"))=0,"",(INDIRECT("'"&INDIRECT("Main!B9")&"'!B72")))} | C58: 0
A59: {=IF((INDIRECT("'"&INDIRECT("Main!B9")&"'!A73"))=0,"",(INDIRECT("'"&INDIRECT("Main!B9")&"'!A73")))} | B59: {=IF((INDIRECT("'"&INDIRECT("Main!B9")&"'!B73"))=0,"",(INDIRECT("'"&INDIRECT("Main!B9")&"'!B73")))} | C59: 0
A60: {=IF((INDIRECT("'"&INDIRECT("Main!B9")&"'!A74"))=0,"",(INDIRECT("'"&INDIRECT("Main!B9")&"'!A74")))} | B60: {=IF((INDIRECT("'"&INDIRECT("Main!B9")&"'!B74"))=0,"",(INDIRECT("'"&INDIRECT("Main!B9")&"'!B74")))} | C60: 0
A61: {=IF((INDIRECT("'"&INDIRECT("Main!B9")&"'!A75"))=0,"",(INDIRECT("'"&INDIRECT("Main!B9")&"'!A75")))} | B61: {=IF((INDIRECT("'"&INDIRECT("Main!B9")&"'!B75"))=0,"",(INDIRECT("'"&INDIRECT("Main!B9")&"'!B75")))} | C61: 0
A62: {=IF((INDIRECT("'"&INDIRECT("Main!B9")&"'!A76"))=0,"",(INDIRECT("'"&INDIRECT("Main!B9")&"'!A76")))} | B62: {=IF((INDIRECT("'"&INDIRECT("Main!B9")&"'!B76"))=0,"",(INDIRECT("'"&INDIRECT("Main!B9")&"'!B76")))} | C62: 0
A63: {=IF((INDIRECT("'"&INDIRECT("Main!B9")&"'!A77"))=0,"",(INDIRECT("'"&INDIRECT("Main!B9")&"'!A77")))} | B63: {=IF((INDIRECT("'"&INDIRECT("Main!B9")&"'!B77"))=0,"",(INDIRECT("'"&INDIRECT("Main!B9")&"'!B77")))} | C63: 0
A64: {=IF((INDIRECT("'"&INDIRECT("Main!B9")&"'!A78"))=0,"",(INDIRECT("'"&INDIRECT("Main!B9")&"'!A78")))} | B64: {=IF((INDIRECT("'"&INDIRECT("Main!B9")&"'!B78"))=0,"",(INDIRECT("'"&INDIRECT("Main!B9")&"'!B78")))} | C64: 0
A65: {=IF((INDIRECT("'"&INDIRECT("Main!B9")&"'!A79"))=0,"",(INDIRECT("'"&INDIRECT("Main!B9")&"'!A79")))} | B65: {=IF((INDIRECT("'"&INDIRECT("Main!B9")&"'!B79"))=0,"",(INDIRECT("'"&INDIRECT("Main!B9")&"'!B79")))} | C65: 0
B66: Total Expenses | C66: =SUM(C57:C65) -> 0
A67: {=IF((INDIRECT("'"&INDIRECT("Main!B9")&"'!A81"))=0,"",(INDIRECT("'"&INDIRECT("Main!B9")&"'!A81")))} -> Donation
A68: {=IF((INDIRECT("'"&INDIRECT("Main!B9")&"'!A82"))=0,"",(INDIRECT("'"&INDIRECT("Main!B9")&"'!A82")))} | B68: {=IF((INDIRECT("'"&INDIRECT("Main!B9")&"'!B82"))=0,"",(INDIRECT("'"&INDIRECT("Main!B9")&"'!B82")))} | C68: 0
